package learnityasmtserver.assessmentportal.standaloneasmt;

import org.grlea.log.*;
import javax.servlet.http.*;
import java.io.*;
import javax.servlet.*;

public class StandAloneAssessment extends HttpServlet
{
    private static final SimpleLogger log;
    
    public void doGet(final HttpServletRequest request, final HttpServletResponse response) throws IOException, ServletException {
        response.setContentType("text/html;charset=utf-8");
        String student_id = "";
        final PrintWriter out = response.getWriter();
        response.setHeader("Pragma", "no-cache");
        response.setHeader("Cache-Control", "no-cache");
        response.setDateHeader("Expires", 0L);
        final HttpSession mysession = request.getSession(true);
        student_id = (String)mysession.getAttribute("student_id");
        StandAloneAssessment.log.debug("student_id=doget=" + student_id);
        if (student_id != null) {
            this.getResult(request, response, out, student_id);
        }
    }
    
    public void getResult(final HttpServletRequest request, final HttpServletResponse response, final PrintWriter out, final String student_id) throws IOException, ServletException {
        // 
        // This method could not be decompiled.
        // 
        // Original Bytecode:
        // 
        //     0: new             Ljava/util/GregorianCalendar;
        //     3: dup            
        //     4: invokespecial   java/util/GregorianCalendar.<init>:()V
        //     7: astore          calendar
        //     9: new             Ljava/util/Date;
        //    12: dup            
        //    13: invokespecial   java/util/Date.<init>:()V
        //    16: astore          trialTime
        //    18: aload           calendar
        //    20: aload           trialTime
        //    22: invokevirtual   java/util/Calendar.setTime:(Ljava/util/Date;)V
        //    25: bipush          12
        //    27: anewarray       Ljava/lang/String;
        //    30: dup            
        //    31: iconst_0       
        //    32: ldc             "January"
        //    34: aastore        
        //    35: dup            
        //    36: iconst_1       
        //    37: ldc             "Feburary"
        //    39: aastore        
        //    40: dup            
        //    41: iconst_2       
        //    42: ldc             "March"
        //    44: aastore        
        //    45: dup            
        //    46: iconst_3       
        //    47: ldc             "April"
        //    49: aastore        
        //    50: dup            
        //    51: iconst_4       
        //    52: ldc             "May"
        //    54: aastore        
        //    55: dup            
        //    56: iconst_5       
        //    57: ldc             "June"
        //    59: aastore        
        //    60: dup            
        //    61: bipush          6
        //    63: ldc             "July"
        //    65: aastore        
        //    66: dup            
        //    67: bipush          7
        //    69: ldc             "August"
        //    71: aastore        
        //    72: dup            
        //    73: bipush          8
        //    75: ldc             "September"
        //    77: aastore        
        //    78: dup            
        //    79: bipush          9
        //    81: ldc             "October"
        //    83: aastore        
        //    84: dup            
        //    85: bipush          10
        //    87: ldc             "November"
        //    89: aastore        
        //    90: dup            
        //    91: bipush          11
        //    93: ldc             "December"
        //    95: aastore        
        //    96: astore          months
        //    98: aload           calendar
        //   100: bipush          12
        //   102: invokevirtual   java/util/Calendar.get:(I)I
        //   105: invokestatic    java/lang/Integer.toString:(I)Ljava/lang/String;
        //   108: astore          mimute11
        //   110: ldc             ""
        //   112: astore          mimute1
        //   114: aload           mimute11
        //   116: invokevirtual   java/lang/String.length:()I
        //   119: iconst_2       
        //   120: if_icmpeq       148
        //   123: new             Ljava/lang/StringBuilder;
        //   126: dup            
        //   127: invokespecial   java/lang/StringBuilder.<init>:()V
        //   130: ldc             "0"
        //   132: invokevirtual   java/lang/StringBuilder.append:(Ljava/lang/String;)Ljava/lang/StringBuilder;
        //   135: aload           mimute11
        //   137: invokevirtual   java/lang/StringBuilder.append:(Ljava/lang/String;)Ljava/lang/StringBuilder;
        //   140: invokevirtual   java/lang/StringBuilder.toString:()Ljava/lang/String;
        //   143: astore          mimute1
        //   145: goto            152
        //   148: aload           mimute11
        //   150: astore          mimute1
        //   152: aload           calendar
        //   154: bipush          13
        //   156: invokevirtual   java/util/Calendar.get:(I)I
        //   159: invokestatic    java/lang/Integer.toString:(I)Ljava/lang/String;
        //   162: astore          sec11
        //   164: ldc             ""
        //   166: astore          sec1
        //   168: aload           sec11
        //   170: invokevirtual   java/lang/String.length:()I
        //   173: iconst_2       
        //   174: if_icmpeq       202
        //   177: new             Ljava/lang/StringBuilder;
        //   180: dup            
        //   181: invokespecial   java/lang/StringBuilder.<init>:()V
        //   184: ldc             "0"
        //   186: invokevirtual   java/lang/StringBuilder.append:(Ljava/lang/String;)Ljava/lang/StringBuilder;
        //   189: aload           sec11
        //   191: invokevirtual   java/lang/StringBuilder.append:(Ljava/lang/String;)Ljava/lang/StringBuilder;
        //   194: invokevirtual   java/lang/StringBuilder.toString:()Ljava/lang/String;
        //   197: astore          sec1
        //   199: goto            206
        //   202: aload           sec11
        //   204: astore          sec1
        //   206: new             Ljava/lang/StringBuilder;
        //   209: dup            
        //   210: invokespecial   java/lang/StringBuilder.<init>:()V
        //   213: aload           calendar
        //   215: bipush          10
        //   217: invokevirtual   java/util/Calendar.get:(I)I
        //   220: invokevirtual   java/lang/StringBuilder.append:(I)Ljava/lang/StringBuilder;
        //   223: ldc             ":"
        //   225: invokevirtual   java/lang/StringBuilder.append:(Ljava/lang/String;)Ljava/lang/StringBuilder;
        //   228: aload           mimute1
        //   230: invokevirtual   java/lang/StringBuilder.append:(Ljava/lang/String;)Ljava/lang/StringBuilder;
        //   233: ldc             ":"
        //   235: invokevirtual   java/lang/StringBuilder.append:(Ljava/lang/String;)Ljava/lang/StringBuilder;
        //   238: aload           sec1
        //   240: invokevirtual   java/lang/StringBuilder.append:(Ljava/lang/String;)Ljava/lang/StringBuilder;
        //   243: invokevirtual   java/lang/StringBuilder.toString:()Ljava/lang/String;
        //   246: astore          strTime
        //   248: new             Ljava/lang/StringBuilder;
        //   251: dup            
        //   252: invokespecial   java/lang/StringBuilder.<init>:()V
        //   255: aload           months
        //   257: aload           calendar
        //   259: iconst_2       
        //   260: invokevirtual   java/util/Calendar.get:(I)I
        //   263: aaload         
        //   264: invokevirtual   java/lang/StringBuilder.append:(Ljava/lang/String;)Ljava/lang/StringBuilder;
        //   267: ldc             " "
        //   269: invokevirtual   java/lang/StringBuilder.append:(Ljava/lang/String;)Ljava/lang/StringBuilder;
        //   272: aload           calendar
        //   274: iconst_5       
        //   275: invokevirtual   java/util/Calendar.get:(I)I
        //   278: invokevirtual   java/lang/StringBuilder.append:(I)Ljava/lang/StringBuilder;
        //   281: ldc             ", "
        //   283: invokevirtual   java/lang/StringBuilder.append:(Ljava/lang/String;)Ljava/lang/StringBuilder;
        //   286: aload           calendar
        //   288: iconst_1       
        //   289: invokevirtual   java/util/Calendar.get:(I)I
        //   292: invokevirtual   java/lang/StringBuilder.append:(I)Ljava/lang/StringBuilder;
        //   295: invokevirtual   java/lang/StringBuilder.toString:()Ljava/lang/String;
        //   298: astore          strDate
        //   300: aload           calendar
        //   302: iconst_2       
        //   303: invokevirtual   java/util/Calendar.get:(I)I
        //   306: iconst_1       
        //   307: iadd           
        //   308: invokestatic    java/lang/Integer.toString:(I)Ljava/lang/String;
        //   311: astore          month11
        //   313: ldc             ""
        //   315: astore          month
        //   317: aload           month11
        //   319: invokevirtual   java/lang/String.length:()I
        //   322: iconst_2       
        //   323: if_icmpeq       351
        //   326: new             Ljava/lang/StringBuilder;
        //   329: dup            
        //   330: invokespecial   java/lang/StringBuilder.<init>:()V
        //   333: ldc             "0"
        //   335: invokevirtual   java/lang/StringBuilder.append:(Ljava/lang/String;)Ljava/lang/StringBuilder;
        //   338: aload           month11
        //   340: invokevirtual   java/lang/StringBuilder.append:(Ljava/lang/String;)Ljava/lang/StringBuilder;
        //   343: invokevirtual   java/lang/StringBuilder.toString:()Ljava/lang/String;
        //   346: astore          month
        //   348: goto            355
        //   351: aload           month11
        //   353: astore          month
        //   355: aload           calendar
        //   357: iconst_5       
        //   358: invokevirtual   java/util/Calendar.get:(I)I
        //   361: invokestatic    java/lang/Integer.toString:(I)Ljava/lang/String;
        //   364: astore          date11
        //   366: ldc             ""
        //   368: astore          date1
        //   370: aload           date11
        //   372: invokevirtual   java/lang/String.length:()I
        //   375: iconst_2       
        //   376: if_icmpeq       404
        //   379: new             Ljava/lang/StringBuilder;
        //   382: dup            
        //   383: invokespecial   java/lang/StringBuilder.<init>:()V
        //   386: ldc             "0"
        //   388: invokevirtual   java/lang/StringBuilder.append:(Ljava/lang/String;)Ljava/lang/StringBuilder;
        //   391: aload           date11
        //   393: invokevirtual   java/lang/StringBuilder.append:(Ljava/lang/String;)Ljava/lang/StringBuilder;
        //   396: invokevirtual   java/lang/StringBuilder.toString:()Ljava/lang/String;
        //   399: astore          date1
        //   401: goto            408
        //   404: aload           date11
        //   406: astore          date1
        //   408: new             Ljava/lang/StringBuilder;
        //   411: dup            
        //   412: invokespecial   java/lang/StringBuilder.<init>:()V
        //   415: aload           calendar
        //   417: iconst_1       
        //   418: invokevirtual   java/util/Calendar.get:(I)I
        //   421: invokevirtual   java/lang/StringBuilder.append:(I)Ljava/lang/StringBuilder;
        //   424: ldc             "-"
        //   426: invokevirtual   java/lang/StringBuilder.append:(Ljava/lang/String;)Ljava/lang/StringBuilder;
        //   429: aload           month
        //   431: invokevirtual   java/lang/StringBuilder.append:(Ljava/lang/String;)Ljava/lang/StringBuilder;
        //   434: ldc             "-"
        //   436: invokevirtual   java/lang/StringBuilder.append:(Ljava/lang/String;)Ljava/lang/StringBuilder;
        //   439: aload           date1
        //   441: invokevirtual   java/lang/StringBuilder.append:(Ljava/lang/String;)Ljava/lang/StringBuilder;
        //   444: invokevirtual   java/lang/StringBuilder.toString:()Ljava/lang/String;
        //   447: astore          strDate1
        //   449: new             Ljava/lang/StringBuilder;
        //   452: dup            
        //   453: invokespecial   java/lang/StringBuilder.<init>:()V
        //   456: ldc             ""
        //   458: invokevirtual   java/lang/StringBuilder.append:(Ljava/lang/String;)Ljava/lang/StringBuilder;
        //   461: aload           calendar
        //   463: bipush          9
        //   465: invokevirtual   java/util/Calendar.get:(I)I
        //   468: invokevirtual   java/lang/StringBuilder.append:(I)Ljava/lang/StringBuilder;
        //   471: invokevirtual   java/lang/StringBuilder.toString:()Ljava/lang/String;
        //   474: astore          ampm
        //   476: aload_1         /* request */
        //   477: iconst_1       
        //   478: invokeinterface javax/servlet/http/HttpServletRequest.getSession:(Z)Ljavax/servlet/http/HttpSession;
        //   483: astore          mysession
        //   485: getstatic       learnityasmtserver/assessmentportal/standaloneasmt/StandAloneAssessment.log:Lorg/grlea/log/SimpleLogger;
        //   488: new             Ljava/lang/StringBuilder;
        //   491: dup            
        //   492: invokespecial   java/lang/StringBuilder.<init>:()V
        //   495: ldc             "student_id====="
        //   497: invokevirtual   java/lang/StringBuilder.append:(Ljava/lang/String;)Ljava/lang/StringBuilder;
        //   500: aload           student_id
        //   502: invokevirtual   java/lang/StringBuilder.append:(Ljava/lang/String;)Ljava/lang/StringBuilder;
        //   505: invokevirtual   java/lang/StringBuilder.toString:()Ljava/lang/String;
        //   508: invokevirtual   org/grlea/log/SimpleLogger.debug:(Ljava/lang/String;)V
        //   511: aload           student_id
        //   513: invokestatic    learnityasmtserver/assessmentportal/dbconnection/ReportDataBaseLayer.getSkinInfo:(Ljava/lang/String;)Ljava/lang/String;
        //   516: astore          skininfo
        //   518: new             Llearnityasmtserver/assessmentportal/dbconnection/ReportDataBaseLayer;
        //   521: dup            
        //   522: invokespecial   learnityasmtserver/assessmentportal/dbconnection/ReportDataBaseLayer.<init>:()V
        //   525: astore          ob1
        //   527: aload           ob1
        //   529: aload           student_id
        //   531: invokevirtual   learnityasmtserver/assessmentportal/dbconnection/ReportDataBaseLayer.getAssessmentInfo1:(Ljava/lang/String;)Ljava/util/Vector;
        //   534: astore          vAssessmentInfo
        //   536: aload_1         /* request */
        //   537: ldc             "checkbox"
        //   539: invokeinterface javax/servlet/http/HttpServletRequest.getParameter:(Ljava/lang/String;)Ljava/lang/String;
        //   544: astore          checkbox
        //   546: aload_1         /* request */
        //   547: ldc             "counter"
        //   549: invokeinterface javax/servlet/http/HttpServletRequest.getParameter:(Ljava/lang/String;)Ljava/lang/String;
        //   554: astore          counter
        //   556: ldc             "checkModelstatus"
        //   558: astore          checkModelstatus
        //   560: ldc             ""
        //   562: astore          avail_time
        //   564: ldc             ""
        //   566: astore          avail
        //   568: ldc             ""
        //   570: astore          valid
        //   572: ldc             ""
        //   574: astore          avail_date
        //   576: ldc             ""
        //   578: astore          valid_date
        //   580: ldc             ""
        //   582: astore          timeavailable
        //   584: aload           checkbox
        //   586: ifnull          929
        //   589: aload           vAssessmentInfo
        //   591: invokevirtual   java/util/Vector.size:()I
        //   594: ifeq            929
        //   597: aload           student_id
        //   599: aload           checkbox
        //   601: invokestatic    learnityasmtserver/assessmentportal/dbconnection/ReportDataBaseLayer.getAssessmentAvailablity:(Ljava/lang/String;Ljava/lang/String;)Ljava/util/Vector;
        //   604: astore          vAssessmentAvailablity
        //   606: aload           vAssessmentAvailablity
        //   608: invokevirtual   java/util/Vector.size:()I
        //   611: ifeq            929
        //   614: aload           vAssessmentAvailablity
        //   616: iconst_0       
        //   617: invokevirtual   java/util/Vector.elementAt:(I)Ljava/lang/Object;
        //   620: checkcast       [Ljava/lang/String;
        //   623: checkcast       [Ljava/lang/String;
        //   626: astore          AssessmentAvailablity
        //   628: aload           AssessmentAvailablity
        //   630: iconst_0       
        //   631: aaload         
        //   632: astore          avail_time
        //   634: aload           AssessmentAvailablity
        //   636: iconst_1       
        //   637: aaload         
        //   638: astore          avail_date
        //   640: aload           AssessmentAvailablity
        //   642: iconst_2       
        //   643: aaload         
        //   644: astore          avail
        //   646: aload           AssessmentAvailablity
        //   648: iconst_3       
        //   649: aaload         
        //   650: astore          valid_date
        //   652: aload           AssessmentAvailablity
        //   654: iconst_4       
        //   655: aaload         
        //   656: astore          valid
        //   658: aload           avail_date
        //   660: iconst_0       
        //   661: aload           avail_date
        //   663: ldc             " "
        //   665: invokevirtual   java/lang/String.indexOf:(Ljava/lang/String;)I
        //   668: invokevirtual   java/lang/String.substring:(II)Ljava/lang/String;
        //   671: astore          avail_date11
        //   673: iconst_0       
        //   674: istore          t1
        //   676: iconst_0       
        //   677: istore          t2
        //   679: iconst_0       
        //   680: istore          t11
        //   682: iconst_0       
        //   683: istore          t22
        //   685: aload           avail
        //   687: ldc             "Available"
        //   689: invokevirtual   java/lang/String.equals:(Ljava/lang/Object;)Z
        //   692: ifeq            879
        //   695: aload           avail_date11
        //   697: aload           strDate1
        //   699: invokevirtual   java/lang/String.equals:(Ljava/lang/Object;)Z
        //   702: ifeq            879
        //   705: aload           avail_time
        //   707: ldc             ""
        //   709: invokevirtual   java/lang/String.equals:(Ljava/lang/Object;)Z
        //   712: ifne            879
        //   715: aload           avail_time
        //   717: iconst_0       
        //   718: aload           avail_time
        //   720: bipush          58
        //   722: invokevirtual   java/lang/String.indexOf:(I)I
        //   725: invokevirtual   java/lang/String.substring:(II)Ljava/lang/String;
        //   728: astore          str1
        //   730: aload           avail_time
        //   732: aload           avail_time
        //   734: bipush          58
        //   736: invokevirtual   java/lang/String.indexOf:(I)I
        //   739: iconst_1       
        //   740: iadd           
        //   741: invokevirtual   java/lang/String.substring:(I)Ljava/lang/String;
        //   744: astore          str2
        //   746: aload           str2
        //   748: iconst_0       
        //   749: aload           str2
        //   751: bipush          58
        //   753: invokevirtual   java/lang/String.indexOf:(I)I
        //   756: invokevirtual   java/lang/String.substring:(II)Ljava/lang/String;
        //   759: astore          str3
        //   761: aload           strTime
        //   763: iconst_0       
        //   764: aload           strTime
        //   766: bipush          58
        //   768: invokevirtual   java/lang/String.indexOf:(I)I
        //   771: invokevirtual   java/lang/String.substring:(II)Ljava/lang/String;
        //   774: astore          str11
        //   776: aload           strTime
        //   778: aload           strTime
        //   780: bipush          58
        //   782: invokevirtual   java/lang/String.indexOf:(I)I
        //   785: iconst_1       
        //   786: iadd           
        //   787: invokevirtual   java/lang/String.substring:(I)Ljava/lang/String;
        //   790: astore          str22
        //   792: aload           str22
        //   794: iconst_0       
        //   795: aload           str22
        //   797: bipush          58
        //   799: invokevirtual   java/lang/String.indexOf:(I)I
        //   802: invokevirtual   java/lang/String.substring:(II)Ljava/lang/String;
        //   805: astore          str33
        //   807: aload           str1
        //   809: invokestatic    java/lang/Integer.parseInt:(Ljava/lang/String;)I
        //   812: istore          t1
        //   814: aload           str3
        //   816: invokestatic    java/lang/Integer.parseInt:(Ljava/lang/String;)I
        //   819: istore          t2
        //   821: aload           str11
        //   823: invokestatic    java/lang/Integer.parseInt:(Ljava/lang/String;)I
        //   826: istore          timeformat1
        //   828: aload           ampm
        //   830: ldc             "1"
        //   832: invokevirtual   java/lang/String.equals:(Ljava/lang/Object;)Z
        //   835: ifeq            865
        //   838: iload           timeformat1
        //   840: bipush          12
        //   842: if_icmpgt       865
        //   845: aload           str11
        //   847: invokestatic    java/lang/Integer.parseInt:(Ljava/lang/String;)I
        //   850: bipush          12
        //   852: iadd           
        //   853: istore          t11
        //   855: aload           str33
        //   857: invokestatic    java/lang/Integer.parseInt:(Ljava/lang/String;)I
        //   860: istore          t22
        //   862: goto            879
        //   865: aload           str11
        //   867: invokestatic    java/lang/Integer.parseInt:(Ljava/lang/String;)I
        //   870: istore          t11
        //   872: aload           str33
        //   874: invokestatic    java/lang/Integer.parseInt:(Ljava/lang/String;)I
        //   877: istore          t22
        //   879: iload           t1
        //   881: iload           t11
        //   883: if_icmpgt       918
        //   886: iload           t1
        //   888: iload           t11
        //   890: if_icmpge       900
        //   893: ldc             "Available"
        //   895: astore          timeavailable
        //   897: goto            918
        //   900: iload           t2
        //   902: iload           t22
        //   904: if_icmpgt       914
        //   907: ldc             "Available"
        //   909: astore          timeavailable
        //   911: goto            918
        //   914: ldc             "Not Available"
        //   916: astore          timeavailable
        //   918: iload           t1
        //   920: iload           t11
        //   922: if_icmple       929
        //   925: ldc             "Not Available"
        //   927: astore          timeavailable
        //   929: aload           ob1
        //   931: aload           student_id
        //   933: invokevirtual   learnityasmtserver/assessmentportal/dbconnection/ReportDataBaseLayer.getAssessmentInfogroup:(Ljava/lang/String;)Ljava/util/Vector;
        //   936: astore          vAssessmentInfogroup
        //   938: aload           checkbox
        //   940: ifnull          1283
        //   943: aload           vAssessmentInfogroup
        //   945: invokevirtual   java/util/Vector.size:()I
        //   948: ifeq            1283
        //   951: aload           student_id
        //   953: aload           checkbox
        //   955: invokestatic    learnityasmtserver/assessmentportal/dbconnection/ReportDataBaseLayer.getAssessmentGroupAvailablity:(Ljava/lang/String;Ljava/lang/String;)Ljava/util/Vector;
        //   958: astore          vAssessmentAvailablity
        //   960: aload           vAssessmentAvailablity
        //   962: invokevirtual   java/util/Vector.size:()I
        //   965: ifeq            1283
        //   968: aload           vAssessmentAvailablity
        //   970: iconst_0       
        //   971: invokevirtual   java/util/Vector.elementAt:(I)Ljava/lang/Object;
        //   974: checkcast       [Ljava/lang/String;
        //   977: checkcast       [Ljava/lang/String;
        //   980: astore          AssessmentAvailablity
        //   982: aload           AssessmentAvailablity
        //   984: iconst_0       
        //   985: aaload         
        //   986: astore          avail_time
        //   988: aload           AssessmentAvailablity
        //   990: iconst_1       
        //   991: aaload         
        //   992: astore          avail_date
        //   994: aload           AssessmentAvailablity
        //   996: iconst_2       
        //   997: aaload         
        //   998: astore          avail
        //  1000: aload           AssessmentAvailablity
        //  1002: iconst_3       
        //  1003: aaload         
        //  1004: astore          valid_date
        //  1006: aload           AssessmentAvailablity
        //  1008: iconst_4       
        //  1009: aaload         
        //  1010: astore          valid
        //  1012: aload           avail_date
        //  1014: iconst_0       
        //  1015: aload           avail_date
        //  1017: ldc             " "
        //  1019: invokevirtual   java/lang/String.indexOf:(Ljava/lang/String;)I
        //  1022: invokevirtual   java/lang/String.substring:(II)Ljava/lang/String;
        //  1025: astore          avail_date11
        //  1027: iconst_0       
        //  1028: istore          t1
        //  1030: iconst_0       
        //  1031: istore          t2
        //  1033: iconst_0       
        //  1034: istore          t11
        //  1036: iconst_0       
        //  1037: istore          t22
        //  1039: aload           avail
        //  1041: ldc             "Available"
        //  1043: invokevirtual   java/lang/String.equals:(Ljava/lang/Object;)Z
        //  1046: ifeq            1233
        //  1049: aload           avail_date11
        //  1051: aload           strDate1
        //  1053: invokevirtual   java/lang/String.equals:(Ljava/lang/Object;)Z
        //  1056: ifeq            1233
        //  1059: aload           avail_time
        //  1061: ldc             ""
        //  1063: invokevirtual   java/lang/String.equals:(Ljava/lang/Object;)Z
        //  1066: ifne            1233
        //  1069: aload           avail_time
        //  1071: iconst_0       
        //  1072: aload           avail_time
        //  1074: bipush          58
        //  1076: invokevirtual   java/lang/String.indexOf:(I)I
        //  1079: invokevirtual   java/lang/String.substring:(II)Ljava/lang/String;
        //  1082: astore          str1
        //  1084: aload           avail_time
        //  1086: aload           avail_time
        //  1088: bipush          58
        //  1090: invokevirtual   java/lang/String.indexOf:(I)I
        //  1093: iconst_1       
        //  1094: iadd           
        //  1095: invokevirtual   java/lang/String.substring:(I)Ljava/lang/String;
        //  1098: astore          str2
        //  1100: aload           str2
        //  1102: iconst_0       
        //  1103: aload           str2
        //  1105: bipush          58
        //  1107: invokevirtual   java/lang/String.indexOf:(I)I
        //  1110: invokevirtual   java/lang/String.substring:(II)Ljava/lang/String;
        //  1113: astore          str3
        //  1115: aload           strTime
        //  1117: iconst_0       
        //  1118: aload           strTime
        //  1120: bipush          58
        //  1122: invokevirtual   java/lang/String.indexOf:(I)I
        //  1125: invokevirtual   java/lang/String.substring:(II)Ljava/lang/String;
        //  1128: astore          str11
        //  1130: aload           strTime
        //  1132: aload           strTime
        //  1134: bipush          58
        //  1136: invokevirtual   java/lang/String.indexOf:(I)I
        //  1139: iconst_1       
        //  1140: iadd           
        //  1141: invokevirtual   java/lang/String.substring:(I)Ljava/lang/String;
        //  1144: astore          str22
        //  1146: aload           str22
        //  1148: iconst_0       
        //  1149: aload           str22
        //  1151: bipush          58
        //  1153: invokevirtual   java/lang/String.indexOf:(I)I
        //  1156: invokevirtual   java/lang/String.substring:(II)Ljava/lang/String;
        //  1159: astore          str33
        //  1161: aload           str1
        //  1163: invokestatic    java/lang/Integer.parseInt:(Ljava/lang/String;)I
        //  1166: istore          t1
        //  1168: aload           str3
        //  1170: invokestatic    java/lang/Integer.parseInt:(Ljava/lang/String;)I
        //  1173: istore          t2
        //  1175: aload           str11
        //  1177: invokestatic    java/lang/Integer.parseInt:(Ljava/lang/String;)I
        //  1180: istore          timeformat1
        //  1182: aload           ampm
        //  1184: ldc             "1"
        //  1186: invokevirtual   java/lang/String.equals:(Ljava/lang/Object;)Z
        //  1189: ifeq            1219
        //  1192: iload           timeformat1
        //  1194: bipush          12
        //  1196: if_icmpgt       1219
        //  1199: aload           str11
        //  1201: invokestatic    java/lang/Integer.parseInt:(Ljava/lang/String;)I
        //  1204: bipush          12
        //  1206: iadd           
        //  1207: istore          t11
        //  1209: aload           str33
        //  1211: invokestatic    java/lang/Integer.parseInt:(Ljava/lang/String;)I
        //  1214: istore          t22
        //  1216: goto            1233
        //  1219: aload           str11
        //  1221: invokestatic    java/lang/Integer.parseInt:(Ljava/lang/String;)I
        //  1224: istore          t11
        //  1226: aload           str33
        //  1228: invokestatic    java/lang/Integer.parseInt:(Ljava/lang/String;)I
        //  1231: istore          t22
        //  1233: iload           t1
        //  1235: iload           t11
        //  1237: if_icmpgt       1272
        //  1240: iload           t1
        //  1242: iload           t11
        //  1244: if_icmpge       1254
        //  1247: ldc             "Available"
        //  1249: astore          timeavailable
        //  1251: goto            1272
        //  1254: iload           t2
        //  1256: iload           t22
        //  1258: if_icmpgt       1268
        //  1261: ldc             "Available"
        //  1263: astore          timeavailable
        //  1265: goto            1272
        //  1268: ldc             "Not Available"
        //  1270: astore          timeavailable
        //  1272: iload           t1
        //  1274: iload           t11
        //  1276: if_icmple       1283
        //  1279: ldc             "Not Available"
        //  1281: astore          timeavailable
        //  1283: ldc             ""
        //  1285: astore          MaxtestTeken
        //  1287: ldc             "0"
        //  1289: astore          nooftimesappeared
        //  1291: ldc             ""
        //  1293: astore          astatus
        //  1295: ldc             ""
        //  1297: astore          save_state
        //  1299: aload           checkbox
        //  1301: ifnull          1365
        //  1304: aload           ob1
        //  1306: aload           checkbox
        //  1308: invokevirtual   learnityasmtserver/assessmentportal/dbconnection/ReportDataBaseLayer.getMaxtestTaken:(Ljava/lang/String;)Ljava/lang/String;
        //  1311: astore          MaxtestTeken
        //  1313: aload           ob1
        //  1315: aload           student_id
        //  1317: aload           checkbox
        //  1319: invokevirtual   learnityasmtserver/assessmentportal/dbconnection/ReportDataBaseLayer.getMaxNoAppearedInTest:(Ljava/lang/String;Ljava/lang/String;)Ljava/lang/String;
        //  1322: astore          nooftimesappeared
        //  1324: aload           ob1
        //  1326: aload           student_id
        //  1328: aload           checkbox
        //  1330: invokevirtual   learnityasmtserver/assessmentportal/dbconnection/ReportDataBaseLayer.isPreviousTestSubmitted:(Ljava/lang/String;Ljava/lang/String;)Ljava/util/Vector;
        //  1333: astore          vv
        //  1335: aload           vv
        //  1337: invokevirtual   java/util/Vector.size:()I
        //  1340: ifeq            1365
        //  1343: aload           vv
        //  1345: iconst_0       
        //  1346: invokevirtual   java/util/Vector.elementAt:(I)Ljava/lang/Object;
        //  1349: checkcast       Ljava/lang/String;
        //  1352: astore          astatus
        //  1354: aload           vv
        //  1356: iconst_1       
        //  1357: invokevirtual   java/util/Vector.elementAt:(I)Ljava/lang/Object;
        //  1360: checkcast       Ljava/lang/String;
        //  1363: astore          save_state
        //  1365: getstatic       learnityasmtserver/assessmentportal/standaloneasmt/StandAloneAssessment.log:Lorg/grlea/log/SimpleLogger;
        //  1368: new             Ljava/lang/StringBuilder;
        //  1371: dup            
        //  1372: invokespecial   java/lang/StringBuilder.<init>:()V
        //  1375: ldc             "save_state==1=="
        //  1377: invokevirtual   java/lang/StringBuilder.append:(Ljava/lang/String;)Ljava/lang/StringBuilder;
        //  1380: aload           save_state
        //  1382: invokevirtual   java/lang/StringBuilder.append:(Ljava/lang/String;)Ljava/lang/StringBuilder;
        //  1385: invokevirtual   java/lang/StringBuilder.toString:()Ljava/lang/String;
        //  1388: invokevirtual   org/grlea/log/SimpleLogger.debug:(Ljava/lang/String;)V
        //  1391: aload           save_state
        //  1393: ifnonnull       1403
        //  1396: ldc             ""
        //  1398: astore          save_state
        //  1400: goto            1407
        //  1403: ldc             "no"
        //  1405: astore          save_state
        //  1407: getstatic       learnityasmtserver/assessmentportal/standaloneasmt/StandAloneAssessment.log:Lorg/grlea/log/SimpleLogger;
        //  1410: new             Ljava/lang/StringBuilder;
        //  1413: dup            
        //  1414: invokespecial   java/lang/StringBuilder.<init>:()V
        //  1417: ldc             "save_state==2=="
        //  1419: invokevirtual   java/lang/StringBuilder.append:(Ljava/lang/String;)Ljava/lang/StringBuilder;
        //  1422: aload           save_state
        //  1424: invokevirtual   java/lang/StringBuilder.append:(Ljava/lang/String;)Ljava/lang/StringBuilder;
        //  1427: invokevirtual   java/lang/StringBuilder.toString:()Ljava/lang/String;
        //  1430: invokevirtual   org/grlea/log/SimpleLogger.debug:(Ljava/lang/String;)V
        //  1433: new             Ljava/lang/StringBuilder;
        //  1436: dup            
        //  1437: invokespecial   java/lang/StringBuilder.<init>:()V
        //  1440: ldc             "You have already appeared for this test. You cannot appear for it again. [ Number of times appeared :- "
        //  1442: invokevirtual   java/lang/StringBuilder.append:(Ljava/lang/String;)Ljava/lang/StringBuilder;
        //  1445: aload           MaxtestTeken
        //  1447: invokevirtual   java/lang/StringBuilder.append:(Ljava/lang/String;)Ljava/lang/StringBuilder;
        //  1450: ldc             " ]"
        //  1452: invokevirtual   java/lang/StringBuilder.append:(Ljava/lang/String;)Ljava/lang/StringBuilder;
        //  1455: invokevirtual   java/lang/StringBuilder.toString:()Ljava/lang/String;
        //  1458: astore          ms
        //  1460: new             Ljava/lang/StringBuilder;
        //  1463: dup            
        //  1464: invokespecial   java/lang/StringBuilder.<init>:()V
        //  1467: ldc             "\n function test() {\n\t\tvar index = 0;\n\t\tfor (var i=0;i<document.frm.elements.length;i++){\n\t\t\tvar e = document.frm.elements[i];\n\t\t\tif (e.type=='radio'){\n\t\t\t\tindex++;\n\t\t\t}\n\t\t}\n\t\treturn index;\n  }\n function check_onclick(){\n\t\tvar i = test();\n\t\tif(i>1) {\n\t\t\tfor(var counter=0; counter<document.frm.checkbox.length; counter++) {\n\t\t\t\tif(document.frm.checkbox[counter].checked) {\n \t\t\t\t\t\tvar cnt=counter;\n\t\t\t\t\t\tdocument.frm.method = \"post\";\n \t\t\t\t\t\tvar temp=document.frm.checkbox[counter].value;\n     \t\t\t\t\tdocument.frm.action=\"./learnityasmtserver.assessmentportal.standaloneasmt.StandAloneAssessment?checkbox=\"+document.frm.checkbox[counter].value+\"&counter=\"+cnt+\"\";\n\t\t\t\t\t\tdocument.frm.submit();\n\t\t\t\t\t\tbreak;\n\t\t\t\t}\n\t\t\t}\n\t\t}\n\t\tif (i==1) {\n\t\t\tif(document.frm.checkbox.checked) {\n\t\t\t\t\tdocument.frm.method = \"post\";\n     \t\t\t\tdocument.frm.action=\"./learnityasmtserver.assessmentportal.standaloneasmt.StandAloneAssessment?checkbox=\"+document.frm.checkbox.value+\"\";\n\t\t\t\t\tdocument.frm.submit();\n\t\t\t}\n\t\t}\n\t}\n  function load() {\n \t\tvar count=\""
        //  1469: invokevirtual   java/lang/StringBuilder.append:(Ljava/lang/String;)Ljava/lang/StringBuilder;
        //  1472: aload           counter
        //  1474: invokevirtual   java/lang/StringBuilder.append:(Ljava/lang/String;)Ljava/lang/StringBuilder;
        //  1477: ldc             "\";"
        //  1479: invokevirtual   java/lang/StringBuilder.append:(Ljava/lang/String;)Ljava/lang/StringBuilder;
        //  1482: ldc             "\n  \t\tvar ass_id=\""
        //  1484: invokevirtual   java/lang/StringBuilder.append:(Ljava/lang/String;)Ljava/lang/StringBuilder;
        //  1487: aload           checkbox
        //  1489: invokevirtual   java/lang/StringBuilder.append:(Ljava/lang/String;)Ljava/lang/StringBuilder;
        //  1492: ldc             "\";"
        //  1494: invokevirtual   java/lang/StringBuilder.append:(Ljava/lang/String;)Ljava/lang/StringBuilder;
        //  1497: ldc             "\n\t\tvar i = test();"
        //  1499: invokevirtual   java/lang/StringBuilder.append:(Ljava/lang/String;)Ljava/lang/StringBuilder;
        //  1502: ldc             "\n   \t\tif(ass_id!=\"null\") {"
        //  1504: invokevirtual   java/lang/StringBuilder.append:(Ljava/lang/String;)Ljava/lang/StringBuilder;
        //  1507: ldc             "\n\t\t\tdocument.frm.checkbox1.value=ass_id;"
        //  1509: invokevirtual   java/lang/StringBuilder.append:(Ljava/lang/String;)Ljava/lang/StringBuilder;
        //  1512: ldc             "\n\t\t  \tif(i>1) {"
        //  1514: invokevirtual   java/lang/StringBuilder.append:(Ljava/lang/String;)Ljava/lang/StringBuilder;
        //  1517: ldc             "\n       \t\t\t\tdocument.frm.checkbox[count].checked=true;"
        //  1519: invokevirtual   java/lang/StringBuilder.append:(Ljava/lang/String;)Ljava/lang/StringBuilder;
        //  1522: ldc             "\n       \t\t}"
        //  1524: invokevirtual   java/lang/StringBuilder.append:(Ljava/lang/String;)Ljava/lang/StringBuilder;
        //  1527: ldc             "\n\t\t  \tif(i==1) {"
        //  1529: invokevirtual   java/lang/StringBuilder.append:(Ljava/lang/String;)Ljava/lang/StringBuilder;
        //  1532: ldc             "\n       \t\t\t\tdocument.frm.checkbox.checked=true;"
        //  1534: invokevirtual   java/lang/StringBuilder.append:(Ljava/lang/String;)Ljava/lang/StringBuilder;
        //  1537: ldc             "\n      \t\t}"
        //  1539: invokevirtual   java/lang/StringBuilder.append:(Ljava/lang/String;)Ljava/lang/StringBuilder;
        //  1542: ldc             "\n    \t\t}"
        //  1544: invokevirtual   java/lang/StringBuilder.append:(Ljava/lang/String;)Ljava/lang/StringBuilder;
        //  1547: ldc             "\n  }"
        //  1549: invokevirtual   java/lang/StringBuilder.append:(Ljava/lang/String;)Ljava/lang/StringBuilder;
        //  1552: ldc             "\n   function help_onClick()"
        //  1554: invokevirtual   java/lang/StringBuilder.append:(Ljava/lang/String;)Ljava/lang/StringBuilder;
        //  1557: ldc             "\n   { "
        //  1559: invokevirtual   java/lang/StringBuilder.append:(Ljava/lang/String;)Ljava/lang/StringBuilder;
        //  1562: ldc             "\n     \twindow.open('../html/AssessmentInstructions.html','_blank','width=800,height=500,status=yes,menubar=no,scrollbars=yes,resizeable=yes');"
        //  1564: invokevirtual   java/lang/StringBuilder.append:(Ljava/lang/String;)Ljava/lang/StringBuilder;
        //  1567: ldc             "\n   }"
        //  1569: invokevirtual   java/lang/StringBuilder.append:(Ljava/lang/String;)Ljava/lang/StringBuilder;
        //  1572: ldc             "\n\tvar count1 = 0;"
        //  1574: invokevirtual   java/lang/StringBuilder.append:(Ljava/lang/String;)Ljava/lang/StringBuilder;
        //  1577: ldc             "\n function start_onclick(){"
        //  1579: invokevirtual   java/lang/StringBuilder.append:(Ljava/lang/String;)Ljava/lang/StringBuilder;
        //  1582: ldc             "\n\tvar checkModelstatus = \""
        //  1584: invokevirtual   java/lang/StringBuilder.append:(Ljava/lang/String;)Ljava/lang/StringBuilder;
        //  1587: aload           checkModelstatus
        //  1589: invokevirtual   java/lang/StringBuilder.append:(Ljava/lang/String;)Ljava/lang/StringBuilder;
        //  1592: ldc             "\";"
        //  1594: invokevirtual   java/lang/StringBuilder.append:(Ljava/lang/String;)Ljava/lang/StringBuilder;
        //  1597: ldc             "\n\tvar timeavailable = \""
        //  1599: invokevirtual   java/lang/StringBuilder.append:(Ljava/lang/String;)Ljava/lang/StringBuilder;
        //  1602: aload           timeavailable
        //  1604: invokevirtual   java/lang/StringBuilder.append:(Ljava/lang/String;)Ljava/lang/StringBuilder;
        //  1607: ldc             "\";"
        //  1609: invokevirtual   java/lang/StringBuilder.append:(Ljava/lang/String;)Ljava/lang/StringBuilder;
        //  1612: ldc             "\n\tvar avail1 = \""
        //  1614: invokevirtual   java/lang/StringBuilder.append:(Ljava/lang/String;)Ljava/lang/StringBuilder;
        //  1617: aload           avail
        //  1619: invokevirtual   java/lang/StringBuilder.append:(Ljava/lang/String;)Ljava/lang/StringBuilder;
        //  1622: ldc             "\";"
        //  1624: invokevirtual   java/lang/StringBuilder.append:(Ljava/lang/String;)Ljava/lang/StringBuilder;
        //  1627: ldc             "\n\tvar valid1 = \""
        //  1629: invokevirtual   java/lang/StringBuilder.append:(Ljava/lang/String;)Ljava/lang/StringBuilder;
        //  1632: aload           valid
        //  1634: invokevirtual   java/lang/StringBuilder.append:(Ljava/lang/String;)Ljava/lang/StringBuilder;
        //  1637: ldc             "\";"
        //  1639: invokevirtual   java/lang/StringBuilder.append:(Ljava/lang/String;)Ljava/lang/StringBuilder;
        //  1642: ldc             "\n\tvar MaxtestTeken = \""
        //  1644: invokevirtual   java/lang/StringBuilder.append:(Ljava/lang/String;)Ljava/lang/StringBuilder;
        //  1647: aload           MaxtestTeken
        //  1649: invokevirtual   java/lang/StringBuilder.append:(Ljava/lang/String;)Ljava/lang/StringBuilder;
        //  1652: ldc             "\";"
        //  1654: invokevirtual   java/lang/StringBuilder.append:(Ljava/lang/String;)Ljava/lang/StringBuilder;
        //  1657: ldc             "\n\tvar nooftimesappeared = \""
        //  1659: invokevirtual   java/lang/StringBuilder.append:(Ljava/lang/String;)Ljava/lang/StringBuilder;
        //  1662: aload           nooftimesappeared
        //  1664: invokevirtual   java/lang/StringBuilder.append:(Ljava/lang/String;)Ljava/lang/StringBuilder;
        //  1667: ldc             "\";"
        //  1669: invokevirtual   java/lang/StringBuilder.append:(Ljava/lang/String;)Ljava/lang/StringBuilder;
        //  1672: ldc             "\n  \tvar message = \""
        //  1674: invokevirtual   java/lang/StringBuilder.append:(Ljava/lang/String;)Ljava/lang/StringBuilder;
        //  1677: aload           ms
        //  1679: invokevirtual   java/lang/StringBuilder.append:(Ljava/lang/String;)Ljava/lang/StringBuilder;
        //  1682: ldc             "\";"
        //  1684: invokevirtual   java/lang/StringBuilder.append:(Ljava/lang/String;)Ljava/lang/StringBuilder;
        //  1687: ldc             "\n\tvar sumissionsatatus=\""
        //  1689: invokevirtual   java/lang/StringBuilder.append:(Ljava/lang/String;)Ljava/lang/StringBuilder;
        //  1692: aload           astatus
        //  1694: invokevirtual   java/lang/StringBuilder.append:(Ljava/lang/String;)Ljava/lang/StringBuilder;
        //  1697: ldc             "\";"
        //  1699: invokevirtual   java/lang/StringBuilder.append:(Ljava/lang/String;)Ljava/lang/StringBuilder;
        //  1702: ldc             "\n\tvar save_state=\""
        //  1704: invokevirtual   java/lang/StringBuilder.append:(Ljava/lang/String;)Ljava/lang/StringBuilder;
        //  1707: aload           save_state
        //  1709: invokevirtual   java/lang/StringBuilder.append:(Ljava/lang/String;)Ljava/lang/StringBuilder;
        //  1712: ldc             "\";"
        //  1714: invokevirtual   java/lang/StringBuilder.append:(Ljava/lang/String;)Ljava/lang/StringBuilder;
        //  1717: ldc             "\n\tvar student_id=\""
        //  1719: invokevirtual   java/lang/StringBuilder.append:(Ljava/lang/String;)Ljava/lang/StringBuilder;
        //  1722: aload           student_id
        //  1724: invokevirtual   java/lang/StringBuilder.append:(Ljava/lang/String;)Ljava/lang/StringBuilder;
        //  1727: ldc             "\";"
        //  1729: invokevirtual   java/lang/StringBuilder.append:(Ljava/lang/String;)Ljava/lang/StringBuilder;
        //  1732: ldc             "\n  \tvar browserName = navigator.appName;"
        //  1734: invokevirtual   java/lang/StringBuilder.append:(Ljava/lang/String;)Ljava/lang/StringBuilder;
        //  1737: ldc             "\n  \tvar browserVersion = parseInt(navigator.appVersion);"
        //  1739: invokevirtual   java/lang/StringBuilder.append:(Ljava/lang/String;)Ljava/lang/StringBuilder;
        //  1742: ldc             "\n   \tif(document.frm.checkbox1.value!=\"\") {"
        //  1744: invokevirtual   java/lang/StringBuilder.append:(Ljava/lang/String;)Ljava/lang/StringBuilder;
        //  1747: ldc             "\n   \t\t\tif((MaxtestTeken!=\"\") && (Number(MaxtestTeken)>Number(nooftimesappeared))) {"
        //  1749: invokevirtual   java/lang/StringBuilder.append:(Ljava/lang/String;)Ljava/lang/StringBuilder;
        //  1752: ldc             "\n\t\t\t\tif(valid1 == \"Available\")"
        //  1754: invokevirtual   java/lang/StringBuilder.append:(Ljava/lang/String;)Ljava/lang/StringBuilder;
        //  1757: ldc             "\n     \t\t\t{"
        //  1759: invokevirtual   java/lang/StringBuilder.append:(Ljava/lang/String;)Ljava/lang/StringBuilder;
        //  1762: ldc             "\n\t\t\t\t\tif((avail1 == \"Available\") && (timeavailable == \"Available\"))"
        //  1764: invokevirtual   java/lang/StringBuilder.append:(Ljava/lang/String;)Ljava/lang/StringBuilder;
        //  1767: ldc             "\n     \t\t\t\t{"
        //  1769: invokevirtual   java/lang/StringBuilder.append:(Ljava/lang/String;)Ljava/lang/StringBuilder;
        //  1772: ldc             "\n\t\t\t\t\t\tif(browserName == \"Microsoft Internet Explorer\" && browserVersion >=4)"
        //  1774: invokevirtual   java/lang/StringBuilder.append:(Ljava/lang/String;)Ljava/lang/StringBuilder;
        //  1777: ldc             "\n     \t\t\t\t\t{"
        //  1779: invokevirtual   java/lang/StringBuilder.append:(Ljava/lang/String;)Ljava/lang/StringBuilder;
        //  1782: ldc             "\n\t\t\t\t\t\t\tif((sumissionsatatus==\"\") || (sumissionsatatus == \"Submitted\"))"
        //  1784: invokevirtual   java/lang/StringBuilder.append:(Ljava/lang/String;)Ljava/lang/StringBuilder;
        //  1787: ldc             "\n\t\t\t\t\t\t\t{"
        //  1789: invokevirtual   java/lang/StringBuilder.append:(Ljava/lang/String;)Ljava/lang/StringBuilder;
        //  1792: ldc             "\n  \t\t\t\t\t\t\t\t\tif(count1!=0) {"
        //  1794: invokevirtual   java/lang/StringBuilder.append:(Ljava/lang/String;)Ljava/lang/StringBuilder;
        //  1797: ldc             "\n\t\t\t\t\t\t\t\t\t\twindow.open(\"./learnityasmtserver.assessmentportal.standaloneasmt.CheckAvailabilityOfTest?newtest=start&browserName=\"+browserName+\"&sumissionsatatus=\"+sumissionsatatus+\"&checkModelstatus=\"+checkModelstatus+\"&assessment_id=\"+document.frm.checkbox1.value+\"&student_id=\"+student_id+\"\",\"new1\",\"height=700,width=800,status=yes,scrollbars=yes,manubar=no,toolbar=no\");"
        //  1799: invokevirtual   java/lang/StringBuilder.append:(Ljava/lang/String;)Ljava/lang/StringBuilder;
        //  1802: ldc             "\n   \t\t\t\t\t\t\t\t\t}"
        //  1804: invokevirtual   java/lang/StringBuilder.append:(Ljava/lang/String;)Ljava/lang/StringBuilder;
        //  1807: ldc             "\n  \t\t\t\t\t\t\t\t\telse {"
        //  1809: invokevirtual   java/lang/StringBuilder.append:(Ljava/lang/String;)Ljava/lang/StringBuilder;
        //  1812: ldc             "\n\t\t\t\t\t\t\t\t\t\tcount1 = Number(count1)+1;"
        //  1814: invokevirtual   java/lang/StringBuilder.append:(Ljava/lang/String;)Ljava/lang/StringBuilder;
        //  1817: ldc             "\n   \t\t\t\t\t\t\t\t\t\twindow.open(\"./learnityasmtserver.assessmentportal.standaloneasmt.GenerateStAloneTestHTML?newtest=start&checkModelstatus=\"+checkModelstatus+\"&assessment_id=\"+document.frm.checkbox1.value+\"\",\"new\",\"height=700,width=800,status=yes,scrollbars=yes,resizable=yes,manubar=no,toolbar=no\");"
        //  1819: invokevirtual   java/lang/StringBuilder.append:(Ljava/lang/String;)Ljava/lang/StringBuilder;
        //  1822: ldc             "\n\t\t\t\t\t\t\t\t\t}"
        //  1824: invokevirtual   java/lang/StringBuilder.append:(Ljava/lang/String;)Ljava/lang/StringBuilder;
        //  1827: ldc             "\n\t\t\t\t\t\t\t}"
        //  1829: invokevirtual   java/lang/StringBuilder.append:(Ljava/lang/String;)Ljava/lang/StringBuilder;
        //  1832: ldc             "\n\t\t\t\t\t\t\telse {"
        //  1834: invokevirtual   java/lang/StringBuilder.append:(Ljava/lang/String;)Ljava/lang/StringBuilder;
        //  1837: ldc             "\n\t\t\t\t\t\t\t\tif(save_state==\"\") {"
        //  1839: invokevirtual   java/lang/StringBuilder.append:(Ljava/lang/String;)Ljava/lang/StringBuilder;
        //  1842: ldc             "\n  \t\t\t\t\t\t\t\t\tif(count1!=0) {"
        //  1844: invokevirtual   java/lang/StringBuilder.append:(Ljava/lang/String;)Ljava/lang/StringBuilder;
        //  1847: ldc             "\n\t\t\t\t\t\t\t\t\t\twindow.open(\"./learnityasmtserver.assessmentportal.standaloneasmt.CheckAvailabilityOfTest?newtest=start&save_state=no&browserName=\"+browserName+\"&sumissionsatatus=\"+sumissionsatatus+\"&checkModelstatus=\"+checkModelstatus+\"&assessment_id=\"+document.frm.checkbox1.value+\"&student_id=\"+student_id+\"\",\"new1\",\"height=700,width=800,status=yes,scrollbars=yes,manubar=no,toolbar=no\");"
        //  1849: invokevirtual   java/lang/StringBuilder.append:(Ljava/lang/String;)Ljava/lang/StringBuilder;
        //  1852: ldc             "\n   \t\t\t\t\t\t\t\t\t}"
        //  1854: invokevirtual   java/lang/StringBuilder.append:(Ljava/lang/String;)Ljava/lang/StringBuilder;
        //  1857: ldc             "\n  \t\t\t\t\t\t\t\t\telse {"
        //  1859: invokevirtual   java/lang/StringBuilder.append:(Ljava/lang/String;)Ljava/lang/StringBuilder;
        //  1862: ldc             "\n\t\t\t\t\t\t\t\t\t\tcount1 = Number(count1)+1;"
        //  1864: invokevirtual   java/lang/StringBuilder.append:(Ljava/lang/String;)Ljava/lang/StringBuilder;
        //  1867: ldc             "\n   \t\t\t\t\t\t\t\t\t\twindow.open(\"./learnityasmtserver.assessmentportal.standaloneasmt.GenerateStAloneTestHTML?newtest=start&save_state=no&checkModelstatus=\"+checkModelstatus+\"&assessment_id=\"+document.frm.checkbox1.value+\"\",\"new\",\"height=700,width=800,status=yes,scrollbars=yes,resizable=yes,manubar=no,toolbar=no\");"
        //  1869: invokevirtual   java/lang/StringBuilder.append:(Ljava/lang/String;)Ljava/lang/StringBuilder;
        //  1872: ldc             "\n\t\t\t\t\t\t\t\t\t}"
        //  1874: invokevirtual   java/lang/StringBuilder.append:(Ljava/lang/String;)Ljava/lang/StringBuilder;
        //  1877: ldc             "\n\t\t\t\t\t\t\t\t}"
        //  1879: invokevirtual   java/lang/StringBuilder.append:(Ljava/lang/String;)Ljava/lang/StringBuilder;
        //  1882: ldc             "\n\t\t\t\t\t\t\t\telse {"
        //  1884: invokevirtual   java/lang/StringBuilder.append:(Ljava/lang/String;)Ljava/lang/StringBuilder;
        //  1887: ldc             "\n  \t\t\t\t\t\t\t\t\tif(count1!=0) {"
        //  1889: invokevirtual   java/lang/StringBuilder.append:(Ljava/lang/String;)Ljava/lang/StringBuilder;
        //  1892: ldc             "\n\t\t\t\t\t\t\t\t\t\twindow.open(\"./learnityasmtserver.assessmentportal.standaloneasmt.CheckAvailabilityOfTest?newtest=start&browserName=\"+browserName+\"&sumissionsatatus=\"+sumissionsatatus+\"&checkModelstatus=\"+checkModelstatus+\"&assessment_id=\"+document.frm.checkbox1.value+\"&student_id=\"+student_id+\"\",\"new1\",\"height=700,width=800,status=yes,scrollbars=yes,manubar=no,toolbar=no\");"
        //  1894: invokevirtual   java/lang/StringBuilder.append:(Ljava/lang/String;)Ljava/lang/StringBuilder;
        //  1897: ldc             "\n   \t\t\t\t\t\t\t\t\t}"
        //  1899: invokevirtual   java/lang/StringBuilder.append:(Ljava/lang/String;)Ljava/lang/StringBuilder;
        //  1902: ldc             "\n  \t\t\t\t\t\t\t\t\telse {"
        //  1904: invokevirtual   java/lang/StringBuilder.append:(Ljava/lang/String;)Ljava/lang/StringBuilder;
        //  1907: ldc             "\n\t\t\t\t\t\t\t\t\t\tcount1 = Number(count1)+1;"
        //  1909: invokevirtual   java/lang/StringBuilder.append:(Ljava/lang/String;)Ljava/lang/StringBuilder;
        //  1912: ldc             "\n   \t\t\t\t\t\t\t\t\t\twindow.open(\"./learnityasmtserver.assessmentportal.standaloneasmt.GenerateTestHTML?newtest=start&browserName=\"+browserName+\"&checkModelstatus=\"+checkModelstatus+\"&assessment_id=\"+document.frm.checkbox1.value+\"\",\"new\",\"height=700,width=800,status=yes,scrollbars=yes,resizable=yes,manubar=no,toolbar=no\");"
        //  1914: invokevirtual   java/lang/StringBuilder.append:(Ljava/lang/String;)Ljava/lang/StringBuilder;
        //  1917: ldc             "\n\t\t\t\t\t\t\t\t\t}"
        //  1919: invokevirtual   java/lang/StringBuilder.append:(Ljava/lang/String;)Ljava/lang/StringBuilder;
        //  1922: ldc             "\n\t\t\t\t\t\t\t\t}"
        //  1924: invokevirtual   java/lang/StringBuilder.append:(Ljava/lang/String;)Ljava/lang/StringBuilder;
        //  1927: ldc             "\n\t\t\t\t\t\t\t}"
        //  1929: invokevirtual   java/lang/StringBuilder.append:(Ljava/lang/String;)Ljava/lang/StringBuilder;
        //  1932: ldc             "\n\t\t\t\t\t\t}"
        //  1934: invokevirtual   java/lang/StringBuilder.append:(Ljava/lang/String;)Ljava/lang/StringBuilder;
        //  1937: ldc             "\n\t\t\t\t\t\telse {"
        //  1939: invokevirtual   java/lang/StringBuilder.append:(Ljava/lang/String;)Ljava/lang/StringBuilder;
        //  1942: ldc             "\n\t\t\t\t\t\t\tif((sumissionsatatus==\"\") || (sumissionsatatus == \"Submitted\"))"
        //  1944: invokevirtual   java/lang/StringBuilder.append:(Ljava/lang/String;)Ljava/lang/StringBuilder;
        //  1947: ldc             "\n\t\t\t\t\t\t\t{"
        //  1949: invokevirtual   java/lang/StringBuilder.append:(Ljava/lang/String;)Ljava/lang/StringBuilder;
        //  1952: ldc             "\n  \t\t\t\t\t\t\t\t\tif(count1!=0) {"
        //  1954: invokevirtual   java/lang/StringBuilder.append:(Ljava/lang/String;)Ljava/lang/StringBuilder;
        //  1957: ldc             "\n\t\t\t\t\t\t\t\t\t\twindow.open(\"./learnityasmtserver.assessmentportal.standaloneasmt.CheckAvailabilityOfTest?newtest=start&browserName=\"+browserName+\"&sumissionsatatus=\"+sumissionsatatus+\"&checkModelstatus=\"+checkModelstatus+\"&assessment_id=\"+document.frm.checkbox1.value+\"&student_id=\"+student_id+\"\",\"new1\",\"height=700,width=800,status=yes,scrollbars=yes,manubar=no,toolbar=no\");"
        //  1959: invokevirtual   java/lang/StringBuilder.append:(Ljava/lang/String;)Ljava/lang/StringBuilder;
        //  1962: ldc             "\n   \t\t\t\t\t\t\t\t\t}"
        //  1964: invokevirtual   java/lang/StringBuilder.append:(Ljava/lang/String;)Ljava/lang/StringBuilder;
        //  1967: ldc             "\n  \t\t\t\t\t\t\t\t\telse {"
        //  1969: invokevirtual   java/lang/StringBuilder.append:(Ljava/lang/String;)Ljava/lang/StringBuilder;
        //  1972: ldc             "\n\t\t\t\t\t\t\t\t\t\tcount1 = Number(count1)+1;"
        //  1974: invokevirtual   java/lang/StringBuilder.append:(Ljava/lang/String;)Ljava/lang/StringBuilder;
        //  1977: ldc             "\n   \t\t\t\t\t\t\t\t\t\twindow.open(\"./learnityasmtserver.assessmentportal.standaloneasmt.GenerateStAloneTest?newtest=start&checkModelstatus=\"+checkModelstatus+\"&assessment_id=\"+document.frm.checkbox1.value+\"\",\"new\",\"height=700,width=800,status=yes,scrollbars=yes,resizable=yes,manubar=no,toolbar=no\");"
        //  1979: invokevirtual   java/lang/StringBuilder.append:(Ljava/lang/String;)Ljava/lang/StringBuilder;
        //  1982: ldc             "\n\t\t\t\t\t\t\t\t\t}"
        //  1984: invokevirtual   java/lang/StringBuilder.append:(Ljava/lang/String;)Ljava/lang/StringBuilder;
        //  1987: ldc             "\n\t\t\t\t\t\t\t}"
        //  1989: invokevirtual   java/lang/StringBuilder.append:(Ljava/lang/String;)Ljava/lang/StringBuilder;
        //  1992: ldc             "\n\t\t\t\t\t\t\telse {"
        //  1994: invokevirtual   java/lang/StringBuilder.append:(Ljava/lang/String;)Ljava/lang/StringBuilder;
        //  1997: ldc             "\n\t\t\t\t\t\t\t\tif(save_state==\"\") {"
        //  1999: invokevirtual   java/lang/StringBuilder.append:(Ljava/lang/String;)Ljava/lang/StringBuilder;
        //  2002: ldc             "\n\t\t\t\t\t\t\t\t\tif(count1!=0) {"
        //  2004: invokevirtual   java/lang/StringBuilder.append:(Ljava/lang/String;)Ljava/lang/StringBuilder;
        //  2007: ldc             "\n\t\t\t\t\t\t\t\t\t\twindow.open(\"./learnityasmtserver.assessmentportal.standaloneasmt.CheckAvailabilityOfTest?newtest=start&save_state=no&browserName=\"+browserName+\"&sumissionsatatus=\"+sumissionsatatus+\"&checkModelstatus=\"+checkModelstatus+\"&assessment_id=\"+document.frm.checkbox1.value+\"&student_id=\"+student_id+\"\",\"new1\",\"height=700,width=800,status=yes,scrollbars=yes,manubar=no,toolbar=no\");"
        //  2009: invokevirtual   java/lang/StringBuilder.append:(Ljava/lang/String;)Ljava/lang/StringBuilder;
        //  2012: ldc             "\n   \t\t\t\t\t\t\t\t\t}"
        //  2014: invokevirtual   java/lang/StringBuilder.append:(Ljava/lang/String;)Ljava/lang/StringBuilder;
        //  2017: ldc             "\n  \t\t\t\t\t\t\t\t\telse {"
        //  2019: invokevirtual   java/lang/StringBuilder.append:(Ljava/lang/String;)Ljava/lang/StringBuilder;
        //  2022: ldc             "\n\t\t\t\t\t\t\t\t\t\tcount1 = Number(count1)+1;"
        //  2024: invokevirtual   java/lang/StringBuilder.append:(Ljava/lang/String;)Ljava/lang/StringBuilder;
        //  2027: ldc             "\n   \t\t\t\t\t\t\t\t\t\twindow.open(\"./learnityasmtserver.assessmentportal.standaloneasmt.GenerateStAloneTest?newtest=start&save_state=no&checkModelstatus=\"+checkModelstatus+\"&assessment_id=\"+document.frm.checkbox1.value+\"\",\"new\",\"height=700,width=800,status=yes,scrollbars=yes,resizable=yes,manubar=no,toolbar=no\");"
        //  2029: invokevirtual   java/lang/StringBuilder.append:(Ljava/lang/String;)Ljava/lang/StringBuilder;
        //  2032: ldc             "\n\t\t\t\t\t\t\t\t\t}"
        //  2034: invokevirtual   java/lang/StringBuilder.append:(Ljava/lang/String;)Ljava/lang/StringBuilder;
        //  2037: ldc             "\n\t\t\t\t\t\t\t\t}"
        //  2039: invokevirtual   java/lang/StringBuilder.append:(Ljava/lang/String;)Ljava/lang/StringBuilder;
        //  2042: ldc             "\n\t\t\t\t\t\t\t\telse {"
        //  2044: invokevirtual   java/lang/StringBuilder.append:(Ljava/lang/String;)Ljava/lang/StringBuilder;
        //  2047: ldc             "\n  \t\t\t\t\t\t\t\t\tif(count1!=0) {"
        //  2049: invokevirtual   java/lang/StringBuilder.append:(Ljava/lang/String;)Ljava/lang/StringBuilder;
        //  2052: ldc             "\n\t\t\t\t\t\t\t\t\t\twindow.open(\"./learnityasmtserver.assessmentportal.standaloneasmt.CheckAvailabilityOfTest?newtest=start&browserName=\"+browserName+\"&sumissionsatatus=\"+sumissionsatatus+\"&checkModelstatus=\"+checkModelstatus+\"&assessment_id=\"+document.frm.checkbox1.value+\"&student_id=\"+student_id+\"\",\"new1\",\"height=700,width=800,status=yes,scrollbars=yes,manubar=no,toolbar=no\");"
        //  2054: invokevirtual   java/lang/StringBuilder.append:(Ljava/lang/String;)Ljava/lang/StringBuilder;
        //  2057: ldc             "\n   \t\t\t\t\t\t\t\t\t}"
        //  2059: invokevirtual   java/lang/StringBuilder.append:(Ljava/lang/String;)Ljava/lang/StringBuilder;
        //  2062: ldc             "\n  \t\t\t\t\t\t\t\t\telse {"
        //  2064: invokevirtual   java/lang/StringBuilder.append:(Ljava/lang/String;)Ljava/lang/StringBuilder;
        //  2067: ldc             "\n\t\t\t\t\t\t\t\t\t\tcount1 = Number(count1)+1;"
        //  2069: invokevirtual   java/lang/StringBuilder.append:(Ljava/lang/String;)Ljava/lang/StringBuilder;
        //  2072: ldc             "\n   \t\t\t\t\t\t\t\t\t\twindow.open(\"./learnityasmtserver.assessmentportal.standaloneasmt.GenerateTestXHTML?newtest=start&browserName=\"+browserName+\"&checkModelstatus=\"+checkModelstatus+\"&assessment_id=\"+document.frm.checkbox1.value+\"\",\"new\",\"height=700,width=800,status=yes,scrollbars=yes,resizable=yes,manubar=no,toolbar=no\");"
        //  2074: invokevirtual   java/lang/StringBuilder.append:(Ljava/lang/String;)Ljava/lang/StringBuilder;
        //  2077: ldc             "\n\t\t\t\t\t\t\t\t\t}"
        //  2079: invokevirtual   java/lang/StringBuilder.append:(Ljava/lang/String;)Ljava/lang/StringBuilder;
        //  2082: ldc             "\n\t\t\t\t\t\t\t\t}"
        //  2084: invokevirtual   java/lang/StringBuilder.append:(Ljava/lang/String;)Ljava/lang/StringBuilder;
        //  2087: ldc             "\n\t\t\t\t\t\t\t}"
        //  2089: invokevirtual   java/lang/StringBuilder.append:(Ljava/lang/String;)Ljava/lang/StringBuilder;
        //  2092: ldc             "\n\t\t\t\t\t\t}"
        //  2094: invokevirtual   java/lang/StringBuilder.append:(Ljava/lang/String;)Ljava/lang/StringBuilder;
        //  2097: ldc             "\n \t\t\t\t\t}"
        //  2099: invokevirtual   java/lang/StringBuilder.append:(Ljava/lang/String;)Ljava/lang/StringBuilder;
        //  2102: ldc             "\n\t\t\t\t\telse{"
        //  2104: invokevirtual   java/lang/StringBuilder.append:(Ljava/lang/String;)Ljava/lang/StringBuilder;
        //  2107: ldc             "\n\t\t\t\t\t\talert(\"Selected Assessment is not available\");"
        //  2109: invokevirtual   java/lang/StringBuilder.append:(Ljava/lang/String;)Ljava/lang/StringBuilder;
        //  2112: ldc             "\n\t\t\t\t\t}"
        //  2114: invokevirtual   java/lang/StringBuilder.append:(Ljava/lang/String;)Ljava/lang/StringBuilder;
        //  2117: ldc             "\n\t\t\t\t}"
        //  2119: invokevirtual   java/lang/StringBuilder.append:(Ljava/lang/String;)Ljava/lang/StringBuilder;
        //  2122: ldc             "\n\t\t\t\telse{"
        //  2124: invokevirtual   java/lang/StringBuilder.append:(Ljava/lang/String;)Ljava/lang/StringBuilder;
        //  2127: ldc             "\n\t\t\t\t\talert(\"Validity finished\");"
        //  2129: invokevirtual   java/lang/StringBuilder.append:(Ljava/lang/String;)Ljava/lang/StringBuilder;
        //  2132: ldc             "\n\t\t\t\t}"
        //  2134: invokevirtual   java/lang/StringBuilder.append:(Ljava/lang/String;)Ljava/lang/StringBuilder;
        //  2137: ldc             "\n\t\t\t}"
        //  2139: invokevirtual   java/lang/StringBuilder.append:(Ljava/lang/String;)Ljava/lang/StringBuilder;
        //  2142: ldc             "\n\t\t\telse{"
        //  2144: invokevirtual   java/lang/StringBuilder.append:(Ljava/lang/String;)Ljava/lang/StringBuilder;
        //  2147: ldc             "\n\t\t\t\talert(message);"
        //  2149: invokevirtual   java/lang/StringBuilder.append:(Ljava/lang/String;)Ljava/lang/StringBuilder;
        //  2152: ldc             "\n\t\t\t}"
        //  2154: invokevirtual   java/lang/StringBuilder.append:(Ljava/lang/String;)Ljava/lang/StringBuilder;
        //  2157: ldc             "\n    \t}"
        //  2159: invokevirtual   java/lang/StringBuilder.append:(Ljava/lang/String;)Ljava/lang/StringBuilder;
        //  2162: ldc             "\n\telse{"
        //  2164: invokevirtual   java/lang/StringBuilder.append:(Ljava/lang/String;)Ljava/lang/StringBuilder;
        //  2167: ldc             "\n\t\talert(\"Please Select a Assessment\");"
        //  2169: invokevirtual   java/lang/StringBuilder.append:(Ljava/lang/String;)Ljava/lang/StringBuilder;
        //  2172: ldc             "\n\t}"
        //  2174: invokevirtual   java/lang/StringBuilder.append:(Ljava/lang/String;)Ljava/lang/StringBuilder;
        //  2177: ldc             "\n }"
        //  2179: invokevirtual   java/lang/StringBuilder.append:(Ljava/lang/String;)Ljava/lang/StringBuilder;
        //  2182: invokevirtual   java/lang/StringBuilder.toString:()Ljava/lang/String;
        //  2185: astore          script
        //  2187: new             Lorg/apache/ecs/html/Html;
        //  2190: dup            
        //  2191: invokespecial   org/apache/ecs/html/Html.<init>:()V
        //  2194: astore          html
        //  2196: new             Lorg/apache/ecs/html/Link;
        //  2199: dup            
        //  2200: invokespecial   org/apache/ecs/html/Link.<init>:()V
        //  2203: astore          link
        //  2205: new             Lorg/apache/ecs/html/Head;
        //  2208: dup            
        //  2209: invokespecial   org/apache/ecs/html/Head.<init>:()V
        //  2212: astore          head
        //  2214: new             Lorg/apache/ecs/html/Body;
        //  2217: dup            
        //  2218: invokespecial   org/apache/ecs/html/Body.<init>:()V
        //  2221: astore          body
        //  2223: aload           body
        //  2225: ldc             "#FF0000"
        //  2227: invokevirtual   org/apache/ecs/html/Body.setLink:(Ljava/lang/String;)Lorg/apache/ecs/html/Body;
        //  2230: pop            
        //  2231: new             Lorg/apache/ecs/html/Script;
        //  2234: dup            
        //  2235: invokespecial   org/apache/ecs/html/Script.<init>:()V
        //  2238: astore          script1
        //  2240: new             Lorg/apache/ecs/html/Div;
        //  2243: dup            
        //  2244: invokespecial   org/apache/ecs/html/Div.<init>:()V
        //  2247: astore          AssessmentMainDiv
        //  2249: new             Lorg/apache/ecs/html/Form;
        //  2252: dup            
        //  2253: invokespecial   org/apache/ecs/html/Form.<init>:()V
        //  2256: ldc             "frm"
        //  2258: invokevirtual   org/apache/ecs/html/Form.setName:(Ljava/lang/String;)Lorg/apache/ecs/html/Form;
        //  2261: ldc             "post"
        //  2263: invokevirtual   org/apache/ecs/html/Form.setMethod:(Ljava/lang/String;)Lorg/apache/ecs/html/Form;
        //  2266: astore          form
        //  2268: aload           link
        //  2270: new             Ljava/lang/StringBuilder;
        //  2273: dup            
        //  2274: invokespecial   java/lang/StringBuilder.<init>:()V
        //  2277: ldc             "./PortalMgmt.portal.cssPortal?skininfo="
        //  2279: invokevirtual   java/lang/StringBuilder.append:(Ljava/lang/String;)Ljava/lang/StringBuilder;
        //  2282: aload           skininfo
        //  2284: invokevirtual   java/lang/StringBuilder.append:(Ljava/lang/String;)Ljava/lang/StringBuilder;
        //  2287: ldc             ""
        //  2289: invokevirtual   java/lang/StringBuilder.append:(Ljava/lang/String;)Ljava/lang/StringBuilder;
        //  2292: invokevirtual   java/lang/StringBuilder.toString:()Ljava/lang/String;
        //  2295: invokevirtual   org/apache/ecs/html/Link.setHref:(Ljava/lang/String;)Lorg/apache/ecs/html/Link;
        //  2298: pop            
        //  2299: aload           link
        //  2301: ldc             "stylesheet"
        //  2303: invokevirtual   org/apache/ecs/html/Link.setRel:(Ljava/lang/String;)Lorg/apache/ecs/html/Link;
        //  2306: pop            
        //  2307: aload           script1
        //  2309: ldc             "javascript"
        //  2311: invokevirtual   org/apache/ecs/html/Script.setLanguage:(Ljava/lang/String;)Lorg/apache/ecs/html/Script;
        //  2314: pop            
        //  2315: aload           script1
        //  2317: aload           script
        //  2319: invokevirtual   org/apache/ecs/html/Script.addElement:(Ljava/lang/String;)Lorg/apache/ecs/html/Script;
        //  2322: pop            
        //  2323: aload           link
        //  2325: aload           script1
        //  2327: invokevirtual   org/apache/ecs/html/Link.addElement:(Lorg/apache/ecs/Element;)Lorg/apache/ecs/html/Link;
        //  2330: pop            
        //  2331: new             Lorg/apache/ecs/html/Table;
        //  2334: dup            
        //  2335: invokespecial   org/apache/ecs/html/Table.<init>:()V
        //  2338: astore          assessmentTableBody
        //  2340: new             Lorg/apache/ecs/html/Table;
        //  2343: dup            
        //  2344: invokespecial   org/apache/ecs/html/Table.<init>:()V
        //  2347: astore          assessmentTableBody2
        //  2349: new             Lorg/apache/ecs/html/Table;
        //  2352: dup            
        //  2353: invokespecial   org/apache/ecs/html/Table.<init>:()V
        //  2356: astore          tblAssessmentStButton
        //  2358: new             Lorg/apache/ecs/html/Div;
        //  2361: dup            
        //  2362: invokespecial   org/apache/ecs/html/Div.<init>:()V
        //  2365: astore          main
        //  2367: new             Lorg/apache/ecs/html/Input;
        //  2370: dup            
        //  2371: invokespecial   org/apache/ecs/html/Input.<init>:()V
        //  2374: astore          inputButton2
        //  2376: aload           inputButton2
        //  2378: ldc             "start_onclick();"
        //  2380: invokevirtual   org/apache/ecs/html/Input.setOnClick:(Ljava/lang/String;)V
        //  2383: aload           form
        //  2385: new             Lorg/apache/ecs/html/Input;
        //  2388: dup            
        //  2389: invokespecial   org/apache/ecs/html/Input.<init>:()V
        //  2392: ldc             "hidden"
        //  2394: invokevirtual   org/apache/ecs/html/Input.setType:(Ljava/lang/String;)Lorg/apache/ecs/html/Input;
        //  2397: ldc             "checkbox1"
        //  2399: invokevirtual   org/apache/ecs/html/Input.setName:(Ljava/lang/String;)Lorg/apache/ecs/html/Input;
        //  2402: invokevirtual   org/apache/ecs/html/Form.addElement:(Lorg/apache/ecs/Element;)Lorg/apache/ecs/html/Form;
        //  2405: pop            
        //  2406: aload           assessmentTableBody
        //  2408: new             Lorg/apache/ecs/html/TR;
        //  2411: dup            
        //  2412: invokespecial   org/apache/ecs/html/TR.<init>:()V
        //  2415: new             Lorg/apache/ecs/html/TD;
        //  2418: dup            
        //  2419: invokespecial   org/apache/ecs/html/TD.<init>:()V
        //  2422: new             Lorg/apache/ecs/html/Div;
        //  2425: dup            
        //  2426: invokespecial   org/apache/ecs/html/Div.<init>:()V
        //  2429: ldc             "Title"
        //  2431: invokevirtual   org/apache/ecs/html/Div.addElement:(Ljava/lang/String;)Lorg/apache/ecs/html/Div;
        //  2434: ldc             "AssessmentTableHadingcol1"
        //  2436: invokevirtual   org/apache/ecs/html/Div.setID:(Ljava/lang/String;)Lorg/apache/ecs/Element;
        //  2439: invokevirtual   org/apache/ecs/html/TD.addElement:(Lorg/apache/ecs/Element;)Lorg/apache/ecs/html/TD;
        //  2442: invokevirtual   org/apache/ecs/html/TR.addElement:(Lorg/apache/ecs/Element;)Lorg/apache/ecs/html/TR;
        //  2445: new             Lorg/apache/ecs/html/TD;
        //  2448: dup            
        //  2449: invokespecial   org/apache/ecs/html/TD.<init>:()V
        //  2452: new             Lorg/apache/ecs/html/Div;
        //  2455: dup            
        //  2456: invokespecial   org/apache/ecs/html/Div.<init>:()V
        //  2459: ldc             "Available from"
        //  2461: invokevirtual   org/apache/ecs/html/Div.addElement:(Ljava/lang/String;)Lorg/apache/ecs/html/Div;
        //  2464: ldc             "AssessmentTableHadingcol2"
        //  2466: invokevirtual   org/apache/ecs/html/Div.setID:(Ljava/lang/String;)Lorg/apache/ecs/Element;
        //  2469: invokevirtual   org/apache/ecs/html/TD.addElement:(Lorg/apache/ecs/Element;)Lorg/apache/ecs/html/TD;
        //  2472: invokevirtual   org/apache/ecs/html/TR.addElement:(Lorg/apache/ecs/Element;)Lorg/apache/ecs/html/TR;
        //  2475: new             Lorg/apache/ecs/html/TD;
        //  2478: dup            
        //  2479: invokespecial   org/apache/ecs/html/TD.<init>:()V
        //  2482: new             Lorg/apache/ecs/html/Div;
        //  2485: dup            
        //  2486: invokespecial   org/apache/ecs/html/Div.<init>:()V
        //  2489: ldc             "Access Allowed Till"
        //  2491: invokevirtual   org/apache/ecs/html/Div.addElement:(Ljava/lang/String;)Lorg/apache/ecs/html/Div;
        //  2494: ldc             "AssessmentTableHadingcol3"
        //  2496: invokevirtual   org/apache/ecs/html/Div.setID:(Ljava/lang/String;)Lorg/apache/ecs/Element;
        //  2499: invokevirtual   org/apache/ecs/html/TD.addElement:(Lorg/apache/ecs/Element;)Lorg/apache/ecs/html/TD;
        //  2502: invokevirtual   org/apache/ecs/html/TR.addElement:(Lorg/apache/ecs/Element;)Lorg/apache/ecs/html/TR;
        //  2505: new             Lorg/apache/ecs/html/TD;
        //  2508: dup            
        //  2509: invokespecial   org/apache/ecs/html/TD.<init>:()V
        //  2512: new             Lorg/apache/ecs/html/Div;
        //  2515: dup            
        //  2516: invokespecial   org/apache/ecs/html/Div.<init>:()V
        //  2519: ldc             "Pass Mark"
        //  2521: invokevirtual   org/apache/ecs/html/Div.addElement:(Ljava/lang/String;)Lorg/apache/ecs/html/Div;
        //  2524: ldc             "AssessmentTableHadingcol4"
        //  2526: invokevirtual   org/apache/ecs/html/Div.setID:(Ljava/lang/String;)Lorg/apache/ecs/Element;
        //  2529: invokevirtual   org/apache/ecs/html/TD.addElement:(Lorg/apache/ecs/Element;)Lorg/apache/ecs/html/TD;
        //  2532: invokevirtual   org/apache/ecs/html/TR.addElement:(Lorg/apache/ecs/Element;)Lorg/apache/ecs/html/TR;
        //  2535: new             Lorg/apache/ecs/html/TD;
        //  2538: dup            
        //  2539: invokespecial   org/apache/ecs/html/TD.<init>:()V
        //  2542: new             Lorg/apache/ecs/html/Div;
        //  2545: dup            
        //  2546: invokespecial   org/apache/ecs/html/Div.<init>:()V
        //  2549: ldc             "Test Time (min)"
        //  2551: invokevirtual   org/apache/ecs/html/Div.addElement:(Ljava/lang/String;)Lorg/apache/ecs/html/Div;
        //  2554: ldc             "AssessmentTableHadingcol5"
        //  2556: invokevirtual   org/apache/ecs/html/Div.setID:(Ljava/lang/String;)Lorg/apache/ecs/Element;
        //  2559: invokevirtual   org/apache/ecs/html/TD.addElement:(Lorg/apache/ecs/Element;)Lorg/apache/ecs/html/TD;
        //  2562: invokevirtual   org/apache/ecs/html/TR.addElement:(Lorg/apache/ecs/Element;)Lorg/apache/ecs/html/TR;
        //  2565: new             Lorg/apache/ecs/html/TD;
        //  2568: dup            
        //  2569: invokespecial   org/apache/ecs/html/TD.<init>:()V
        //  2572: new             Lorg/apache/ecs/html/Div;
        //  2575: dup            
        //  2576: invokespecial   org/apache/ecs/html/Div.<init>:()V
        //  2579: ldc             "No of question"
        //  2581: invokevirtual   org/apache/ecs/html/Div.addElement:(Ljava/lang/String;)Lorg/apache/ecs/html/Div;
        //  2584: ldc             "AssessmentTableHadingcol6"
        //  2586: invokevirtual   org/apache/ecs/html/Div.setID:(Ljava/lang/String;)Lorg/apache/ecs/Element;
        //  2589: invokevirtual   org/apache/ecs/html/TD.addElement:(Lorg/apache/ecs/Element;)Lorg/apache/ecs/html/TD;
        //  2592: invokevirtual   org/apache/ecs/html/TR.addElement:(Lorg/apache/ecs/Element;)Lorg/apache/ecs/html/TR;
        //  2595: new             Lorg/apache/ecs/html/TD;
        //  2598: dup            
        //  2599: invokespecial   org/apache/ecs/html/TD.<init>:()V
        //  2602: new             Lorg/apache/ecs/html/Div;
        //  2605: dup            
        //  2606: invokespecial   org/apache/ecs/html/Div.<init>:()V
        //  2609: ldc             "Status"
        //  2611: invokevirtual   org/apache/ecs/html/Div.addElement:(Ljava/lang/String;)Lorg/apache/ecs/html/Div;
        //  2614: ldc             "AssessmentTableHadingcol7"
        //  2616: invokevirtual   org/apache/ecs/html/Div.setID:(Ljava/lang/String;)Lorg/apache/ecs/Element;
        //  2619: invokevirtual   org/apache/ecs/html/TD.addElement:(Lorg/apache/ecs/Element;)Lorg/apache/ecs/html/TD;
        //  2622: invokevirtual   org/apache/ecs/html/TR.addElement:(Lorg/apache/ecs/Element;)Lorg/apache/ecs/html/TR;
        //  2625: ldc             "AssessmentTableHadingRow"
        //  2627: invokevirtual   org/apache/ecs/html/TR.setID:(Ljava/lang/String;)Lorg/apache/ecs/Element;
        //  2630: invokevirtual   org/apache/ecs/html/Table.addElement:(Lorg/apache/ecs/Element;)Lorg/apache/ecs/html/Table;
        //  2633: pop            
        //  2634: aload           AssessmentMainDiv
        //  2636: new             Lorg/apache/ecs/html/Table;
        //  2639: dup            
        //  2640: invokespecial   org/apache/ecs/html/Table.<init>:()V
        //  2643: new             Lorg/apache/ecs/html/TR;
        //  2646: dup            
        //  2647: invokespecial   org/apache/ecs/html/TR.<init>:()V
        //  2650: new             Lorg/apache/ecs/html/TD;
        //  2653: dup            
        //  2654: invokespecial   org/apache/ecs/html/TD.<init>:()V
        //  2657: new             Lorg/apache/ecs/html/Div;
        //  2660: dup            
        //  2661: invokespecial   org/apache/ecs/html/Div.<init>:()V
        //  2664: aload           assessmentTableBody
        //  2666: invokevirtual   org/apache/ecs/html/Div.addElement:(Lorg/apache/ecs/Element;)Lorg/apache/ecs/html/Div;
        //  2669: ldc             "AssessmentTablebodyrow1"
        //  2671: invokevirtual   org/apache/ecs/html/Div.setID:(Ljava/lang/String;)Lorg/apache/ecs/Element;
        //  2674: invokevirtual   org/apache/ecs/html/TD.addElement:(Lorg/apache/ecs/Element;)Lorg/apache/ecs/html/TD;
        //  2677: invokevirtual   org/apache/ecs/html/TR.addElement:(Lorg/apache/ecs/Element;)Lorg/apache/ecs/html/TR;
        //  2680: invokevirtual   org/apache/ecs/html/Table.addElement:(Lorg/apache/ecs/Element;)Lorg/apache/ecs/html/Table;
        //  2683: new             Lorg/apache/ecs/html/TR;
        //  2686: dup            
        //  2687: invokespecial   org/apache/ecs/html/TR.<init>:()V
        //  2690: new             Lorg/apache/ecs/html/TD;
        //  2693: dup            
        //  2694: invokespecial   org/apache/ecs/html/TD.<init>:()V
        //  2697: new             Lorg/apache/ecs/html/Div;
        //  2700: dup            
        //  2701: invokespecial   org/apache/ecs/html/Div.<init>:()V
        //  2704: aload           assessmentTableBody2
        //  2706: invokevirtual   org/apache/ecs/html/Div.addElement:(Lorg/apache/ecs/Element;)Lorg/apache/ecs/html/Div;
        //  2709: ldc             "AssessmentTablebodyrow2"
        //  2711: invokevirtual   org/apache/ecs/html/Div.setID:(Ljava/lang/String;)Lorg/apache/ecs/Element;
        //  2714: invokevirtual   org/apache/ecs/html/TD.addElement:(Lorg/apache/ecs/Element;)Lorg/apache/ecs/html/TD;
        //  2717: invokevirtual   org/apache/ecs/html/TR.addElement:(Lorg/apache/ecs/Element;)Lorg/apache/ecs/html/TR;
        //  2720: invokevirtual   org/apache/ecs/html/Table.addElement:(Lorg/apache/ecs/Element;)Lorg/apache/ecs/html/Table;
        //  2723: new             Lorg/apache/ecs/html/TR;
        //  2726: dup            
        //  2727: invokespecial   org/apache/ecs/html/TR.<init>:()V
        //  2730: new             Lorg/apache/ecs/html/TD;
        //  2733: dup            
        //  2734: invokespecial   org/apache/ecs/html/TD.<init>:()V
        //  2737: new             Lorg/apache/ecs/html/Div;
        //  2740: dup            
        //  2741: invokespecial   org/apache/ecs/html/Div.<init>:()V
        //  2744: aload           tblAssessmentStButton
        //  2746: invokevirtual   org/apache/ecs/html/Div.addElement:(Lorg/apache/ecs/Element;)Lorg/apache/ecs/html/Div;
        //  2749: new             Lorg/apache/ecs/html/A;
        //  2752: dup            
        //  2753: invokespecial   org/apache/ecs/html/A.<init>:()V
        //  2756: ldc             "Test Instructions"
        //  2758: invokevirtual   org/apache/ecs/html/A.addElement:(Ljava/lang/String;)Lorg/apache/ecs/html/A;
        //  2761: ldc             "javascript:help_onClick()"
        //  2763: invokevirtual   org/apache/ecs/html/A.setHref:(Ljava/lang/String;)Lorg/apache/ecs/html/A;
        //  2766: invokevirtual   org/apache/ecs/html/Div.addElement:(Lorg/apache/ecs/Element;)Lorg/apache/ecs/html/Div;
        //  2769: ldc             "AssessmentTablebodyrow3"
        //  2771: invokevirtual   org/apache/ecs/html/Div.setID:(Ljava/lang/String;)Lorg/apache/ecs/Element;
        //  2774: invokevirtual   org/apache/ecs/html/TD.addElement:(Lorg/apache/ecs/Element;)Lorg/apache/ecs/html/TD;
        //  2777: invokevirtual   org/apache/ecs/html/TR.addElement:(Lorg/apache/ecs/Element;)Lorg/apache/ecs/html/TR;
        //  2780: invokevirtual   org/apache/ecs/html/Table.addElement:(Lorg/apache/ecs/Element;)Lorg/apache/ecs/html/Table;
        //  2783: invokevirtual   org/apache/ecs/html/Div.addElement:(Lorg/apache/ecs/Element;)Lorg/apache/ecs/html/Div;
        //  2786: pop            
        //  2787: aload           AssessmentMainDiv
        //  2789: ldc             "AssessmentTablebody"
        //  2791: invokevirtual   org/apache/ecs/html/Div.setID:(Ljava/lang/String;)Lorg/apache/ecs/Element;
        //  2794: pop            
        //  2795: aload           tblAssessmentStButton
        //  2797: new             Lorg/apache/ecs/html/TR;
        //  2800: dup            
        //  2801: invokespecial   org/apache/ecs/html/TR.<init>:()V
        //  2804: new             Lorg/apache/ecs/html/TD;
        //  2807: dup            
        //  2808: invokespecial   org/apache/ecs/html/TD.<init>:()V
        //  2811: aload           inputButton2
        //  2813: ldc             "sbttn"
        //  2815: invokevirtual   org/apache/ecs/html/Input.setClassId:(Ljava/lang/String;)Lorg/apache/ecs/html/Input;
        //  2818: ldc             "Start"
        //  2820: invokevirtual   org/apache/ecs/html/Input.setName:(Ljava/lang/String;)Lorg/apache/ecs/html/Input;
        //  2823: iconst_2       
        //  2824: invokevirtual   org/apache/ecs/html/Input.setTabindex:(I)Lorg/apache/ecs/html/Input;
        //  2827: ldc             "StartTest"
        //  2829: invokevirtual   org/apache/ecs/html/Input.setTitleValue:(Ljava/lang/String;)Lorg/apache/ecs/html/Input;
        //  2832: ldc             "button"
        //  2834: invokevirtual   org/apache/ecs/html/Input.setType:(Ljava/lang/String;)Lorg/apache/ecs/html/Input;
        //  2837: ldc             "StartTest"
        //  2839: invokevirtual   org/apache/ecs/html/Input.setValue:(Ljava/lang/String;)Lorg/apache/ecs/html/Input;
        //  2842: invokevirtual   org/apache/ecs/html/TD.addElement:(Lorg/apache/ecs/Element;)Lorg/apache/ecs/html/TD;
        //  2845: ldc             "AssessmentTableBodyRowStbtn"
        //  2847: invokevirtual   org/apache/ecs/html/TD.setID:(Ljava/lang/String;)Lorg/apache/ecs/Element;
        //  2850: invokevirtual   org/apache/ecs/html/TR.addElement:(Lorg/apache/ecs/Element;)Lorg/apache/ecs/html/TR;
        //  2853: invokevirtual   org/apache/ecs/html/Table.addElement:(Lorg/apache/ecs/Element;)Lorg/apache/ecs/html/Table;
        //  2856: pop            
        //  2857: aload           vAssessmentInfo
        //  2859: invokevirtual   java/util/Vector.size:()I
        //  2862: ifne            3804
        //  2865: aload           vAssessmentInfogroup
        //  2867: invokevirtual   java/util/Vector.size:()I
        //  2870: ifne            2876
        //  2873: goto            5724
        //  2876: iconst_0       
        //  2877: istore          i
        //  2879: iload           i
        //  2881: aload           vAssessmentInfogroup
        //  2883: invokevirtual   java/util/Vector.size:()I
        //  2886: if_icmpge       3801
        //  2889: new             Lorg/apache/ecs/html/Input;
        //  2892: dup            
        //  2893: invokespecial   org/apache/ecs/html/Input.<init>:()V
        //  2896: astore          inputButton1
        //  2898: aload           inputButton1
        //  2900: ldc             "check_onclick();"
        //  2902: invokevirtual   org/apache/ecs/html/Input.setOnClick:(Ljava/lang/String;)V
        //  2905: aload           vAssessmentInfogroup
        //  2907: iload           i
        //  2909: invokevirtual   java/util/Vector.elementAt:(I)Ljava/lang/Object;
        //  2912: checkcast       [Ljava/lang/String;
        //  2915: checkcast       [Ljava/lang/String;
        //  2918: astore          strAssess
        //  2920: ldc             ""
        //  2922: astore          availablitydate
        //  2924: ldc             ""
        //  2926: astore          valid_upto
        //  2928: aload           strAssess
        //  2930: iconst_2       
        //  2931: aaload         
        //  2932: ldc             ""
        //  2934: invokevirtual   java/lang/String.equals:(Ljava/lang/Object;)Z
        //  2937: ifne            3058
        //  2940: aload           strAssess
        //  2942: iconst_2       
        //  2943: aaload         
        //  2944: iconst_0       
        //  2945: aload           strAssess
        //  2947: iconst_2       
        //  2948: aaload         
        //  2949: bipush          32
        //  2951: invokevirtual   java/lang/String.indexOf:(I)I
        //  2954: invokevirtual   java/lang/String.substring:(II)Ljava/lang/String;
        //  2957: astore          str11
        //  2959: aload           str11
        //  2961: iconst_0       
        //  2962: aload           str11
        //  2964: bipush          45
        //  2966: invokevirtual   java/lang/String.indexOf:(I)I
        //  2969: invokevirtual   java/lang/String.substring:(II)Ljava/lang/String;
        //  2972: astore          str1
        //  2974: aload           str11
        //  2976: aload           str11
        //  2978: bipush          45
        //  2980: invokevirtual   java/lang/String.indexOf:(I)I
        //  2983: iconst_1       
        //  2984: iadd           
        //  2985: invokevirtual   java/lang/String.substring:(I)Ljava/lang/String;
        //  2988: astore          str2
        //  2990: aload           str2
        //  2992: iconst_0       
        //  2993: aload           str2
        //  2995: bipush          45
        //  2997: invokevirtual   java/lang/String.indexOf:(I)I
        //  3000: invokevirtual   java/lang/String.substring:(II)Ljava/lang/String;
        //  3003: astore          str3
        //  3005: aload           str2
        //  3007: aload           str2
        //  3009: bipush          45
        //  3011: invokevirtual   java/lang/String.indexOf:(I)I
        //  3014: iconst_1       
        //  3015: iadd           
        //  3016: invokevirtual   java/lang/String.substring:(I)Ljava/lang/String;
        //  3019: astore          str4
        //  3021: new             Ljava/lang/StringBuilder;
        //  3024: dup            
        //  3025: invokespecial   java/lang/StringBuilder.<init>:()V
        //  3028: aload           str4
        //  3030: invokevirtual   java/lang/StringBuilder.append:(Ljava/lang/String;)Ljava/lang/StringBuilder;
        //  3033: ldc             "-"
        //  3035: invokevirtual   java/lang/StringBuilder.append:(Ljava/lang/String;)Ljava/lang/StringBuilder;
        //  3038: aload           str3
        //  3040: invokevirtual   java/lang/StringBuilder.append:(Ljava/lang/String;)Ljava/lang/StringBuilder;
        //  3043: ldc             "-"
        //  3045: invokevirtual   java/lang/StringBuilder.append:(Ljava/lang/String;)Ljava/lang/StringBuilder;
        //  3048: aload           str1
        //  3050: invokevirtual   java/lang/StringBuilder.append:(Ljava/lang/String;)Ljava/lang/StringBuilder;
        //  3053: invokevirtual   java/lang/StringBuilder.toString:()Ljava/lang/String;
        //  3056: astore          availablitydate
        //  3058: aload           strAssess
        //  3060: iconst_3       
        //  3061: aaload         
        //  3062: ldc             ""
        //  3064: invokevirtual   java/lang/String.equals:(Ljava/lang/Object;)Z
        //  3067: ifne            3188
        //  3070: aload           strAssess
        //  3072: iconst_3       
        //  3073: aaload         
        //  3074: iconst_0       
        //  3075: aload           strAssess
        //  3077: iconst_2       
        //  3078: aaload         
        //  3079: bipush          32
        //  3081: invokevirtual   java/lang/String.indexOf:(I)I
        //  3084: invokevirtual   java/lang/String.substring:(II)Ljava/lang/String;
        //  3087: astore          str11
        //  3089: aload           str11
        //  3091: iconst_0       
        //  3092: aload           str11
        //  3094: bipush          45
        //  3096: invokevirtual   java/lang/String.indexOf:(I)I
        //  3099: invokevirtual   java/lang/String.substring:(II)Ljava/lang/String;
        //  3102: astore          str1
        //  3104: aload           str11
        //  3106: aload           str11
        //  3108: bipush          45
        //  3110: invokevirtual   java/lang/String.indexOf:(I)I
        //  3113: iconst_1       
        //  3114: iadd           
        //  3115: invokevirtual   java/lang/String.substring:(I)Ljava/lang/String;
        //  3118: astore          str2
        //  3120: aload           str2
        //  3122: iconst_0       
        //  3123: aload           str2
        //  3125: bipush          45
        //  3127: invokevirtual   java/lang/String.indexOf:(I)I
        //  3130: invokevirtual   java/lang/String.substring:(II)Ljava/lang/String;
        //  3133: astore          str3
        //  3135: aload           str2
        //  3137: aload           str2
        //  3139: bipush          45
        //  3141: invokevirtual   java/lang/String.indexOf:(I)I
        //  3144: iconst_1       
        //  3145: iadd           
        //  3146: invokevirtual   java/lang/String.substring:(I)Ljava/lang/String;
        //  3149: astore          str4
        //  3151: new             Ljava/lang/StringBuilder;
        //  3154: dup            
        //  3155: invokespecial   java/lang/StringBuilder.<init>:()V
        //  3158: aload           str4
        //  3160: invokevirtual   java/lang/StringBuilder.append:(Ljava/lang/String;)Ljava/lang/StringBuilder;
        //  3163: ldc             "-"
        //  3165: invokevirtual   java/lang/StringBuilder.append:(Ljava/lang/String;)Ljava/lang/StringBuilder;
        //  3168: aload           str3
        //  3170: invokevirtual   java/lang/StringBuilder.append:(Ljava/lang/String;)Ljava/lang/StringBuilder;
        //  3173: ldc             "-"
        //  3175: invokevirtual   java/lang/StringBuilder.append:(Ljava/lang/String;)Ljava/lang/StringBuilder;
        //  3178: aload           str1
        //  3180: invokevirtual   java/lang/StringBuilder.append:(Ljava/lang/String;)Ljava/lang/StringBuilder;
        //  3183: invokevirtual   java/lang/StringBuilder.toString:()Ljava/lang/String;
        //  3186: astore          valid_upto
        //  3188: aload           ob1
        //  3190: aload           strAssess
        //  3192: iconst_0       
        //  3193: aaload         
        //  3194: invokevirtual   learnityasmtserver/assessmentportal/dbconnection/ReportDataBaseLayer.getTotalquesno:(Ljava/lang/String;)Ljava/lang/String;
        //  3197: astore          no_of_ques
        //  3199: aload           ob1
        //  3201: aload           student_id
        //  3203: aload           strAssess
        //  3205: iconst_0       
        //  3206: aaload         
        //  3207: invokevirtual   learnityasmtserver/assessmentportal/dbconnection/ReportDataBaseLayer.getLastStatus:(Ljava/lang/String;Ljava/lang/String;)Ljava/lang/String;
        //  3210: astore          status
        //  3212: iload           i
        //  3214: iconst_2       
        //  3215: irem           
        //  3216: ifne            3505
        //  3219: aload           assessmentTableBody2
        //  3221: new             Lorg/apache/ecs/html/TR;
        //  3224: dup            
        //  3225: invokespecial   org/apache/ecs/html/TR.<init>:()V
        //  3228: new             Lorg/apache/ecs/html/TD;
        //  3231: dup            
        //  3232: invokespecial   org/apache/ecs/html/TD.<init>:()V
        //  3235: new             Lorg/apache/ecs/html/Div;
        //  3238: dup            
        //  3239: invokespecial   org/apache/ecs/html/Div.<init>:()V
        //  3242: aload           inputButton1
        //  3244: ldc             "radio"
        //  3246: invokevirtual   org/apache/ecs/html/Input.setType:(Ljava/lang/String;)Lorg/apache/ecs/html/Input;
        //  3249: ldc             "checkbox"
        //  3251: invokevirtual   org/apache/ecs/html/Input.setName:(Ljava/lang/String;)Lorg/apache/ecs/html/Input;
        //  3254: aload           strAssess
        //  3256: iconst_0       
        //  3257: aaload         
        //  3258: invokevirtual   org/apache/ecs/html/Input.setValue:(Ljava/lang/String;)Lorg/apache/ecs/html/Input;
        //  3261: invokevirtual   org/apache/ecs/html/Div.addElement:(Lorg/apache/ecs/Element;)Lorg/apache/ecs/html/Div;
        //  3264: ldc             "AssessmentTableBodyRowSelect"
        //  3266: invokevirtual   org/apache/ecs/html/Div.setID:(Ljava/lang/String;)Lorg/apache/ecs/Element;
        //  3269: invokevirtual   org/apache/ecs/html/TD.addElement:(Lorg/apache/ecs/Element;)Lorg/apache/ecs/html/TD;
        //  3272: invokevirtual   org/apache/ecs/html/TR.addElement:(Lorg/apache/ecs/Element;)Lorg/apache/ecs/html/TR;
        //  3275: new             Lorg/apache/ecs/html/TD;
        //  3278: dup            
        //  3279: invokespecial   org/apache/ecs/html/TD.<init>:()V
        //  3282: new             Lorg/apache/ecs/html/Div;
        //  3285: dup            
        //  3286: invokespecial   org/apache/ecs/html/Div.<init>:()V
        //  3289: aload           strAssess
        //  3291: iconst_1       
        //  3292: aaload         
        //  3293: invokevirtual   org/apache/ecs/html/Div.addElement:(Ljava/lang/String;)Lorg/apache/ecs/html/Div;
        //  3296: ldc             "AssessmentTableBodyRowcol1"
        //  3298: invokevirtual   org/apache/ecs/html/Div.setID:(Ljava/lang/String;)Lorg/apache/ecs/Element;
        //  3301: invokevirtual   org/apache/ecs/html/TD.addElement:(Lorg/apache/ecs/Element;)Lorg/apache/ecs/html/TD;
        //  3304: invokevirtual   org/apache/ecs/html/TR.addElement:(Lorg/apache/ecs/Element;)Lorg/apache/ecs/html/TR;
        //  3307: new             Lorg/apache/ecs/html/TD;
        //  3310: dup            
        //  3311: invokespecial   org/apache/ecs/html/TD.<init>:()V
        //  3314: new             Lorg/apache/ecs/html/Div;
        //  3317: dup            
        //  3318: invokespecial   org/apache/ecs/html/Div.<init>:()V
        //  3321: aload           availablitydate
        //  3323: invokevirtual   org/apache/ecs/html/Div.addElement:(Ljava/lang/String;)Lorg/apache/ecs/html/Div;
        //  3326: ldc             "AssessmentTableBodyRowcol2"
        //  3328: invokevirtual   org/apache/ecs/html/Div.setID:(Ljava/lang/String;)Lorg/apache/ecs/Element;
        //  3331: invokevirtual   org/apache/ecs/html/TD.addElement:(Lorg/apache/ecs/Element;)Lorg/apache/ecs/html/TD;
        //  3334: invokevirtual   org/apache/ecs/html/TR.addElement:(Lorg/apache/ecs/Element;)Lorg/apache/ecs/html/TR;
        //  3337: new             Lorg/apache/ecs/html/TD;
        //  3340: dup            
        //  3341: invokespecial   org/apache/ecs/html/TD.<init>:()V
        //  3344: new             Lorg/apache/ecs/html/Div;
        //  3347: dup            
        //  3348: invokespecial   org/apache/ecs/html/Div.<init>:()V
        //  3351: aload           valid_upto
        //  3353: invokevirtual   org/apache/ecs/html/Div.addElement:(Ljava/lang/String;)Lorg/apache/ecs/html/Div;
        //  3356: ldc             "AssessmentTableBodyRowcol3"
        //  3358: invokevirtual   org/apache/ecs/html/Div.setID:(Ljava/lang/String;)Lorg/apache/ecs/Element;
        //  3361: invokevirtual   org/apache/ecs/html/TD.addElement:(Lorg/apache/ecs/Element;)Lorg/apache/ecs/html/TD;
        //  3364: invokevirtual   org/apache/ecs/html/TR.addElement:(Lorg/apache/ecs/Element;)Lorg/apache/ecs/html/TR;
        //  3367: new             Lorg/apache/ecs/html/TD;
        //  3370: dup            
        //  3371: invokespecial   org/apache/ecs/html/TD.<init>:()V
        //  3374: new             Lorg/apache/ecs/html/Div;
        //  3377: dup            
        //  3378: invokespecial   org/apache/ecs/html/Div.<init>:()V
        //  3381: aload           strAssess
        //  3383: iconst_5       
        //  3384: aaload         
        //  3385: invokevirtual   org/apache/ecs/html/Div.addElement:(Ljava/lang/String;)Lorg/apache/ecs/html/Div;
        //  3388: ldc             "AssessmentTableBodyRowcol4"
        //  3390: invokevirtual   org/apache/ecs/html/Div.setID:(Ljava/lang/String;)Lorg/apache/ecs/Element;
        //  3393: invokevirtual   org/apache/ecs/html/TD.addElement:(Lorg/apache/ecs/Element;)Lorg/apache/ecs/html/TD;
        //  3396: invokevirtual   org/apache/ecs/html/TR.addElement:(Lorg/apache/ecs/Element;)Lorg/apache/ecs/html/TR;
        //  3399: new             Lorg/apache/ecs/html/TD;
        //  3402: dup            
        //  3403: invokespecial   org/apache/ecs/html/TD.<init>:()V
        //  3406: new             Lorg/apache/ecs/html/Div;
        //  3409: dup            
        //  3410: invokespecial   org/apache/ecs/html/Div.<init>:()V
        //  3413: aload           strAssess
        //  3415: iconst_4       
        //  3416: aaload         
        //  3417: invokevirtual   org/apache/ecs/html/Div.addElement:(Ljava/lang/String;)Lorg/apache/ecs/html/Div;
        //  3420: ldc             "AssessmentTableBodyRowcol5"
        //  3422: invokevirtual   org/apache/ecs/html/Div.setID:(Ljava/lang/String;)Lorg/apache/ecs/Element;
        //  3425: invokevirtual   org/apache/ecs/html/TD.addElement:(Lorg/apache/ecs/Element;)Lorg/apache/ecs/html/TD;
        //  3428: invokevirtual   org/apache/ecs/html/TR.addElement:(Lorg/apache/ecs/Element;)Lorg/apache/ecs/html/TR;
        //  3431: new             Lorg/apache/ecs/html/TD;
        //  3434: dup            
        //  3435: invokespecial   org/apache/ecs/html/TD.<init>:()V
        //  3438: new             Lorg/apache/ecs/html/Div;
        //  3441: dup            
        //  3442: invokespecial   org/apache/ecs/html/Div.<init>:()V
        //  3445: aload           no_of_ques
        //  3447: invokevirtual   org/apache/ecs/html/Div.addElement:(Ljava/lang/String;)Lorg/apache/ecs/html/Div;
        //  3450: ldc             "AssessmentTableBodyRowcol6"
        //  3452: invokevirtual   org/apache/ecs/html/Div.setID:(Ljava/lang/String;)Lorg/apache/ecs/Element;
        //  3455: invokevirtual   org/apache/ecs/html/TD.addElement:(Lorg/apache/ecs/Element;)Lorg/apache/ecs/html/TD;
        //  3458: invokevirtual   org/apache/ecs/html/TR.addElement:(Lorg/apache/ecs/Element;)Lorg/apache/ecs/html/TR;
        //  3461: new             Lorg/apache/ecs/html/TD;
        //  3464: dup            
        //  3465: invokespecial   org/apache/ecs/html/TD.<init>:()V
        //  3468: new             Lorg/apache/ecs/html/Div;
        //  3471: dup            
        //  3472: invokespecial   org/apache/ecs/html/Div.<init>:()V
        //  3475: aload           status
        //  3477: invokevirtual   org/apache/ecs/html/Div.addElement:(Ljava/lang/String;)Lorg/apache/ecs/html/Div;
        //  3480: ldc_w           "AssessmentTableBodyRowcol7"
        //  3483: invokevirtual   org/apache/ecs/html/Div.setID:(Ljava/lang/String;)Lorg/apache/ecs/Element;
        //  3486: invokevirtual   org/apache/ecs/html/TD.addElement:(Lorg/apache/ecs/Element;)Lorg/apache/ecs/html/TD;
        //  3489: invokevirtual   org/apache/ecs/html/TR.addElement:(Lorg/apache/ecs/Element;)Lorg/apache/ecs/html/TR;
        //  3492: ldc_w           "AssessmentTableBodyRow"
        //  3495: invokevirtual   org/apache/ecs/html/TR.setID:(Ljava/lang/String;)Lorg/apache/ecs/Element;
        //  3498: invokevirtual   org/apache/ecs/html/Table.addElement:(Lorg/apache/ecs/Element;)Lorg/apache/ecs/html/Table;
        //  3501: pop            
        //  3502: goto            3795
        //  3505: aload           assessmentTableBody2
        //  3507: new             Lorg/apache/ecs/html/TR;
        //  3510: dup            
        //  3511: invokespecial   org/apache/ecs/html/TR.<init>:()V
        //  3514: new             Lorg/apache/ecs/html/TD;
        //  3517: dup            
        //  3518: invokespecial   org/apache/ecs/html/TD.<init>:()V
        //  3521: new             Lorg/apache/ecs/html/Div;
        //  3524: dup            
        //  3525: invokespecial   org/apache/ecs/html/Div.<init>:()V
        //  3528: aload           inputButton1
        //  3530: ldc             "radio"
        //  3532: invokevirtual   org/apache/ecs/html/Input.setType:(Ljava/lang/String;)Lorg/apache/ecs/html/Input;
        //  3535: ldc             "checkbox"
        //  3537: invokevirtual   org/apache/ecs/html/Input.setName:(Ljava/lang/String;)Lorg/apache/ecs/html/Input;
        //  3540: aload           strAssess
        //  3542: iconst_0       
        //  3543: aaload         
        //  3544: invokevirtual   org/apache/ecs/html/Input.setValue:(Ljava/lang/String;)Lorg/apache/ecs/html/Input;
        //  3547: invokevirtual   org/apache/ecs/html/Div.addElement:(Lorg/apache/ecs/Element;)Lorg/apache/ecs/html/Div;
        //  3550: ldc_w           "AssessmentTableBodyAltRowSelect"
        //  3553: invokevirtual   org/apache/ecs/html/Div.setID:(Ljava/lang/String;)Lorg/apache/ecs/Element;
        //  3556: invokevirtual   org/apache/ecs/html/TD.addElement:(Lorg/apache/ecs/Element;)Lorg/apache/ecs/html/TD;
        //  3559: invokevirtual   org/apache/ecs/html/TR.addElement:(Lorg/apache/ecs/Element;)Lorg/apache/ecs/html/TR;
        //  3562: new             Lorg/apache/ecs/html/TD;
        //  3565: dup            
        //  3566: invokespecial   org/apache/ecs/html/TD.<init>:()V
        //  3569: new             Lorg/apache/ecs/html/Div;
        //  3572: dup            
        //  3573: invokespecial   org/apache/ecs/html/Div.<init>:()V
        //  3576: aload           strAssess
        //  3578: iconst_1       
        //  3579: aaload         
        //  3580: invokevirtual   org/apache/ecs/html/Div.addElement:(Ljava/lang/String;)Lorg/apache/ecs/html/Div;
        //  3583: ldc_w           "AssessmentTableBodyAltRowcol1"
        //  3586: invokevirtual   org/apache/ecs/html/Div.setID:(Ljava/lang/String;)Lorg/apache/ecs/Element;
        //  3589: invokevirtual   org/apache/ecs/html/TD.addElement:(Lorg/apache/ecs/Element;)Lorg/apache/ecs/html/TD;
        //  3592: invokevirtual   org/apache/ecs/html/TR.addElement:(Lorg/apache/ecs/Element;)Lorg/apache/ecs/html/TR;
        //  3595: new             Lorg/apache/ecs/html/TD;
        //  3598: dup            
        //  3599: invokespecial   org/apache/ecs/html/TD.<init>:()V
        //  3602: new             Lorg/apache/ecs/html/Div;
        //  3605: dup            
        //  3606: invokespecial   org/apache/ecs/html/Div.<init>:()V
        //  3609: aload           availablitydate
        //  3611: invokevirtual   org/apache/ecs/html/Div.addElement:(Ljava/lang/String;)Lorg/apache/ecs/html/Div;
        //  3614: ldc_w           "AssessmentTableBodyAltRowcol2"
        //  3617: invokevirtual   org/apache/ecs/html/Div.setID:(Ljava/lang/String;)Lorg/apache/ecs/Element;
        //  3620: invokevirtual   org/apache/ecs/html/TD.addElement:(Lorg/apache/ecs/Element;)Lorg/apache/ecs/html/TD;
        //  3623: invokevirtual   org/apache/ecs/html/TR.addElement:(Lorg/apache/ecs/Element;)Lorg/apache/ecs/html/TR;
        //  3626: new             Lorg/apache/ecs/html/TD;
        //  3629: dup            
        //  3630: invokespecial   org/apache/ecs/html/TD.<init>:()V
        //  3633: new             Lorg/apache/ecs/html/Div;
        //  3636: dup            
        //  3637: invokespecial   org/apache/ecs/html/Div.<init>:()V
        //  3640: aload           valid_upto
        //  3642: invokevirtual   org/apache/ecs/html/Div.addElement:(Ljava/lang/String;)Lorg/apache/ecs/html/Div;
        //  3645: ldc_w           "AssessmentTableBodyAltRowcol3"
        //  3648: invokevirtual   org/apache/ecs/html/Div.setID:(Ljava/lang/String;)Lorg/apache/ecs/Element;
        //  3651: invokevirtual   org/apache/ecs/html/TD.addElement:(Lorg/apache/ecs/Element;)Lorg/apache/ecs/html/TD;
        //  3654: invokevirtual   org/apache/ecs/html/TR.addElement:(Lorg/apache/ecs/Element;)Lorg/apache/ecs/html/TR;
        //  3657: new             Lorg/apache/ecs/html/TD;
        //  3660: dup            
        //  3661: invokespecial   org/apache/ecs/html/TD.<init>:()V
        //  3664: new             Lorg/apache/ecs/html/Div;
        //  3667: dup            
        //  3668: invokespecial   org/apache/ecs/html/Div.<init>:()V
        //  3671: aload           strAssess
        //  3673: iconst_5       
        //  3674: aaload         
        //  3675: invokevirtual   org/apache/ecs/html/Div.addElement:(Ljava/lang/String;)Lorg/apache/ecs/html/Div;
        //  3678: ldc_w           "AssessmentTableBodyAltRowcol4"
        //  3681: invokevirtual   org/apache/ecs/html/Div.setID:(Ljava/lang/String;)Lorg/apache/ecs/Element;
        //  3684: invokevirtual   org/apache/ecs/html/TD.addElement:(Lorg/apache/ecs/Element;)Lorg/apache/ecs/html/TD;
        //  3687: invokevirtual   org/apache/ecs/html/TR.addElement:(Lorg/apache/ecs/Element;)Lorg/apache/ecs/html/TR;
        //  3690: new             Lorg/apache/ecs/html/TD;
        //  3693: dup            
        //  3694: invokespecial   org/apache/ecs/html/TD.<init>:()V
        //  3697: new             Lorg/apache/ecs/html/Div;
        //  3700: dup            
        //  3701: invokespecial   org/apache/ecs/html/Div.<init>:()V
        //  3704: aload           strAssess
        //  3706: iconst_4       
        //  3707: aaload         
        //  3708: invokevirtual   org/apache/ecs/html/Div.addElement:(Ljava/lang/String;)Lorg/apache/ecs/html/Div;
        //  3711: ldc_w           "AssessmentTableBodyAltRowcol5"
        //  3714: invokevirtual   org/apache/ecs/html/Div.setID:(Ljava/lang/String;)Lorg/apache/ecs/Element;
        //  3717: invokevirtual   org/apache/ecs/html/TD.addElement:(Lorg/apache/ecs/Element;)Lorg/apache/ecs/html/TD;
        //  3720: invokevirtual   org/apache/ecs/html/TR.addElement:(Lorg/apache/ecs/Element;)Lorg/apache/ecs/html/TR;
        //  3723: new             Lorg/apache/ecs/html/TD;
        //  3726: dup            
        //  3727: invokespecial   org/apache/ecs/html/TD.<init>:()V
        //  3730: new             Lorg/apache/ecs/html/Div;
        //  3733: dup            
        //  3734: invokespecial   org/apache/ecs/html/Div.<init>:()V
        //  3737: aload           no_of_ques
        //  3739: invokevirtual   org/apache/ecs/html/Div.addElement:(Ljava/lang/String;)Lorg/apache/ecs/html/Div;
        //  3742: ldc_w           "AssessmentTableBodyAltRowcol6"
        //  3745: invokevirtual   org/apache/ecs/html/Div.setID:(Ljava/lang/String;)Lorg/apache/ecs/Element;
        //  3748: invokevirtual   org/apache/ecs/html/TD.addElement:(Lorg/apache/ecs/Element;)Lorg/apache/ecs/html/TD;
        //  3751: invokevirtual   org/apache/ecs/html/TR.addElement:(Lorg/apache/ecs/Element;)Lorg/apache/ecs/html/TR;
        //  3754: new             Lorg/apache/ecs/html/TD;
        //  3757: dup            
        //  3758: invokespecial   org/apache/ecs/html/TD.<init>:()V
        //  3761: new             Lorg/apache/ecs/html/Div;
        //  3764: dup            
        //  3765: invokespecial   org/apache/ecs/html/Div.<init>:()V
        //  3768: aload           status
        //  3770: invokevirtual   org/apache/ecs/html/Div.addElement:(Ljava/lang/String;)Lorg/apache/ecs/html/Div;
        //  3773: ldc_w           "AssessmentTableBodyAltRowcol7"
        //  3776: invokevirtual   org/apache/ecs/html/Div.setID:(Ljava/lang/String;)Lorg/apache/ecs/Element;
        //  3779: invokevirtual   org/apache/ecs/html/TD.addElement:(Lorg/apache/ecs/Element;)Lorg/apache/ecs/html/TD;
        //  3782: invokevirtual   org/apache/ecs/html/TR.addElement:(Lorg/apache/ecs/Element;)Lorg/apache/ecs/html/TR;
        //  3785: ldc_w           "AssessmentTableBodyAltRow"
        //  3788: invokevirtual   org/apache/ecs/html/TR.setID:(Ljava/lang/String;)Lorg/apache/ecs/Element;
        //  3791: invokevirtual   org/apache/ecs/html/Table.addElement:(Lorg/apache/ecs/Element;)Lorg/apache/ecs/html/Table;
        //  3794: pop            
        //  3795: iinc            i, 1
        //  3798: goto            2879
        //  3801: goto            5724
        //  3804: aload           vAssessmentInfogroup
        //  3806: invokevirtual   java/util/Vector.size:()I
        //  3809: ifne            4740
        //  3812: iconst_0       
        //  3813: istore          i
        //  3815: iload           i
        //  3817: aload           vAssessmentInfo
        //  3819: invokevirtual   java/util/Vector.size:()I
        //  3822: if_icmpge       4737
        //  3825: new             Lorg/apache/ecs/html/Input;
        //  3828: dup            
        //  3829: invokespecial   org/apache/ecs/html/Input.<init>:()V
        //  3832: astore          inputButton1
        //  3834: aload           inputButton1
        //  3836: ldc             "check_onclick();"
        //  3838: invokevirtual   org/apache/ecs/html/Input.setOnClick:(Ljava/lang/String;)V
        //  3841: aload           vAssessmentInfo
        //  3843: iload           i
        //  3845: invokevirtual   java/util/Vector.elementAt:(I)Ljava/lang/Object;
        //  3848: checkcast       [Ljava/lang/String;
        //  3851: checkcast       [Ljava/lang/String;
        //  3854: astore          strAssess
        //  3856: ldc             ""
        //  3858: astore          availablitydate
        //  3860: ldc             ""
        //  3862: astore          valid_upto
        //  3864: aload           strAssess
        //  3866: iconst_2       
        //  3867: aaload         
        //  3868: ldc             ""
        //  3870: invokevirtual   java/lang/String.equals:(Ljava/lang/Object;)Z
        //  3873: ifne            3994
        //  3876: aload           strAssess
        //  3878: iconst_2       
        //  3879: aaload         
        //  3880: iconst_0       
        //  3881: aload           strAssess
        //  3883: iconst_2       
        //  3884: aaload         
        //  3885: bipush          32
        //  3887: invokevirtual   java/lang/String.indexOf:(I)I
        //  3890: invokevirtual   java/lang/String.substring:(II)Ljava/lang/String;
        //  3893: astore          str11
        //  3895: aload           str11
        //  3897: iconst_0       
        //  3898: aload           str11
        //  3900: bipush          45
        //  3902: invokevirtual   java/lang/String.indexOf:(I)I
        //  3905: invokevirtual   java/lang/String.substring:(II)Ljava/lang/String;
        //  3908: astore          str1
        //  3910: aload           str11
        //  3912: aload           str11
        //  3914: bipush          45
        //  3916: invokevirtual   java/lang/String.indexOf:(I)I
        //  3919: iconst_1       
        //  3920: iadd           
        //  3921: invokevirtual   java/lang/String.substring:(I)Ljava/lang/String;
        //  3924: astore          str2
        //  3926: aload           str2
        //  3928: iconst_0       
        //  3929: aload           str2
        //  3931: bipush          45
        //  3933: invokevirtual   java/lang/String.indexOf:(I)I
        //  3936: invokevirtual   java/lang/String.substring:(II)Ljava/lang/String;
        //  3939: astore          str3
        //  3941: aload           str2
        //  3943: aload           str2
        //  3945: bipush          45
        //  3947: invokevirtual   java/lang/String.indexOf:(I)I
        //  3950: iconst_1       
        //  3951: iadd           
        //  3952: invokevirtual   java/lang/String.substring:(I)Ljava/lang/String;
        //  3955: astore          str4
        //  3957: new             Ljava/lang/StringBuilder;
        //  3960: dup            
        //  3961: invokespecial   java/lang/StringBuilder.<init>:()V
        //  3964: aload           str4
        //  3966: invokevirtual   java/lang/StringBuilder.append:(Ljava/lang/String;)Ljava/lang/StringBuilder;
        //  3969: ldc             "-"
        //  3971: invokevirtual   java/lang/StringBuilder.append:(Ljava/lang/String;)Ljava/lang/StringBuilder;
        //  3974: aload           str3
        //  3976: invokevirtual   java/lang/StringBuilder.append:(Ljava/lang/String;)Ljava/lang/StringBuilder;
        //  3979: ldc             "-"
        //  3981: invokevirtual   java/lang/StringBuilder.append:(Ljava/lang/String;)Ljava/lang/StringBuilder;
        //  3984: aload           str1
        //  3986: invokevirtual   java/lang/StringBuilder.append:(Ljava/lang/String;)Ljava/lang/StringBuilder;
        //  3989: invokevirtual   java/lang/StringBuilder.toString:()Ljava/lang/String;
        //  3992: astore          availablitydate
        //  3994: aload           strAssess
        //  3996: iconst_3       
        //  3997: aaload         
        //  3998: ldc             ""
        //  4000: invokevirtual   java/lang/String.equals:(Ljava/lang/Object;)Z
        //  4003: ifne            4124
        //  4006: aload           strAssess
        //  4008: iconst_3       
        //  4009: aaload         
        //  4010: iconst_0       
        //  4011: aload           strAssess
        //  4013: iconst_2       
        //  4014: aaload         
        //  4015: bipush          32
        //  4017: invokevirtual   java/lang/String.indexOf:(I)I
        //  4020: invokevirtual   java/lang/String.substring:(II)Ljava/lang/String;
        //  4023: astore          str11
        //  4025: aload           str11
        //  4027: iconst_0       
        //  4028: aload           str11
        //  4030: bipush          45
        //  4032: invokevirtual   java/lang/String.indexOf:(I)I
        //  4035: invokevirtual   java/lang/String.substring:(II)Ljava/lang/String;
        //  4038: astore          str1
        //  4040: aload           str11
        //  4042: aload           str11
        //  4044: bipush          45
        //  4046: invokevirtual   java/lang/String.indexOf:(I)I
        //  4049: iconst_1       
        //  4050: iadd           
        //  4051: invokevirtual   java/lang/String.substring:(I)Ljava/lang/String;
        //  4054: astore          str2
        //  4056: aload           str2
        //  4058: iconst_0       
        //  4059: aload           str2
        //  4061: bipush          45
        //  4063: invokevirtual   java/lang/String.indexOf:(I)I
        //  4066: invokevirtual   java/lang/String.substring:(II)Ljava/lang/String;
        //  4069: astore          str3
        //  4071: aload           str2
        //  4073: aload           str2
        //  4075: bipush          45
        //  4077: invokevirtual   java/lang/String.indexOf:(I)I
        //  4080: iconst_1       
        //  4081: iadd           
        //  4082: invokevirtual   java/lang/String.substring:(I)Ljava/lang/String;
        //  4085: astore          str4
        //  4087: new             Ljava/lang/StringBuilder;
        //  4090: dup            
        //  4091: invokespecial   java/lang/StringBuilder.<init>:()V
        //  4094: aload           str4
        //  4096: invokevirtual   java/lang/StringBuilder.append:(Ljava/lang/String;)Ljava/lang/StringBuilder;
        //  4099: ldc             "-"
        //  4101: invokevirtual   java/lang/StringBuilder.append:(Ljava/lang/String;)Ljava/lang/StringBuilder;
        //  4104: aload           str3
        //  4106: invokevirtual   java/lang/StringBuilder.append:(Ljava/lang/String;)Ljava/lang/StringBuilder;
        //  4109: ldc             "-"
        //  4111: invokevirtual   java/lang/StringBuilder.append:(Ljava/lang/String;)Ljava/lang/StringBuilder;
        //  4114: aload           str1
        //  4116: invokevirtual   java/lang/StringBuilder.append:(Ljava/lang/String;)Ljava/lang/StringBuilder;
        //  4119: invokevirtual   java/lang/StringBuilder.toString:()Ljava/lang/String;
        //  4122: astore          valid_upto
        //  4124: aload           ob1
        //  4126: aload           strAssess
        //  4128: iconst_0       
        //  4129: aaload         
        //  4130: invokevirtual   learnityasmtserver/assessmentportal/dbconnection/ReportDataBaseLayer.getTotalquesno:(Ljava/lang/String;)Ljava/lang/String;
        //  4133: astore          no_of_ques
        //  4135: aload           ob1
        //  4137: aload           student_id
        //  4139: aload           strAssess
        //  4141: iconst_0       
        //  4142: aaload         
        //  4143: invokevirtual   learnityasmtserver/assessmentportal/dbconnection/ReportDataBaseLayer.getLastStatus:(Ljava/lang/String;Ljava/lang/String;)Ljava/lang/String;
        //  4146: astore          status
        //  4148: iload           i
        //  4150: iconst_2       
        //  4151: irem           
        //  4152: ifne            4441
        //  4155: aload           assessmentTableBody2
        //  4157: new             Lorg/apache/ecs/html/TR;
        //  4160: dup            
        //  4161: invokespecial   org/apache/ecs/html/TR.<init>:()V
        //  4164: new             Lorg/apache/ecs/html/TD;
        //  4167: dup            
        //  4168: invokespecial   org/apache/ecs/html/TD.<init>:()V
        //  4171: new             Lorg/apache/ecs/html/Div;
        //  4174: dup            
        //  4175: invokespecial   org/apache/ecs/html/Div.<init>:()V
        //  4178: aload           inputButton1
        //  4180: ldc             "radio"
        //  4182: invokevirtual   org/apache/ecs/html/Input.setType:(Ljava/lang/String;)Lorg/apache/ecs/html/Input;
        //  4185: ldc             "checkbox"
        //  4187: invokevirtual   org/apache/ecs/html/Input.setName:(Ljava/lang/String;)Lorg/apache/ecs/html/Input;
        //  4190: aload           strAssess
        //  4192: iconst_0       
        //  4193: aaload         
        //  4194: invokevirtual   org/apache/ecs/html/Input.setValue:(Ljava/lang/String;)Lorg/apache/ecs/html/Input;
        //  4197: invokevirtual   org/apache/ecs/html/Div.addElement:(Lorg/apache/ecs/Element;)Lorg/apache/ecs/html/Div;
        //  4200: ldc             "AssessmentTableBodyRowSelect"
        //  4202: invokevirtual   org/apache/ecs/html/Div.setID:(Ljava/lang/String;)Lorg/apache/ecs/Element;
        //  4205: invokevirtual   org/apache/ecs/html/TD.addElement:(Lorg/apache/ecs/Element;)Lorg/apache/ecs/html/TD;
        //  4208: invokevirtual   org/apache/ecs/html/TR.addElement:(Lorg/apache/ecs/Element;)Lorg/apache/ecs/html/TR;
        //  4211: new             Lorg/apache/ecs/html/TD;
        //  4214: dup            
        //  4215: invokespecial   org/apache/ecs/html/TD.<init>:()V
        //  4218: new             Lorg/apache/ecs/html/Div;
        //  4221: dup            
        //  4222: invokespecial   org/apache/ecs/html/Div.<init>:()V
        //  4225: aload           strAssess
        //  4227: iconst_1       
        //  4228: aaload         
        //  4229: invokevirtual   org/apache/ecs/html/Div.addElement:(Ljava/lang/String;)Lorg/apache/ecs/html/Div;
        //  4232: ldc             "AssessmentTableBodyRowcol1"
        //  4234: invokevirtual   org/apache/ecs/html/Div.setID:(Ljava/lang/String;)Lorg/apache/ecs/Element;
        //  4237: invokevirtual   org/apache/ecs/html/TD.addElement:(Lorg/apache/ecs/Element;)Lorg/apache/ecs/html/TD;
        //  4240: invokevirtual   org/apache/ecs/html/TR.addElement:(Lorg/apache/ecs/Element;)Lorg/apache/ecs/html/TR;
        //  4243: new             Lorg/apache/ecs/html/TD;
        //  4246: dup            
        //  4247: invokespecial   org/apache/ecs/html/TD.<init>:()V
        //  4250: new             Lorg/apache/ecs/html/Div;
        //  4253: dup            
        //  4254: invokespecial   org/apache/ecs/html/Div.<init>:()V
        //  4257: aload           availablitydate
        //  4259: invokevirtual   org/apache/ecs/html/Div.addElement:(Ljava/lang/String;)Lorg/apache/ecs/html/Div;
        //  4262: ldc             "AssessmentTableBodyRowcol2"
        //  4264: invokevirtual   org/apache/ecs/html/Div.setID:(Ljava/lang/String;)Lorg/apache/ecs/Element;
        //  4267: invokevirtual   org/apache/ecs/html/TD.addElement:(Lorg/apache/ecs/Element;)Lorg/apache/ecs/html/TD;
        //  4270: invokevirtual   org/apache/ecs/html/TR.addElement:(Lorg/apache/ecs/Element;)Lorg/apache/ecs/html/TR;
        //  4273: new             Lorg/apache/ecs/html/TD;
        //  4276: dup            
        //  4277: invokespecial   org/apache/ecs/html/TD.<init>:()V
        //  4280: new             Lorg/apache/ecs/html/Div;
        //  4283: dup            
        //  4284: invokespecial   org/apache/ecs/html/Div.<init>:()V
        //  4287: aload           valid_upto
        //  4289: invokevirtual   org/apache/ecs/html/Div.addElement:(Ljava/lang/String;)Lorg/apache/ecs/html/Div;
        //  4292: ldc             "AssessmentTableBodyRowcol3"
        //  4294: invokevirtual   org/apache/ecs/html/Div.setID:(Ljava/lang/String;)Lorg/apache/ecs/Element;
        //  4297: invokevirtual   org/apache/ecs/html/TD.addElement:(Lorg/apache/ecs/Element;)Lorg/apache/ecs/html/TD;
        //  4300: invokevirtual   org/apache/ecs/html/TR.addElement:(Lorg/apache/ecs/Element;)Lorg/apache/ecs/html/TR;
        //  4303: new             Lorg/apache/ecs/html/TD;
        //  4306: dup            
        //  4307: invokespecial   org/apache/ecs/html/TD.<init>:()V
        //  4310: new             Lorg/apache/ecs/html/Div;
        //  4313: dup            
        //  4314: invokespecial   org/apache/ecs/html/Div.<init>:()V
        //  4317: aload           strAssess
        //  4319: iconst_5       
        //  4320: aaload         
        //  4321: invokevirtual   org/apache/ecs/html/Div.addElement:(Ljava/lang/String;)Lorg/apache/ecs/html/Div;
        //  4324: ldc             "AssessmentTableBodyRowcol4"
        //  4326: invokevirtual   org/apache/ecs/html/Div.setID:(Ljava/lang/String;)Lorg/apache/ecs/Element;
        //  4329: invokevirtual   org/apache/ecs/html/TD.addElement:(Lorg/apache/ecs/Element;)Lorg/apache/ecs/html/TD;
        //  4332: invokevirtual   org/apache/ecs/html/TR.addElement:(Lorg/apache/ecs/Element;)Lorg/apache/ecs/html/TR;
        //  4335: new             Lorg/apache/ecs/html/TD;
        //  4338: dup            
        //  4339: invokespecial   org/apache/ecs/html/TD.<init>:()V
        //  4342: new             Lorg/apache/ecs/html/Div;
        //  4345: dup            
        //  4346: invokespecial   org/apache/ecs/html/Div.<init>:()V
        //  4349: aload           strAssess
        //  4351: iconst_4       
        //  4352: aaload         
        //  4353: invokevirtual   org/apache/ecs/html/Div.addElement:(Ljava/lang/String;)Lorg/apache/ecs/html/Div;
        //  4356: ldc             "AssessmentTableBodyRowcol5"
        //  4358: invokevirtual   org/apache/ecs/html/Div.setID:(Ljava/lang/String;)Lorg/apache/ecs/Element;
        //  4361: invokevirtual   org/apache/ecs/html/TD.addElement:(Lorg/apache/ecs/Element;)Lorg/apache/ecs/html/TD;
        //  4364: invokevirtual   org/apache/ecs/html/TR.addElement:(Lorg/apache/ecs/Element;)Lorg/apache/ecs/html/TR;
        //  4367: new             Lorg/apache/ecs/html/TD;
        //  4370: dup            
        //  4371: invokespecial   org/apache/ecs/html/TD.<init>:()V
        //  4374: new             Lorg/apache/ecs/html/Div;
        //  4377: dup            
        //  4378: invokespecial   org/apache/ecs/html/Div.<init>:()V
        //  4381: aload           no_of_ques
        //  4383: invokevirtual   org/apache/ecs/html/Div.addElement:(Ljava/lang/String;)Lorg/apache/ecs/html/Div;
        //  4386: ldc             "AssessmentTableBodyRowcol6"
        //  4388: invokevirtual   org/apache/ecs/html/Div.setID:(Ljava/lang/String;)Lorg/apache/ecs/Element;
        //  4391: invokevirtual   org/apache/ecs/html/TD.addElement:(Lorg/apache/ecs/Element;)Lorg/apache/ecs/html/TD;
        //  4394: invokevirtual   org/apache/ecs/html/TR.addElement:(Lorg/apache/ecs/Element;)Lorg/apache/ecs/html/TR;
        //  4397: new             Lorg/apache/ecs/html/TD;
        //  4400: dup            
        //  4401: invokespecial   org/apache/ecs/html/TD.<init>:()V
        //  4404: new             Lorg/apache/ecs/html/Div;
        //  4407: dup            
        //  4408: invokespecial   org/apache/ecs/html/Div.<init>:()V
        //  4411: aload           status
        //  4413: invokevirtual   org/apache/ecs/html/Div.addElement:(Ljava/lang/String;)Lorg/apache/ecs/html/Div;
        //  4416: ldc_w           "AssessmentTableBodyRowcol7"
        //  4419: invokevirtual   org/apache/ecs/html/Div.setID:(Ljava/lang/String;)Lorg/apache/ecs/Element;
        //  4422: invokevirtual   org/apache/ecs/html/TD.addElement:(Lorg/apache/ecs/Element;)Lorg/apache/ecs/html/TD;
        //  4425: invokevirtual   org/apache/ecs/html/TR.addElement:(Lorg/apache/ecs/Element;)Lorg/apache/ecs/html/TR;
        //  4428: ldc_w           "AssessmentTableBodyRow"
        //  4431: invokevirtual   org/apache/ecs/html/TR.setID:(Ljava/lang/String;)Lorg/apache/ecs/Element;
        //  4434: invokevirtual   org/apache/ecs/html/Table.addElement:(Lorg/apache/ecs/Element;)Lorg/apache/ecs/html/Table;
        //  4437: pop            
        //  4438: goto            4731
        //  4441: aload           assessmentTableBody2
        //  4443: new             Lorg/apache/ecs/html/TR;
        //  4446: dup            
        //  4447: invokespecial   org/apache/ecs/html/TR.<init>:()V
        //  4450: new             Lorg/apache/ecs/html/TD;
        //  4453: dup            
        //  4454: invokespecial   org/apache/ecs/html/TD.<init>:()V
        //  4457: new             Lorg/apache/ecs/html/Div;
        //  4460: dup            
        //  4461: invokespecial   org/apache/ecs/html/Div.<init>:()V
        //  4464: aload           inputButton1
        //  4466: ldc             "radio"
        //  4468: invokevirtual   org/apache/ecs/html/Input.setType:(Ljava/lang/String;)Lorg/apache/ecs/html/Input;
        //  4471: ldc             "checkbox"
        //  4473: invokevirtual   org/apache/ecs/html/Input.setName:(Ljava/lang/String;)Lorg/apache/ecs/html/Input;
        //  4476: aload           strAssess
        //  4478: iconst_0       
        //  4479: aaload         
        //  4480: invokevirtual   org/apache/ecs/html/Input.setValue:(Ljava/lang/String;)Lorg/apache/ecs/html/Input;
        //  4483: invokevirtual   org/apache/ecs/html/Div.addElement:(Lorg/apache/ecs/Element;)Lorg/apache/ecs/html/Div;
        //  4486: ldc_w           "AssessmentTableBodyAltRowSelect"
        //  4489: invokevirtual   org/apache/ecs/html/Div.setID:(Ljava/lang/String;)Lorg/apache/ecs/Element;
        //  4492: invokevirtual   org/apache/ecs/html/TD.addElement:(Lorg/apache/ecs/Element;)Lorg/apache/ecs/html/TD;
        //  4495: invokevirtual   org/apache/ecs/html/TR.addElement:(Lorg/apache/ecs/Element;)Lorg/apache/ecs/html/TR;
        //  4498: new             Lorg/apache/ecs/html/TD;
        //  4501: dup            
        //  4502: invokespecial   org/apache/ecs/html/TD.<init>:()V
        //  4505: new             Lorg/apache/ecs/html/Div;
        //  4508: dup            
        //  4509: invokespecial   org/apache/ecs/html/Div.<init>:()V
        //  4512: aload           strAssess
        //  4514: iconst_1       
        //  4515: aaload         
        //  4516: invokevirtual   org/apache/ecs/html/Div.addElement:(Ljava/lang/String;)Lorg/apache/ecs/html/Div;
        //  4519: ldc_w           "AssessmentTableBodyAltRowcol1"
        //  4522: invokevirtual   org/apache/ecs/html/Div.setID:(Ljava/lang/String;)Lorg/apache/ecs/Element;
        //  4525: invokevirtual   org/apache/ecs/html/TD.addElement:(Lorg/apache/ecs/Element;)Lorg/apache/ecs/html/TD;
        //  4528: invokevirtual   org/apache/ecs/html/TR.addElement:(Lorg/apache/ecs/Element;)Lorg/apache/ecs/html/TR;
        //  4531: new             Lorg/apache/ecs/html/TD;
        //  4534: dup            
        //  4535: invokespecial   org/apache/ecs/html/TD.<init>:()V
        //  4538: new             Lorg/apache/ecs/html/Div;
        //  4541: dup            
        //  4542: invokespecial   org/apache/ecs/html/Div.<init>:()V
        //  4545: aload           availablitydate
        //  4547: invokevirtual   org/apache/ecs/html/Div.addElement:(Ljava/lang/String;)Lorg/apache/ecs/html/Div;
        //  4550: ldc_w           "AssessmentTableBodyAltRowcol2"
        //  4553: invokevirtual   org/apache/ecs/html/Div.setID:(Ljava/lang/String;)Lorg/apache/ecs/Element;
        //  4556: invokevirtual   org/apache/ecs/html/TD.addElement:(Lorg/apache/ecs/Element;)Lorg/apache/ecs/html/TD;
        //  4559: invokevirtual   org/apache/ecs/html/TR.addElement:(Lorg/apache/ecs/Element;)Lorg/apache/ecs/html/TR;
        //  4562: new             Lorg/apache/ecs/html/TD;
        //  4565: dup            
        //  4566: invokespecial   org/apache/ecs/html/TD.<init>:()V
        //  4569: new             Lorg/apache/ecs/html/Div;
        //  4572: dup            
        //  4573: invokespecial   org/apache/ecs/html/Div.<init>:()V
        //  4576: aload           valid_upto
        //  4578: invokevirtual   org/apache/ecs/html/Div.addElement:(Ljava/lang/String;)Lorg/apache/ecs/html/Div;
        //  4581: ldc_w           "AssessmentTableBodyAltRowcol3"
        //  4584: invokevirtual   org/apache/ecs/html/Div.setID:(Ljava/lang/String;)Lorg/apache/ecs/Element;
        //  4587: invokevirtual   org/apache/ecs/html/TD.addElement:(Lorg/apache/ecs/Element;)Lorg/apache/ecs/html/TD;
        //  4590: invokevirtual   org/apache/ecs/html/TR.addElement:(Lorg/apache/ecs/Element;)Lorg/apache/ecs/html/TR;
        //  4593: new             Lorg/apache/ecs/html/TD;
        //  4596: dup            
        //  4597: invokespecial   org/apache/ecs/html/TD.<init>:()V
        //  4600: new             Lorg/apache/ecs/html/Div;
        //  4603: dup            
        //  4604: invokespecial   org/apache/ecs/html/Div.<init>:()V
        //  4607: aload           strAssess
        //  4609: iconst_5       
        //  4610: aaload         
        //  4611: invokevirtual   org/apache/ecs/html/Div.addElement:(Ljava/lang/String;)Lorg/apache/ecs/html/Div;
        //  4614: ldc_w           "AssessmentTableBodyAltRowcol4"
        //  4617: invokevirtual   org/apache/ecs/html/Div.setID:(Ljava/lang/String;)Lorg/apache/ecs/Element;
        //  4620: invokevirtual   org/apache/ecs/html/TD.addElement:(Lorg/apache/ecs/Element;)Lorg/apache/ecs/html/TD;
        //  4623: invokevirtual   org/apache/ecs/html/TR.addElement:(Lorg/apache/ecs/Element;)Lorg/apache/ecs/html/TR;
        //  4626: new             Lorg/apache/ecs/html/TD;
        //  4629: dup            
        //  4630: invokespecial   org/apache/ecs/html/TD.<init>:()V
        //  4633: new             Lorg/apache/ecs/html/Div;
        //  4636: dup            
        //  4637: invokespecial   org/apache/ecs/html/Div.<init>:()V
        //  4640: aload           strAssess
        //  4642: iconst_4       
        //  4643: aaload         
        //  4644: invokevirtual   org/apache/ecs/html/Div.addElement:(Ljava/lang/String;)Lorg/apache/ecs/html/Div;
        //  4647: ldc_w           "AssessmentTableBodyAltRowcol5"
        //  4650: invokevirtual   org/apache/ecs/html/Div.setID:(Ljava/lang/String;)Lorg/apache/ecs/Element;
        //  4653: invokevirtual   org/apache/ecs/html/TD.addElement:(Lorg/apache/ecs/Element;)Lorg/apache/ecs/html/TD;
        //  4656: invokevirtual   org/apache/ecs/html/TR.addElement:(Lorg/apache/ecs/Element;)Lorg/apache/ecs/html/TR;
        //  4659: new             Lorg/apache/ecs/html/TD;
        //  4662: dup            
        //  4663: invokespecial   org/apache/ecs/html/TD.<init>:()V
        //  4666: new             Lorg/apache/ecs/html/Div;
        //  4669: dup            
        //  4670: invokespecial   org/apache/ecs/html/Div.<init>:()V
        //  4673: aload           no_of_ques
        //  4675: invokevirtual   org/apache/ecs/html/Div.addElement:(Ljava/lang/String;)Lorg/apache/ecs/html/Div;
        //  4678: ldc_w           "AssessmentTableBodyAltRowcol6"
        //  4681: invokevirtual   org/apache/ecs/html/Div.setID:(Ljava/lang/String;)Lorg/apache/ecs/Element;
        //  4684: invokevirtual   org/apache/ecs/html/TD.addElement:(Lorg/apache/ecs/Element;)Lorg/apache/ecs/html/TD;
        //  4687: invokevirtual   org/apache/ecs/html/TR.addElement:(Lorg/apache/ecs/Element;)Lorg/apache/ecs/html/TR;
        //  4690: new             Lorg/apache/ecs/html/TD;
        //  4693: dup            
        //  4694: invokespecial   org/apache/ecs/html/TD.<init>:()V
        //  4697: new             Lorg/apache/ecs/html/Div;
        //  4700: dup            
        //  4701: invokespecial   org/apache/ecs/html/Div.<init>:()V
        //  4704: aload           status
        //  4706: invokevirtual   org/apache/ecs/html/Div.addElement:(Ljava/lang/String;)Lorg/apache/ecs/html/Div;
        //  4709: ldc_w           "AssessmentTableBodyAltRowcol7"
        //  4712: invokevirtual   org/apache/ecs/html/Div.setID:(Ljava/lang/String;)Lorg/apache/ecs/Element;
        //  4715: invokevirtual   org/apache/ecs/html/TD.addElement:(Lorg/apache/ecs/Element;)Lorg/apache/ecs/html/TD;
        //  4718: invokevirtual   org/apache/ecs/html/TR.addElement:(Lorg/apache/ecs/Element;)Lorg/apache/ecs/html/TR;
        //  4721: ldc_w           "AssessmentTableBodyAltRow"
        //  4724: invokevirtual   org/apache/ecs/html/TR.setID:(Ljava/lang/String;)Lorg/apache/ecs/Element;
        //  4727: invokevirtual   org/apache/ecs/html/Table.addElement:(Lorg/apache/ecs/Element;)Lorg/apache/ecs/html/Table;
        //  4730: pop            
        //  4731: iinc            i, 1
        //  4734: goto            3815
        //  4737: goto            5724
        //  4740: aload           vAssessmentInfogroup
        //  4742: invokevirtual   java/util/Vector.size:()I
        //  4745: aload           vAssessmentInfo
        //  4747: invokevirtual   java/util/Vector.size:()I
        //  4750: iadd           
        //  4751: istore          sizeass
        //  4753: iconst_0       
        //  4754: istore          i
        //  4756: iload           i
        //  4758: iload           sizeass
        //  4760: if_icmpge       5724
        //  4763: new             Lorg/apache/ecs/html/Input;
        //  4766: dup            
        //  4767: invokespecial   org/apache/ecs/html/Input.<init>:()V
        //  4770: astore          inputButton1
        //  4772: aload           inputButton1
        //  4774: ldc             "check_onclick();"
        //  4776: invokevirtual   org/apache/ecs/html/Input.setOnClick:(Ljava/lang/String;)V
        //  4779: bipush          8
        //  4781: anewarray       Ljava/lang/String;
        //  4784: astore          strAssess
        //  4786: aload           vAssessmentInfo
        //  4788: invokevirtual   java/util/Vector.size:()I
        //  4791: istore          size11
        //  4793: iload           i
        //  4795: iload           size11
        //  4797: if_icmpge       4818
        //  4800: aload           vAssessmentInfo
        //  4802: iload           i
        //  4804: invokevirtual   java/util/Vector.elementAt:(I)Ljava/lang/Object;
        //  4807: checkcast       [Ljava/lang/String;
        //  4810: checkcast       [Ljava/lang/String;
        //  4813: astore          strAssess
        //  4815: goto            4843
        //  4818: iload           i
        //  4820: aload           vAssessmentInfo
        //  4822: invokevirtual   java/util/Vector.size:()I
        //  4825: isub           
        //  4826: istore          j
        //  4828: aload           vAssessmentInfogroup
        //  4830: iload           j
        //  4832: invokevirtual   java/util/Vector.elementAt:(I)Ljava/lang/Object;
        //  4835: checkcast       [Ljava/lang/String;
        //  4838: checkcast       [Ljava/lang/String;
        //  4841: astore          strAssess
        //  4843: ldc             ""
        //  4845: astore          availablitydate
        //  4847: ldc             ""
        //  4849: astore          valid_upto
        //  4851: aload           strAssess
        //  4853: iconst_2       
        //  4854: aaload         
        //  4855: ldc             ""
        //  4857: invokevirtual   java/lang/String.equals:(Ljava/lang/Object;)Z
        //  4860: ifne            4981
        //  4863: aload           strAssess
        //  4865: iconst_2       
        //  4866: aaload         
        //  4867: iconst_0       
        //  4868: aload           strAssess
        //  4870: iconst_2       
        //  4871: aaload         
        //  4872: bipush          32
        //  4874: invokevirtual   java/lang/String.indexOf:(I)I
        //  4877: invokevirtual   java/lang/String.substring:(II)Ljava/lang/String;
        //  4880: astore          str11
        //  4882: aload           str11
        //  4884: iconst_0       
        //  4885: aload           str11
        //  4887: bipush          45
        //  4889: invokevirtual   java/lang/String.indexOf:(I)I
        //  4892: invokevirtual   java/lang/String.substring:(II)Ljava/lang/String;
        //  4895: astore          str1
        //  4897: aload           str11
        //  4899: aload           str11
        //  4901: bipush          45
        //  4903: invokevirtual   java/lang/String.indexOf:(I)I
        //  4906: iconst_1       
        //  4907: iadd           
        //  4908: invokevirtual   java/lang/String.substring:(I)Ljava/lang/String;
        //  4911: astore          str2
        //  4913: aload           str2
        //  4915: iconst_0       
        //  4916: aload           str2
        //  4918: bipush          45
        //  4920: invokevirtual   java/lang/String.indexOf:(I)I
        //  4923: invokevirtual   java/lang/String.substring:(II)Ljava/lang/String;
        //  4926: astore          str3
        //  4928: aload           str2
        //  4930: aload           str2
        //  4932: bipush          45
        //  4934: invokevirtual   java/lang/String.indexOf:(I)I
        //  4937: iconst_1       
        //  4938: iadd           
        //  4939: invokevirtual   java/lang/String.substring:(I)Ljava/lang/String;
        //  4942: astore          str4
        //  4944: new             Ljava/lang/StringBuilder;
        //  4947: dup            
        //  4948: invokespecial   java/lang/StringBuilder.<init>:()V
        //  4951: aload           str4
        //  4953: invokevirtual   java/lang/StringBuilder.append:(Ljava/lang/String;)Ljava/lang/StringBuilder;
        //  4956: ldc             "-"
        //  4958: invokevirtual   java/lang/StringBuilder.append:(Ljava/lang/String;)Ljava/lang/StringBuilder;
        //  4961: aload           str3
        //  4963: invokevirtual   java/lang/StringBuilder.append:(Ljava/lang/String;)Ljava/lang/StringBuilder;
        //  4966: ldc             "-"
        //  4968: invokevirtual   java/lang/StringBuilder.append:(Ljava/lang/String;)Ljava/lang/StringBuilder;
        //  4971: aload           str1
        //  4973: invokevirtual   java/lang/StringBuilder.append:(Ljava/lang/String;)Ljava/lang/StringBuilder;
        //  4976: invokevirtual   java/lang/StringBuilder.toString:()Ljava/lang/String;
        //  4979: astore          availablitydate
        //  4981: aload           strAssess
        //  4983: iconst_3       
        //  4984: aaload         
        //  4985: ldc             ""
        //  4987: invokevirtual   java/lang/String.equals:(Ljava/lang/Object;)Z
        //  4990: ifne            5111
        //  4993: aload           strAssess
        //  4995: iconst_3       
        //  4996: aaload         
        //  4997: iconst_0       
        //  4998: aload           strAssess
        //  5000: iconst_2       
        //  5001: aaload         
        //  5002: bipush          32
        //  5004: invokevirtual   java/lang/String.indexOf:(I)I
        //  5007: invokevirtual   java/lang/String.substring:(II)Ljava/lang/String;
        //  5010: astore          str11
        //  5012: aload           str11
        //  5014: iconst_0       
        //  5015: aload           str11
        //  5017: bipush          45
        //  5019: invokevirtual   java/lang/String.indexOf:(I)I
        //  5022: invokevirtual   java/lang/String.substring:(II)Ljava/lang/String;
        //  5025: astore          str1
        //  5027: aload           str11
        //  5029: aload           str11
        //  5031: bipush          45
        //  5033: invokevirtual   java/lang/String.indexOf:(I)I
        //  5036: iconst_1       
        //  5037: iadd           
        //  5038: invokevirtual   java/lang/String.substring:(I)Ljava/lang/String;
        //  5041: astore          str2
        //  5043: aload           str2
        //  5045: iconst_0       
        //  5046: aload           str2
        //  5048: bipush          45
        //  5050: invokevirtual   java/lang/String.indexOf:(I)I
        //  5053: invokevirtual   java/lang/String.substring:(II)Ljava/lang/String;
        //  5056: astore          str3
        //  5058: aload           str2
        //  5060: aload           str2
        //  5062: bipush          45
        //  5064: invokevirtual   java/lang/String.indexOf:(I)I
        //  5067: iconst_1       
        //  5068: iadd           
        //  5069: invokevirtual   java/lang/String.substring:(I)Ljava/lang/String;
        //  5072: astore          str4
        //  5074: new             Ljava/lang/StringBuilder;
        //  5077: dup            
        //  5078: invokespecial   java/lang/StringBuilder.<init>:()V
        //  5081: aload           str4
        //  5083: invokevirtual   java/lang/StringBuilder.append:(Ljava/lang/String;)Ljava/lang/StringBuilder;
        //  5086: ldc             "-"
        //  5088: invokevirtual   java/lang/StringBuilder.append:(Ljava/lang/String;)Ljava/lang/StringBuilder;
        //  5091: aload           str3
        //  5093: invokevirtual   java/lang/StringBuilder.append:(Ljava/lang/String;)Ljava/lang/StringBuilder;
        //  5096: ldc             "-"
        //  5098: invokevirtual   java/lang/StringBuilder.append:(Ljava/lang/String;)Ljava/lang/StringBuilder;
        //  5101: aload           str1
        //  5103: invokevirtual   java/lang/StringBuilder.append:(Ljava/lang/String;)Ljava/lang/StringBuilder;
        //  5106: invokevirtual   java/lang/StringBuilder.toString:()Ljava/lang/String;
        //  5109: astore          valid_upto
        //  5111: aload           ob1
        //  5113: aload           strAssess
        //  5115: iconst_0       
        //  5116: aaload         
        //  5117: invokevirtual   learnityasmtserver/assessmentportal/dbconnection/ReportDataBaseLayer.getTotalquesno:(Ljava/lang/String;)Ljava/lang/String;
        //  5120: astore          no_of_ques
        //  5122: aload           ob1
        //  5124: aload           student_id
        //  5126: aload           strAssess
        //  5128: iconst_0       
        //  5129: aaload         
        //  5130: invokevirtual   learnityasmtserver/assessmentportal/dbconnection/ReportDataBaseLayer.getLastStatus:(Ljava/lang/String;Ljava/lang/String;)Ljava/lang/String;
        //  5133: astore          status
        //  5135: iload           i
        //  5137: iconst_2       
        //  5138: irem           
        //  5139: ifne            5428
        //  5142: aload           assessmentTableBody2
        //  5144: new             Lorg/apache/ecs/html/TR;
        //  5147: dup            
        //  5148: invokespecial   org/apache/ecs/html/TR.<init>:()V
        //  5151: new             Lorg/apache/ecs/html/TD;
        //  5154: dup            
        //  5155: invokespecial   org/apache/ecs/html/TD.<init>:()V
        //  5158: new             Lorg/apache/ecs/html/Div;
        //  5161: dup            
        //  5162: invokespecial   org/apache/ecs/html/Div.<init>:()V
        //  5165: aload           inputButton1
        //  5167: ldc             "radio"
        //  5169: invokevirtual   org/apache/ecs/html/Input.setType:(Ljava/lang/String;)Lorg/apache/ecs/html/Input;
        //  5172: ldc             "checkbox"
        //  5174: invokevirtual   org/apache/ecs/html/Input.setName:(Ljava/lang/String;)Lorg/apache/ecs/html/Input;
        //  5177: aload           strAssess
        //  5179: iconst_0       
        //  5180: aaload         
        //  5181: invokevirtual   org/apache/ecs/html/Input.setValue:(Ljava/lang/String;)Lorg/apache/ecs/html/Input;
        //  5184: invokevirtual   org/apache/ecs/html/Div.addElement:(Lorg/apache/ecs/Element;)Lorg/apache/ecs/html/Div;
        //  5187: ldc             "AssessmentTableBodyRowSelect"
        //  5189: invokevirtual   org/apache/ecs/html/Div.setID:(Ljava/lang/String;)Lorg/apache/ecs/Element;
        //  5192: invokevirtual   org/apache/ecs/html/TD.addElement:(Lorg/apache/ecs/Element;)Lorg/apache/ecs/html/TD;
        //  5195: invokevirtual   org/apache/ecs/html/TR.addElement:(Lorg/apache/ecs/Element;)Lorg/apache/ecs/html/TR;
        //  5198: new             Lorg/apache/ecs/html/TD;
        //  5201: dup            
        //  5202: invokespecial   org/apache/ecs/html/TD.<init>:()V
        //  5205: new             Lorg/apache/ecs/html/Div;
        //  5208: dup            
        //  5209: invokespecial   org/apache/ecs/html/Div.<init>:()V
        //  5212: aload           strAssess
        //  5214: iconst_1       
        //  5215: aaload         
        //  5216: invokevirtual   org/apache/ecs/html/Div.addElement:(Ljava/lang/String;)Lorg/apache/ecs/html/Div;
        //  5219: ldc             "AssessmentTableBodyRowcol1"
        //  5221: invokevirtual   org/apache/ecs/html/Div.setID:(Ljava/lang/String;)Lorg/apache/ecs/Element;
        //  5224: invokevirtual   org/apache/ecs/html/TD.addElement:(Lorg/apache/ecs/Element;)Lorg/apache/ecs/html/TD;
        //  5227: invokevirtual   org/apache/ecs/html/TR.addElement:(Lorg/apache/ecs/Element;)Lorg/apache/ecs/html/TR;
        //  5230: new             Lorg/apache/ecs/html/TD;
        //  5233: dup            
        //  5234: invokespecial   org/apache/ecs/html/TD.<init>:()V
        //  5237: new             Lorg/apache/ecs/html/Div;
        //  5240: dup            
        //  5241: invokespecial   org/apache/ecs/html/Div.<init>:()V
        //  5244: aload           availablitydate
        //  5246: invokevirtual   org/apache/ecs/html/Div.addElement:(Ljava/lang/String;)Lorg/apache/ecs/html/Div;
        //  5249: ldc             "AssessmentTableBodyRowcol2"
        //  5251: invokevirtual   org/apache/ecs/html/Div.setID:(Ljava/lang/String;)Lorg/apache/ecs/Element;
        //  5254: invokevirtual   org/apache/ecs/html/TD.addElement:(Lorg/apache/ecs/Element;)Lorg/apache/ecs/html/TD;
        //  5257: invokevirtual   org/apache/ecs/html/TR.addElement:(Lorg/apache/ecs/Element;)Lorg/apache/ecs/html/TR;
        //  5260: new             Lorg/apache/ecs/html/TD;
        //  5263: dup            
        //  5264: invokespecial   org/apache/ecs/html/TD.<init>:()V
        //  5267: new             Lorg/apache/ecs/html/Div;
        //  5270: dup            
        //  5271: invokespecial   org/apache/ecs/html/Div.<init>:()V
        //  5274: aload           valid_upto
        //  5276: invokevirtual   org/apache/ecs/html/Div.addElement:(Ljava/lang/String;)Lorg/apache/ecs/html/Div;
        //  5279: ldc             "AssessmentTableBodyRowcol3"
        //  5281: invokevirtual   org/apache/ecs/html/Div.setID:(Ljava/lang/String;)Lorg/apache/ecs/Element;
        //  5284: invokevirtual   org/apache/ecs/html/TD.addElement:(Lorg/apache/ecs/Element;)Lorg/apache/ecs/html/TD;
        //  5287: invokevirtual   org/apache/ecs/html/TR.addElement:(Lorg/apache/ecs/Element;)Lorg/apache/ecs/html/TR;
        //  5290: new             Lorg/apache/ecs/html/TD;
        //  5293: dup            
        //  5294: invokespecial   org/apache/ecs/html/TD.<init>:()V
        //  5297: new             Lorg/apache/ecs/html/Div;
        //  5300: dup            
        //  5301: invokespecial   org/apache/ecs/html/Div.<init>:()V
        //  5304: aload           strAssess
        //  5306: iconst_5       
        //  5307: aaload         
        //  5308: invokevirtual   org/apache/ecs/html/Div.addElement:(Ljava/lang/String;)Lorg/apache/ecs/html/Div;
        //  5311: ldc             "AssessmentTableBodyRowcol4"
        //  5313: invokevirtual   org/apache/ecs/html/Div.setID:(Ljava/lang/String;)Lorg/apache/ecs/Element;
        //  5316: invokevirtual   org/apache/ecs/html/TD.addElement:(Lorg/apache/ecs/Element;)Lorg/apache/ecs/html/TD;
        //  5319: invokevirtual   org/apache/ecs/html/TR.addElement:(Lorg/apache/ecs/Element;)Lorg/apache/ecs/html/TR;
        //  5322: new             Lorg/apache/ecs/html/TD;
        //  5325: dup            
        //  5326: invokespecial   org/apache/ecs/html/TD.<init>:()V
        //  5329: new             Lorg/apache/ecs/html/Div;
        //  5332: dup            
        //  5333: invokespecial   org/apache/ecs/html/Div.<init>:()V
        //  5336: aload           strAssess
        //  5338: iconst_4       
        //  5339: aaload         
        //  5340: invokevirtual   org/apache/ecs/html/Div.addElement:(Ljava/lang/String;)Lorg/apache/ecs/html/Div;
        //  5343: ldc             "AssessmentTableBodyRowcol5"
        //  5345: invokevirtual   org/apache/ecs/html/Div.setID:(Ljava/lang/String;)Lorg/apache/ecs/Element;
        //  5348: invokevirtual   org/apache/ecs/html/TD.addElement:(Lorg/apache/ecs/Element;)Lorg/apache/ecs/html/TD;
        //  5351: invokevirtual   org/apache/ecs/html/TR.addElement:(Lorg/apache/ecs/Element;)Lorg/apache/ecs/html/TR;
        //  5354: new             Lorg/apache/ecs/html/TD;
        //  5357: dup            
        //  5358: invokespecial   org/apache/ecs/html/TD.<init>:()V
        //  5361: new             Lorg/apache/ecs/html/Div;
        //  5364: dup            
        //  5365: invokespecial   org/apache/ecs/html/Div.<init>:()V
        //  5368: aload           no_of_ques
        //  5370: invokevirtual   org/apache/ecs/html/Div.addElement:(Ljava/lang/String;)Lorg/apache/ecs/html/Div;
        //  5373: ldc             "AssessmentTableBodyRowcol6"
        //  5375: invokevirtual   org/apache/ecs/html/Div.setID:(Ljava/lang/String;)Lorg/apache/ecs/Element;
        //  5378: invokevirtual   org/apache/ecs/html/TD.addElement:(Lorg/apache/ecs/Element;)Lorg/apache/ecs/html/TD;
        //  5381: invokevirtual   org/apache/ecs/html/TR.addElement:(Lorg/apache/ecs/Element;)Lorg/apache/ecs/html/TR;
        //  5384: new             Lorg/apache/ecs/html/TD;
        //  5387: dup            
        //  5388: invokespecial   org/apache/ecs/html/TD.<init>:()V
        //  5391: new             Lorg/apache/ecs/html/Div;
        //  5394: dup            
        //  5395: invokespecial   org/apache/ecs/html/Div.<init>:()V
        //  5398: aload           status
        //  5400: invokevirtual   org/apache/ecs/html/Div.addElement:(Ljava/lang/String;)Lorg/apache/ecs/html/Div;
        //  5403: ldc_w           "AssessmentTableBodyRowcol7"
        //  5406: invokevirtual   org/apache/ecs/html/Div.setID:(Ljava/lang/String;)Lorg/apache/ecs/Element;
        //  5409: invokevirtual   org/apache/ecs/html/TD.addElement:(Lorg/apache/ecs/Element;)Lorg/apache/ecs/html/TD;
        //  5412: invokevirtual   org/apache/ecs/html/TR.addElement:(Lorg/apache/ecs/Element;)Lorg/apache/ecs/html/TR;
        //  5415: ldc_w           "AssessmentTableBodyRow"
        //  5418: invokevirtual   org/apache/ecs/html/TR.setID:(Ljava/lang/String;)Lorg/apache/ecs/Element;
        //  5421: invokevirtual   org/apache/ecs/html/Table.addElement:(Lorg/apache/ecs/Element;)Lorg/apache/ecs/html/Table;
        //  5424: pop            
        //  5425: goto            5718
        //  5428: aload           assessmentTableBody2
        //  5430: new             Lorg/apache/ecs/html/TR;
        //  5433: dup            
        //  5434: invokespecial   org/apache/ecs/html/TR.<init>:()V
        //  5437: new             Lorg/apache/ecs/html/TD;
        //  5440: dup            
        //  5441: invokespecial   org/apache/ecs/html/TD.<init>:()V
        //  5444: new             Lorg/apache/ecs/html/Div;
        //  5447: dup            
        //  5448: invokespecial   org/apache/ecs/html/Div.<init>:()V
        //  5451: aload           inputButton1
        //  5453: ldc             "radio"
        //  5455: invokevirtual   org/apache/ecs/html/Input.setType:(Ljava/lang/String;)Lorg/apache/ecs/html/Input;
        //  5458: ldc             "checkbox"
        //  5460: invokevirtual   org/apache/ecs/html/Input.setName:(Ljava/lang/String;)Lorg/apache/ecs/html/Input;
        //  5463: aload           strAssess
        //  5465: iconst_0       
        //  5466: aaload         
        //  5467: invokevirtual   org/apache/ecs/html/Input.setValue:(Ljava/lang/String;)Lorg/apache/ecs/html/Input;
        //  5470: invokevirtual   org/apache/ecs/html/Div.addElement:(Lorg/apache/ecs/Element;)Lorg/apache/ecs/html/Div;
        //  5473: ldc_w           "AssessmentTableBodyAltRowSelect"
        //  5476: invokevirtual   org/apache/ecs/html/Div.setID:(Ljava/lang/String;)Lorg/apache/ecs/Element;
        //  5479: invokevirtual   org/apache/ecs/html/TD.addElement:(Lorg/apache/ecs/Element;)Lorg/apache/ecs/html/TD;
        //  5482: invokevirtual   org/apache/ecs/html/TR.addElement:(Lorg/apache/ecs/Element;)Lorg/apache/ecs/html/TR;
        //  5485: new             Lorg/apache/ecs/html/TD;
        //  5488: dup            
        //  5489: invokespecial   org/apache/ecs/html/TD.<init>:()V
        //  5492: new             Lorg/apache/ecs/html/Div;
        //  5495: dup            
        //  5496: invokespecial   org/apache/ecs/html/Div.<init>:()V
        //  5499: aload           strAssess
        //  5501: iconst_1       
        //  5502: aaload         
        //  5503: invokevirtual   org/apache/ecs/html/Div.addElement:(Ljava/lang/String;)Lorg/apache/ecs/html/Div;
        //  5506: ldc_w           "AssessmentTableBodyAltRowcol1"
        //  5509: invokevirtual   org/apache/ecs/html/Div.setID:(Ljava/lang/String;)Lorg/apache/ecs/Element;
        //  5512: invokevirtual   org/apache/ecs/html/TD.addElement:(Lorg/apache/ecs/Element;)Lorg/apache/ecs/html/TD;
        //  5515: invokevirtual   org/apache/ecs/html/TR.addElement:(Lorg/apache/ecs/Element;)Lorg/apache/ecs/html/TR;
        //  5518: new             Lorg/apache/ecs/html/TD;
        //  5521: dup            
        //  5522: invokespecial   org/apache/ecs/html/TD.<init>:()V
        //  5525: new             Lorg/apache/ecs/html/Div;
        //  5528: dup            
        //  5529: invokespecial   org/apache/ecs/html/Div.<init>:()V
        //  5532: aload           availablitydate
        //  5534: invokevirtual   org/apache/ecs/html/Div.addElement:(Ljava/lang/String;)Lorg/apache/ecs/html/Div;
        //  5537: ldc_w           "AssessmentTableBodyAltRowcol2"
        //  5540: invokevirtual   org/apache/ecs/html/Div.setID:(Ljava/lang/String;)Lorg/apache/ecs/Element;
        //  5543: invokevirtual   org/apache/ecs/html/TD.addElement:(Lorg/apache/ecs/Element;)Lorg/apache/ecs/html/TD;
        //  5546: invokevirtual   org/apache/ecs/html/TR.addElement:(Lorg/apache/ecs/Element;)Lorg/apache/ecs/html/TR;
        //  5549: new             Lorg/apache/ecs/html/TD;
        //  5552: dup            
        //  5553: invokespecial   org/apache/ecs/html/TD.<init>:()V
        //  5556: new             Lorg/apache/ecs/html/Div;
        //  5559: dup            
        //  5560: invokespecial   org/apache/ecs/html/Div.<init>:()V
        //  5563: aload           valid_upto
        //  5565: invokevirtual   org/apache/ecs/html/Div.addElement:(Ljava/lang/String;)Lorg/apache/ecs/html/Div;
        //  5568: ldc_w           "AssessmentTableBodyAltRowcol3"
        //  5571: invokevirtual   org/apache/ecs/html/Div.setID:(Ljava/lang/String;)Lorg/apache/ecs/Element;
        //  5574: invokevirtual   org/apache/ecs/html/TD.addElement:(Lorg/apache/ecs/Element;)Lorg/apache/ecs/html/TD;
        //  5577: invokevirtual   org/apache/ecs/html/TR.addElement:(Lorg/apache/ecs/Element;)Lorg/apache/ecs/html/TR;
        //  5580: new             Lorg/apache/ecs/html/TD;
        //  5583: dup            
        //  5584: invokespecial   org/apache/ecs/html/TD.<init>:()V
        //  5587: new             Lorg/apache/ecs/html/Div;
        //  5590: dup            
        //  5591: invokespecial   org/apache/ecs/html/Div.<init>:()V
        //  5594: aload           strAssess
        //  5596: iconst_5       
        //  5597: aaload         
        //  5598: invokevirtual   org/apache/ecs/html/Div.addElement:(Ljava/lang/String;)Lorg/apache/ecs/html/Div;
        //  5601: ldc_w           "AssessmentTableBodyAltRowcol4"
        //  5604: invokevirtual   org/apache/ecs/html/Div.setID:(Ljava/lang/String;)Lorg/apache/ecs/Element;
        //  5607: invokevirtual   org/apache/ecs/html/TD.addElement:(Lorg/apache/ecs/Element;)Lorg/apache/ecs/html/TD;
        //  5610: invokevirtual   org/apache/ecs/html/TR.addElement:(Lorg/apache/ecs/Element;)Lorg/apache/ecs/html/TR;
        //  5613: new             Lorg/apache/ecs/html/TD;
        //  5616: dup            
        //  5617: invokespecial   org/apache/ecs/html/TD.<init>:()V
        //  5620: new             Lorg/apache/ecs/html/Div;
        //  5623: dup            
        //  5624: invokespecial   org/apache/ecs/html/Div.<init>:()V
        //  5627: aload           strAssess
        //  5629: iconst_4       
        //  5630: aaload         
        //  5631: invokevirtual   org/apache/ecs/html/Div.addElement:(Ljava/lang/String;)Lorg/apache/ecs/html/Div;
        //  5634: ldc_w           "AssessmentTableBodyAltRowcol5"
        //  5637: invokevirtual   org/apache/ecs/html/Div.setID:(Ljava/lang/String;)Lorg/apache/ecs/Element;
        //  5640: invokevirtual   org/apache/ecs/html/TD.addElement:(Lorg/apache/ecs/Element;)Lorg/apache/ecs/html/TD;
        //  5643: invokevirtual   org/apache/ecs/html/TR.addElement:(Lorg/apache/ecs/Element;)Lorg/apache/ecs/html/TR;
        //  5646: new             Lorg/apache/ecs/html/TD;
        //  5649: dup            
        //  5650: invokespecial   org/apache/ecs/html/TD.<init>:()V
        //  5653: new             Lorg/apache/ecs/html/Div;
        //  5656: dup            
        //  5657: invokespecial   org/apache/ecs/html/Div.<init>:()V
        //  5660: aload           no_of_ques
        //  5662: invokevirtual   org/apache/ecs/html/Div.addElement:(Ljava/lang/String;)Lorg/apache/ecs/html/Div;
        //  5665: ldc_w           "AssessmentTableBodyAltRowcol6"
        //  5668: invokevirtual   org/apache/ecs/html/Div.setID:(Ljava/lang/String;)Lorg/apache/ecs/Element;
        //  5671: invokevirtual   org/apache/ecs/html/TD.addElement:(Lorg/apache/ecs/Element;)Lorg/apache/ecs/html/TD;
        //  5674: invokevirtual   org/apache/ecs/html/TR.addElement:(Lorg/apache/ecs/Element;)Lorg/apache/ecs/html/TR;
        //  5677: new             Lorg/apache/ecs/html/TD;
        //  5680: dup            
        //  5681: invokespecial   org/apache/ecs/html/TD.<init>:()V
        //  5684: new             Lorg/apache/ecs/html/Div;
        //  5687: dup            
        //  5688: invokespecial   org/apache/ecs/html/Div.<init>:()V
        //  5691: aload           status
        //  5693: invokevirtual   org/apache/ecs/html/Div.addElement:(Ljava/lang/String;)Lorg/apache/ecs/html/Div;
        //  5696: ldc_w           "AssessmentTableBodyAltRowcol7"
        //  5699: invokevirtual   org/apache/ecs/html/Div.setID:(Ljava/lang/String;)Lorg/apache/ecs/Element;
        //  5702: invokevirtual   org/apache/ecs/html/TD.addElement:(Lorg/apache/ecs/Element;)Lorg/apache/ecs/html/TD;
        //  5705: invokevirtual   org/apache/ecs/html/TR.addElement:(Lorg/apache/ecs/Element;)Lorg/apache/ecs/html/TR;
        //  5708: ldc_w           "AssessmentTableBodyAltRow"
        //  5711: invokevirtual   org/apache/ecs/html/TR.setID:(Ljava/lang/String;)Lorg/apache/ecs/Element;
        //  5714: invokevirtual   org/apache/ecs/html/Table.addElement:(Lorg/apache/ecs/Element;)Lorg/apache/ecs/html/Table;
        //  5717: pop            
        //  5718: iinc            i, 1
        //  5721: goto            4756
        //  5724: aload           main
        //  5726: ldc_w           "mainsub"
        //  5729: invokevirtual   org/apache/ecs/html/Div.setID:(Ljava/lang/String;)Lorg/apache/ecs/Element;
        //  5732: pop            
        //  5733: aload           main
        //  5735: aload           AssessmentMainDiv
        //  5737: invokevirtual   org/apache/ecs/html/Div.addElement:(Lorg/apache/ecs/Element;)Lorg/apache/ecs/html/Div;
        //  5740: pop            
        //  5741: aload           body
        //  5743: aload           form
        //  5745: aload           main
        //  5747: invokevirtual   org/apache/ecs/html/Form.addElement:(Lorg/apache/ecs/Element;)Lorg/apache/ecs/html/Form;
        //  5750: invokevirtual   org/apache/ecs/html/Body.addElement:(Lorg/apache/ecs/Element;)Lorg/apache/ecs/html/Body;
        //  5753: pop            
        //  5754: aload           body
        //  5756: ldc_w           "load()"
        //  5759: invokevirtual   org/apache/ecs/html/Body.setOnLoad:(Ljava/lang/String;)V
        //  5762: aload           head
        //  5764: aload           link
        //  5766: invokevirtual   org/apache/ecs/html/Head.addElement:(Lorg/apache/ecs/Element;)Lorg/apache/ecs/html/Head;
        //  5769: pop            
        //  5770: aload           html
        //  5772: aload           head
        //  5774: invokevirtual   org/apache/ecs/html/Html.addElement:(Lorg/apache/ecs/Element;)Lorg/apache/ecs/html/Html;
        //  5777: pop            
        //  5778: aload           html
        //  5780: aload           body
        //  5782: invokevirtual   org/apache/ecs/html/Html.addElement:(Lorg/apache/ecs/Element;)Lorg/apache/ecs/html/Html;
        //  5785: pop            
        //  5786: aload_3         /* out */
        //  5787: aload           html
        //  5789: invokevirtual   org/apache/ecs/html/Html.toString:()Ljava/lang/String;
        //  5792: invokevirtual   java/io/PrintWriter.println:(Ljava/lang/String;)V
        //  5795: return         
        //    Exceptions:
        //  throws java.io.IOException
        //  throws javax.servlet.ServletException
        //    LocalVariableTable:
        //  Start  Length  Slot  Name                    Signature
        //  -----  ------  ----  ----------------------  -------------------------------------------------------------------------
        //  730    149     40    str1                    Ljava/lang/String;
        //  746    133     41    str2                    Ljava/lang/String;
        //  761    118     42    str3                    Ljava/lang/String;
        //  776    103     43    str11                   Ljava/lang/String;
        //  792    87      44    str22                   Ljava/lang/String;
        //  807    72      45    str33                   Ljava/lang/String;
        //  828    51      46    timeformat1             I
        //  628    301     34    AssessmentAvailablity   [Ljava/lang/String;
        //  673    256     35    avail_date11            Ljava/lang/String;
        //  676    253     36    t1                      I
        //  679    250     37    t2                      I
        //  682    247     38    t11                     I
        //  685    244     39    t22                     I
        //  606    323     33    vAssessmentAvailablity  Ljava/util/Vector;
        //  1084   149     41    str1                    Ljava/lang/String;
        //  1100   133     42    str2                    Ljava/lang/String;
        //  1115   118     43    str3                    Ljava/lang/String;
        //  1130   103     44    str11                   Ljava/lang/String;
        //  1146   87      45    str22                   Ljava/lang/String;
        //  1161   72      46    str33                   Ljava/lang/String;
        //  1182   51      47    timeformat1             I
        //  982    301     35    AssessmentAvailablity   [Ljava/lang/String;
        //  1027   256     36    avail_date11            Ljava/lang/String;
        //  1030   253     37    t1                      I
        //  1033   250     38    t2                      I
        //  1036   247     39    t11                     I
        //  1039   244     40    t22                     I
        //  960    323     34    vAssessmentAvailablity  Ljava/util/Vector;
        //  1335   30      38    vv                      Ljava/util/Vector;
        //  2959   99      57    str11                   Ljava/lang/String;
        //  2974   84      58    str1                    Ljava/lang/String;
        //  2990   68      59    str2                    Ljava/lang/String;
        //  3005   53      60    str3                    Ljava/lang/String;
        //  3021   37      61    str4                    Ljava/lang/String;
        //  3089   99      57    str11                   Ljava/lang/String;
        //  3104   84      58    str1                    Ljava/lang/String;
        //  3120   68      59    str2                    Ljava/lang/String;
        //  3135   53      60    str3                    Ljava/lang/String;
        //  3151   37      61    str4                    Ljava/lang/String;
        //  2898   897     53    inputButton1            Lorg/apache/ecs/html/Input;
        //  2920   875     54    strAssess               [Ljava/lang/String;
        //  2924   871     55    availablitydate         Ljava/lang/String;
        //  2928   867     56    valid_upto              Ljava/lang/String;
        //  3199   596     57    no_of_ques              Ljava/lang/String;
        //  3212   583     58    status                  Ljava/lang/String;
        //  2879   922     52    i                       I
        //  3895   99      57    str11                   Ljava/lang/String;
        //  3910   84      58    str1                    Ljava/lang/String;
        //  3926   68      59    str2                    Ljava/lang/String;
        //  3941   53      60    str3                    Ljava/lang/String;
        //  3957   37      61    str4                    Ljava/lang/String;
        //  4025   99      57    str11                   Ljava/lang/String;
        //  4040   84      58    str1                    Ljava/lang/String;
        //  4056   68      59    str2                    Ljava/lang/String;
        //  4071   53      60    str3                    Ljava/lang/String;
        //  4087   37      61    str4                    Ljava/lang/String;
        //  3834   897     53    inputButton1            Lorg/apache/ecs/html/Input;
        //  3856   875     54    strAssess               [Ljava/lang/String;
        //  3860   871     55    availablitydate         Ljava/lang/String;
        //  3864   867     56    valid_upto              Ljava/lang/String;
        //  4135   596     57    no_of_ques              Ljava/lang/String;
        //  4148   583     58    status                  Ljava/lang/String;
        //  3815   922     52    i                       I
        //  4828   15      57    j                       I
        //  4882   99      59    str11                   Ljava/lang/String;
        //  4897   84      60    str1                    Ljava/lang/String;
        //  4913   68      61    str2                    Ljava/lang/String;
        //  4928   53      62    str3                    Ljava/lang/String;
        //  4944   37      63    str4                    Ljava/lang/String;
        //  5012   99      59    str11                   Ljava/lang/String;
        //  5027   84      60    str1                    Ljava/lang/String;
        //  5043   68      61    str2                    Ljava/lang/String;
        //  5058   53      62    str3                    Ljava/lang/String;
        //  5074   37      63    str4                    Ljava/lang/String;
        //  4772   946     54    inputButton1            Lorg/apache/ecs/html/Input;
        //  4786   932     55    strAssess               [Ljava/lang/String;
        //  4793   925     56    size11                  I
        //  4847   871     57    availablitydate         Ljava/lang/String;
        //  4851   867     58    valid_upto              Ljava/lang/String;
        //  5122   596     59    no_of_ques              Ljava/lang/String;
        //  5135   583     60    status                  Ljava/lang/String;
        //  4756   968     53    i                       I
        //  4753   971     52    sizeass                 I
        //  0      5796    0     this                    Llearnityasmtserver/assessmentportal/standaloneasmt/StandAloneAssessment;
        //  0      5796    1     request                 Ljavax/servlet/http/HttpServletRequest;
        //  0      5796    2     response                Ljavax/servlet/http/HttpServletResponse;
        //  0      5796    3     out                     Ljava/io/PrintWriter;
        //  0      5796    4     student_id              Ljava/lang/String;
        //  9      5787    5     calendar                Ljava/util/Calendar;
        //  18     5778    6     trialTime               Ljava/util/Date;
        //  98     5698    7     months                  [Ljava/lang/String;
        //  110    5686    8     mimute11                Ljava/lang/String;
        //  114    5682    9     mimute1                 Ljava/lang/String;
        //  164    5632    10    sec11                   Ljava/lang/String;
        //  168    5628    11    sec1                    Ljava/lang/String;
        //  248    5548    12    strTime                 Ljava/lang/String;
        //  300    5496    13    strDate                 Ljava/lang/String;
        //  313    5483    14    month11                 Ljava/lang/String;
        //  317    5479    15    month                   Ljava/lang/String;
        //  366    5430    16    date11                  Ljava/lang/String;
        //  370    5426    17    date1                   Ljava/lang/String;
        //  449    5347    18    strDate1                Ljava/lang/String;
        //  476    5320    19    ampm                    Ljava/lang/String;
        //  485    5311    20    mysession               Ljavax/servlet/http/HttpSession;
        //  518    5278    21    skininfo                Ljava/lang/String;
        //  527    5269    22    ob1                     Llearnityasmtserver/assessmentportal/dbconnection/ReportDataBaseLayer;
        //  536    5260    23    vAssessmentInfo         Ljava/util/Vector;
        //  546    5250    24    checkbox                Ljava/lang/String;
        //  556    5240    25    counter                 Ljava/lang/String;
        //  560    5236    26    checkModelstatus        Ljava/lang/String;
        //  564    5232    27    avail_time              Ljava/lang/String;
        //  568    5228    28    avail                   Ljava/lang/String;
        //  572    5224    29    valid                   Ljava/lang/String;
        //  576    5220    30    avail_date              Ljava/lang/String;
        //  580    5216    31    valid_date              Ljava/lang/String;
        //  584    5212    32    timeavailable           Ljava/lang/String;
        //  938    4858    33    vAssessmentInfogroup    Ljava/util/Vector;
        //  1287   4509    34    MaxtestTeken            Ljava/lang/String;
        //  1291   4505    35    nooftimesappeared       Ljava/lang/String;
        //  1295   4501    36    astatus                 Ljava/lang/String;
        //  1299   4497    37    save_state              Ljava/lang/String;
        //  1460   4336    38    ms                      Ljava/lang/String;
        //  2187   3609    39    script                  Ljava/lang/String;
        //  2196   3600    40    html                    Lorg/apache/ecs/html/Html;
        //  2205   3591    41    link                    Lorg/apache/ecs/html/Link;
        //  2214   3582    42    head                    Lorg/apache/ecs/html/Head;
        //  2223   3573    43    body                    Lorg/apache/ecs/html/Body;
        //  2240   3556    44    script1                 Lorg/apache/ecs/html/Script;
        //  2249   3547    45    AssessmentMainDiv       Lorg/apache/ecs/html/Div;
        //  2268   3528    46    form                    Lorg/apache/ecs/html/Form;
        //  2340   3456    47    assessmentTableBody     Lorg/apache/ecs/html/Table;
        //  2349   3447    48    assessmentTableBody2    Lorg/apache/ecs/html/Table;
        //  2358   3438    49    tblAssessmentStButton   Lorg/apache/ecs/html/Table;
        //  2367   3429    50    main                    Lorg/apache/ecs/html/Div;
        //  2376   3420    51    inputButton2            Lorg/apache/ecs/html/Input;
        // 
        // The error that occurred was:
        // 
        // java.lang.StackOverflowError
        //     at com.strobel.assembler.metadata.TypeReference.getInternalName(TypeReference.java:95)
        //     at com.strobel.assembler.metadata.CoreMetadataFactory$UnresolvedType.getInternalName(CoreMetadataFactory.java:529)
        //     at com.strobel.assembler.metadata.MetadataSystem.resolveCore(MetadataSystem.java:76)
        //     at com.strobel.assembler.metadata.MetadataResolver.resolve(MetadataResolver.java:104)
        //     at com.strobel.assembler.metadata.CoreMetadataFactory$UnresolvedType.resolve(CoreMetadataFactory.java:576)
        //     at com.strobel.assembler.metadata.MetadataResolver.resolve(MetadataResolver.java:128)
        //     at com.strobel.assembler.metadata.CoreMetadataFactory$UnresolvedType.resolve(CoreMetadataFactory.java:586)
        //     at com.strobel.assembler.metadata.MethodReference.resolve(MethodReference.java:172)
        //     at com.strobel.decompiler.ast.TypeAnalysis.inferCall(TypeAnalysis.java:2420)
        //     at com.strobel.decompiler.ast.TypeAnalysis.doInferTypeForExpression(TypeAnalysis.java:1029)
        //     at com.strobel.decompiler.ast.TypeAnalysis.inferTypeForExpression(TypeAnalysis.java:803)
        //     at com.strobel.decompiler.ast.TypeAnalysis.inferTypeForExpression(TypeAnalysis.java:770)
        //     at com.strobel.decompiler.ast.TypeAnalysis.inferTypeForExpression(TypeAnalysis.java:766)
        //     at com.strobel.decompiler.ast.TypeAnalysis.inferCall(TypeAnalysis.java:2445)
        //     at com.strobel.decompiler.ast.TypeAnalysis.doInferTypeForExpression(TypeAnalysis.java:1029)
        //     at com.strobel.decompiler.ast.TypeAnalysis.inferTypeForExpression(TypeAnalysis.java:803)
        //     at com.strobel.decompiler.ast.TypeAnalysis.inferTypeForExpression(TypeAnalysis.java:770)
        //     at com.strobel.decompiler.ast.TypeAnalysis.inferTypeForExpression(TypeAnalysis.java:766)
        //     at com.strobel.decompiler.ast.TypeAnalysis.inferCall(TypeAnalysis.java:2445)
        //     at com.strobel.decompiler.ast.TypeAnalysis.doInferTypeForExpression(TypeAnalysis.java:1029)
        //     at com.strobel.decompiler.ast.TypeAnalysis.inferTypeForExpression(TypeAnalysis.java:803)
        //     at com.strobel.decompiler.ast.TypeAnalysis.inferTypeForExpression(TypeAnalysis.java:770)
        //     at com.strobel.decompiler.ast.TypeAnalysis.inferTypeForExpression(TypeAnalysis.java:766)
        //     at com.strobel.decompiler.ast.TypeAnalysis.inferCall(TypeAnalysis.java:2445)
        //     at com.strobel.decompiler.ast.TypeAnalysis.doInferTypeForExpression(TypeAnalysis.java:1029)
        //     at com.strobel.decompiler.ast.TypeAnalysis.inferTypeForExpression(TypeAnalysis.java:803)
        //     at com.strobel.decompiler.ast.TypeAnalysis.inferTypeForExpression(TypeAnalysis.java:770)
        //     at com.strobel.decompiler.ast.TypeAnalysis.inferTypeForExpression(TypeAnalysis.java:766)
        //     at com.strobel.decompiler.ast.TypeAnalysis.inferCall(TypeAnalysis.java:2445)
        //     at com.strobel.decompiler.ast.TypeAnalysis.doInferTypeForExpression(TypeAnalysis.java:1029)
        //     at com.strobel.decompiler.ast.TypeAnalysis.inferTypeForExpression(TypeAnalysis.java:803)
        //     at com.strobel.decompiler.ast.TypeAnalysis.inferTypeForExpression(TypeAnalysis.java:770)
        //     at com.strobel.decompiler.ast.TypeAnalysis.inferTypeForExpression(TypeAnalysis.java:766)
        //     at com.strobel.decompiler.ast.TypeAnalysis.inferCall(TypeAnalysis.java:2445)
        //     at com.strobel.decompiler.ast.TypeAnalysis.doInferTypeForExpression(TypeAnalysis.java:1029)
        //     at com.strobel.decompiler.ast.TypeAnalysis.inferTypeForExpression(TypeAnalysis.java:803)
        //     at com.strobel.decompiler.ast.TypeAnalysis.inferTypeForExpression(TypeAnalysis.java:770)
        //     at com.strobel.decompiler.ast.TypeAnalysis.inferTypeForExpression(TypeAnalysis.java:766)
        //     at com.strobel.decompiler.ast.TypeAnalysis.inferCall(TypeAnalysis.java:2445)
        //     at com.strobel.decompiler.ast.TypeAnalysis.doInferTypeForExpression(TypeAnalysis.java:1029)
        //     at com.strobel.decompiler.ast.TypeAnalysis.inferTypeForExpression(TypeAnalysis.java:803)
        //     at com.strobel.decompiler.ast.TypeAnalysis.inferTypeForExpression(TypeAnalysis.java:770)
        //     at com.strobel.decompiler.ast.TypeAnalysis.inferTypeForExpression(TypeAnalysis.java:766)
        //     at com.strobel.decompiler.ast.TypeAnalysis.inferCall(TypeAnalysis.java:2445)
        //     at com.strobel.decompiler.ast.TypeAnalysis.doInferTypeForExpression(TypeAnalysis.java:1029)
        //     at com.strobel.decompiler.ast.TypeAnalysis.inferTypeForExpression(TypeAnalysis.java:803)
        //     at com.strobel.decompiler.ast.TypeAnalysis.inferTypeForExpression(TypeAnalysis.java:770)
        //     at com.strobel.decompiler.ast.TypeAnalysis.inferTypeForExpression(TypeAnalysis.java:766)
        //     at com.strobel.decompiler.ast.TypeAnalysis.inferCall(TypeAnalysis.java:2445)
        //     at com.strobel.decompiler.ast.TypeAnalysis.doInferTypeForExpression(TypeAnalysis.java:1029)
        //     at com.strobel.decompiler.ast.TypeAnalysis.inferTypeForExpression(TypeAnalysis.java:803)
        //     at com.strobel.decompiler.ast.TypeAnalysis.inferTypeForExpression(TypeAnalysis.java:770)
        //     at com.strobel.decompiler.ast.TypeAnalysis.inferTypeForExpression(TypeAnalysis.java:766)
        //     at com.strobel.decompiler.ast.TypeAnalysis.inferCall(TypeAnalysis.java:2445)
        //     at com.strobel.decompiler.ast.TypeAnalysis.doInferTypeForExpression(TypeAnalysis.java:1029)
        //     at com.strobel.decompiler.ast.TypeAnalysis.inferTypeForExpression(TypeAnalysis.java:803)
        //     at com.strobel.decompiler.ast.TypeAnalysis.inferTypeForExpression(TypeAnalysis.java:770)
        //     at com.strobel.decompiler.ast.TypeAnalysis.inferTypeForExpression(TypeAnalysis.java:766)
        //     at com.strobel.decompiler.ast.TypeAnalysis.inferCall(TypeAnalysis.java:2445)
        //     at com.strobel.decompiler.ast.TypeAnalysis.doInferTypeForExpression(TypeAnalysis.java:1029)
        //     at com.strobel.decompiler.ast.TypeAnalysis.inferTypeForExpression(TypeAnalysis.java:803)
        //     at com.strobel.decompiler.ast.TypeAnalysis.inferTypeForExpression(TypeAnalysis.java:770)
        //     at com.strobel.decompiler.ast.TypeAnalysis.inferTypeForExpression(TypeAnalysis.java:766)
        //     at com.strobel.decompiler.ast.TypeAnalysis.inferCall(TypeAnalysis.java:2445)
        //     at com.strobel.decompiler.ast.TypeAnalysis.doInferTypeForExpression(TypeAnalysis.java:1029)
        //     at com.strobel.decompiler.ast.TypeAnalysis.inferTypeForExpression(TypeAnalysis.java:803)
        //     at com.strobel.decompiler.ast.TypeAnalysis.inferTypeForExpression(TypeAnalysis.java:770)
        //     at com.strobel.decompiler.ast.TypeAnalysis.inferTypeForExpression(TypeAnalysis.java:766)
        //     at com.strobel.decompiler.ast.TypeAnalysis.inferCall(TypeAnalysis.java:2445)
        //     at com.strobel.decompiler.ast.TypeAnalysis.doInferTypeForExpression(TypeAnalysis.java:1029)
        //     at com.strobel.decompiler.ast.TypeAnalysis.inferTypeForExpression(TypeAnalysis.java:803)
        //     at com.strobel.decompiler.ast.TypeAnalysis.inferTypeForExpression(TypeAnalysis.java:770)
        //     at com.strobel.decompiler.ast.TypeAnalysis.inferTypeForExpression(TypeAnalysis.java:766)
        //     at com.strobel.decompiler.ast.TypeAnalysis.inferCall(TypeAnalysis.java:2445)
        //     at com.strobel.decompiler.ast.TypeAnalysis.doInferTypeForExpression(TypeAnalysis.java:1029)
        //     at com.strobel.decompiler.ast.TypeAnalysis.inferTypeForExpression(TypeAnalysis.java:803)
        //     at com.strobel.decompiler.ast.TypeAnalysis.inferTypeForExpression(TypeAnalysis.java:770)
        //     at com.strobel.decompiler.ast.TypeAnalysis.inferTypeForExpression(TypeAnalysis.java:766)
        //     at com.strobel.decompiler.ast.TypeAnalysis.inferCall(TypeAnalysis.java:2445)
        //     at com.strobel.decompiler.ast.TypeAnalysis.doInferTypeForExpression(TypeAnalysis.java:1029)
        //     at com.strobel.decompiler.ast.TypeAnalysis.inferTypeForExpression(TypeAnalysis.java:803)
        //     at com.strobel.decompiler.ast.TypeAnalysis.inferTypeForExpression(TypeAnalysis.java:770)
        //     at com.strobel.decompiler.ast.TypeAnalysis.inferTypeForExpression(TypeAnalysis.java:766)
        //     at com.strobel.decompiler.ast.TypeAnalysis.inferCall(TypeAnalysis.java:2445)
        //     at com.strobel.decompiler.ast.TypeAnalysis.doInferTypeForExpression(TypeAnalysis.java:1029)
        //     at com.strobel.decompiler.ast.TypeAnalysis.inferTypeForExpression(TypeAnalysis.java:803)
        //     at com.strobel.decompiler.ast.TypeAnalysis.inferTypeForExpression(TypeAnalysis.java:770)
        //     at com.strobel.decompiler.ast.TypeAnalysis.inferTypeForExpression(TypeAnalysis.java:766)
        //     at com.strobel.decompiler.ast.TypeAnalysis.inferCall(TypeAnalysis.java:2445)
        //     at com.strobel.decompiler.ast.TypeAnalysis.doInferTypeForExpression(TypeAnalysis.java:1029)
        //     at com.strobel.decompiler.ast.TypeAnalysis.inferTypeForExpression(TypeAnalysis.java:803)
        //     at com.strobel.decompiler.ast.TypeAnalysis.inferTypeForExpression(TypeAnalysis.java:770)
        //     at com.strobel.decompiler.ast.TypeAnalysis.inferTypeForExpression(TypeAnalysis.java:766)
        //     at com.strobel.decompiler.ast.TypeAnalysis.inferCall(TypeAnalysis.java:2445)
        //     at com.strobel.decompiler.ast.TypeAnalysis.doInferTypeForExpression(TypeAnalysis.java:1029)
        //     at com.strobel.decompiler.ast.TypeAnalysis.inferTypeForExpression(TypeAnalysis.java:803)
        //     at com.strobel.decompiler.ast.TypeAnalysis.inferTypeForExpression(TypeAnalysis.java:770)
        //     at com.strobel.decompiler.ast.TypeAnalysis.inferTypeForExpression(TypeAnalysis.java:766)
        //     at com.strobel.decompiler.ast.TypeAnalysis.inferCall(TypeAnalysis.java:2445)
        //     at com.strobel.decompiler.ast.TypeAnalysis.doInferTypeForExpression(TypeAnalysis.java:1029)
        //     at com.strobel.decompiler.ast.TypeAnalysis.inferTypeForExpression(TypeAnalysis.java:803)
        //     at com.strobel.decompiler.ast.TypeAnalysis.inferTypeForExpression(TypeAnalysis.java:770)
        //     at com.strobel.decompiler.ast.TypeAnalysis.inferTypeForExpression(TypeAnalysis.java:766)
        //     at com.strobel.decompiler.ast.TypeAnalysis.inferCall(TypeAnalysis.java:2445)
        //     at com.strobel.decompiler.ast.TypeAnalysis.doInferTypeForExpression(TypeAnalysis.java:1029)
        //     at com.strobel.decompiler.ast.TypeAnalysis.inferTypeForExpression(TypeAnalysis.java:803)
        //     at com.strobel.decompiler.ast.TypeAnalysis.inferTypeForExpression(TypeAnalysis.java:770)
        //     at com.strobel.decompiler.ast.TypeAnalysis.inferTypeForExpression(TypeAnalysis.java:766)
        //     at com.strobel.decompiler.ast.TypeAnalysis.inferCall(TypeAnalysis.java:2445)
        //     at com.strobel.decompiler.ast.TypeAnalysis.doInferTypeForExpression(TypeAnalysis.java:1029)
        //     at com.strobel.decompiler.ast.TypeAnalysis.inferTypeForExpression(TypeAnalysis.java:803)
        //     at com.strobel.decompiler.ast.TypeAnalysis.inferTypeForExpression(TypeAnalysis.java:770)
        //     at com.strobel.decompiler.ast.TypeAnalysis.inferTypeForExpression(TypeAnalysis.java:766)
        //     at com.strobel.decompiler.ast.TypeAnalysis.inferCall(TypeAnalysis.java:2445)
        //     at com.strobel.decompiler.ast.TypeAnalysis.doInferTypeForExpression(TypeAnalysis.java:1029)
        //     at com.strobel.decompiler.ast.TypeAnalysis.inferTypeForExpression(TypeAnalysis.java:803)
        //     at com.strobel.decompiler.ast.TypeAnalysis.inferTypeForExpression(TypeAnalysis.java:770)
        //     at com.strobel.decompiler.ast.TypeAnalysis.inferTypeForExpression(TypeAnalysis.java:766)
        //     at com.strobel.decompiler.ast.TypeAnalysis.inferCall(TypeAnalysis.java:2445)
        //     at com.strobel.decompiler.ast.TypeAnalysis.doInferTypeForExpression(TypeAnalysis.java:1029)
        //     at com.strobel.decompiler.ast.TypeAnalysis.inferTypeForExpression(TypeAnalysis.java:803)
        //     at com.strobel.decompiler.ast.TypeAnalysis.inferTypeForExpression(TypeAnalysis.java:770)
        //     at com.strobel.decompiler.ast.TypeAnalysis.inferTypeForExpression(TypeAnalysis.java:766)
        //     at com.strobel.decompiler.ast.TypeAnalysis.inferCall(TypeAnalysis.java:2445)
        //     at com.strobel.decompiler.ast.TypeAnalysis.doInferTypeForExpression(TypeAnalysis.java:1029)
        //     at com.strobel.decompiler.ast.TypeAnalysis.inferTypeForExpression(TypeAnalysis.java:803)
        //     at com.strobel.decompiler.ast.TypeAnalysis.inferTypeForExpression(TypeAnalysis.java:770)
        //     at com.strobel.decompiler.ast.TypeAnalysis.inferTypeForExpression(TypeAnalysis.java:766)
        //     at com.strobel.decompiler.ast.TypeAnalysis.inferCall(TypeAnalysis.java:2445)
        //     at com.strobel.decompiler.ast.TypeAnalysis.doInferTypeForExpression(TypeAnalysis.java:1029)
        //     at com.strobel.decompiler.ast.TypeAnalysis.inferTypeForExpression(TypeAnalysis.java:803)
        //     at com.strobel.decompiler.ast.TypeAnalysis.inferTypeForExpression(TypeAnalysis.java:770)
        //     at com.strobel.decompiler.ast.TypeAnalysis.inferTypeForExpression(TypeAnalysis.java:766)
        //     at com.strobel.decompiler.ast.TypeAnalysis.inferCall(TypeAnalysis.java:2445)
        //     at com.strobel.decompiler.ast.TypeAnalysis.doInferTypeForExpression(TypeAnalysis.java:1029)
        //     at com.strobel.decompiler.ast.TypeAnalysis.inferTypeForExpression(TypeAnalysis.java:803)
        //     at com.strobel.decompiler.ast.TypeAnalysis.inferTypeForExpression(TypeAnalysis.java:770)
        //     at com.strobel.decompiler.ast.TypeAnalysis.inferTypeForExpression(TypeAnalysis.java:766)
        //     at com.strobel.decompiler.ast.TypeAnalysis.inferCall(TypeAnalysis.java:2445)
        //     at com.strobel.decompiler.ast.TypeAnalysis.doInferTypeForExpression(TypeAnalysis.java:1029)
        //     at com.strobel.decompiler.ast.TypeAnalysis.inferTypeForExpression(TypeAnalysis.java:803)
        //     at com.strobel.decompiler.ast.TypeAnalysis.inferTypeForExpression(TypeAnalysis.java:770)
        //     at com.strobel.decompiler.ast.TypeAnalysis.inferTypeForExpression(TypeAnalysis.java:766)
        //     at com.strobel.decompiler.ast.TypeAnalysis.inferCall(TypeAnalysis.java:2445)
        //     at com.strobel.decompiler.ast.TypeAnalysis.doInferTypeForExpression(TypeAnalysis.java:1029)
        //     at com.strobel.decompiler.ast.TypeAnalysis.inferTypeForExpression(TypeAnalysis.java:803)
        //     at com.strobel.decompiler.ast.TypeAnalysis.inferTypeForExpression(TypeAnalysis.java:770)
        //     at com.strobel.decompiler.ast.TypeAnalysis.inferTypeForExpression(TypeAnalysis.java:766)
        //     at com.strobel.decompiler.ast.TypeAnalysis.inferCall(TypeAnalysis.java:2445)
        //     at com.strobel.decompiler.ast.TypeAnalysis.doInferTypeForExpression(TypeAnalysis.java:1029)
        //     at com.strobel.decompiler.ast.TypeAnalysis.inferTypeForExpression(TypeAnalysis.java:803)
        //     at com.strobel.decompiler.ast.TypeAnalysis.inferTypeForExpression(TypeAnalysis.java:770)
        //     at com.strobel.decompiler.ast.TypeAnalysis.inferTypeForExpression(TypeAnalysis.java:766)
        //     at com.strobel.decompiler.ast.TypeAnalysis.inferCall(TypeAnalysis.java:2445)
        //     at com.strobel.decompiler.ast.TypeAnalysis.doInferTypeForExpression(TypeAnalysis.java:1029)
        //     at com.strobel.decompiler.ast.TypeAnalysis.inferTypeForExpression(TypeAnalysis.java:803)
        //     at com.strobel.decompiler.ast.TypeAnalysis.inferTypeForExpression(TypeAnalysis.java:770)
        //     at com.strobel.decompiler.ast.TypeAnalysis.inferTypeForExpression(TypeAnalysis.java:766)
        //     at com.strobel.decompiler.ast.TypeAnalysis.inferCall(TypeAnalysis.java:2445)
        //     at com.strobel.decompiler.ast.TypeAnalysis.doInferTypeForExpression(TypeAnalysis.java:1029)
        //     at com.strobel.decompiler.ast.TypeAnalysis.inferTypeForExpression(TypeAnalysis.java:803)
        //     at com.strobel.decompiler.ast.TypeAnalysis.inferTypeForExpression(TypeAnalysis.java:770)
        //     at com.strobel.decompiler.ast.TypeAnalysis.inferTypeForExpression(TypeAnalysis.java:766)
        //     at com.strobel.decompiler.ast.TypeAnalysis.inferCall(TypeAnalysis.java:2445)
        //     at com.strobel.decompiler.ast.TypeAnalysis.doInferTypeForExpression(TypeAnalysis.java:1029)
        //     at com.strobel.decompiler.ast.TypeAnalysis.inferTypeForExpression(TypeAnalysis.java:803)
        //     at com.strobel.decompiler.ast.TypeAnalysis.inferTypeForExpression(TypeAnalysis.java:770)
        //     at com.strobel.decompiler.ast.TypeAnalysis.inferTypeForExpression(TypeAnalysis.java:766)
        //     at com.strobel.decompiler.ast.TypeAnalysis.inferCall(TypeAnalysis.java:2445)
        //     at com.strobel.decompiler.ast.TypeAnalysis.doInferTypeForExpression(TypeAnalysis.java:1029)
        //     at com.strobel.decompiler.ast.TypeAnalysis.inferTypeForExpression(TypeAnalysis.java:803)
        //     at com.strobel.decompiler.ast.TypeAnalysis.inferTypeForExpression(TypeAnalysis.java:770)
        //     at com.strobel.decompiler.ast.TypeAnalysis.inferTypeForExpression(TypeAnalysis.java:766)
        //     at com.strobel.decompiler.ast.TypeAnalysis.inferCall(TypeAnalysis.java:2445)
        //     at com.strobel.decompiler.ast.TypeAnalysis.doInferTypeForExpression(TypeAnalysis.java:1029)
        //     at com.strobel.decompiler.ast.TypeAnalysis.inferTypeForExpression(TypeAnalysis.java:803)
        //     at com.strobel.decompiler.ast.TypeAnalysis.inferTypeForExpression(TypeAnalysis.java:770)
        //     at com.strobel.decompiler.ast.TypeAnalysis.inferTypeForExpression(TypeAnalysis.java:766)
        //     at com.strobel.decompiler.ast.TypeAnalysis.inferCall(TypeAnalysis.java:2445)
        //     at com.strobel.decompiler.ast.TypeAnalysis.doInferTypeForExpression(TypeAnalysis.java:1029)
        //     at com.strobel.decompiler.ast.TypeAnalysis.inferTypeForExpression(TypeAnalysis.java:803)
        //     at com.strobel.decompiler.ast.TypeAnalysis.inferTypeForExpression(TypeAnalysis.java:770)
        //     at com.strobel.decompiler.ast.TypeAnalysis.inferTypeForExpression(TypeAnalysis.java:766)
        //     at com.strobel.decompiler.ast.TypeAnalysis.inferCall(TypeAnalysis.java:2445)
        //     at com.strobel.decompiler.ast.TypeAnalysis.doInferTypeForExpression(TypeAnalysis.java:1029)
        //     at com.strobel.decompiler.ast.TypeAnalysis.inferTypeForExpression(TypeAnalysis.java:803)
        //     at com.strobel.decompiler.ast.TypeAnalysis.inferTypeForExpression(TypeAnalysis.java:770)
        //     at com.strobel.decompiler.ast.TypeAnalysis.inferTypeForExpression(TypeAnalysis.java:766)
        //     at com.strobel.decompiler.ast.TypeAnalysis.inferCall(TypeAnalysis.java:2445)
        //     at com.strobel.decompiler.ast.TypeAnalysis.doInferTypeForExpression(TypeAnalysis.java:1029)
        //     at com.strobel.decompiler.ast.TypeAnalysis.inferTypeForExpression(TypeAnalysis.java:803)
        //     at com.strobel.decompiler.ast.TypeAnalysis.inferTypeForExpression(TypeAnalysis.java:770)
        //     at com.strobel.decompiler.ast.TypeAnalysis.inferTypeForExpression(TypeAnalysis.java:766)
        //     at com.strobel.decompiler.ast.TypeAnalysis.inferCall(TypeAnalysis.java:2445)
        //     at com.strobel.decompiler.ast.TypeAnalysis.doInferTypeForExpression(TypeAnalysis.java:1029)
        //     at com.strobel.decompiler.ast.TypeAnalysis.inferTypeForExpression(TypeAnalysis.java:803)
        //     at com.strobel.decompiler.ast.TypeAnalysis.inferTypeForExpression(TypeAnalysis.java:770)
        //     at com.strobel.decompiler.ast.TypeAnalysis.inferTypeForExpression(TypeAnalysis.java:766)
        //     at com.strobel.decompiler.ast.TypeAnalysis.inferCall(TypeAnalysis.java:2445)
        //     at com.strobel.decompiler.ast.TypeAnalysis.doInferTypeForExpression(TypeAnalysis.java:1029)
        //     at com.strobel.decompiler.ast.TypeAnalysis.inferTypeForExpression(TypeAnalysis.java:803)
        //     at com.strobel.decompiler.ast.TypeAnalysis.inferTypeForExpression(TypeAnalysis.java:770)
        //     at com.strobel.decompiler.ast.TypeAnalysis.inferTypeForExpression(TypeAnalysis.java:766)
        //     at com.strobel.decompiler.ast.TypeAnalysis.inferCall(TypeAnalysis.java:2445)
        //     at com.strobel.decompiler.ast.TypeAnalysis.doInferTypeForExpression(TypeAnalysis.java:1029)
        //     at com.strobel.decompiler.ast.TypeAnalysis.inferTypeForExpression(TypeAnalysis.java:803)
        //     at com.strobel.decompiler.ast.TypeAnalysis.inferTypeForExpression(TypeAnalysis.java:770)
        //     at com.strobel.decompiler.ast.TypeAnalysis.inferTypeForExpression(TypeAnalysis.java:766)
        //     at com.strobel.decompiler.ast.TypeAnalysis.inferCall(TypeAnalysis.java:2445)
        //     at com.strobel.decompiler.ast.TypeAnalysis.doInferTypeForExpression(TypeAnalysis.java:1029)
        //     at com.strobel.decompiler.ast.TypeAnalysis.inferTypeForExpression(TypeAnalysis.java:803)
        //     at com.strobel.decompiler.ast.TypeAnalysis.inferTypeForExpression(TypeAnalysis.java:770)
        //     at com.strobel.decompiler.ast.TypeAnalysis.inferTypeForExpression(TypeAnalysis.java:766)
        //     at com.strobel.decompiler.ast.TypeAnalysis.inferCall(TypeAnalysis.java:2445)
        //     at com.strobel.decompiler.ast.TypeAnalysis.doInferTypeForExpression(TypeAnalysis.java:1029)
        //     at com.strobel.decompiler.ast.TypeAnalysis.inferTypeForExpression(TypeAnalysis.java:803)
        //     at com.strobel.decompiler.ast.TypeAnalysis.inferTypeForExpression(TypeAnalysis.java:770)
        //     at com.strobel.decompiler.ast.TypeAnalysis.inferTypeForExpression(TypeAnalysis.java:766)
        //     at com.strobel.decompiler.ast.TypeAnalysis.inferCall(TypeAnalysis.java:2445)
        //     at com.strobel.decompiler.ast.TypeAnalysis.doInferTypeForExpression(TypeAnalysis.java:1029)
        //     at com.strobel.decompiler.ast.TypeAnalysis.inferTypeForExpression(TypeAnalysis.java:803)
        //     at com.strobel.decompiler.ast.TypeAnalysis.inferTypeForExpression(TypeAnalysis.java:770)
        //     at com.strobel.decompiler.ast.TypeAnalysis.inferTypeForExpression(TypeAnalysis.java:766)
        //     at com.strobel.decompiler.ast.TypeAnalysis.inferCall(TypeAnalysis.java:2445)
        //     at com.strobel.decompiler.ast.TypeAnalysis.doInferTypeForExpression(TypeAnalysis.java:1029)
        //     at com.strobel.decompiler.ast.TypeAnalysis.inferTypeForExpression(TypeAnalysis.java:803)
        //     at com.strobel.decompiler.ast.TypeAnalysis.inferTypeForExpression(TypeAnalysis.java:770)
        //     at com.strobel.decompiler.ast.TypeAnalysis.inferTypeForExpression(TypeAnalysis.java:766)
        //     at com.strobel.decompiler.ast.TypeAnalysis.inferCall(TypeAnalysis.java:2445)
        //     at com.strobel.decompiler.ast.TypeAnalysis.doInferTypeForExpression(TypeAnalysis.java:1029)
        //     at com.strobel.decompiler.ast.TypeAnalysis.inferTypeForExpression(TypeAnalysis.java:803)
        //     at com.strobel.decompiler.ast.TypeAnalysis.inferTypeForExpression(TypeAnalysis.java:770)
        //     at com.strobel.decompiler.ast.TypeAnalysis.inferTypeForExpression(TypeAnalysis.java:766)
        //     at com.strobel.decompiler.ast.TypeAnalysis.inferCall(TypeAnalysis.java:2445)
        //     at com.strobel.decompiler.ast.TypeAnalysis.doInferTypeForExpression(TypeAnalysis.java:1029)
        //     at com.strobel.decompiler.ast.TypeAnalysis.inferTypeForExpression(TypeAnalysis.java:803)
        //     at com.strobel.decompiler.ast.TypeAnalysis.inferTypeForExpression(TypeAnalysis.java:770)
        //     at com.strobel.decompiler.ast.TypeAnalysis.inferTypeForExpression(TypeAnalysis.java:766)
        //     at com.strobel.decompiler.ast.TypeAnalysis.inferCall(TypeAnalysis.java:2445)
        //     at com.strobel.decompiler.ast.TypeAnalysis.doInferTypeForExpression(TypeAnalysis.java:1029)
        //     at com.strobel.decompiler.ast.TypeAnalysis.inferTypeForExpression(TypeAnalysis.java:803)
        //     at com.strobel.decompiler.ast.TypeAnalysis.inferTypeForExpression(TypeAnalysis.java:770)
        //     at com.strobel.decompiler.ast.TypeAnalysis.inferTypeForExpression(TypeAnalysis.java:766)
        //     at com.strobel.decompiler.ast.TypeAnalysis.inferCall(TypeAnalysis.java:2445)
        //     at com.strobel.decompiler.ast.TypeAnalysis.doInferTypeForExpression(TypeAnalysis.java:1029)
        //     at com.strobel.decompiler.ast.TypeAnalysis.inferTypeForExpression(TypeAnalysis.java:803)
        //     at com.strobel.decompiler.ast.TypeAnalysis.inferTypeForExpression(TypeAnalysis.java:770)
        //     at com.strobel.decompiler.ast.TypeAnalysis.inferTypeForExpression(TypeAnalysis.java:766)
        //     at com.strobel.decompiler.ast.TypeAnalysis.inferCall(TypeAnalysis.java:2445)
        //     at com.strobel.decompiler.ast.TypeAnalysis.doInferTypeForExpression(TypeAnalysis.java:1029)
        //     at com.strobel.decompiler.ast.TypeAnalysis.inferTypeForExpression(TypeAnalysis.java:803)
        //     at com.strobel.decompiler.ast.TypeAnalysis.inferTypeForExpression(TypeAnalysis.java:770)
        //     at com.strobel.decompiler.ast.TypeAnalysis.inferTypeForExpression(TypeAnalysis.java:766)
        //     at com.strobel.decompiler.ast.TypeAnalysis.inferCall(TypeAnalysis.java:2445)
        //     at com.strobel.decompiler.ast.TypeAnalysis.doInferTypeForExpression(TypeAnalysis.java:1029)
        //     at com.strobel.decompiler.ast.TypeAnalysis.inferTypeForExpression(TypeAnalysis.java:803)
        //     at com.strobel.decompiler.ast.TypeAnalysis.inferTypeForExpression(TypeAnalysis.java:770)
        //     at com.strobel.decompiler.ast.TypeAnalysis.inferTypeForExpression(TypeAnalysis.java:766)
        //     at com.strobel.decompiler.ast.TypeAnalysis.inferCall(TypeAnalysis.java:2445)
        //     at com.strobel.decompiler.ast.TypeAnalysis.doInferTypeForExpression(TypeAnalysis.java:1029)
        //     at com.strobel.decompiler.ast.TypeAnalysis.inferTypeForExpression(TypeAnalysis.java:803)
        //     at com.strobel.decompiler.ast.TypeAnalysis.inferTypeForExpression(TypeAnalysis.java:770)
        //     at com.strobel.decompiler.ast.TypeAnalysis.inferTypeForExpression(TypeAnalysis.java:766)
        //     at com.strobel.decompiler.ast.TypeAnalysis.inferCall(TypeAnalysis.java:2445)
        //     at com.strobel.decompiler.ast.TypeAnalysis.doInferTypeForExpression(TypeAnalysis.java:1029)
        //     at com.strobel.decompiler.ast.TypeAnalysis.inferTypeForExpression(TypeAnalysis.java:803)
        //     at com.strobel.decompiler.ast.TypeAnalysis.inferTypeForExpression(TypeAnalysis.java:770)
        //     at com.strobel.decompiler.ast.TypeAnalysis.inferTypeForExpression(TypeAnalysis.java:766)
        //     at com.strobel.decompiler.ast.TypeAnalysis.inferCall(TypeAnalysis.java:2445)
        //     at com.strobel.decompiler.ast.TypeAnalysis.doInferTypeForExpression(TypeAnalysis.java:1029)
        //     at com.strobel.decompiler.ast.TypeAnalysis.inferTypeForExpression(TypeAnalysis.java:803)
        //     at com.strobel.decompiler.ast.TypeAnalysis.inferTypeForExpression(TypeAnalysis.java:770)
        //     at com.strobel.decompiler.ast.TypeAnalysis.inferTypeForExpression(TypeAnalysis.java:766)
        //     at com.strobel.decompiler.ast.TypeAnalysis.inferCall(TypeAnalysis.java:2445)
        //     at com.strobel.decompiler.ast.TypeAnalysis.doInferTypeForExpression(TypeAnalysis.java:1029)
        //     at com.strobel.decompiler.ast.TypeAnalysis.inferTypeForExpression(TypeAnalysis.java:803)
        //     at com.strobel.decompiler.ast.TypeAnalysis.inferTypeForExpression(TypeAnalysis.java:770)
        //     at com.strobel.decompiler.ast.TypeAnalysis.inferTypeForExpression(TypeAnalysis.java:766)
        //     at com.strobel.decompiler.ast.TypeAnalysis.inferCall(TypeAnalysis.java:2445)
        //     at com.strobel.decompiler.ast.TypeAnalysis.doInferTypeForExpression(TypeAnalysis.java:1029)
        //     at com.strobel.decompiler.ast.TypeAnalysis.inferTypeForExpression(TypeAnalysis.java:803)
        //     at com.strobel.decompiler.ast.TypeAnalysis.inferTypeForExpression(TypeAnalysis.java:770)
        //     at com.strobel.decompiler.ast.TypeAnalysis.inferTypeForExpression(TypeAnalysis.java:766)
        //     at com.strobel.decompiler.ast.TypeAnalysis.inferCall(TypeAnalysis.java:2445)
        //     at com.strobel.decompiler.ast.TypeAnalysis.doInferTypeForExpression(TypeAnalysis.java:1029)
        //     at com.strobel.decompiler.ast.TypeAnalysis.inferTypeForExpression(TypeAnalysis.java:803)
        //     at com.strobel.decompiler.ast.TypeAnalysis.inferTypeForExpression(TypeAnalysis.java:770)
        //     at com.strobel.decompiler.ast.TypeAnalysis.inferTypeForExpression(TypeAnalysis.java:766)
        //     at com.strobel.decompiler.ast.TypeAnalysis.inferCall(TypeAnalysis.java:2445)
        //     at com.strobel.decompiler.ast.TypeAnalysis.doInferTypeForExpression(TypeAnalysis.java:1029)
        //     at com.strobel.decompiler.ast.TypeAnalysis.inferTypeForExpression(TypeAnalysis.java:803)
        //     at com.strobel.decompiler.ast.TypeAnalysis.inferTypeForExpression(TypeAnalysis.java:770)
        //     at com.strobel.decompiler.ast.TypeAnalysis.inferTypeForExpression(TypeAnalysis.java:766)
        //     at com.strobel.decompiler.ast.TypeAnalysis.inferCall(TypeAnalysis.java:2445)
        //     at com.strobel.decompiler.ast.TypeAnalysis.doInferTypeForExpression(TypeAnalysis.java:1029)
        //     at com.strobel.decompiler.ast.TypeAnalysis.inferTypeForExpression(TypeAnalysis.java:803)
        //     at com.strobel.decompiler.ast.TypeAnalysis.inferTypeForExpression(TypeAnalysis.java:770)
        //     at com.strobel.decompiler.ast.TypeAnalysis.inferTypeForExpression(TypeAnalysis.java:766)
        //     at com.strobel.decompiler.ast.TypeAnalysis.inferCall(TypeAnalysis.java:2445)
        //     at com.strobel.decompiler.ast.TypeAnalysis.doInferTypeForExpression(TypeAnalysis.java:1029)
        //     at com.strobel.decompiler.ast.TypeAnalysis.inferTypeForExpression(TypeAnalysis.java:803)
        //     at com.strobel.decompiler.ast.TypeAnalysis.inferTypeForExpression(TypeAnalysis.java:770)
        //     at com.strobel.decompiler.ast.TypeAnalysis.inferTypeForExpression(TypeAnalysis.java:766)
        //     at com.strobel.decompiler.ast.TypeAnalysis.inferCall(TypeAnalysis.java:2445)
        //     at com.strobel.decompiler.ast.TypeAnalysis.doInferTypeForExpression(TypeAnalysis.java:1029)
        //     at com.strobel.decompiler.ast.TypeAnalysis.inferTypeForExpression(TypeAnalysis.java:803)
        //     at com.strobel.decompiler.ast.TypeAnalysis.inferTypeForExpression(TypeAnalysis.java:770)
        //     at com.strobel.decompiler.ast.TypeAnalysis.inferTypeForExpression(TypeAnalysis.java:766)
        //     at com.strobel.decompiler.ast.TypeAnalysis.inferCall(TypeAnalysis.java:2445)
        //     at com.strobel.decompiler.ast.TypeAnalysis.doInferTypeForExpression(TypeAnalysis.java:1029)
        //     at com.strobel.decompiler.ast.TypeAnalysis.inferTypeForExpression(TypeAnalysis.java:803)
        //     at com.strobel.decompiler.ast.TypeAnalysis.inferTypeForExpression(TypeAnalysis.java:770)
        //     at com.strobel.decompiler.ast.TypeAnalysis.inferTypeForExpression(TypeAnalysis.java:766)
        //     at com.strobel.decompiler.ast.TypeAnalysis.inferCall(TypeAnalysis.java:2445)
        //     at com.strobel.decompiler.ast.TypeAnalysis.doInferTypeForExpression(TypeAnalysis.java:1029)
        //     at com.strobel.decompiler.ast.TypeAnalysis.inferTypeForExpression(TypeAnalysis.java:803)
        //     at com.strobel.decompiler.ast.TypeAnalysis.inferTypeForExpression(TypeAnalysis.java:770)
        //     at com.strobel.decompiler.ast.TypeAnalysis.inferTypeForExpression(TypeAnalysis.java:766)
        //     at com.strobel.decompiler.ast.TypeAnalysis.inferCall(TypeAnalysis.java:2445)
        //     at com.strobel.decompiler.ast.TypeAnalysis.doInferTypeForExpression(TypeAnalysis.java:1029)
        //     at com.strobel.decompiler.ast.TypeAnalysis.inferTypeForExpression(TypeAnalysis.java:803)
        //     at com.strobel.decompiler.ast.TypeAnalysis.inferTypeForExpression(TypeAnalysis.java:770)
        //     at com.strobel.decompiler.ast.TypeAnalysis.inferTypeForExpression(TypeAnalysis.java:766)
        //     at com.strobel.decompiler.ast.TypeAnalysis.inferCall(TypeAnalysis.java:2445)
        //     at com.strobel.decompiler.ast.TypeAnalysis.doInferTypeForExpression(TypeAnalysis.java:1029)
        //     at com.strobel.decompiler.ast.TypeAnalysis.inferTypeForExpression(TypeAnalysis.java:803)
        //     at com.strobel.decompiler.ast.TypeAnalysis.inferTypeForExpression(TypeAnalysis.java:770)
        //     at com.strobel.decompiler.ast.TypeAnalysis.inferTypeForExpression(TypeAnalysis.java:766)
        //     at com.strobel.decompiler.ast.TypeAnalysis.inferCall(TypeAnalysis.java:2445)
        //     at com.strobel.decompiler.ast.TypeAnalysis.doInferTypeForExpression(TypeAnalysis.java:1029)
        //     at com.strobel.decompiler.ast.TypeAnalysis.inferTypeForExpression(TypeAnalysis.java:803)
        //     at com.strobel.decompiler.ast.TypeAnalysis.inferTypeForExpression(TypeAnalysis.java:770)
        //     at com.strobel.decompiler.ast.TypeAnalysis.inferTypeForExpression(TypeAnalysis.java:766)
        //     at com.strobel.decompiler.ast.TypeAnalysis.inferCall(TypeAnalysis.java:2445)
        //     at com.strobel.decompiler.ast.TypeAnalysis.doInferTypeForExpression(TypeAnalysis.java:1029)
        //     at com.strobel.decompiler.ast.TypeAnalysis.inferTypeForExpression(TypeAnalysis.java:803)
        //     at com.strobel.decompiler.ast.TypeAnalysis.inferTypeForExpression(TypeAnalysis.java:770)
        //     at com.strobel.decompiler.ast.TypeAnalysis.inferTypeForExpression(TypeAnalysis.java:766)
        //     at com.strobel.decompiler.ast.TypeAnalysis.inferCall(TypeAnalysis.java:2445)
        //     at com.strobel.decompiler.ast.TypeAnalysis.doInferTypeForExpression(TypeAnalysis.java:1029)
        //     at com.strobel.decompiler.ast.TypeAnalysis.inferTypeForExpression(TypeAnalysis.java:803)
        //     at com.strobel.decompiler.ast.TypeAnalysis.inferTypeForExpression(TypeAnalysis.java:770)
        //     at com.strobel.decompiler.ast.TypeAnalysis.inferTypeForExpression(TypeAnalysis.java:766)
        //     at com.strobel.decompiler.ast.TypeAnalysis.inferCall(TypeAnalysis.java:2445)
        //     at com.strobel.decompiler.ast.TypeAnalysis.doInferTypeForExpression(TypeAnalysis.java:1029)
        //     at com.strobel.decompiler.ast.TypeAnalysis.inferTypeForExpression(TypeAnalysis.java:803)
        //     at com.strobel.decompiler.ast.TypeAnalysis.inferTypeForExpression(TypeAnalysis.java:770)
        //     at com.strobel.decompiler.ast.TypeAnalysis.inferTypeForExpression(TypeAnalysis.java:766)
        //     at com.strobel.decompiler.ast.TypeAnalysis.inferCall(TypeAnalysis.java:2445)
        //     at com.strobel.decompiler.ast.TypeAnalysis.doInferTypeForExpression(TypeAnalysis.java:1029)
        //     at com.strobel.decompiler.ast.TypeAnalysis.inferTypeForExpression(TypeAnalysis.java:803)
        //     at com.strobel.decompiler.ast.TypeAnalysis.inferTypeForExpression(TypeAnalysis.java:770)
        //     at com.strobel.decompiler.ast.TypeAnalysis.inferTypeForExpression(TypeAnalysis.java:766)
        //     at com.strobel.decompiler.ast.TypeAnalysis.inferCall(TypeAnalysis.java:2445)
        //     at com.strobel.decompiler.ast.TypeAnalysis.doInferTypeForExpression(TypeAnalysis.java:1029)
        //     at com.strobel.decompiler.ast.TypeAnalysis.inferTypeForExpression(TypeAnalysis.java:803)
        //     at com.strobel.decompiler.ast.TypeAnalysis.inferTypeForExpression(TypeAnalysis.java:770)
        //     at com.strobel.decompiler.ast.TypeAnalysis.inferTypeForExpression(TypeAnalysis.java:766)
        //     at com.strobel.decompiler.ast.TypeAnalysis.inferCall(TypeAnalysis.java:2445)
        //     at com.strobel.decompiler.ast.TypeAnalysis.doInferTypeForExpression(TypeAnalysis.java:1029)
        //     at com.strobel.decompiler.ast.TypeAnalysis.inferTypeForExpression(TypeAnalysis.java:803)
        //     at com.strobel.decompiler.ast.TypeAnalysis.inferTypeForExpression(TypeAnalysis.java:770)
        //     at com.strobel.decompiler.ast.TypeAnalysis.inferTypeForExpression(TypeAnalysis.java:766)
        //     at com.strobel.decompiler.ast.TypeAnalysis.inferCall(TypeAnalysis.java:2445)
        //     at com.strobel.decompiler.ast.TypeAnalysis.doInferTypeForExpression(TypeAnalysis.java:1029)
        //     at com.strobel.decompiler.ast.TypeAnalysis.inferTypeForExpression(TypeAnalysis.java:803)
        //     at com.strobel.decompiler.ast.TypeAnalysis.inferTypeForExpression(TypeAnalysis.java:770)
        //     at com.strobel.decompiler.ast.TypeAnalysis.inferTypeForExpression(TypeAnalysis.java:766)
        //     at com.strobel.decompiler.ast.TypeAnalysis.inferCall(TypeAnalysis.java:2445)
        //     at com.strobel.decompiler.ast.TypeAnalysis.doInferTypeForExpression(TypeAnalysis.java:1029)
        //     at com.strobel.decompiler.ast.TypeAnalysis.inferTypeForExpression(TypeAnalysis.java:803)
        //     at com.strobel.decompiler.ast.TypeAnalysis.inferTypeForExpression(TypeAnalysis.java:770)
        //     at com.strobel.decompiler.ast.TypeAnalysis.inferTypeForExpression(TypeAnalysis.java:766)
        //     at com.strobel.decompiler.ast.TypeAnalysis.inferCall(TypeAnalysis.java:2445)
        //     at com.strobel.decompiler.ast.TypeAnalysis.doInferTypeForExpression(TypeAnalysis.java:1029)
        //     at com.strobel.decompiler.ast.TypeAnalysis.inferTypeForExpression(TypeAnalysis.java:803)
        //     at com.strobel.decompiler.ast.TypeAnalysis.inferTypeForExpression(TypeAnalysis.java:770)
        //     at com.strobel.decompiler.ast.TypeAnalysis.inferTypeForExpression(TypeAnalysis.java:766)
        //     at com.strobel.decompiler.ast.TypeAnalysis.inferCall(TypeAnalysis.java:2445)
        //     at com.strobel.decompiler.ast.TypeAnalysis.doInferTypeForExpression(TypeAnalysis.java:1029)
        //     at com.strobel.decompiler.ast.TypeAnalysis.inferTypeForExpression(TypeAnalysis.java:803)
        //     at com.strobel.decompiler.ast.TypeAnalysis.inferTypeForExpression(TypeAnalysis.java:770)
        //     at com.strobel.decompiler.ast.TypeAnalysis.inferTypeForExpression(TypeAnalysis.java:766)
        //     at com.strobel.decompiler.ast.TypeAnalysis.inferCall(TypeAnalysis.java:2445)
        //     at com.strobel.decompiler.ast.TypeAnalysis.doInferTypeForExpression(TypeAnalysis.java:1029)
        //     at com.strobel.decompiler.ast.TypeAnalysis.inferTypeForExpression(TypeAnalysis.java:803)
        //     at com.strobel.decompiler.ast.TypeAnalysis.inferTypeForExpression(TypeAnalysis.java:770)
        //     at com.strobel.decompiler.ast.TypeAnalysis.inferTypeForExpression(TypeAnalysis.java:766)
        //     at com.strobel.decompiler.ast.TypeAnalysis.inferCall(TypeAnalysis.java:2445)
        //     at com.strobel.decompiler.ast.TypeAnalysis.doInferTypeForExpression(TypeAnalysis.java:1029)
        //     at com.strobel.decompiler.ast.TypeAnalysis.inferTypeForExpression(TypeAnalysis.java:803)
        //     at com.strobel.decompiler.ast.TypeAnalysis.inferTypeForExpression(TypeAnalysis.java:770)
        //     at com.strobel.decompiler.ast.TypeAnalysis.inferTypeForExpression(TypeAnalysis.java:766)
        //     at com.strobel.decompiler.ast.TypeAnalysis.inferCall(TypeAnalysis.java:2445)
        //     at com.strobel.decompiler.ast.TypeAnalysis.doInferTypeForExpression(TypeAnalysis.java:1029)
        //     at com.strobel.decompiler.ast.TypeAnalysis.inferTypeForExpression(TypeAnalysis.java:803)
        //     at com.strobel.decompiler.ast.TypeAnalysis.inferTypeForExpression(TypeAnalysis.java:770)
        //     at com.strobel.decompiler.ast.TypeAnalysis.inferTypeForExpression(TypeAnalysis.java:766)
        //     at com.strobel.decompiler.ast.TypeAnalysis.inferCall(TypeAnalysis.java:2445)
        //     at com.strobel.decompiler.ast.TypeAnalysis.doInferTypeForExpression(TypeAnalysis.java:1029)
        //     at com.strobel.decompiler.ast.TypeAnalysis.inferTypeForExpression(TypeAnalysis.java:803)
        //     at com.strobel.decompiler.ast.TypeAnalysis.inferTypeForExpression(TypeAnalysis.java:770)
        //     at com.strobel.decompiler.ast.TypeAnalysis.inferTypeForExpression(TypeAnalysis.java:766)
        //     at com.strobel.decompiler.ast.TypeAnalysis.inferCall(TypeAnalysis.java:2445)
        //     at com.strobel.decompiler.ast.TypeAnalysis.doInferTypeForExpression(TypeAnalysis.java:1029)
        //     at com.strobel.decompiler.ast.TypeAnalysis.inferTypeForExpression(TypeAnalysis.java:803)
        //     at com.strobel.decompiler.ast.TypeAnalysis.inferTypeForExpression(TypeAnalysis.java:770)
        //     at com.strobel.decompiler.ast.TypeAnalysis.inferTypeForExpression(TypeAnalysis.java:766)
        //     at com.strobel.decompiler.ast.TypeAnalysis.inferCall(TypeAnalysis.java:2445)
        //     at com.strobel.decompiler.ast.TypeAnalysis.doInferTypeForExpression(TypeAnalysis.java:1029)
        //     at com.strobel.decompiler.ast.TypeAnalysis.inferTypeForExpression(TypeAnalysis.java:803)
        //     at com.strobel.decompiler.ast.TypeAnalysis.inferTypeForExpression(TypeAnalysis.java:770)
        //     at com.strobel.decompiler.ast.TypeAnalysis.doInferTypeForExpression(TypeAnalysis.java:881)
        //     at com.strobel.decompiler.ast.TypeAnalysis.inferTypeForExpression(TypeAnalysis.java:803)
        //     at com.strobel.decompiler.ast.TypeAnalysis.runInference(TypeAnalysis.java:672)
        //     at com.strobel.decompiler.ast.TypeAnalysis.inferTypesForVariables(TypeAnalysis.java:586)
        //     at com.strobel.decompiler.ast.TypeAnalysis.runInference(TypeAnalysis.java:397)
        //     at com.strobel.decompiler.ast.TypeAnalysis.run(TypeAnalysis.java:96)
        //     at com.strobel.decompiler.ast.AstOptimizer.optimize(AstOptimizer.java:109)
        //     at com.strobel.decompiler.ast.AstOptimizer.optimize(AstOptimizer.java:42)
        //     at com.strobel.decompiler.languages.java.ast.AstMethodBodyBuilder.createMethodBody(AstMethodBodyBuilder.java:214)
        //     at com.strobel.decompiler.languages.java.ast.AstMethodBodyBuilder.createMethodBody(AstMethodBodyBuilder.java:99)
        //     at com.strobel.decompiler.languages.java.ast.AstBuilder.createMethodBody(AstBuilder.java:757)
        //     at com.strobel.decompiler.languages.java.ast.AstBuilder.createMethod(AstBuilder.java:655)
        //     at com.strobel.decompiler.languages.java.ast.AstBuilder.addTypeMembers(AstBuilder.java:532)
        //     at com.strobel.decompiler.languages.java.ast.AstBuilder.createTypeCore(AstBuilder.java:499)
        //     at com.strobel.decompiler.languages.java.ast.AstBuilder.createTypeNoCache(AstBuilder.java:141)
        //     at com.strobel.decompiler.languages.java.ast.AstBuilder.createType(AstBuilder.java:130)
        //     at com.strobel.decompiler.languages.java.ast.AstBuilder.addType(AstBuilder.java:105)
        //     at com.strobel.decompiler.languages.java.JavaLanguage.buildAst(JavaLanguage.java:71)
        //     at com.strobel.decompiler.languages.java.JavaLanguage.decompileType(JavaLanguage.java:59)
        //     at com.strobel.decompiler.Decompiler.decompile(Decompiler.java:70)
        //     at com.edu.dibyarup.DecompilerUtil.decompileFiles(DecompilerUtil.java:28)
        //     at com.edu.dibyarup.FileDB.decompileAllFiles(FileDB.java:48)
        //     at com.edu.dibyarup.FileDB.decompileAllFiles(FileDB.java:42)
        //     at com.edu.dibyarup.FileDB.decompileAllFiles(FileDB.java:42)
        //     at com.edu.dibyarup.FileDB.decompileAllFiles(FileDB.java:42)
        //     at com.edu.dibyarup.FileDB.decompileAllFiles(FileDB.java:42)
        //     at com.edu.dibyarup.FileDB.main(FileDB.java:14)
        // 
        throw new IllegalStateException("An error occurred while decompiling this method.");
    }
    
    public void doPost(final HttpServletRequest request, final HttpServletResponse response) throws IOException, ServletException {
        this.doGet(request, response);
    }
    
    static {
        log = new SimpleLogger((Class)StandAloneAssessment.class);
    }
}
