package learnityasmtserver.assessmentportal.embeddedasmt;

import org.grlea.log.*;
import java.util.*;

import org.apache.ecs.*;
import learnityInit.*;
import org.apache.ecs.xhtml.*;

public class GenerateXHTML
{
    public static final SimpleLogger log;
    String course_id;
    
    public GenerateXHTML(final String c_id) {
        this.course_id = null;
        this.course_id = c_id;
    }
    
    public String generateHTML(final Vector strSub, final Vector questionAll, final String strButton, final String strButtonResult, final String duration, final boolean bRefresh, final int iSec, final Vector vAssessment) {
        // 
        // This method could not be decompiled.
        // 
        // Original Bytecode:
        // 
        //     0: new             Ljava/util/GregorianCalendar;
        //     3: dup            
        //     4: invokespecial   java/util/GregorianCalendar.<init>:()V
        //     7: astore          calendar
        //     9: new             Ljava/util/Date;
        //    12: dup            
        //    13: invokespecial   java/util/Date.<init>:()V
        //    16: astore          trialTime
        //    18: aload           calendar
        //    20: aload           trialTime
        //    22: invokevirtual   java/util/Calendar.setTime:(Ljava/util/Date;)V
        //    25: bipush          12
        //    27: anewarray       Ljava/lang/String;
        //    30: dup            
        //    31: iconst_0       
        //    32: ldc             "January"
        //    34: aastore        
        //    35: dup            
        //    36: iconst_1       
        //    37: ldc             "Feburary"
        //    39: aastore        
        //    40: dup            
        //    41: iconst_2       
        //    42: ldc             "March"
        //    44: aastore        
        //    45: dup            
        //    46: iconst_3       
        //    47: ldc             "April"
        //    49: aastore        
        //    50: dup            
        //    51: iconst_4       
        //    52: ldc             "May"
        //    54: aastore        
        //    55: dup            
        //    56: iconst_5       
        //    57: ldc             "June"
        //    59: aastore        
        //    60: dup            
        //    61: bipush          6
        //    63: ldc             "July"
        //    65: aastore        
        //    66: dup            
        //    67: bipush          7
        //    69: ldc             "August"
        //    71: aastore        
        //    72: dup            
        //    73: bipush          8
        //    75: ldc             "September"
        //    77: aastore        
        //    78: dup            
        //    79: bipush          9
        //    81: ldc             "October"
        //    83: aastore        
        //    84: dup            
        //    85: bipush          10
        //    87: ldc             "November"
        //    89: aastore        
        //    90: dup            
        //    91: bipush          11
        //    93: ldc             "December"
        //    95: aastore        
        //    96: astore          months
        //    98: new             Ljava/lang/StringBuilder;
        //   101: dup            
        //   102: invokespecial   java/lang/StringBuilder.<init>:()V
        //   105: aload           calendar
        //   107: bipush          10
        //   109: invokevirtual   java/util/Calendar.get:(I)I
        //   112: invokevirtual   java/lang/StringBuilder.append:(I)Ljava/lang/StringBuilder;
        //   115: ldc             ":"
        //   117: invokevirtual   java/lang/StringBuilder.append:(Ljava/lang/String;)Ljava/lang/StringBuilder;
        //   120: aload           calendar
        //   122: bipush          12
        //   124: invokevirtual   java/util/Calendar.get:(I)I
        //   127: invokevirtual   java/lang/StringBuilder.append:(I)Ljava/lang/StringBuilder;
        //   130: invokevirtual   java/lang/StringBuilder.toString:()Ljava/lang/String;
        //   133: astore          strTime
        //   135: new             Ljava/lang/StringBuilder;
        //   138: dup            
        //   139: invokespecial   java/lang/StringBuilder.<init>:()V
        //   142: aload           months
        //   144: aload           calendar
        //   146: iconst_2       
        //   147: invokevirtual   java/util/Calendar.get:(I)I
        //   150: aaload         
        //   151: invokevirtual   java/lang/StringBuilder.append:(Ljava/lang/String;)Ljava/lang/StringBuilder;
        //   154: ldc             " "
        //   156: invokevirtual   java/lang/StringBuilder.append:(Ljava/lang/String;)Ljava/lang/StringBuilder;
        //   159: aload           calendar
        //   161: iconst_5       
        //   162: invokevirtual   java/util/Calendar.get:(I)I
        //   165: invokevirtual   java/lang/StringBuilder.append:(I)Ljava/lang/StringBuilder;
        //   168: ldc             ", "
        //   170: invokevirtual   java/lang/StringBuilder.append:(Ljava/lang/String;)Ljava/lang/StringBuilder;
        //   173: aload           calendar
        //   175: iconst_1       
        //   176: invokevirtual   java/util/Calendar.get:(I)I
        //   179: invokevirtual   java/lang/StringBuilder.append:(I)Ljava/lang/StringBuilder;
        //   182: invokevirtual   java/lang/StringBuilder.toString:()Ljava/lang/String;
        //   185: astore          strDate
        //   187: new             Ljava/lang/StringBuffer;
        //   190: dup            
        //   191: invokespecial   java/lang/StringBuffer.<init>:()V
        //   194: astore          strHTML
        //   196: aload_1         /* strSub */
        //   197: iconst_0       
        //   198: invokevirtual   java/util/Vector.elementAt:(I)Ljava/lang/Object;
        //   201: checkcast       Ljava/lang/String;
        //   204: astore          entitle
        //   206: new             Lorg/apache/ecs/Doctype;
        //   209: dup            
        //   210: ldc             "html"
        //   212: ldc             "\"-//W3C//DTD XHTML 1.0 Strict//EN\""
        //   214: ldc             "\"http://www.w3.org/TR/xhtml1/DTD/xhtml1-strict.dtd\""
        //   216: invokespecial   org/apache/ecs/Doctype.<init>:(Ljava/lang/String;Ljava/lang/String;Ljava/lang/String;)V
        //   219: astore          doc1
        //   221: new             Lorg/apache/ecs/xhtml/html;
        //   224: dup            
        //   225: invokespecial   org/apache/ecs/xhtml/html.<init>:()V
        //   228: astore          html1
        //   230: aload           html1
        //   232: ldc             "xlink"
        //   234: ldc             "http://www.w3.org/1999/xlink"
        //   236: invokevirtual   org/apache/ecs/xhtml/html.addAttribute:(Ljava/lang/String;Ljava/lang/String;)Lorg/apache/ecs/Element;
        //   239: pop            
        //   240: aload           html1
        //   242: ldc             "math"
        //   244: ldc             "http://www.w3.org/1998/Math/MathML"
        //   246: invokevirtual   org/apache/ecs/xhtml/html.addAttribute:(Ljava/lang/String;Ljava/lang/String;)Lorg/apache/ecs/Element;
        //   249: pop            
        //   250: aload           html1
        //   252: ldc             "xmlns"
        //   254: ldc             "http://www.w3.org/1999/xhtml"
        //   256: invokevirtual   org/apache/ecs/xhtml/html.addAttribute:(Ljava/lang/String;Ljava/lang/String;)Lorg/apache/ecs/Element;
        //   259: pop            
        //   260: new             Lorg/apache/ecs/xhtml/head;
        //   263: dup            
        //   264: invokespecial   org/apache/ecs/xhtml/head.<init>:()V
        //   267: astore          head1
        //   269: new             Lorg/apache/ecs/xhtml/title;
        //   272: dup            
        //   273: invokespecial   org/apache/ecs/xhtml/title.<init>:()V
        //   276: astore          title1
        //   278: new             Lorg/apache/ecs/xhtml/link;
        //   281: dup            
        //   282: invokespecial   org/apache/ecs/xhtml/link.<init>:()V
        //   285: ldc             "stylesheet"
        //   287: invokevirtual   org/apache/ecs/xhtml/link.setRel:(Ljava/lang/String;)Lorg/apache/ecs/xhtml/link;
        //   290: astore          csslink
        //   292: new             Lorg/apache/ecs/xhtml/link;
        //   295: dup            
        //   296: invokespecial   org/apache/ecs/xhtml/link.<init>:()V
        //   299: astore          csslink1
        //   301: aload           csslink1
        //   303: ldc             "stylesheet"
        //   305: invokevirtual   org/apache/ecs/xhtml/link.setRel:(Ljava/lang/String;)Lorg/apache/ecs/xhtml/link;
        //   308: pop            
        //   309: aload           csslink1
        //   311: ldc             "../coreadmin/js/AssessmentServer.css"
        //   313: invokevirtual   org/apache/ecs/xhtml/link.setHref:(Ljava/lang/String;)Lorg/apache/ecs/xhtml/link;
        //   316: pop            
        //   317: aload           head1
        //   319: aload           csslink1
        //   321: invokevirtual   org/apache/ecs/xhtml/head.addElement:(Lorg/apache/ecs/Element;)Lorg/apache/ecs/xhtml/head;
        //   324: pop            
        //   325: new             Lorg/apache/ecs/xhtml/script;
        //   328: dup            
        //   329: invokespecial   org/apache/ecs/xhtml/script.<init>:()V
        //   332: ldc             "javascript"
        //   334: invokevirtual   org/apache/ecs/xhtml/script.setLanguage:(Ljava/lang/String;)Lorg/apache/ecs/xhtml/script;
        //   337: astore          script1
        //   339: new             Lorg/apache/ecs/xhtml/body;
        //   342: dup            
        //   343: invokespecial   org/apache/ecs/xhtml/body.<init>:()V
        //   346: astore          body1
        //   348: aload           body1
        //   350: ldc             "trapKey()"
        //   352: invokevirtual   org/apache/ecs/xhtml/body.setOnKeyDown:(Ljava/lang/String;)V
        //   355: aload           body1
        //   357: new             Ljava/lang/StringBuilder;
        //   360: dup            
        //   361: invokespecial   java/lang/StringBuilder.<init>:()V
        //   364: ldc             "Down("
        //   366: invokevirtual   java/lang/StringBuilder.append:(Ljava/lang/String;)Ljava/lang/StringBuilder;
        //   369: aload           duration
        //   371: invokevirtual   java/lang/StringBuilder.append:(Ljava/lang/String;)Ljava/lang/StringBuilder;
        //   374: ldc             ")"
        //   376: invokevirtual   java/lang/StringBuilder.append:(Ljava/lang/String;)Ljava/lang/StringBuilder;
        //   379: invokevirtual   java/lang/StringBuilder.toString:()Ljava/lang/String;
        //   382: invokevirtual   org/apache/ecs/xhtml/body.setOnLoad:(Ljava/lang/String;)V
        //   385: new             Lorg/apache/ecs/xhtml/form;
        //   388: dup            
        //   389: invokespecial   org/apache/ecs/xhtml/form.<init>:()V
        //   392: astore          form1
        //   394: aload           form1
        //   396: ldc             "frm"
        //   398: invokevirtual   org/apache/ecs/xhtml/form.setID:(Ljava/lang/String;)Lorg/apache/ecs/Element;
        //   401: pop            
        //   402: new             Lorg/apache/ecs/xhtml/table;
        //   405: dup            
        //   406: invokespecial   org/apache/ecs/xhtml/table.<init>:()V
        //   409: iconst_0       
        //   410: invokevirtual   org/apache/ecs/xhtml/table.setCellPadding:(I)Lorg/apache/ecs/xhtml/table;
        //   413: iconst_1       
        //   414: invokevirtual   org/apache/ecs/xhtml/table.setCellSpacing:(I)Lorg/apache/ecs/xhtml/table;
        //   417: ldc             "75%"
        //   419: invokevirtual   org/apache/ecs/xhtml/table.setWidth:(Ljava/lang/String;)Lorg/apache/ecs/xhtml/table;
        //   422: astore          table1
        //   424: new             Lorg/apache/ecs/xhtml/tr;
        //   427: dup            
        //   428: invokespecial   org/apache/ecs/xhtml/tr.<init>:()V
        //   431: astore          tr1
        //   433: new             Lorg/apache/ecs/xhtml/td;
        //   436: dup            
        //   437: invokespecial   org/apache/ecs/xhtml/td.<init>:()V
        //   440: ldc             "50%"
        //   442: invokevirtual   org/apache/ecs/xhtml/td.setWidth:(Ljava/lang/String;)Lorg/apache/ecs/xhtml/td;
        //   445: bipush          23
        //   447: invokevirtual   org/apache/ecs/xhtml/td.setHeight:(I)Lorg/apache/ecs/xhtml/td;
        //   450: astore          td1
        //   452: new             Lorg/apache/ecs/xhtml/td;
        //   455: dup            
        //   456: invokespecial   org/apache/ecs/xhtml/td.<init>:()V
        //   459: ldc             "25%"
        //   461: invokevirtual   org/apache/ecs/xhtml/td.setWidth:(Ljava/lang/String;)Lorg/apache/ecs/xhtml/td;
        //   464: astore          td2
        //   466: new             Lorg/apache/ecs/xhtml/td;
        //   469: dup            
        //   470: invokespecial   org/apache/ecs/xhtml/td.<init>:()V
        //   473: ldc             "25%"
        //   475: invokevirtual   org/apache/ecs/xhtml/td.setWidth:(Ljava/lang/String;)Lorg/apache/ecs/xhtml/td;
        //   478: astore          td3
        //   480: new             Lorg/apache/ecs/xhtml/tr;
        //   483: dup            
        //   484: invokespecial   org/apache/ecs/xhtml/tr.<init>:()V
        //   487: ldc             "#336699"
        //   489: invokevirtual   org/apache/ecs/xhtml/tr.setBgColor:(Ljava/lang/String;)Lorg/apache/ecs/xhtml/tr;
        //   492: astore          tr2
        //   494: new             Lorg/apache/ecs/xhtml/td;
        //   497: dup            
        //   498: invokespecial   org/apache/ecs/xhtml/td.<init>:()V
        //   501: ldc             "3"
        //   503: invokevirtual   org/apache/ecs/xhtml/td.setColSpan:(Ljava/lang/String;)Lorg/apache/ecs/xhtml/td;
        //   506: ldc             "25%"
        //   508: invokevirtual   org/apache/ecs/xhtml/td.setWidth:(Ljava/lang/String;)Lorg/apache/ecs/xhtml/td;
        //   511: astore          td4
        //   513: new             Lorg/apache/ecs/xhtml/tr;
        //   516: dup            
        //   517: invokespecial   org/apache/ecs/xhtml/tr.<init>:()V
        //   520: ldc             "#336699"
        //   522: invokevirtual   org/apache/ecs/xhtml/tr.setBgColor:(Ljava/lang/String;)Lorg/apache/ecs/xhtml/tr;
        //   525: astore          tr3
        //   527: new             Lorg/apache/ecs/xhtml/td;
        //   530: dup            
        //   531: invokespecial   org/apache/ecs/xhtml/td.<init>:()V
        //   534: ldc             "3"
        //   536: invokevirtual   org/apache/ecs/xhtml/td.setColSpan:(Ljava/lang/String;)Lorg/apache/ecs/xhtml/td;
        //   539: ldc             "25%"
        //   541: invokevirtual   org/apache/ecs/xhtml/td.setWidth:(Ljava/lang/String;)Lorg/apache/ecs/xhtml/td;
        //   544: iconst_5       
        //   545: invokevirtual   org/apache/ecs/xhtml/td.setHeight:(I)Lorg/apache/ecs/xhtml/td;
        //   548: astore          td5
        //   550: new             Lorg/apache/ecs/xhtml/tr;
        //   553: dup            
        //   554: invokespecial   org/apache/ecs/xhtml/tr.<init>:()V
        //   557: astore          tr4
        //   559: new             Lorg/apache/ecs/xhtml/td;
        //   562: dup            
        //   563: invokespecial   org/apache/ecs/xhtml/td.<init>:()V
        //   566: ldc             "3"
        //   568: invokevirtual   org/apache/ecs/xhtml/td.setColSpan:(Ljava/lang/String;)Lorg/apache/ecs/xhtml/td;
        //   571: ldc             "25%"
        //   573: invokevirtual   org/apache/ecs/xhtml/td.setWidth:(Ljava/lang/String;)Lorg/apache/ecs/xhtml/td;
        //   576: bipush          23
        //   578: invokevirtual   org/apache/ecs/xhtml/td.setHeight:(I)Lorg/apache/ecs/xhtml/td;
        //   581: astore          td6
        //   583: new             Lorg/apache/ecs/xhtml/tr;
        //   586: dup            
        //   587: invokespecial   org/apache/ecs/xhtml/tr.<init>:()V
        //   590: astore          tr41
        //   592: new             Lorg/apache/ecs/xhtml/td;
        //   595: dup            
        //   596: invokespecial   org/apache/ecs/xhtml/td.<init>:()V
        //   599: ldc             "3"
        //   601: invokevirtual   org/apache/ecs/xhtml/td.setColSpan:(Ljava/lang/String;)Lorg/apache/ecs/xhtml/td;
        //   604: ldc             "25%"
        //   606: invokevirtual   org/apache/ecs/xhtml/td.setWidth:(Ljava/lang/String;)Lorg/apache/ecs/xhtml/td;
        //   609: bipush          23
        //   611: invokevirtual   org/apache/ecs/xhtml/td.setHeight:(I)Lorg/apache/ecs/xhtml/td;
        //   614: astore          td61
        //   616: new             Lorg/apache/ecs/xhtml/tr;
        //   619: dup            
        //   620: invokespecial   org/apache/ecs/xhtml/tr.<init>:()V
        //   623: ldc             "#336699"
        //   625: invokevirtual   org/apache/ecs/xhtml/tr.setBgColor:(Ljava/lang/String;)Lorg/apache/ecs/xhtml/tr;
        //   628: astore          tr5
        //   630: new             Lorg/apache/ecs/xhtml/td;
        //   633: dup            
        //   634: invokespecial   org/apache/ecs/xhtml/td.<init>:()V
        //   637: ldc             "3"
        //   639: invokevirtual   org/apache/ecs/xhtml/td.setColSpan:(Ljava/lang/String;)Lorg/apache/ecs/xhtml/td;
        //   642: ldc             "25%"
        //   644: invokevirtual   org/apache/ecs/xhtml/td.setWidth:(Ljava/lang/String;)Lorg/apache/ecs/xhtml/td;
        //   647: astore          td7
        //   649: new             Lorg/apache/ecs/xhtml/table;
        //   652: dup            
        //   653: invokespecial   org/apache/ecs/xhtml/table.<init>:()V
        //   656: iconst_0       
        //   657: invokevirtual   org/apache/ecs/xhtml/table.setBorder:(I)Lorg/apache/ecs/xhtml/table;
        //   660: iconst_1       
        //   661: invokevirtual   org/apache/ecs/xhtml/table.setCellPadding:(I)Lorg/apache/ecs/xhtml/table;
        //   664: iconst_0       
        //   665: invokevirtual   org/apache/ecs/xhtml/table.setCellSpacing:(I)Lorg/apache/ecs/xhtml/table;
        //   668: ldc             "75%"
        //   670: invokevirtual   org/apache/ecs/xhtml/table.setWidth:(Ljava/lang/String;)Lorg/apache/ecs/xhtml/table;
        //   673: astore          table2
        //   675: new             Lorg/apache/ecs/xhtml/tr;
        //   678: dup            
        //   679: invokespecial   org/apache/ecs/xhtml/tr.<init>:()V
        //   682: astore          tr6
        //   684: new             Lorg/apache/ecs/xhtml/td;
        //   687: dup            
        //   688: invokespecial   org/apache/ecs/xhtml/td.<init>:()V
        //   691: ldc             "3"
        //   693: invokevirtual   org/apache/ecs/xhtml/td.setColSpan:(Ljava/lang/String;)Lorg/apache/ecs/xhtml/td;
        //   696: astore          td8
        //   698: new             Lorg/apache/ecs/xhtml/table;
        //   701: dup            
        //   702: invokespecial   org/apache/ecs/xhtml/table.<init>:()V
        //   705: iconst_0       
        //   706: invokevirtual   org/apache/ecs/xhtml/table.setCellPadding:(I)Lorg/apache/ecs/xhtml/table;
        //   709: iconst_4       
        //   710: invokevirtual   org/apache/ecs/xhtml/table.setCellSpacing:(I)Lorg/apache/ecs/xhtml/table;
        //   713: ldc             "100%"
        //   715: invokevirtual   org/apache/ecs/xhtml/table.setWidth:(Ljava/lang/String;)Lorg/apache/ecs/xhtml/table;
        //   718: astore          table3
        //   720: new             Lorg/apache/ecs/xhtml/tr;
        //   723: dup            
        //   724: invokespecial   org/apache/ecs/xhtml/tr.<init>:()V
        //   727: astore          tr9
        //   729: new             Lorg/apache/ecs/xhtml/td;
        //   732: dup            
        //   733: invokespecial   org/apache/ecs/xhtml/td.<init>:()V
        //   736: ldc             "center"
        //   738: invokevirtual   org/apache/ecs/xhtml/td.setAlign:(Ljava/lang/String;)Lorg/apache/ecs/xhtml/td;
        //   741: astore          td14
        //   743: new             Lorg/apache/ecs/xhtml/table;
        //   746: dup            
        //   747: invokespecial   org/apache/ecs/xhtml/table.<init>:()V
        //   750: astore          table4
        //   752: new             Lorg/apache/ecs/xhtml/tbody;
        //   755: dup            
        //   756: invokespecial   org/apache/ecs/xhtml/tbody.<init>:()V
        //   759: astore          tbody1
        //   761: new             Lorg/apache/ecs/xhtml/tr;
        //   764: dup            
        //   765: invokespecial   org/apache/ecs/xhtml/tr.<init>:()V
        //   768: astore          tr11
        //   770: new             Lorg/apache/ecs/xhtml/td;
        //   773: dup            
        //   774: invokespecial   org/apache/ecs/xhtml/td.<init>:()V
        //   777: sipush          140
        //   780: invokevirtual   org/apache/ecs/xhtml/td.setWidth:(I)Lorg/apache/ecs/xhtml/td;
        //   783: astore          td19
        //   785: new             Lorg/apache/ecs/xhtml/td;
        //   788: dup            
        //   789: invokespecial   org/apache/ecs/xhtml/td.<init>:()V
        //   792: ldc             "100%"
        //   794: invokevirtual   org/apache/ecs/xhtml/td.setWidth:(Ljava/lang/String;)Lorg/apache/ecs/xhtml/td;
        //   797: astore          td20
        //   799: new             Lorg/apache/ecs/xhtml/table;
        //   802: dup            
        //   803: invokespecial   org/apache/ecs/xhtml/table.<init>:()V
        //   806: iconst_0       
        //   807: invokevirtual   org/apache/ecs/xhtml/table.setBorder:(I)Lorg/apache/ecs/xhtml/table;
        //   810: iconst_3       
        //   811: invokevirtual   org/apache/ecs/xhtml/table.setCellPadding:(I)Lorg/apache/ecs/xhtml/table;
        //   814: iconst_4       
        //   815: invokevirtual   org/apache/ecs/xhtml/table.setCellSpacing:(I)Lorg/apache/ecs/xhtml/table;
        //   818: astore          table5
        //   820: new             Lorg/apache/ecs/xhtml/tr;
        //   823: dup            
        //   824: invokespecial   org/apache/ecs/xhtml/tr.<init>:()V
        //   827: astore          tr12
        //   829: new             Lorg/apache/ecs/xhtml/td;
        //   832: dup            
        //   833: invokespecial   org/apache/ecs/xhtml/td.<init>:()V
        //   836: astore          td21
        //   838: new             Lorg/apache/ecs/xhtml/td;
        //   841: dup            
        //   842: invokespecial   org/apache/ecs/xhtml/td.<init>:()V
        //   845: astore          td22
        //   847: new             Lorg/apache/ecs/xhtml/td;
        //   850: dup            
        //   851: invokespecial   org/apache/ecs/xhtml/td.<init>:()V
        //   854: iconst_5       
        //   855: invokevirtual   org/apache/ecs/xhtml/td.setWidth:(I)Lorg/apache/ecs/xhtml/td;
        //   858: astore          td23
        //   860: new             Lorg/apache/ecs/xhtml/font;
        //   863: dup            
        //   864: invokespecial   org/apache/ecs/xhtml/font.<init>:()V
        //   867: iconst_3       
        //   868: invokevirtual   org/apache/ecs/xhtml/font.setSize:(I)Lorg/apache/ecs/xhtml/font;
        //   871: astore          font1
        //   873: new             Lorg/apache/ecs/xhtml/font;
        //   876: dup            
        //   877: invokespecial   org/apache/ecs/xhtml/font.<init>:()V
        //   880: iconst_4       
        //   881: invokevirtual   org/apache/ecs/xhtml/font.setSize:(I)Lorg/apache/ecs/xhtml/font;
        //   884: ldc             "#CC0000"
        //   886: invokevirtual   org/apache/ecs/xhtml/font.setColor:(Ljava/lang/String;)Lorg/apache/ecs/xhtml/font;
        //   889: astore          font2
        //   891: new             Lorg/apache/ecs/xhtml/font;
        //   894: dup            
        //   895: invokespecial   org/apache/ecs/xhtml/font.<init>:()V
        //   898: iconst_3       
        //   899: invokevirtual   org/apache/ecs/xhtml/font.setSize:(I)Lorg/apache/ecs/xhtml/font;
        //   902: astore          font3
        //   904: aload           title1
        //   906: aload           entitle
        //   908: invokevirtual   org/apache/ecs/xhtml/title.addElement:(Ljava/lang/String;)Lorg/apache/ecs/xhtml/title;
        //   911: pop            
        //   912: aload           script1
        //   914: ldc             "../coreadmin/js/ansEAM.js"
        //   916: invokevirtual   org/apache/ecs/xhtml/script.setSrc:(Ljava/lang/String;)Lorg/apache/ecs/xhtml/script;
        //   919: pop            
        //   920: aload           csslink
        //   922: ldc             "../coreadmin/js/stylesheet.css"
        //   924: invokevirtual   org/apache/ecs/xhtml/link.setHref:(Ljava/lang/String;)Lorg/apache/ecs/xhtml/link;
        //   927: pop            
        //   928: aload           body1
        //   930: new             Lorg/apache/ecs/xhtml/br;
        //   933: dup            
        //   934: invokespecial   org/apache/ecs/xhtml/br.<init>:()V
        //   937: invokevirtual   org/apache/ecs/xhtml/body.addElement:(Lorg/apache/ecs/Element;)Lorg/apache/ecs/xhtml/body;
        //   940: pop            
        //   941: aload           body1
        //   943: new             Lorg/apache/ecs/xhtml/center;
        //   946: dup            
        //   947: invokespecial   org/apache/ecs/xhtml/center.<init>:()V
        //   950: aload           font1
        //   952: invokevirtual   org/apache/ecs/xhtml/center.addElement:(Lorg/apache/ecs/Element;)Lorg/apache/ecs/xhtml/center;
        //   955: aload           font2
        //   957: invokevirtual   org/apache/ecs/xhtml/center.addElement:(Lorg/apache/ecs/Element;)Lorg/apache/ecs/xhtml/center;
        //   960: aload           font3
        //   962: invokevirtual   org/apache/ecs/xhtml/center.addElement:(Lorg/apache/ecs/Element;)Lorg/apache/ecs/xhtml/center;
        //   965: invokevirtual   org/apache/ecs/xhtml/body.addElement:(Lorg/apache/ecs/Element;)Lorg/apache/ecs/xhtml/body;
        //   968: pop            
        //   969: aload           font1
        //   971: new             Lorg/apache/ecs/xhtml/b;
        //   974: dup            
        //   975: invokespecial   org/apache/ecs/xhtml/b.<init>:()V
        //   978: invokevirtual   org/apache/ecs/xhtml/font.addElement:(Lorg/apache/ecs/Element;)Lorg/apache/ecs/xhtml/font;
        //   981: pop            
        //   982: aload           font1
        //   984: new             Lorg/apache/ecs/xhtml/em;
        //   987: dup            
        //   988: invokespecial   org/apache/ecs/xhtml/em.<init>:()V
        //   991: ldc             "Powered BY &nbsp;&nbsp;"
        //   993: invokevirtual   org/apache/ecs/xhtml/em.addElement:(Ljava/lang/String;)Lorg/apache/ecs/xhtml/em;
        //   996: invokevirtual   org/apache/ecs/xhtml/font.addElement:(Lorg/apache/ecs/Element;)Lorg/apache/ecs/xhtml/font;
        //   999: pop            
        //  1000: aload           font2
        //  1002: ldc             "LearnITy&#8482;&nbsp;&nbsp;"
        //  1004: invokevirtual   org/apache/ecs/xhtml/font.addElement:(Ljava/lang/String;)Lorg/apache/ecs/xhtml/font;
        //  1007: pop            
        //  1008: aload           font3
        //  1010: new             Lorg/apache/ecs/xhtml/b;
        //  1013: dup            
        //  1014: invokespecial   org/apache/ecs/xhtml/b.<init>:()V
        //  1017: invokevirtual   org/apache/ecs/xhtml/font.addElement:(Lorg/apache/ecs/Element;)Lorg/apache/ecs/xhtml/font;
        //  1020: pop            
        //  1021: aload           font3
        //  1023: new             Lorg/apache/ecs/xhtml/em;
        //  1026: dup            
        //  1027: invokespecial   org/apache/ecs/xhtml/em.<init>:()V
        //  1030: ldc             "Assessment Server"
        //  1032: invokevirtual   org/apache/ecs/xhtml/em.addElement:(Ljava/lang/String;)Lorg/apache/ecs/xhtml/em;
        //  1035: invokevirtual   org/apache/ecs/xhtml/font.addElement:(Lorg/apache/ecs/Element;)Lorg/apache/ecs/xhtml/font;
        //  1038: pop            
        //  1039: aload           table1
        //  1041: aload           tr1
        //  1043: aload           td1
        //  1045: new             Lorg/apache/ecs/xhtml/nobr;
        //  1048: dup            
        //  1049: invokespecial   org/apache/ecs/xhtml/nobr.<init>:()V
        //  1052: new             Ljava/lang/StringBuilder;
        //  1055: dup            
        //  1056: invokespecial   java/lang/StringBuilder.<init>:()V
        //  1059: ldc             "&nbsp;Assessment :&nbsp;"
        //  1061: invokevirtual   java/lang/StringBuilder.append:(Ljava/lang/String;)Ljava/lang/StringBuilder;
        //  1064: aload           vAssessment
        //  1066: iconst_0       
        //  1067: invokevirtual   java/util/Vector.elementAt:(I)Ljava/lang/Object;
        //  1070: checkcast       Ljava/util/Vector;
        //  1073: iconst_0       
        //  1074: invokevirtual   java/util/Vector.elementAt:(I)Ljava/lang/Object;
        //  1077: checkcast       Ljava/lang/String;
        //  1080: invokevirtual   java/lang/StringBuilder.append:(Ljava/lang/String;)Ljava/lang/StringBuilder;
        //  1083: ldc             "&nbsp;"
        //  1085: invokevirtual   java/lang/StringBuilder.append:(Ljava/lang/String;)Ljava/lang/StringBuilder;
        //  1088: invokevirtual   java/lang/StringBuilder.toString:()Ljava/lang/String;
        //  1091: invokevirtual   org/apache/ecs/xhtml/nobr.addElement:(Ljava/lang/String;)Lorg/apache/ecs/xhtml/nobr;
        //  1094: invokevirtual   org/apache/ecs/xhtml/td.addElement:(Lorg/apache/ecs/Element;)Lorg/apache/ecs/xhtml/td;
        //  1097: invokevirtual   org/apache/ecs/xhtml/tr.addElement:(Lorg/apache/ecs/Element;)Lorg/apache/ecs/xhtml/tr;
        //  1100: aload           td2
        //  1102: new             Lorg/apache/ecs/xhtml/nobr;
        //  1105: dup            
        //  1106: invokespecial   org/apache/ecs/xhtml/nobr.<init>:()V
        //  1109: new             Lorg/apache/ecs/xhtml/div;
        //  1112: dup            
        //  1113: invokespecial   org/apache/ecs/xhtml/div.<init>:()V
        //  1116: new             Ljava/lang/StringBuilder;
        //  1119: dup            
        //  1120: invokespecial   java/lang/StringBuilder.<init>:()V
        //  1123: ldc             "&nbsp;Date:  "
        //  1125: invokevirtual   java/lang/StringBuilder.append:(Ljava/lang/String;)Ljava/lang/StringBuilder;
        //  1128: aload           strDate
        //  1130: invokevirtual   java/lang/StringBuilder.append:(Ljava/lang/String;)Ljava/lang/StringBuilder;
        //  1133: ldc             "&nbsp;"
        //  1135: invokevirtual   java/lang/StringBuilder.append:(Ljava/lang/String;)Ljava/lang/StringBuilder;
        //  1138: invokevirtual   java/lang/StringBuilder.toString:()Ljava/lang/String;
        //  1141: invokevirtual   org/apache/ecs/xhtml/div.addElement:(Ljava/lang/String;)Lorg/apache/ecs/xhtml/div;
        //  1144: ldc             "DateTime"
        //  1146: invokevirtual   org/apache/ecs/xhtml/div.setID:(Ljava/lang/String;)Lorg/apache/ecs/Element;
        //  1149: invokevirtual   org/apache/ecs/xhtml/nobr.addElement:(Lorg/apache/ecs/Element;)Lorg/apache/ecs/xhtml/nobr;
        //  1152: invokevirtual   org/apache/ecs/xhtml/td.addElement:(Lorg/apache/ecs/Element;)Lorg/apache/ecs/xhtml/td;
        //  1155: invokevirtual   org/apache/ecs/xhtml/tr.addElement:(Lorg/apache/ecs/Element;)Lorg/apache/ecs/xhtml/tr;
        //  1158: aload           td3
        //  1160: new             Lorg/apache/ecs/xhtml/nobr;
        //  1163: dup            
        //  1164: invokespecial   org/apache/ecs/xhtml/nobr.<init>:()V
        //  1167: new             Lorg/apache/ecs/xhtml/div;
        //  1170: dup            
        //  1171: invokespecial   org/apache/ecs/xhtml/div.<init>:()V
        //  1174: new             Ljava/lang/StringBuilder;
        //  1177: dup            
        //  1178: invokespecial   java/lang/StringBuilder.<init>:()V
        //  1181: ldc             "&nbsp;Time: "
        //  1183: invokevirtual   java/lang/StringBuilder.append:(Ljava/lang/String;)Ljava/lang/StringBuilder;
        //  1186: aload           strTime
        //  1188: invokevirtual   java/lang/StringBuilder.append:(Ljava/lang/String;)Ljava/lang/StringBuilder;
        //  1191: ldc             "&nbsp;"
        //  1193: invokevirtual   java/lang/StringBuilder.append:(Ljava/lang/String;)Ljava/lang/StringBuilder;
        //  1196: invokevirtual   java/lang/StringBuilder.toString:()Ljava/lang/String;
        //  1199: invokevirtual   org/apache/ecs/xhtml/div.addElement:(Ljava/lang/String;)Lorg/apache/ecs/xhtml/div;
        //  1202: ldc             "DateTime"
        //  1204: invokevirtual   org/apache/ecs/xhtml/div.setID:(Ljava/lang/String;)Lorg/apache/ecs/Element;
        //  1207: invokevirtual   org/apache/ecs/xhtml/nobr.addElement:(Lorg/apache/ecs/Element;)Lorg/apache/ecs/xhtml/nobr;
        //  1210: invokevirtual   org/apache/ecs/xhtml/td.addElement:(Lorg/apache/ecs/Element;)Lorg/apache/ecs/xhtml/td;
        //  1213: invokevirtual   org/apache/ecs/xhtml/tr.addElement:(Lorg/apache/ecs/Element;)Lorg/apache/ecs/xhtml/tr;
        //  1216: ldc             "AssessmentSectionHeading"
        //  1218: invokevirtual   org/apache/ecs/xhtml/tr.setClass:(Ljava/lang/String;)Lorg/apache/ecs/Element;
        //  1221: invokevirtual   org/apache/ecs/xhtml/table.addElement:(Lorg/apache/ecs/Element;)Lorg/apache/ecs/xhtml/table;
        //  1224: pop            
        //  1225: aload           vAssessment
        //  1227: iconst_0       
        //  1228: invokevirtual   java/util/Vector.elementAt:(I)Ljava/lang/Object;
        //  1231: checkcast       Ljava/util/Vector;
        //  1234: iconst_2       
        //  1235: invokevirtual   java/util/Vector.elementAt:(I)Ljava/lang/Object;
        //  1238: checkcast       Ljava/lang/String;
        //  1241: astore          strAsmtPatern
        //  1243: aload           strAsmtPatern
        //  1245: ifnull          1338
        //  1248: aload           strAsmtPatern
        //  1250: ldc             ""
        //  1252: invokevirtual   java/lang/String.equals:(Ljava/lang/Object;)Z
        //  1255: ifne            1338
        //  1258: aload           table1
        //  1260: aload           tr2
        //  1262: aload           td4
        //  1264: new             Lorg/apache/ecs/xhtml/nobr;
        //  1267: dup            
        //  1268: invokespecial   org/apache/ecs/xhtml/nobr.<init>:()V
        //  1271: new             Lorg/apache/ecs/xhtml/div;
        //  1274: dup            
        //  1275: invokespecial   org/apache/ecs/xhtml/div.<init>:()V
        //  1278: new             Ljava/lang/StringBuilder;
        //  1281: dup            
        //  1282: invokespecial   java/lang/StringBuilder.<init>:()V
        //  1285: ldc             "&nbsp;"
        //  1287: invokevirtual   java/lang/StringBuilder.append:(Ljava/lang/String;)Ljava/lang/StringBuilder;
        //  1290: aload           vAssessment
        //  1292: iconst_0       
        //  1293: invokevirtual   java/util/Vector.elementAt:(I)Ljava/lang/Object;
        //  1296: checkcast       Ljava/util/Vector;
        //  1299: iconst_2       
        //  1300: invokevirtual   java/util/Vector.elementAt:(I)Ljava/lang/Object;
        //  1303: checkcast       Ljava/lang/String;
        //  1306: invokevirtual   java/lang/StringBuilder.append:(Ljava/lang/String;)Ljava/lang/StringBuilder;
        //  1309: ldc             "&nbsp;"
        //  1311: invokevirtual   java/lang/StringBuilder.append:(Ljava/lang/String;)Ljava/lang/StringBuilder;
        //  1314: invokevirtual   java/lang/StringBuilder.toString:()Ljava/lang/String;
        //  1317: invokevirtual   org/apache/ecs/xhtml/div.addElement:(Ljava/lang/String;)Lorg/apache/ecs/xhtml/div;
        //  1320: ldc             "DivB"
        //  1322: invokevirtual   org/apache/ecs/xhtml/div.setID:(Ljava/lang/String;)Lorg/apache/ecs/Element;
        //  1325: invokevirtual   org/apache/ecs/xhtml/nobr.addElement:(Lorg/apache/ecs/Element;)Lorg/apache/ecs/xhtml/nobr;
        //  1328: invokevirtual   org/apache/ecs/xhtml/td.addElement:(Lorg/apache/ecs/Element;)Lorg/apache/ecs/xhtml/td;
        //  1331: invokevirtual   org/apache/ecs/xhtml/tr.addElement:(Lorg/apache/ecs/Element;)Lorg/apache/ecs/xhtml/tr;
        //  1334: invokevirtual   org/apache/ecs/xhtml/table.addElement:(Lorg/apache/ecs/Element;)Lorg/apache/ecs/xhtml/table;
        //  1337: pop            
        //  1338: aload           table1
        //  1340: aload           tr3
        //  1342: aload           td5
        //  1344: invokevirtual   org/apache/ecs/xhtml/tr.addElement:(Lorg/apache/ecs/Element;)Lorg/apache/ecs/xhtml/tr;
        //  1347: invokevirtual   org/apache/ecs/xhtml/table.addElement:(Lorg/apache/ecs/Element;)Lorg/apache/ecs/xhtml/table;
        //  1350: pop            
        //  1351: aload           table1
        //  1353: aload           tr4
        //  1355: aload           td6
        //  1357: new             Lorg/apache/ecs/xhtml/nobr;
        //  1360: dup            
        //  1361: invokespecial   org/apache/ecs/xhtml/nobr.<init>:()V
        //  1364: new             Ljava/lang/StringBuilder;
        //  1367: dup            
        //  1368: invokespecial   java/lang/StringBuilder.<init>:()V
        //  1371: ldc             "Section: "
        //  1373: invokevirtual   java/lang/StringBuilder.append:(Ljava/lang/String;)Ljava/lang/StringBuilder;
        //  1376: aload_1         /* strSub */
        //  1377: iconst_0       
        //  1378: invokevirtual   java/util/Vector.elementAt:(I)Ljava/lang/Object;
        //  1381: invokevirtual   java/lang/StringBuilder.append:(Ljava/lang/Object;)Ljava/lang/StringBuilder;
        //  1384: ldc             " &nbsp;&nbsp;&nbsp;&nbsp;&nbsp;"
        //  1386: invokevirtual   java/lang/StringBuilder.append:(Ljava/lang/String;)Ljava/lang/StringBuilder;
        //  1389: invokevirtual   java/lang/StringBuilder.toString:()Ljava/lang/String;
        //  1392: invokevirtual   org/apache/ecs/xhtml/nobr.addElement:(Ljava/lang/String;)Lorg/apache/ecs/xhtml/nobr;
        //  1395: new             Lorg/apache/ecs/xhtml/nobr;
        //  1398: dup            
        //  1399: invokespecial   org/apache/ecs/xhtml/nobr.<init>:()V
        //  1402: new             Ljava/lang/StringBuilder;
        //  1405: dup            
        //  1406: invokespecial   java/lang/StringBuilder.<init>:()V
        //  1409: ldc             "Section Time Left:<input type=\"hidden\" name=\"beg2\" size=\"7\"  value=\""
        //  1411: invokevirtual   java/lang/StringBuilder.append:(Ljava/lang/String;)Ljava/lang/StringBuilder;
        //  1414: aload           duration
        //  1416: invokevirtual   java/lang/StringBuilder.append:(Ljava/lang/String;)Ljava/lang/StringBuilder;
        //  1419: ldc             "\"/>"
        //  1421: invokevirtual   java/lang/StringBuilder.append:(Ljava/lang/String;)Ljava/lang/StringBuilder;
        //  1424: invokevirtual   java/lang/StringBuilder.toString:()Ljava/lang/String;
        //  1427: invokevirtual   org/apache/ecs/xhtml/nobr.addElement:(Ljava/lang/String;)Lorg/apache/ecs/xhtml/nobr;
        //  1430: ldc             "<input type=\"text\" name=\"disp2\" size=\"9\"/>"
        //  1432: invokevirtual   org/apache/ecs/xhtml/nobr.addElement:(Ljava/lang/String;)Lorg/apache/ecs/xhtml/nobr;
        //  1435: ldc             "minutes"
        //  1437: invokevirtual   org/apache/ecs/xhtml/nobr.addElement:(Ljava/lang/String;)Lorg/apache/ecs/xhtml/nobr;
        //  1440: invokevirtual   org/apache/ecs/xhtml/nobr.addElement:(Lorg/apache/ecs/Element;)Lorg/apache/ecs/xhtml/nobr;
        //  1443: invokevirtual   org/apache/ecs/xhtml/td.addElement:(Lorg/apache/ecs/Element;)Lorg/apache/ecs/xhtml/td;
        //  1446: invokevirtual   org/apache/ecs/xhtml/tr.addElement:(Lorg/apache/ecs/Element;)Lorg/apache/ecs/xhtml/tr;
        //  1449: ldc             "AssessmentSectionHeading"
        //  1451: invokevirtual   org/apache/ecs/xhtml/tr.setClass:(Ljava/lang/String;)Lorg/apache/ecs/Element;
        //  1454: invokevirtual   org/apache/ecs/xhtml/table.addElement:(Lorg/apache/ecs/Element;)Lorg/apache/ecs/xhtml/table;
        //  1457: pop            
        //  1458: aload_1         /* strSub */
        //  1459: iconst_2       
        //  1460: invokevirtual   java/util/Vector.elementAt:(I)Ljava/lang/Object;
        //  1463: checkcast       Ljava/lang/String;
        //  1466: astore          strSectionPatern
        //  1468: aload           strSectionPatern
        //  1470: ifnull          1552
        //  1473: aload           strSectionPatern
        //  1475: ldc             ""
        //  1477: invokevirtual   java/lang/String.equals:(Ljava/lang/Object;)Z
        //  1480: ifne            1552
        //  1483: aload           table1
        //  1485: aload           tr5
        //  1487: aload           td7
        //  1489: new             Lorg/apache/ecs/xhtml/nobr;
        //  1492: dup            
        //  1493: invokespecial   org/apache/ecs/xhtml/nobr.<init>:()V
        //  1496: new             Lorg/apache/ecs/xhtml/div;
        //  1499: dup            
        //  1500: invokespecial   org/apache/ecs/xhtml/div.<init>:()V
        //  1503: new             Ljava/lang/StringBuilder;
        //  1506: dup            
        //  1507: invokespecial   java/lang/StringBuilder.<init>:()V
        //  1510: ldc             "&nbsp;"
        //  1512: invokevirtual   java/lang/StringBuilder.append:(Ljava/lang/String;)Ljava/lang/StringBuilder;
        //  1515: aload_1         /* strSub */
        //  1516: iconst_2       
        //  1517: invokevirtual   java/util/Vector.elementAt:(I)Ljava/lang/Object;
        //  1520: invokevirtual   java/lang/StringBuilder.append:(Ljava/lang/Object;)Ljava/lang/StringBuilder;
        //  1523: ldc             "&nbsp;"
        //  1525: invokevirtual   java/lang/StringBuilder.append:(Ljava/lang/String;)Ljava/lang/StringBuilder;
        //  1528: invokevirtual   java/lang/StringBuilder.toString:()Ljava/lang/String;
        //  1531: invokevirtual   org/apache/ecs/xhtml/div.addElement:(Ljava/lang/String;)Lorg/apache/ecs/xhtml/div;
        //  1534: ldc             "DivB"
        //  1536: invokevirtual   org/apache/ecs/xhtml/div.setID:(Ljava/lang/String;)Lorg/apache/ecs/Element;
        //  1539: invokevirtual   org/apache/ecs/xhtml/nobr.addElement:(Lorg/apache/ecs/Element;)Lorg/apache/ecs/xhtml/nobr;
        //  1542: invokevirtual   org/apache/ecs/xhtml/td.addElement:(Lorg/apache/ecs/Element;)Lorg/apache/ecs/xhtml/td;
        //  1545: invokevirtual   org/apache/ecs/xhtml/tr.addElement:(Lorg/apache/ecs/Element;)Lorg/apache/ecs/xhtml/tr;
        //  1548: invokevirtual   org/apache/ecs/xhtml/table.addElement:(Lorg/apache/ecs/Element;)Lorg/apache/ecs/xhtml/table;
        //  1551: pop            
        //  1552: aload           table2
        //  1554: aload           tr6
        //  1556: aload           td8
        //  1558: new             Lorg/apache/ecs/xhtml/hr;
        //  1561: dup            
        //  1562: invokespecial   org/apache/ecs/xhtml/hr.<init>:()V
        //  1565: iconst_1       
        //  1566: invokevirtual   org/apache/ecs/xhtml/hr.setSize:(I)Lorg/apache/ecs/xhtml/hr;
        //  1569: invokevirtual   org/apache/ecs/xhtml/td.addElement:(Lorg/apache/ecs/Element;)Lorg/apache/ecs/xhtml/td;
        //  1572: invokevirtual   org/apache/ecs/xhtml/tr.addElement:(Lorg/apache/ecs/Element;)Lorg/apache/ecs/xhtml/tr;
        //  1575: invokevirtual   org/apache/ecs/xhtml/table.addElement:(Lorg/apache/ecs/Element;)Lorg/apache/ecs/xhtml/table;
        //  1578: pop            
        //  1579: new             Lorg/apache/ecs/xhtml/tr;
        //  1582: dup            
        //  1583: invokespecial   org/apache/ecs/xhtml/tr.<init>:()V
        //  1586: astore          tr7
        //  1588: new             Lorg/apache/ecs/xhtml/td;
        //  1591: dup            
        //  1592: invokespecial   org/apache/ecs/xhtml/td.<init>:()V
        //  1595: astore          td9
        //  1597: new             Lorg/apache/ecs/xhtml/td;
        //  1600: dup            
        //  1601: invokespecial   org/apache/ecs/xhtml/td.<init>:()V
        //  1604: astore          td10
        //  1606: new             Lorg/apache/ecs/xhtml/td;
        //  1609: dup            
        //  1610: invokespecial   org/apache/ecs/xhtml/td.<init>:()V
        //  1613: astore          td11
        //  1615: aload           table2
        //  1617: aload           tr7
        //  1619: aload           td9
        //  1621: invokevirtual   org/apache/ecs/xhtml/tr.addElement:(Lorg/apache/ecs/Element;)Lorg/apache/ecs/xhtml/tr;
        //  1624: aload           td10
        //  1626: invokevirtual   org/apache/ecs/xhtml/tr.addElement:(Lorg/apache/ecs/Element;)Lorg/apache/ecs/xhtml/tr;
        //  1629: aload           td11
        //  1631: invokevirtual   org/apache/ecs/xhtml/tr.addElement:(Lorg/apache/ecs/Element;)Lorg/apache/ecs/xhtml/tr;
        //  1634: invokevirtual   org/apache/ecs/xhtml/table.addElement:(Lorg/apache/ecs/Element;)Lorg/apache/ecs/xhtml/table;
        //  1637: pop            
        //  1638: new             Lorg/apache/ecs/xhtml/tr;
        //  1641: dup            
        //  1642: invokespecial   org/apache/ecs/xhtml/tr.<init>:()V
        //  1645: astore          tr8
        //  1647: new             Lorg/apache/ecs/xhtml/td;
        //  1650: dup            
        //  1651: invokespecial   org/apache/ecs/xhtml/td.<init>:()V
        //  1654: astore          td12
        //  1656: new             Lorg/apache/ecs/xhtml/td;
        //  1659: dup            
        //  1660: invokespecial   org/apache/ecs/xhtml/td.<init>:()V
        //  1663: sipush          560
        //  1666: invokevirtual   org/apache/ecs/xhtml/td.setWidth:(I)Lorg/apache/ecs/xhtml/td;
        //  1669: ldc             "top"
        //  1671: invokevirtual   org/apache/ecs/xhtml/td.setVAlign:(Ljava/lang/String;)Lorg/apache/ecs/xhtml/td;
        //  1674: astore          td13
        //  1676: new             Lorg/apache/ecs/xhtml/td;
        //  1679: dup            
        //  1680: invokespecial   org/apache/ecs/xhtml/td.<init>:()V
        //  1683: astore          td15
        //  1685: new             Lorg/apache/ecs/xhtml/tr;
        //  1688: dup            
        //  1689: invokespecial   org/apache/ecs/xhtml/tr.<init>:()V
        //  1692: astore          tr10
        //  1694: new             Lorg/apache/ecs/xhtml/td;
        //  1697: dup            
        //  1698: invokespecial   org/apache/ecs/xhtml/td.<init>:()V
        //  1701: astore          td16
        //  1703: new             Lorg/apache/ecs/xhtml/td;
        //  1706: dup            
        //  1707: invokespecial   org/apache/ecs/xhtml/td.<init>:()V
        //  1710: astore          td17
        //  1712: new             Lorg/apache/ecs/xhtml/td;
        //  1715: dup            
        //  1716: invokespecial   org/apache/ecs/xhtml/td.<init>:()V
        //  1719: astore          td18
        //  1721: new             Lorg/apache/ecs/xhtml/div;
        //  1724: dup            
        //  1725: invokespecial   org/apache/ecs/xhtml/div.<init>:()V
        //  1728: astore          divQA
        //  1730: aload           table2
        //  1732: aload           tr8
        //  1734: aload           td12
        //  1736: invokevirtual   org/apache/ecs/xhtml/tr.addElement:(Lorg/apache/ecs/Element;)Lorg/apache/ecs/xhtml/tr;
        //  1739: aload           td13
        //  1741: aload           table3
        //  1743: aload           divQA
        //  1745: ldc             "QuestionAnswer"
        //  1747: invokevirtual   org/apache/ecs/xhtml/div.setID:(Ljava/lang/String;)Lorg/apache/ecs/Element;
        //  1750: invokevirtual   org/apache/ecs/xhtml/table.addElement:(Lorg/apache/ecs/Element;)Lorg/apache/ecs/xhtml/table;
        //  1753: invokevirtual   org/apache/ecs/xhtml/td.addElement:(Lorg/apache/ecs/Element;)Lorg/apache/ecs/xhtml/td;
        //  1756: invokevirtual   org/apache/ecs/xhtml/tr.addElement:(Lorg/apache/ecs/Element;)Lorg/apache/ecs/xhtml/tr;
        //  1759: aload           td15
        //  1761: invokevirtual   org/apache/ecs/xhtml/tr.addElement:(Lorg/apache/ecs/Element;)Lorg/apache/ecs/xhtml/tr;
        //  1764: invokevirtual   org/apache/ecs/xhtml/table.addElement:(Lorg/apache/ecs/Element;)Lorg/apache/ecs/xhtml/table;
        //  1767: pop            
        //  1768: aload           table2
        //  1770: aload           tr10
        //  1772: aload           td16
        //  1774: invokevirtual   org/apache/ecs/xhtml/tr.addElement:(Lorg/apache/ecs/Element;)Lorg/apache/ecs/xhtml/tr;
        //  1777: aload           td17
        //  1779: invokevirtual   org/apache/ecs/xhtml/tr.addElement:(Lorg/apache/ecs/Element;)Lorg/apache/ecs/xhtml/tr;
        //  1782: aload           td18
        //  1784: invokevirtual   org/apache/ecs/xhtml/tr.addElement:(Lorg/apache/ecs/Element;)Lorg/apache/ecs/xhtml/tr;
        //  1787: invokevirtual   org/apache/ecs/xhtml/table.addElement:(Lorg/apache/ecs/Element;)Lorg/apache/ecs/xhtml/table;
        //  1790: pop            
        //  1791: ldc             ""
        //  1793: astore          strReturn
        //  1795: iconst_0       
        //  1796: istore          i
        //  1798: iload           i
        //  1800: aload_2         /* questionAll */
        //  1801: invokevirtual   java/util/Vector.size:()I
        //  1804: if_icmpge       2107
        //  1807: aload_2         /* questionAll */
        //  1808: iload           i
        //  1810: invokevirtual   java/util/Vector.elementAt:(I)Ljava/lang/Object;
        //  1813: checkcast       Ljava/util/Vector;
        //  1816: astore          questionMatter
        //  1818: aload           questionMatter
        //  1820: iconst_0       
        //  1821: invokevirtual   java/util/Vector.elementAt:(I)Ljava/lang/Object;
        //  1824: checkcast       Ljava/util/Vector;
        //  1827: astore          response
        //  1829: aload           questionMatter
        //  1831: iconst_1       
        //  1832: invokevirtual   java/util/Vector.elementAt:(I)Ljava/lang/Object;
        //  1835: checkcast       Ljava/util/Vector;
        //  1838: astore          question
        //  1840: aload           response
        //  1842: iconst_0       
        //  1843: invokevirtual   java/util/Vector.elementAt:(I)Ljava/lang/Object;
        //  1846: checkcast       Ljava/lang/Integer;
        //  1849: astore          iTitle
        //  1851: aload           iTitle
        //  1853: invokevirtual   java/lang/Integer.intValue:()I
        //  1856: tableswitch {
        //                0: 1904
        //                1: 1929
        //                2: 1954
        //                3: 1979
        //                4: 2004
        //                5: 2029
        //                6: 2054
        //                7: 2079
        //          default: 2101
        //        }
        //  1904: aload_0         /* this */
        //  1905: aload           response
        //  1907: aload           question
        //  1909: iload           i
        //  1911: iconst_1       
        //  1912: iadd           
        //  1913: invokevirtual   learnityasmtserver/assessmentportal/embeddedasmt/GenerateXHTML.MultipleChoiceHTML:(Ljava/util/Vector;Ljava/util/Vector;I)Ljava/lang/String;
        //  1916: astore          strReturn
        //  1918: aload           divQA
        //  1920: aload           strReturn
        //  1922: invokevirtual   org/apache/ecs/xhtml/div.addElement:(Ljava/lang/String;)Lorg/apache/ecs/xhtml/div;
        //  1925: pop            
        //  1926: goto            2101
        //  1929: aload_0         /* this */
        //  1930: aload           response
        //  1932: aload           question
        //  1934: iload           i
        //  1936: iconst_1       
        //  1937: iadd           
        //  1938: invokevirtual   learnityasmtserver/assessmentportal/embeddedasmt/GenerateXHTML.MultipleResponseHTML:(Ljava/util/Vector;Ljava/util/Vector;I)Ljava/lang/String;
        //  1941: astore          strReturn
        //  1943: aload           divQA
        //  1945: aload           strReturn
        //  1947: invokevirtual   org/apache/ecs/xhtml/div.addElement:(Ljava/lang/String;)Lorg/apache/ecs/xhtml/div;
        //  1950: pop            
        //  1951: goto            2101
        //  1954: aload_0         /* this */
        //  1955: aload           response
        //  1957: aload           question
        //  1959: iload           i
        //  1961: iconst_1       
        //  1962: iadd           
        //  1963: invokevirtual   learnityasmtserver/assessmentportal/embeddedasmt/GenerateXHTML.FillBlanks:(Ljava/util/Vector;Ljava/util/Vector;I)Ljava/lang/String;
        //  1966: astore          strReturn
        //  1968: aload           divQA
        //  1970: aload           strReturn
        //  1972: invokevirtual   org/apache/ecs/xhtml/div.addElement:(Ljava/lang/String;)Lorg/apache/ecs/xhtml/div;
        //  1975: pop            
        //  1976: goto            2101
        //  1979: aload_0         /* this */
        //  1980: aload           response
        //  1982: aload           question
        //  1984: iload           i
        //  1986: iconst_1       
        //  1987: iadd           
        //  1988: invokevirtual   learnityasmtserver/assessmentportal/embeddedasmt/GenerateXHTML.MultipleChoiceHTML:(Ljava/util/Vector;Ljava/util/Vector;I)Ljava/lang/String;
        //  1991: astore          strReturn
        //  1993: aload           divQA
        //  1995: aload           strReturn
        //  1997: invokevirtual   org/apache/ecs/xhtml/div.addElement:(Ljava/lang/String;)Lorg/apache/ecs/xhtml/div;
        //  2000: pop            
        //  2001: goto            2101
        //  2004: aload_0         /* this */
        //  2005: aload           response
        //  2007: aload           question
        //  2009: iload           i
        //  2011: iconst_1       
        //  2012: iadd           
        //  2013: invokevirtual   learnityasmtserver/assessmentportal/embeddedasmt/GenerateXHTML.MultipleChoiceImage:(Ljava/util/Vector;Ljava/util/Vector;I)Ljava/lang/String;
        //  2016: astore          strReturn
        //  2018: aload           divQA
        //  2020: aload           strReturn
        //  2022: invokevirtual   org/apache/ecs/xhtml/div.addElement:(Ljava/lang/String;)Lorg/apache/ecs/xhtml/div;
        //  2025: pop            
        //  2026: goto            2101
        //  2029: aload_0         /* this */
        //  2030: aload           response
        //  2032: aload           question
        //  2034: iload           i
        //  2036: iconst_1       
        //  2037: iadd           
        //  2038: invokevirtual   learnityasmtserver/assessmentportal/embeddedasmt/GenerateXHTML.EssayTypeQuestion:(Ljava/util/Vector;Ljava/util/Vector;I)Ljava/lang/String;
        //  2041: astore          strReturn
        //  2043: aload           divQA
        //  2045: aload           strReturn
        //  2047: invokevirtual   org/apache/ecs/xhtml/div.addElement:(Ljava/lang/String;)Lorg/apache/ecs/xhtml/div;
        //  2050: pop            
        //  2051: goto            2101
        //  2054: aload_0         /* this */
        //  2055: aload           response
        //  2057: aload           question
        //  2059: iload           i
        //  2061: iconst_1       
        //  2062: iadd           
        //  2063: invokevirtual   learnityasmtserver/assessmentportal/embeddedasmt/GenerateXHTML.Slider:(Ljava/util/Vector;Ljava/util/Vector;I)Ljava/lang/String;
        //  2066: astore          strReturn
        //  2068: aload           divQA
        //  2070: aload           strReturn
        //  2072: invokevirtual   org/apache/ecs/xhtml/div.addElement:(Ljava/lang/String;)Lorg/apache/ecs/xhtml/div;
        //  2075: pop            
        //  2076: goto            2101
        //  2079: aload_0         /* this */
        //  2080: aload           response
        //  2082: aload           question
        //  2084: iload           i
        //  2086: iconst_1       
        //  2087: iadd           
        //  2088: invokevirtual   learnityasmtserver/assessmentportal/embeddedasmt/GenerateXHTML.MatchingQuestionHTML:(Ljava/util/Vector;Ljava/util/Vector;I)Ljava/lang/String;
        //  2091: astore          strReturn
        //  2093: aload           divQA
        //  2095: aload           strReturn
        //  2097: invokevirtual   org/apache/ecs/xhtml/div.addElement:(Ljava/lang/String;)Lorg/apache/ecs/xhtml/div;
        //  2100: pop            
        //  2101: iinc            i, 1
        //  2104: goto            1798
        //  2107: aload           table4
        //  2109: aload           tbody1
        //  2111: aload           tr11
        //  2113: aload           td19
        //  2115: new             Lorg/apache/ecs/xhtml/img;
        //  2118: dup            
        //  2119: invokespecial   org/apache/ecs/xhtml/img.<init>:()V
        //  2122: iconst_0       
        //  2123: invokevirtual   org/apache/ecs/xhtml/img.setBorder:(I)Lorg/apache/ecs/xhtml/img;
        //  2126: iconst_5       
        //  2127: invokevirtual   org/apache/ecs/xhtml/img.setHeight:(I)Lorg/apache/ecs/xhtml/img;
        //  2130: sipush          140
        //  2133: invokevirtual   org/apache/ecs/xhtml/img.setWidth:(I)Lorg/apache/ecs/xhtml/img;
        //  2136: ldc             "../images/T.gif"
        //  2138: invokevirtual   org/apache/ecs/xhtml/img.setSrc:(Ljava/lang/String;)Lorg/apache/ecs/xhtml/img;
        //  2141: invokevirtual   org/apache/ecs/xhtml/td.addElement:(Lorg/apache/ecs/Element;)Lorg/apache/ecs/xhtml/td;
        //  2144: invokevirtual   org/apache/ecs/xhtml/tr.addElement:(Lorg/apache/ecs/Element;)Lorg/apache/ecs/xhtml/tr;
        //  2147: aload           td20
        //  2149: new             Lorg/apache/ecs/xhtml/img;
        //  2152: dup            
        //  2153: invokespecial   org/apache/ecs/xhtml/img.<init>:()V
        //  2156: iconst_0       
        //  2157: invokevirtual   org/apache/ecs/xhtml/img.setBorder:(I)Lorg/apache/ecs/xhtml/img;
        //  2160: iconst_5       
        //  2161: invokevirtual   org/apache/ecs/xhtml/img.setHeight:(I)Lorg/apache/ecs/xhtml/img;
        //  2164: iconst_1       
        //  2165: invokevirtual   org/apache/ecs/xhtml/img.setWidth:(I)Lorg/apache/ecs/xhtml/img;
        //  2168: ldc             "../images/T.gif"
        //  2170: invokevirtual   org/apache/ecs/xhtml/img.setSrc:(Ljava/lang/String;)Lorg/apache/ecs/xhtml/img;
        //  2173: invokevirtual   org/apache/ecs/xhtml/td.addElement:(Lorg/apache/ecs/Element;)Lorg/apache/ecs/xhtml/td;
        //  2176: invokevirtual   org/apache/ecs/xhtml/tr.addElement:(Lorg/apache/ecs/Element;)Lorg/apache/ecs/xhtml/tr;
        //  2179: invokevirtual   org/apache/ecs/xhtml/tbody.addElement:(Lorg/apache/ecs/Element;)Lorg/apache/ecs/xhtml/tbody;
        //  2182: invokevirtual   org/apache/ecs/xhtml/table.addElement:(Lorg/apache/ecs/Element;)Lorg/apache/ecs/xhtml/table;
        //  2185: pop            
        //  2186: aload           table5
        //  2188: aload           tr12
        //  2190: aload           td21
        //  2192: aload_3         /* strButton */
        //  2193: invokevirtual   org/apache/ecs/xhtml/td.addElement:(Ljava/lang/String;)Lorg/apache/ecs/xhtml/td;
        //  2196: invokevirtual   org/apache/ecs/xhtml/tr.addElement:(Lorg/apache/ecs/Element;)Lorg/apache/ecs/xhtml/tr;
        //  2199: aload           td22
        //  2201: new             Ljava/lang/StringBuilder;
        //  2204: dup            
        //  2205: invokespecial   java/lang/StringBuilder.<init>:()V
        //  2208: ldc             "&nbsp;&nbsp;"
        //  2210: invokevirtual   java/lang/StringBuilder.append:(Ljava/lang/String;)Ljava/lang/StringBuilder;
        //  2213: aload           strButtonResult
        //  2215: invokevirtual   java/lang/StringBuilder.append:(Ljava/lang/String;)Ljava/lang/StringBuilder;
        //  2218: invokevirtual   java/lang/StringBuilder.toString:()Ljava/lang/String;
        //  2221: invokevirtual   org/apache/ecs/xhtml/td.addElement:(Ljava/lang/String;)Lorg/apache/ecs/xhtml/td;
        //  2224: invokevirtual   org/apache/ecs/xhtml/tr.addElement:(Lorg/apache/ecs/Element;)Lorg/apache/ecs/xhtml/tr;
        //  2227: aload           td23
        //  2229: invokevirtual   org/apache/ecs/xhtml/tr.addElement:(Lorg/apache/ecs/Element;)Lorg/apache/ecs/xhtml/tr;
        //  2232: invokevirtual   org/apache/ecs/xhtml/table.addElement:(Lorg/apache/ecs/Element;)Lorg/apache/ecs/xhtml/table;
        //  2235: pop            
        //  2236: ldc             ""
        //  2238: astore          javaScript1
        //  2240: ldc             ""
        //  2242: astore          javaScript2
        //  2244: ldc             "test"
        //  2246: astore          test
        //  2248: iload           bRefresh
        //  2250: ifeq            2293
        //  2253: new             Ljava/lang/StringBuilder;
        //  2256: dup            
        //  2257: invokespecial   java/lang/StringBuilder.<init>:()V
        //  2260: ldc             "\n //<![CDATA[\n  function submitPage()  {\n\t//window.document.frmsec.hddTimeLeft.value=timeleft\n\t//buildSectionString()\n\tsubmit_onclick("
        //  2262: invokevirtual   java/lang/StringBuilder.append:(Ljava/lang/String;)Ljava/lang/StringBuilder;
        //  2265: iload           iSec
        //  2267: invokevirtual   java/lang/StringBuilder.append:(I)Ljava/lang/StringBuilder;
        //  2270: ldc             ");"
        //  2272: invokevirtual   java/lang/StringBuilder.append:(Ljava/lang/String;)Ljava/lang/StringBuilder;
        //  2275: ldc             "\n}"
        //  2277: invokevirtual   java/lang/StringBuilder.append:(Ljava/lang/String;)Ljava/lang/StringBuilder;
        //  2280: ldc             "\n  //]]>"
        //  2282: invokevirtual   java/lang/StringBuilder.append:(Ljava/lang/String;)Ljava/lang/StringBuilder;
        //  2285: invokevirtual   java/lang/StringBuilder.toString:()Ljava/lang/String;
        //  2288: astore          javaScript1
        //  2290: goto            2360
        //  2293: new             Ljava/lang/StringBuilder;
        //  2296: dup            
        //  2297: invokespecial   java/lang/StringBuilder.<init>:()V
        //  2300: ldc             "\n //<![CDATA[\n  function submitPage() {\n  var test=\""
        //  2302: invokevirtual   java/lang/StringBuilder.append:(Ljava/lang/String;)Ljava/lang/StringBuilder;
        //  2305: aload           test
        //  2307: invokevirtual   java/lang/StringBuilder.append:(Ljava/lang/String;)Ljava/lang/StringBuilder;
        //  2310: ldc             "\";"
        //  2312: invokevirtual   java/lang/StringBuilder.append:(Ljava/lang/String;)Ljava/lang/StringBuilder;
        //  2315: ldc             "\n\tdocument.getElementById('frm').method=\"post\";"
        //  2317: invokevirtual   java/lang/StringBuilder.append:(Ljava/lang/String;)Ljava/lang/StringBuilder;
        //  2320: ldc             "\n\tdocument.getElementById('frm').action=\"./learnityasmtserver.assessmentportal.embeddedasmt.OutComesXHTML?secID="
        //  2322: invokevirtual   java/lang/StringBuilder.append:(Ljava/lang/String;)Ljava/lang/StringBuilder;
        //  2325: iload           iSec
        //  2327: invokevirtual   java/lang/StringBuilder.append:(I)Ljava/lang/StringBuilder;
        //  2330: ldc             "&slide=\"+test;"
        //  2332: invokevirtual   java/lang/StringBuilder.append:(Ljava/lang/String;)Ljava/lang/StringBuilder;
        //  2335: ldc             "\n\tdocument.getElementById('frm').target=\"_self\";"
        //  2337: invokevirtual   java/lang/StringBuilder.append:(Ljava/lang/String;)Ljava/lang/StringBuilder;
        //  2340: ldc             "\n\tdocument.getElementById('frm').submit();"
        //  2342: invokevirtual   java/lang/StringBuilder.append:(Ljava/lang/String;)Ljava/lang/StringBuilder;
        //  2345: ldc             "\n}"
        //  2347: invokevirtual   java/lang/StringBuilder.append:(Ljava/lang/String;)Ljava/lang/StringBuilder;
        //  2350: ldc             "\n  //]]>"
        //  2352: invokevirtual   java/lang/StringBuilder.append:(Ljava/lang/String;)Ljava/lang/StringBuilder;
        //  2355: invokevirtual   java/lang/StringBuilder.toString:()Ljava/lang/String;
        //  2358: astore          javaScript2
        //  2360: new             Ljava/lang/StringBuilder;
        //  2363: dup            
        //  2364: invokespecial   java/lang/StringBuilder.<init>:()V
        //  2367: ldc             "\n //<![CDATA[\n    function submit_onclick(i) {\n\t\tdocument.getElementById('frm').method=\"post\";\n    \tdocument.getElementById('frm').action=\"learnityasmtserver.assessmentportal.embeddedasmt.AssessmentXHTML?secID=\"+i;\n\t\tdocument.getElementById('frm').target=\"_self\";\n\t\tdocument.getElementById('frm').submit();\n    }\n    function Resultsubmit_onclick(i) {\n\t\tdocument.getElementById('frm').method=\"post\";\n    \tdocument.getElementById('frm').action=\"learnityasmtserver.assessmentportal.embeddedasmt.OutComesSection?secID=\"+i;\n\t\tdocument.getElementById('frm').target=\"_self\";\n\t\tdocument.getElementById('frm').submit();\n    }\n    function Resultsubmit1_onclick(i) {\n\t\tdocument.getElementById('frm').method=\"post\";\n    \tdocument.getElementById('frm').action=\"learnityasmtserver.assessmentportal.embeddedasmt.OutComesSection?sectionID=test&secID=\"+i+\"&slide=\"+test;\n\t\tdocument.getElementById('frm').target=\"_self\";\n\t\tdocument.getElementById('frm').submit();\n    }\n  function unload() {\n\t//window.document.frmsec.hddTimeLeft.value=timeleft\n\t//buildSectionString()\n\tdocument.getElementById('frm').method=\"post\";\n\tdocument.getElementById('frm').action=\"./learnityasmtserver.assessmentportal.embeddedasmt.OutComesXHTML?secID="
        //  2369: invokevirtual   java/lang/StringBuilder.append:(Ljava/lang/String;)Ljava/lang/StringBuilder;
        //  2372: iload           iSec
        //  2374: invokevirtual   java/lang/StringBuilder.append:(I)Ljava/lang/StringBuilder;
        //  2377: ldc             "\";"
        //  2379: invokevirtual   java/lang/StringBuilder.append:(Ljava/lang/String;)Ljava/lang/StringBuilder;
        //  2382: ldc             "\n\t\tdocument.getElementById('frm').target=\"_self\";"
        //  2384: invokevirtual   java/lang/StringBuilder.append:(Ljava/lang/String;)Ljava/lang/StringBuilder;
        //  2387: ldc             "\n\tdocument.getElementById('frm').submit();"
        //  2389: invokevirtual   java/lang/StringBuilder.append:(Ljava/lang/String;)Ljava/lang/StringBuilder;
        //  2392: ldc             "\n}"
        //  2394: invokevirtual   java/lang/StringBuilder.append:(Ljava/lang/String;)Ljava/lang/StringBuilder;
        //  2397: ldc             "\n var timeleft"
        //  2399: invokevirtual   java/lang/StringBuilder.append:(Ljava/lang/String;)Ljava/lang/StringBuilder;
        //  2402: ldc             "\n var timeleftr"
        //  2404: invokevirtual   java/lang/StringBuilder.append:(Ljava/lang/String;)Ljava/lang/StringBuilder;
        //  2407: ldc             "\n var up,down"
        //  2409: invokevirtual   java/lang/StringBuilder.append:(Ljava/lang/String;)Ljava/lang/StringBuilder;
        //  2412: ldc             "\n   var min1,sec1"
        //  2414: invokevirtual   java/lang/StringBuilder.append:(Ljava/lang/String;)Ljava/lang/StringBuilder;
        //  2417: ldc             "\n  var cmin1,csec1,cmin2,csec2"
        //  2419: invokevirtual   java/lang/StringBuilder.append:(Ljava/lang/String;)Ljava/lang/StringBuilder;
        //  2422: ldc             "\n function Minutes(data) {"
        //  2424: invokevirtual   java/lang/StringBuilder.append:(Ljava/lang/String;)Ljava/lang/StringBuilder;
        //  2427: ldc             "\n  for(var i=0;i<data.length;i++)"
        //  2429: invokevirtual   java/lang/StringBuilder.append:(Ljava/lang/String;)Ljava/lang/StringBuilder;
        //  2432: ldc             "\n if(data.substring(i,i+1)==\":\")"
        //  2434: invokevirtual   java/lang/StringBuilder.append:(Ljava/lang/String;)Ljava/lang/StringBuilder;
        //  2437: ldc             "\n break"
        //  2439: invokevirtual   java/lang/StringBuilder.append:(Ljava/lang/String;)Ljava/lang/StringBuilder;
        //  2442: ldc             "\n  return(data.substring(0,i)); }"
        //  2444: invokevirtual   java/lang/StringBuilder.append:(Ljava/lang/String;)Ljava/lang/StringBuilder;
        //  2447: ldc             "\n  function Seconds(data) {"
        //  2449: invokevirtual   java/lang/StringBuilder.append:(Ljava/lang/String;)Ljava/lang/StringBuilder;
        //  2452: ldc             "\n for(var i=0;i<data.length;i++)"
        //  2454: invokevirtual   java/lang/StringBuilder.append:(Ljava/lang/String;)Ljava/lang/StringBuilder;
        //  2457: ldc             "\n if(data.substring(i,i+1)==\":\")"
        //  2459: invokevirtual   java/lang/StringBuilder.append:(Ljava/lang/String;)Ljava/lang/StringBuilder;
        //  2462: ldc             "\n break"
        //  2464: invokevirtual   java/lang/StringBuilder.append:(Ljava/lang/String;)Ljava/lang/StringBuilder;
        //  2467: ldc             "\n  return(data.substring(i+1,data.length)); }"
        //  2469: invokevirtual   java/lang/StringBuilder.append:(Ljava/lang/String;)Ljava/lang/StringBuilder;
        //  2472: ldc             "\n function Display(min,sec) {"
        //  2474: invokevirtual   java/lang/StringBuilder.append:(Ljava/lang/String;)Ljava/lang/StringBuilder;
        //  2477: ldc             "\n   var disp;"
        //  2479: invokevirtual   java/lang/StringBuilder.append:(Ljava/lang/String;)Ljava/lang/StringBuilder;
        //  2482: ldc             "\n if(min<=9) disp=\" 0\";"
        //  2484: invokevirtual   java/lang/StringBuilder.append:(Ljava/lang/String;)Ljava/lang/StringBuilder;
        //  2487: ldc             "\n else disp=\" \";"
        //  2489: invokevirtual   java/lang/StringBuilder.append:(Ljava/lang/String;)Ljava/lang/StringBuilder;
        //  2492: ldc             "\n disp+=min+\":\";"
        //  2494: invokevirtual   java/lang/StringBuilder.append:(Ljava/lang/String;)Ljava/lang/StringBuilder;
        //  2497: ldc             "\n if(sec<=9) disp+=\"0\"+sec;"
        //  2499: invokevirtual   java/lang/StringBuilder.append:(Ljava/lang/String;)Ljava/lang/StringBuilder;
        //  2502: ldc             "\n else disp+=sec;"
        //  2504: invokevirtual   java/lang/StringBuilder.append:(Ljava/lang/String;)Ljava/lang/StringBuilder;
        //  2507: ldc             "\n return(disp); }"
        //  2509: invokevirtual   java/lang/StringBuilder.append:(Ljava/lang/String;)Ljava/lang/StringBuilder;
        //  2512: ldc             "\n function Up() {"
        //  2514: invokevirtual   java/lang/StringBuilder.append:(Ljava/lang/String;)Ljava/lang/StringBuilder;
        //  2517: ldc             "\n  cmin1=0;"
        //  2519: invokevirtual   java/lang/StringBuilder.append:(Ljava/lang/String;)Ljava/lang/StringBuilder;
        //  2522: ldc             "\n csec1=0;"
        //  2524: invokevirtual   java/lang/StringBuilder.append:(Ljava/lang/String;)Ljava/lang/StringBuilder;
        //  2527: ldc             "\n min1=0+Minutes(document.getElementById('frm').beg1.value);"
        //  2529: invokevirtual   java/lang/StringBuilder.append:(Ljava/lang/String;)Ljava/lang/StringBuilder;
        //  2532: ldc             "\n sec1=0+Seconds(document.getElementById('frm').beg1.value);"
        //  2534: invokevirtual   java/lang/StringBuilder.append:(Ljava/lang/String;)Ljava/lang/StringBuilder;
        //  2537: ldc             "\n UpRepeat(); }"
        //  2539: invokevirtual   java/lang/StringBuilder.append:(Ljava/lang/String;)Ljava/lang/StringBuilder;
        //  2542: ldc             "\n function UpRepeat() {"
        //  2544: invokevirtual   java/lang/StringBuilder.append:(Ljava/lang/String;)Ljava/lang/StringBuilder;
        //  2547: ldc             "\n    csec1++;"
        //  2549: invokevirtual   java/lang/StringBuilder.append:(Ljava/lang/String;)Ljava/lang/StringBuilder;
        //  2552: ldc             "\n    if(csec1==60) { csec1=0; cmin1++; }"
        //  2554: invokevirtual   java/lang/StringBuilder.append:(Ljava/lang/String;)Ljava/lang/StringBuilder;
        //  2557: ldc             "\n        document.getElementById('frm').disp1.value=Display(cmin1,csec1);"
        //  2559: invokevirtual   java/lang/StringBuilder.append:(Ljava/lang/String;)Ljava/lang/StringBuilder;
        //  2562: ldc             "\n  up=setTimeout(\"UpRepeat()\",1000); }"
        //  2564: invokevirtual   java/lang/StringBuilder.append:(Ljava/lang/String;)Ljava/lang/StringBuilder;
        //  2567: ldc             "\n var lefttime=\""
        //  2569: invokevirtual   java/lang/StringBuilder.append:(Ljava/lang/String;)Ljava/lang/StringBuilder;
        //  2572: aload           duration
        //  2574: invokevirtual   java/lang/StringBuilder.append:(Ljava/lang/String;)Ljava/lang/StringBuilder;
        //  2577: ldc             "\";"
        //  2579: invokevirtual   java/lang/StringBuilder.append:(Ljava/lang/String;)Ljava/lang/StringBuilder;
        //  2582: ldc             "\n function Down(lefttime) {"
        //  2584: invokevirtual   java/lang/StringBuilder.append:(Ljava/lang/String;)Ljava/lang/StringBuilder;
        //  2587: ldc             "\n timeleftr=lefttime"
        //  2589: invokevirtual   java/lang/StringBuilder.append:(Ljava/lang/String;)Ljava/lang/StringBuilder;
        //  2592: ldc             "\n countdown()"
        //  2594: invokevirtual   java/lang/StringBuilder.append:(Ljava/lang/String;)Ljava/lang/StringBuilder;
        //  2597: ldc             "\n cmin2=1*Minutes(document.getElementById('frm').beg2.value);"
        //  2599: invokevirtual   java/lang/StringBuilder.append:(Ljava/lang/String;)Ljava/lang/StringBuilder;
        //  2602: ldc             "\n  csec2=0+Seconds(document.getElementById('frm').beg2.value);"
        //  2604: invokevirtual   java/lang/StringBuilder.append:(Ljava/lang/String;)Ljava/lang/StringBuilder;
        //  2607: ldc             "\n DownRepeat(); }"
        //  2609: invokevirtual   java/lang/StringBuilder.append:(Ljava/lang/String;)Ljava/lang/StringBuilder;
        //  2612: ldc             "\n function countdown()"
        //  2614: invokevirtual   java/lang/StringBuilder.append:(Ljava/lang/String;)Ljava/lang/StringBuilder;
        //  2617: ldc             "\n{"
        //  2619: invokevirtual   java/lang/StringBuilder.append:(Ljava/lang/String;)Ljava/lang/StringBuilder;
        //  2622: ldc             "\n sb();"
        //  2624: invokevirtual   java/lang/StringBuilder.append:(Ljava/lang/String;)Ljava/lang/StringBuilder;
        //  2627: ldc             "\n  counter();"
        //  2629: invokevirtual   java/lang/StringBuilder.append:(Ljava/lang/String;)Ljava/lang/StringBuilder;
        //  2632: ldc             "\n }"
        //  2634: invokevirtual   java/lang/StringBuilder.append:(Ljava/lang/String;)Ljava/lang/StringBuilder;
        //  2637: ldc             "\n function sb()"
        //  2639: invokevirtual   java/lang/StringBuilder.append:(Ljava/lang/String;)Ljava/lang/StringBuilder;
        //  2642: ldc             "\n{"
        //  2644: invokevirtual   java/lang/StringBuilder.append:(Ljava/lang/String;)Ljava/lang/StringBuilder;
        //  2647: ldc             "\n if (timeleftr>0)"
        //  2649: invokevirtual   java/lang/StringBuilder.append:(Ljava/lang/String;)Ljava/lang/StringBuilder;
        //  2652: ldc             "\n {                   timeleft =Math.round(timeleftr)"
        //  2654: invokevirtual   java/lang/StringBuilder.append:(Ljava/lang/String;)Ljava/lang/StringBuilder;
        //  2657: ldc             "\n  defaultStatus=\"TIME LEFT   : \"+timeleft+\" MINUTES\";"
        //  2659: invokevirtual   java/lang/StringBuilder.append:(Ljava/lang/String;)Ljava/lang/StringBuilder;
        //  2662: ldc             "\n setTimeout(\"sb()\",30000);"
        //  2664: invokevirtual   java/lang/StringBuilder.append:(Ljava/lang/String;)Ljava/lang/StringBuilder;
        //  2667: ldc             "\n}"
        //  2669: invokevirtual   java/lang/StringBuilder.append:(Ljava/lang/String;)Ljava/lang/StringBuilder;
        //  2672: ldc             "\n else"
        //  2674: invokevirtual   java/lang/StringBuilder.append:(Ljava/lang/String;)Ljava/lang/StringBuilder;
        //  2677: ldc             "\n {"
        //  2679: invokevirtual   java/lang/StringBuilder.append:(Ljava/lang/String;)Ljava/lang/StringBuilder;
        //  2682: ldc             "\n  alert(\"The Time Alloted for this Section has Elapsed. The section is Over now\")"
        //  2684: invokevirtual   java/lang/StringBuilder.append:(Ljava/lang/String;)Ljava/lang/StringBuilder;
        //  2687: ldc             "\n submitPage()"
        //  2689: invokevirtual   java/lang/StringBuilder.append:(Ljava/lang/String;)Ljava/lang/StringBuilder;
        //  2692: ldc             "\n }"
        //  2694: invokevirtual   java/lang/StringBuilder.append:(Ljava/lang/String;)Ljava/lang/StringBuilder;
        //  2697: ldc             "\n  }"
        //  2699: invokevirtual   java/lang/StringBuilder.append:(Ljava/lang/String;)Ljava/lang/StringBuilder;
        //  2702: ldc             "\n function counter()"
        //  2704: invokevirtual   java/lang/StringBuilder.append:(Ljava/lang/String;)Ljava/lang/StringBuilder;
        //  2707: ldc             "\n{"
        //  2709: invokevirtual   java/lang/StringBuilder.append:(Ljava/lang/String;)Ljava/lang/StringBuilder;
        //  2712: ldc             "\n timeleftr=timeleftr - 0.25;"
        //  2714: invokevirtual   java/lang/StringBuilder.append:(Ljava/lang/String;)Ljava/lang/StringBuilder;
        //  2717: ldc             "\n setTimeout(\"counter()\",15000);"
        //  2719: invokevirtual   java/lang/StringBuilder.append:(Ljava/lang/String;)Ljava/lang/StringBuilder;
        //  2722: ldc             "\n }"
        //  2724: invokevirtual   java/lang/StringBuilder.append:(Ljava/lang/String;)Ljava/lang/StringBuilder;
        //  2727: ldc             "\n function DownRepeat() {"
        //  2729: invokevirtual   java/lang/StringBuilder.append:(Ljava/lang/String;)Ljava/lang/StringBuilder;
        //  2732: ldc             "\n csec2--;"
        //  2734: invokevirtual   java/lang/StringBuilder.append:(Ljava/lang/String;)Ljava/lang/StringBuilder;
        //  2737: ldc             "\n if(csec2==-1) { csec2=59; cmin2--; }"
        //  2739: invokevirtual   java/lang/StringBuilder.append:(Ljava/lang/String;)Ljava/lang/StringBuilder;
        //  2742: ldc             "\n document.getElementById('frm').disp2.value=Display(cmin2,csec2);"
        //  2744: invokevirtual   java/lang/StringBuilder.append:(Ljava/lang/String;)Ljava/lang/StringBuilder;
        //  2747: ldc             "\n  if((cmin2==0)&&(csec2==0)) document.getElementById('frm').disp2.value=Display(cmin2,csec2);"
        //  2749: invokevirtual   java/lang/StringBuilder.append:(Ljava/lang/String;)Ljava/lang/StringBuilder;
        //  2752: ldc             "\n else"
        //  2754: invokevirtual   java/lang/StringBuilder.append:(Ljava/lang/String;)Ljava/lang/StringBuilder;
        //  2757: ldc             "\n down=setTimeout(\"DownRepeat()\",1000); }"
        //  2759: invokevirtual   java/lang/StringBuilder.append:(Ljava/lang/String;)Ljava/lang/StringBuilder;
        //  2762: ldc             "\n  //]]>"
        //  2764: invokevirtual   java/lang/StringBuilder.append:(Ljava/lang/String;)Ljava/lang/StringBuilder;
        //  2767: invokevirtual   java/lang/StringBuilder.toString:()Ljava/lang/String;
        //  2770: astore          javaScript3
        //  2772: new             Lorg/apache/ecs/xhtml/script;
        //  2775: dup            
        //  2776: invokespecial   org/apache/ecs/xhtml/script.<init>:()V
        //  2779: ldc             "javascript"
        //  2781: invokevirtual   org/apache/ecs/xhtml/script.setLanguage:(Ljava/lang/String;)Lorg/apache/ecs/xhtml/script;
        //  2784: aload           javaScript1
        //  2786: invokevirtual   org/apache/ecs/xhtml/script.addElement:(Ljava/lang/String;)Lorg/apache/ecs/xhtml/script;
        //  2789: astore          javaScript11
        //  2791: new             Lorg/apache/ecs/xhtml/script;
        //  2794: dup            
        //  2795: invokespecial   org/apache/ecs/xhtml/script.<init>:()V
        //  2798: ldc             "javascript"
        //  2800: invokevirtual   org/apache/ecs/xhtml/script.setLanguage:(Ljava/lang/String;)Lorg/apache/ecs/xhtml/script;
        //  2803: aload           javaScript2
        //  2805: invokevirtual   org/apache/ecs/xhtml/script.addElement:(Ljava/lang/String;)Lorg/apache/ecs/xhtml/script;
        //  2808: astore          javaScript22
        //  2810: new             Lorg/apache/ecs/xhtml/script;
        //  2813: dup            
        //  2814: invokespecial   org/apache/ecs/xhtml/script.<init>:()V
        //  2817: ldc             "javascript"
        //  2819: invokevirtual   org/apache/ecs/xhtml/script.setLanguage:(Ljava/lang/String;)Lorg/apache/ecs/xhtml/script;
        //  2822: aload           javaScript3
        //  2824: invokevirtual   org/apache/ecs/xhtml/script.addElement:(Ljava/lang/String;)Lorg/apache/ecs/xhtml/script;
        //  2827: astore          javaScript33
        //  2829: aload           head1
        //  2831: aload           title1
        //  2833: invokevirtual   org/apache/ecs/xhtml/head.addElement:(Lorg/apache/ecs/Element;)Lorg/apache/ecs/xhtml/head;
        //  2836: pop            
        //  2837: aload           head1
        //  2839: aload           csslink
        //  2841: invokevirtual   org/apache/ecs/xhtml/head.addElement:(Lorg/apache/ecs/Element;)Lorg/apache/ecs/xhtml/head;
        //  2844: pop            
        //  2845: aload           head1
        //  2847: aload           script1
        //  2849: invokevirtual   org/apache/ecs/xhtml/head.addElement:(Lorg/apache/ecs/Element;)Lorg/apache/ecs/xhtml/head;
        //  2852: pop            
        //  2853: aload           form1
        //  2855: aload           table1
        //  2857: invokevirtual   org/apache/ecs/xhtml/form.addElement:(Lorg/apache/ecs/Element;)Lorg/apache/ecs/xhtml/form;
        //  2860: pop            
        //  2861: aload           form1
        //  2863: aload           table2
        //  2865: invokevirtual   org/apache/ecs/xhtml/form.addElement:(Lorg/apache/ecs/Element;)Lorg/apache/ecs/xhtml/form;
        //  2868: pop            
        //  2869: aload           form1
        //  2871: aload           table4
        //  2873: invokevirtual   org/apache/ecs/xhtml/form.addElement:(Lorg/apache/ecs/Element;)Lorg/apache/ecs/xhtml/form;
        //  2876: pop            
        //  2877: aload           form1
        //  2879: aload           table5
        //  2881: invokevirtual   org/apache/ecs/xhtml/form.addElement:(Lorg/apache/ecs/Element;)Lorg/apache/ecs/xhtml/form;
        //  2884: pop            
        //  2885: aload           form1
        //  2887: aload           javaScript11
        //  2889: invokevirtual   org/apache/ecs/xhtml/form.addElement:(Lorg/apache/ecs/Element;)Lorg/apache/ecs/xhtml/form;
        //  2892: pop            
        //  2893: aload           form1
        //  2895: aload           javaScript22
        //  2897: invokevirtual   org/apache/ecs/xhtml/form.addElement:(Lorg/apache/ecs/Element;)Lorg/apache/ecs/xhtml/form;
        //  2900: pop            
        //  2901: aload           form1
        //  2903: aload           javaScript33
        //  2905: invokevirtual   org/apache/ecs/xhtml/form.addElement:(Lorg/apache/ecs/Element;)Lorg/apache/ecs/xhtml/form;
        //  2908: pop            
        //  2909: aload           body1
        //  2911: aload           form1
        //  2913: invokevirtual   org/apache/ecs/xhtml/body.addElement:(Lorg/apache/ecs/Element;)Lorg/apache/ecs/xhtml/body;
        //  2916: pop            
        //  2917: aload           html1
        //  2919: aload           head1
        //  2921: invokevirtual   org/apache/ecs/xhtml/html.addElement:(Lorg/apache/ecs/Element;)Lorg/apache/ecs/xhtml/html;
        //  2924: pop            
        //  2925: aload           html1
        //  2927: aload           body1
        //  2929: invokevirtual   org/apache/ecs/xhtml/html.addElement:(Lorg/apache/ecs/Element;)Lorg/apache/ecs/xhtml/html;
        //  2932: pop            
        //  2933: aload           doc1
        //  2935: aload           html1
        //  2937: invokevirtual   org/apache/ecs/Doctype.addElement:(Lorg/apache/ecs/Element;)Lorg/apache/ecs/Doctype;
        //  2940: pop            
        //  2941: aload           doc1
        //  2943: invokevirtual   org/apache/ecs/Doctype.toString:()Ljava/lang/String;
        //  2946: astore          abcd
        //  2948: aload           abcd
        //  2950: areturn        
        //    LocalVariableTable:
        //  Start  Length  Slot  Name              Signature
        //  -----  ------  ----  ----------------  ----------------------------------------------------------------
        //  1818   283     76    questionMatter    Ljava/util/Vector;
        //  1829   272     77    response          Ljava/util/Vector;
        //  1840   261     78    question          Ljava/util/Vector;
        //  1851   250     79    iTitle            Ljava/lang/Integer;
        //  1798   309     75    i                 I
        //  0      2951    0     this              Llearnityasmtserver/assessmentportal/embeddedasmt/GenerateXHTML;
        //  0      2951    1     strSub            Ljava/util/Vector;
        //  0      2951    2     questionAll       Ljava/util/Vector;
        //  0      2951    3     strButton         Ljava/lang/String;
        //  0      2951    4     strButtonResult   Ljava/lang/String;
        //  0      2951    5     duration          Ljava/lang/String;
        //  0      2951    6     bRefresh          Z
        //  0      2951    7     iSec              I
        //  0      2951    8     vAssessment       Ljava/util/Vector;
        //  9      2942    9     calendar          Ljava/util/Calendar;
        //  18     2933    10    trialTime         Ljava/util/Date;
        //  98     2853    11    months            [Ljava/lang/String;
        //  135    2816    12    strTime           Ljava/lang/String;
        //  187    2764    13    strDate           Ljava/lang/String;
        //  196    2755    14    strHTML           Ljava/lang/StringBuffer;
        //  206    2745    15    entitle           Ljava/lang/String;
        //  221    2730    16    doc1              Lorg/apache/ecs/Doctype;
        //  230    2721    17    html1             Lorg/apache/ecs/xhtml/html;
        //  269    2682    18    head1             Lorg/apache/ecs/xhtml/head;
        //  278    2673    19    title1            Lorg/apache/ecs/xhtml/title;
        //  292    2659    20    csslink           Lorg/apache/ecs/xhtml/link;
        //  301    2650    21    csslink1          Lorg/apache/ecs/xhtml/link;
        //  339    2612    22    script1           Lorg/apache/ecs/xhtml/script;
        //  348    2603    23    body1             Lorg/apache/ecs/xhtml/body;
        //  394    2557    24    form1             Lorg/apache/ecs/xhtml/form;
        //  424    2527    25    table1            Lorg/apache/ecs/xhtml/table;
        //  433    2518    26    tr1               Lorg/apache/ecs/xhtml/tr;
        //  452    2499    27    td1               Lorg/apache/ecs/xhtml/td;
        //  466    2485    28    td2               Lorg/apache/ecs/xhtml/td;
        //  480    2471    29    td3               Lorg/apache/ecs/xhtml/td;
        //  494    2457    30    tr2               Lorg/apache/ecs/xhtml/tr;
        //  513    2438    31    td4               Lorg/apache/ecs/xhtml/td;
        //  527    2424    32    tr3               Lorg/apache/ecs/xhtml/tr;
        //  550    2401    33    td5               Lorg/apache/ecs/xhtml/td;
        //  559    2392    34    tr4               Lorg/apache/ecs/xhtml/tr;
        //  583    2368    35    td6               Lorg/apache/ecs/xhtml/td;
        //  592    2359    36    tr41              Lorg/apache/ecs/xhtml/tr;
        //  616    2335    37    td61              Lorg/apache/ecs/xhtml/td;
        //  630    2321    38    tr5               Lorg/apache/ecs/xhtml/tr;
        //  649    2302    39    td7               Lorg/apache/ecs/xhtml/td;
        //  675    2276    40    table2            Lorg/apache/ecs/xhtml/table;
        //  684    2267    41    tr6               Lorg/apache/ecs/xhtml/tr;
        //  698    2253    42    td8               Lorg/apache/ecs/xhtml/td;
        //  720    2231    43    table3            Lorg/apache/ecs/xhtml/table;
        //  729    2222    44    tr9               Lorg/apache/ecs/xhtml/tr;
        //  743    2208    45    td14              Lorg/apache/ecs/xhtml/td;
        //  752    2199    46    table4            Lorg/apache/ecs/xhtml/table;
        //  761    2190    47    tbody1            Lorg/apache/ecs/xhtml/tbody;
        //  770    2181    48    tr11              Lorg/apache/ecs/xhtml/tr;
        //  785    2166    49    td19              Lorg/apache/ecs/xhtml/td;
        //  799    2152    50    td20              Lorg/apache/ecs/xhtml/td;
        //  820    2131    51    table5            Lorg/apache/ecs/xhtml/table;
        //  829    2122    52    tr12              Lorg/apache/ecs/xhtml/tr;
        //  838    2113    53    td21              Lorg/apache/ecs/xhtml/td;
        //  847    2104    54    td22              Lorg/apache/ecs/xhtml/td;
        //  860    2091    55    td23              Lorg/apache/ecs/xhtml/td;
        //  873    2078    56    font1             Lorg/apache/ecs/xhtml/font;
        //  891    2060    57    font2             Lorg/apache/ecs/xhtml/font;
        //  904    2047    58    font3             Lorg/apache/ecs/xhtml/font;
        //  1243   1708    59    strAsmtPatern     Ljava/lang/String;
        //  1468   1483    60    strSectionPatern  Ljava/lang/String;
        //  1588   1363    61    tr7               Lorg/apache/ecs/xhtml/tr;
        //  1597   1354    62    td9               Lorg/apache/ecs/xhtml/td;
        //  1606   1345    63    td10              Lorg/apache/ecs/xhtml/td;
        //  1615   1336    64    td11              Lorg/apache/ecs/xhtml/td;
        //  1647   1304    65    tr8               Lorg/apache/ecs/xhtml/tr;
        //  1656   1295    66    td12              Lorg/apache/ecs/xhtml/td;
        //  1676   1275    67    td13              Lorg/apache/ecs/xhtml/td;
        //  1685   1266    68    td15              Lorg/apache/ecs/xhtml/td;
        //  1694   1257    69    tr10              Lorg/apache/ecs/xhtml/tr;
        //  1703   1248    70    td16              Lorg/apache/ecs/xhtml/td;
        //  1712   1239    71    td17              Lorg/apache/ecs/xhtml/td;
        //  1721   1230    72    td18              Lorg/apache/ecs/xhtml/td;
        //  1730   1221    73    divQA             Lorg/apache/ecs/xhtml/div;
        //  1795   1156    74    strReturn         Ljava/lang/String;
        //  2240   711     75    javaScript1       Ljava/lang/String;
        //  2244   707     76    javaScript2       Ljava/lang/String;
        //  2248   703     77    test              Ljava/lang/String;
        //  2772   179     78    javaScript3       Ljava/lang/String;
        //  2791   160     79    javaScript11      Lorg/apache/ecs/xhtml/script;
        //  2810   141     80    javaScript22      Lorg/apache/ecs/xhtml/script;
        //  2829   122     81    javaScript33      Lorg/apache/ecs/xhtml/script;
        //  2948   3       82    abcd              Ljava/lang/String;
        // 
        // The error that occurred was:
        // 
        // java.lang.StackOverflowError
        //     at com.strobel.assembler.metadata.TypeReference.getInternalName(TypeReference.java:95)
        //     at com.strobel.assembler.metadata.CoreMetadataFactory$UnresolvedType.getInternalName(CoreMetadataFactory.java:529)
        //     at com.strobel.assembler.metadata.MetadataSystem.resolveCore(MetadataSystem.java:76)
        //     at com.strobel.assembler.metadata.MetadataResolver.resolve(MetadataResolver.java:104)
        //     at com.strobel.assembler.metadata.CoreMetadataFactory$UnresolvedType.resolve(CoreMetadataFactory.java:576)
        //     at com.strobel.assembler.metadata.MetadataResolver.resolve(MetadataResolver.java:128)
        //     at com.strobel.assembler.metadata.CoreMetadataFactory$UnresolvedType.resolve(CoreMetadataFactory.java:586)
        //     at com.strobel.assembler.metadata.MethodReference.resolve(MethodReference.java:172)
        //     at com.strobel.decompiler.ast.TypeAnalysis.inferCall(TypeAnalysis.java:2420)
        //     at com.strobel.decompiler.ast.TypeAnalysis.doInferTypeForExpression(TypeAnalysis.java:1029)
        //     at com.strobel.decompiler.ast.TypeAnalysis.inferTypeForExpression(TypeAnalysis.java:803)
        //     at com.strobel.decompiler.ast.TypeAnalysis.inferTypeForExpression(TypeAnalysis.java:770)
        //     at com.strobel.decompiler.ast.TypeAnalysis.inferTypeForExpression(TypeAnalysis.java:766)
        //     at com.strobel.decompiler.ast.TypeAnalysis.inferCall(TypeAnalysis.java:2445)
        //     at com.strobel.decompiler.ast.TypeAnalysis.doInferTypeForExpression(TypeAnalysis.java:1029)
        //     at com.strobel.decompiler.ast.TypeAnalysis.inferTypeForExpression(TypeAnalysis.java:803)
        //     at com.strobel.decompiler.ast.TypeAnalysis.inferTypeForExpression(TypeAnalysis.java:770)
        //     at com.strobel.decompiler.ast.TypeAnalysis.inferTypeForExpression(TypeAnalysis.java:766)
        //     at com.strobel.decompiler.ast.TypeAnalysis.inferCall(TypeAnalysis.java:2445)
        //     at com.strobel.decompiler.ast.TypeAnalysis.doInferTypeForExpression(TypeAnalysis.java:1029)
        //     at com.strobel.decompiler.ast.TypeAnalysis.inferTypeForExpression(TypeAnalysis.java:803)
        //     at com.strobel.decompiler.ast.TypeAnalysis.inferTypeForExpression(TypeAnalysis.java:770)
        //     at com.strobel.decompiler.ast.TypeAnalysis.inferTypeForExpression(TypeAnalysis.java:766)
        //     at com.strobel.decompiler.ast.TypeAnalysis.inferCall(TypeAnalysis.java:2445)
        //     at com.strobel.decompiler.ast.TypeAnalysis.doInferTypeForExpression(TypeAnalysis.java:1029)
        //     at com.strobel.decompiler.ast.TypeAnalysis.inferTypeForExpression(TypeAnalysis.java:803)
        //     at com.strobel.decompiler.ast.TypeAnalysis.inferTypeForExpression(TypeAnalysis.java:770)
        //     at com.strobel.decompiler.ast.TypeAnalysis.inferTypeForExpression(TypeAnalysis.java:766)
        //     at com.strobel.decompiler.ast.TypeAnalysis.inferCall(TypeAnalysis.java:2445)
        //     at com.strobel.decompiler.ast.TypeAnalysis.doInferTypeForExpression(TypeAnalysis.java:1029)
        //     at com.strobel.decompiler.ast.TypeAnalysis.inferTypeForExpression(TypeAnalysis.java:803)
        //     at com.strobel.decompiler.ast.TypeAnalysis.inferTypeForExpression(TypeAnalysis.java:770)
        //     at com.strobel.decompiler.ast.TypeAnalysis.inferTypeForExpression(TypeAnalysis.java:766)
        //     at com.strobel.decompiler.ast.TypeAnalysis.inferCall(TypeAnalysis.java:2445)
        //     at com.strobel.decompiler.ast.TypeAnalysis.doInferTypeForExpression(TypeAnalysis.java:1029)
        //     at com.strobel.decompiler.ast.TypeAnalysis.inferTypeForExpression(TypeAnalysis.java:803)
        //     at com.strobel.decompiler.ast.TypeAnalysis.inferTypeForExpression(TypeAnalysis.java:770)
        //     at com.strobel.decompiler.ast.TypeAnalysis.inferTypeForExpression(TypeAnalysis.java:766)
        //     at com.strobel.decompiler.ast.TypeAnalysis.inferCall(TypeAnalysis.java:2445)
        //     at com.strobel.decompiler.ast.TypeAnalysis.doInferTypeForExpression(TypeAnalysis.java:1029)
        //     at com.strobel.decompiler.ast.TypeAnalysis.inferTypeForExpression(TypeAnalysis.java:803)
        //     at com.strobel.decompiler.ast.TypeAnalysis.inferTypeForExpression(TypeAnalysis.java:770)
        //     at com.strobel.decompiler.ast.TypeAnalysis.inferTypeForExpression(TypeAnalysis.java:766)
        //     at com.strobel.decompiler.ast.TypeAnalysis.inferCall(TypeAnalysis.java:2445)
        //     at com.strobel.decompiler.ast.TypeAnalysis.doInferTypeForExpression(TypeAnalysis.java:1029)
        //     at com.strobel.decompiler.ast.TypeAnalysis.inferTypeForExpression(TypeAnalysis.java:803)
        //     at com.strobel.decompiler.ast.TypeAnalysis.inferTypeForExpression(TypeAnalysis.java:770)
        //     at com.strobel.decompiler.ast.TypeAnalysis.inferTypeForExpression(TypeAnalysis.java:766)
        //     at com.strobel.decompiler.ast.TypeAnalysis.inferCall(TypeAnalysis.java:2445)
        //     at com.strobel.decompiler.ast.TypeAnalysis.doInferTypeForExpression(TypeAnalysis.java:1029)
        //     at com.strobel.decompiler.ast.TypeAnalysis.inferTypeForExpression(TypeAnalysis.java:803)
        //     at com.strobel.decompiler.ast.TypeAnalysis.inferTypeForExpression(TypeAnalysis.java:770)
        //     at com.strobel.decompiler.ast.TypeAnalysis.inferTypeForExpression(TypeAnalysis.java:766)
        //     at com.strobel.decompiler.ast.TypeAnalysis.inferCall(TypeAnalysis.java:2445)
        //     at com.strobel.decompiler.ast.TypeAnalysis.doInferTypeForExpression(TypeAnalysis.java:1029)
        //     at com.strobel.decompiler.ast.TypeAnalysis.inferTypeForExpression(TypeAnalysis.java:803)
        //     at com.strobel.decompiler.ast.TypeAnalysis.inferTypeForExpression(TypeAnalysis.java:770)
        //     at com.strobel.decompiler.ast.TypeAnalysis.inferTypeForExpression(TypeAnalysis.java:766)
        //     at com.strobel.decompiler.ast.TypeAnalysis.inferCall(TypeAnalysis.java:2445)
        //     at com.strobel.decompiler.ast.TypeAnalysis.doInferTypeForExpression(TypeAnalysis.java:1029)
        //     at com.strobel.decompiler.ast.TypeAnalysis.inferTypeForExpression(TypeAnalysis.java:803)
        //     at com.strobel.decompiler.ast.TypeAnalysis.inferTypeForExpression(TypeAnalysis.java:770)
        //     at com.strobel.decompiler.ast.TypeAnalysis.inferTypeForExpression(TypeAnalysis.java:766)
        //     at com.strobel.decompiler.ast.TypeAnalysis.inferCall(TypeAnalysis.java:2445)
        //     at com.strobel.decompiler.ast.TypeAnalysis.doInferTypeForExpression(TypeAnalysis.java:1029)
        //     at com.strobel.decompiler.ast.TypeAnalysis.inferTypeForExpression(TypeAnalysis.java:803)
        //     at com.strobel.decompiler.ast.TypeAnalysis.inferTypeForExpression(TypeAnalysis.java:770)
        //     at com.strobel.decompiler.ast.TypeAnalysis.inferTypeForExpression(TypeAnalysis.java:766)
        //     at com.strobel.decompiler.ast.TypeAnalysis.inferCall(TypeAnalysis.java:2445)
        //     at com.strobel.decompiler.ast.TypeAnalysis.doInferTypeForExpression(TypeAnalysis.java:1029)
        //     at com.strobel.decompiler.ast.TypeAnalysis.inferTypeForExpression(TypeAnalysis.java:803)
        //     at com.strobel.decompiler.ast.TypeAnalysis.inferTypeForExpression(TypeAnalysis.java:770)
        //     at com.strobel.decompiler.ast.TypeAnalysis.inferTypeForExpression(TypeAnalysis.java:766)
        //     at com.strobel.decompiler.ast.TypeAnalysis.inferCall(TypeAnalysis.java:2445)
        //     at com.strobel.decompiler.ast.TypeAnalysis.doInferTypeForExpression(TypeAnalysis.java:1029)
        //     at com.strobel.decompiler.ast.TypeAnalysis.inferTypeForExpression(TypeAnalysis.java:803)
        //     at com.strobel.decompiler.ast.TypeAnalysis.inferTypeForExpression(TypeAnalysis.java:770)
        //     at com.strobel.decompiler.ast.TypeAnalysis.inferTypeForExpression(TypeAnalysis.java:766)
        //     at com.strobel.decompiler.ast.TypeAnalysis.inferCall(TypeAnalysis.java:2445)
        //     at com.strobel.decompiler.ast.TypeAnalysis.doInferTypeForExpression(TypeAnalysis.java:1029)
        //     at com.strobel.decompiler.ast.TypeAnalysis.inferTypeForExpression(TypeAnalysis.java:803)
        //     at com.strobel.decompiler.ast.TypeAnalysis.inferTypeForExpression(TypeAnalysis.java:770)
        //     at com.strobel.decompiler.ast.TypeAnalysis.inferTypeForExpression(TypeAnalysis.java:766)
        //     at com.strobel.decompiler.ast.TypeAnalysis.inferCall(TypeAnalysis.java:2445)
        //     at com.strobel.decompiler.ast.TypeAnalysis.doInferTypeForExpression(TypeAnalysis.java:1029)
        //     at com.strobel.decompiler.ast.TypeAnalysis.inferTypeForExpression(TypeAnalysis.java:803)
        //     at com.strobel.decompiler.ast.TypeAnalysis.inferTypeForExpression(TypeAnalysis.java:770)
        //     at com.strobel.decompiler.ast.TypeAnalysis.inferTypeForExpression(TypeAnalysis.java:766)
        //     at com.strobel.decompiler.ast.TypeAnalysis.inferCall(TypeAnalysis.java:2445)
        //     at com.strobel.decompiler.ast.TypeAnalysis.doInferTypeForExpression(TypeAnalysis.java:1029)
        //     at com.strobel.decompiler.ast.TypeAnalysis.inferTypeForExpression(TypeAnalysis.java:803)
        //     at com.strobel.decompiler.ast.TypeAnalysis.inferTypeForExpression(TypeAnalysis.java:770)
        //     at com.strobel.decompiler.ast.TypeAnalysis.inferTypeForExpression(TypeAnalysis.java:766)
        //     at com.strobel.decompiler.ast.TypeAnalysis.inferCall(TypeAnalysis.java:2445)
        //     at com.strobel.decompiler.ast.TypeAnalysis.doInferTypeForExpression(TypeAnalysis.java:1029)
        //     at com.strobel.decompiler.ast.TypeAnalysis.inferTypeForExpression(TypeAnalysis.java:803)
        //     at com.strobel.decompiler.ast.TypeAnalysis.inferTypeForExpression(TypeAnalysis.java:770)
        //     at com.strobel.decompiler.ast.TypeAnalysis.inferTypeForExpression(TypeAnalysis.java:766)
        //     at com.strobel.decompiler.ast.TypeAnalysis.inferCall(TypeAnalysis.java:2445)
        //     at com.strobel.decompiler.ast.TypeAnalysis.doInferTypeForExpression(TypeAnalysis.java:1029)
        //     at com.strobel.decompiler.ast.TypeAnalysis.inferTypeForExpression(TypeAnalysis.java:803)
        //     at com.strobel.decompiler.ast.TypeAnalysis.inferTypeForExpression(TypeAnalysis.java:770)
        //     at com.strobel.decompiler.ast.TypeAnalysis.inferTypeForExpression(TypeAnalysis.java:766)
        //     at com.strobel.decompiler.ast.TypeAnalysis.inferCall(TypeAnalysis.java:2445)
        //     at com.strobel.decompiler.ast.TypeAnalysis.doInferTypeForExpression(TypeAnalysis.java:1029)
        //     at com.strobel.decompiler.ast.TypeAnalysis.inferTypeForExpression(TypeAnalysis.java:803)
        //     at com.strobel.decompiler.ast.TypeAnalysis.inferTypeForExpression(TypeAnalysis.java:770)
        //     at com.strobel.decompiler.ast.TypeAnalysis.inferTypeForExpression(TypeAnalysis.java:766)
        //     at com.strobel.decompiler.ast.TypeAnalysis.inferCall(TypeAnalysis.java:2445)
        //     at com.strobel.decompiler.ast.TypeAnalysis.doInferTypeForExpression(TypeAnalysis.java:1029)
        //     at com.strobel.decompiler.ast.TypeAnalysis.inferTypeForExpression(TypeAnalysis.java:803)
        //     at com.strobel.decompiler.ast.TypeAnalysis.inferTypeForExpression(TypeAnalysis.java:770)
        //     at com.strobel.decompiler.ast.TypeAnalysis.inferTypeForExpression(TypeAnalysis.java:766)
        //     at com.strobel.decompiler.ast.TypeAnalysis.inferCall(TypeAnalysis.java:2445)
        //     at com.strobel.decompiler.ast.TypeAnalysis.doInferTypeForExpression(TypeAnalysis.java:1029)
        //     at com.strobel.decompiler.ast.TypeAnalysis.inferTypeForExpression(TypeAnalysis.java:803)
        //     at com.strobel.decompiler.ast.TypeAnalysis.inferTypeForExpression(TypeAnalysis.java:770)
        //     at com.strobel.decompiler.ast.TypeAnalysis.inferTypeForExpression(TypeAnalysis.java:766)
        //     at com.strobel.decompiler.ast.TypeAnalysis.inferCall(TypeAnalysis.java:2445)
        //     at com.strobel.decompiler.ast.TypeAnalysis.doInferTypeForExpression(TypeAnalysis.java:1029)
        //     at com.strobel.decompiler.ast.TypeAnalysis.inferTypeForExpression(TypeAnalysis.java:803)
        //     at com.strobel.decompiler.ast.TypeAnalysis.inferTypeForExpression(TypeAnalysis.java:770)
        //     at com.strobel.decompiler.ast.TypeAnalysis.inferTypeForExpression(TypeAnalysis.java:766)
        //     at com.strobel.decompiler.ast.TypeAnalysis.inferCall(TypeAnalysis.java:2445)
        //     at com.strobel.decompiler.ast.TypeAnalysis.doInferTypeForExpression(TypeAnalysis.java:1029)
        //     at com.strobel.decompiler.ast.TypeAnalysis.inferTypeForExpression(TypeAnalysis.java:803)
        //     at com.strobel.decompiler.ast.TypeAnalysis.inferTypeForExpression(TypeAnalysis.java:770)
        //     at com.strobel.decompiler.ast.TypeAnalysis.inferTypeForExpression(TypeAnalysis.java:766)
        //     at com.strobel.decompiler.ast.TypeAnalysis.inferCall(TypeAnalysis.java:2445)
        //     at com.strobel.decompiler.ast.TypeAnalysis.doInferTypeForExpression(TypeAnalysis.java:1029)
        //     at com.strobel.decompiler.ast.TypeAnalysis.inferTypeForExpression(TypeAnalysis.java:803)
        //     at com.strobel.decompiler.ast.TypeAnalysis.inferTypeForExpression(TypeAnalysis.java:770)
        //     at com.strobel.decompiler.ast.TypeAnalysis.inferTypeForExpression(TypeAnalysis.java:766)
        //     at com.strobel.decompiler.ast.TypeAnalysis.inferCall(TypeAnalysis.java:2445)
        //     at com.strobel.decompiler.ast.TypeAnalysis.doInferTypeForExpression(TypeAnalysis.java:1029)
        //     at com.strobel.decompiler.ast.TypeAnalysis.inferTypeForExpression(TypeAnalysis.java:803)
        //     at com.strobel.decompiler.ast.TypeAnalysis.inferTypeForExpression(TypeAnalysis.java:770)
        //     at com.strobel.decompiler.ast.TypeAnalysis.inferTypeForExpression(TypeAnalysis.java:766)
        //     at com.strobel.decompiler.ast.TypeAnalysis.inferCall(TypeAnalysis.java:2445)
        //     at com.strobel.decompiler.ast.TypeAnalysis.doInferTypeForExpression(TypeAnalysis.java:1029)
        //     at com.strobel.decompiler.ast.TypeAnalysis.inferTypeForExpression(TypeAnalysis.java:803)
        //     at com.strobel.decompiler.ast.TypeAnalysis.inferTypeForExpression(TypeAnalysis.java:770)
        //     at com.strobel.decompiler.ast.TypeAnalysis.inferTypeForExpression(TypeAnalysis.java:766)
        //     at com.strobel.decompiler.ast.TypeAnalysis.inferCall(TypeAnalysis.java:2445)
        //     at com.strobel.decompiler.ast.TypeAnalysis.doInferTypeForExpression(TypeAnalysis.java:1029)
        //     at com.strobel.decompiler.ast.TypeAnalysis.inferTypeForExpression(TypeAnalysis.java:803)
        //     at com.strobel.decompiler.ast.TypeAnalysis.inferTypeForExpression(TypeAnalysis.java:770)
        //     at com.strobel.decompiler.ast.TypeAnalysis.inferTypeForExpression(TypeAnalysis.java:766)
        //     at com.strobel.decompiler.ast.TypeAnalysis.inferCall(TypeAnalysis.java:2445)
        //     at com.strobel.decompiler.ast.TypeAnalysis.doInferTypeForExpression(TypeAnalysis.java:1029)
        //     at com.strobel.decompiler.ast.TypeAnalysis.inferTypeForExpression(TypeAnalysis.java:803)
        //     at com.strobel.decompiler.ast.TypeAnalysis.inferTypeForExpression(TypeAnalysis.java:770)
        //     at com.strobel.decompiler.ast.TypeAnalysis.inferTypeForExpression(TypeAnalysis.java:766)
        //     at com.strobel.decompiler.ast.TypeAnalysis.inferCall(TypeAnalysis.java:2445)
        //     at com.strobel.decompiler.ast.TypeAnalysis.doInferTypeForExpression(TypeAnalysis.java:1029)
        //     at com.strobel.decompiler.ast.TypeAnalysis.inferTypeForExpression(TypeAnalysis.java:803)
        //     at com.strobel.decompiler.ast.TypeAnalysis.inferTypeForExpression(TypeAnalysis.java:770)
        //     at com.strobel.decompiler.ast.TypeAnalysis.inferTypeForExpression(TypeAnalysis.java:766)
        //     at com.strobel.decompiler.ast.TypeAnalysis.inferCall(TypeAnalysis.java:2445)
        //     at com.strobel.decompiler.ast.TypeAnalysis.doInferTypeForExpression(TypeAnalysis.java:1029)
        //     at com.strobel.decompiler.ast.TypeAnalysis.inferTypeForExpression(TypeAnalysis.java:803)
        //     at com.strobel.decompiler.ast.TypeAnalysis.inferTypeForExpression(TypeAnalysis.java:770)
        //     at com.strobel.decompiler.ast.TypeAnalysis.inferTypeForExpression(TypeAnalysis.java:766)
        //     at com.strobel.decompiler.ast.TypeAnalysis.inferCall(TypeAnalysis.java:2445)
        //     at com.strobel.decompiler.ast.TypeAnalysis.doInferTypeForExpression(TypeAnalysis.java:1029)
        //     at com.strobel.decompiler.ast.TypeAnalysis.inferTypeForExpression(TypeAnalysis.java:803)
        //     at com.strobel.decompiler.ast.TypeAnalysis.inferTypeForExpression(TypeAnalysis.java:770)
        //     at com.strobel.decompiler.ast.TypeAnalysis.inferTypeForExpression(TypeAnalysis.java:766)
        //     at com.strobel.decompiler.ast.TypeAnalysis.inferCall(TypeAnalysis.java:2445)
        //     at com.strobel.decompiler.ast.TypeAnalysis.doInferTypeForExpression(TypeAnalysis.java:1029)
        //     at com.strobel.decompiler.ast.TypeAnalysis.inferTypeForExpression(TypeAnalysis.java:803)
        //     at com.strobel.decompiler.ast.TypeAnalysis.inferTypeForExpression(TypeAnalysis.java:770)
        //     at com.strobel.decompiler.ast.TypeAnalysis.inferTypeForExpression(TypeAnalysis.java:766)
        //     at com.strobel.decompiler.ast.TypeAnalysis.inferCall(TypeAnalysis.java:2445)
        //     at com.strobel.decompiler.ast.TypeAnalysis.doInferTypeForExpression(TypeAnalysis.java:1029)
        //     at com.strobel.decompiler.ast.TypeAnalysis.inferTypeForExpression(TypeAnalysis.java:803)
        //     at com.strobel.decompiler.ast.TypeAnalysis.inferTypeForExpression(TypeAnalysis.java:770)
        //     at com.strobel.decompiler.ast.TypeAnalysis.inferTypeForExpression(TypeAnalysis.java:766)
        //     at com.strobel.decompiler.ast.TypeAnalysis.inferCall(TypeAnalysis.java:2445)
        //     at com.strobel.decompiler.ast.TypeAnalysis.doInferTypeForExpression(TypeAnalysis.java:1029)
        //     at com.strobel.decompiler.ast.TypeAnalysis.inferTypeForExpression(TypeAnalysis.java:803)
        //     at com.strobel.decompiler.ast.TypeAnalysis.inferTypeForExpression(TypeAnalysis.java:770)
        //     at com.strobel.decompiler.ast.TypeAnalysis.inferTypeForExpression(TypeAnalysis.java:766)
        //     at com.strobel.decompiler.ast.TypeAnalysis.inferCall(TypeAnalysis.java:2445)
        //     at com.strobel.decompiler.ast.TypeAnalysis.doInferTypeForExpression(TypeAnalysis.java:1029)
        //     at com.strobel.decompiler.ast.TypeAnalysis.inferTypeForExpression(TypeAnalysis.java:803)
        //     at com.strobel.decompiler.ast.TypeAnalysis.inferTypeForExpression(TypeAnalysis.java:770)
        //     at com.strobel.decompiler.ast.TypeAnalysis.inferTypeForExpression(TypeAnalysis.java:766)
        //     at com.strobel.decompiler.ast.TypeAnalysis.inferCall(TypeAnalysis.java:2445)
        //     at com.strobel.decompiler.ast.TypeAnalysis.doInferTypeForExpression(TypeAnalysis.java:1029)
        //     at com.strobel.decompiler.ast.TypeAnalysis.inferTypeForExpression(TypeAnalysis.java:803)
        //     at com.strobel.decompiler.ast.TypeAnalysis.inferTypeForExpression(TypeAnalysis.java:770)
        //     at com.strobel.decompiler.ast.TypeAnalysis.inferTypeForExpression(TypeAnalysis.java:766)
        //     at com.strobel.decompiler.ast.TypeAnalysis.inferCall(TypeAnalysis.java:2445)
        //     at com.strobel.decompiler.ast.TypeAnalysis.doInferTypeForExpression(TypeAnalysis.java:1029)
        //     at com.strobel.decompiler.ast.TypeAnalysis.inferTypeForExpression(TypeAnalysis.java:803)
        //     at com.strobel.decompiler.ast.TypeAnalysis.inferTypeForExpression(TypeAnalysis.java:770)
        //     at com.strobel.decompiler.ast.TypeAnalysis.inferTypeForExpression(TypeAnalysis.java:766)
        //     at com.strobel.decompiler.ast.TypeAnalysis.inferCall(TypeAnalysis.java:2445)
        //     at com.strobel.decompiler.ast.TypeAnalysis.doInferTypeForExpression(TypeAnalysis.java:1029)
        //     at com.strobel.decompiler.ast.TypeAnalysis.inferTypeForExpression(TypeAnalysis.java:803)
        //     at com.strobel.decompiler.ast.TypeAnalysis.inferTypeForExpression(TypeAnalysis.java:770)
        //     at com.strobel.decompiler.ast.TypeAnalysis.inferTypeForExpression(TypeAnalysis.java:766)
        //     at com.strobel.decompiler.ast.TypeAnalysis.inferCall(TypeAnalysis.java:2445)
        //     at com.strobel.decompiler.ast.TypeAnalysis.doInferTypeForExpression(TypeAnalysis.java:1029)
        //     at com.strobel.decompiler.ast.TypeAnalysis.inferTypeForExpression(TypeAnalysis.java:803)
        //     at com.strobel.decompiler.ast.TypeAnalysis.inferTypeForExpression(TypeAnalysis.java:770)
        //     at com.strobel.decompiler.ast.TypeAnalysis.inferTypeForExpression(TypeAnalysis.java:766)
        //     at com.strobel.decompiler.ast.TypeAnalysis.inferCall(TypeAnalysis.java:2445)
        //     at com.strobel.decompiler.ast.TypeAnalysis.doInferTypeForExpression(TypeAnalysis.java:1029)
        //     at com.strobel.decompiler.ast.TypeAnalysis.inferTypeForExpression(TypeAnalysis.java:803)
        //     at com.strobel.decompiler.ast.TypeAnalysis.inferTypeForExpression(TypeAnalysis.java:770)
        //     at com.strobel.decompiler.ast.TypeAnalysis.inferTypeForExpression(TypeAnalysis.java:766)
        //     at com.strobel.decompiler.ast.TypeAnalysis.inferCall(TypeAnalysis.java:2445)
        //     at com.strobel.decompiler.ast.TypeAnalysis.doInferTypeForExpression(TypeAnalysis.java:1029)
        //     at com.strobel.decompiler.ast.TypeAnalysis.inferTypeForExpression(TypeAnalysis.java:803)
        //     at com.strobel.decompiler.ast.TypeAnalysis.inferTypeForExpression(TypeAnalysis.java:770)
        //     at com.strobel.decompiler.ast.TypeAnalysis.inferTypeForExpression(TypeAnalysis.java:766)
        //     at com.strobel.decompiler.ast.TypeAnalysis.inferCall(TypeAnalysis.java:2445)
        //     at com.strobel.decompiler.ast.TypeAnalysis.doInferTypeForExpression(TypeAnalysis.java:1029)
        //     at com.strobel.decompiler.ast.TypeAnalysis.inferTypeForExpression(TypeAnalysis.java:803)
        //     at com.strobel.decompiler.ast.TypeAnalysis.inferTypeForExpression(TypeAnalysis.java:770)
        //     at com.strobel.decompiler.ast.TypeAnalysis.inferTypeForExpression(TypeAnalysis.java:766)
        //     at com.strobel.decompiler.ast.TypeAnalysis.inferCall(TypeAnalysis.java:2445)
        //     at com.strobel.decompiler.ast.TypeAnalysis.doInferTypeForExpression(TypeAnalysis.java:1029)
        //     at com.strobel.decompiler.ast.TypeAnalysis.inferTypeForExpression(TypeAnalysis.java:803)
        //     at com.strobel.decompiler.ast.TypeAnalysis.inferTypeForExpression(TypeAnalysis.java:770)
        //     at com.strobel.decompiler.ast.TypeAnalysis.inferTypeForExpression(TypeAnalysis.java:766)
        //     at com.strobel.decompiler.ast.TypeAnalysis.inferCall(TypeAnalysis.java:2445)
        //     at com.strobel.decompiler.ast.TypeAnalysis.doInferTypeForExpression(TypeAnalysis.java:1029)
        //     at com.strobel.decompiler.ast.TypeAnalysis.inferTypeForExpression(TypeAnalysis.java:803)
        //     at com.strobel.decompiler.ast.TypeAnalysis.inferTypeForExpression(TypeAnalysis.java:770)
        //     at com.strobel.decompiler.ast.TypeAnalysis.inferTypeForExpression(TypeAnalysis.java:766)
        //     at com.strobel.decompiler.ast.TypeAnalysis.inferCall(TypeAnalysis.java:2445)
        //     at com.strobel.decompiler.ast.TypeAnalysis.doInferTypeForExpression(TypeAnalysis.java:1029)
        //     at com.strobel.decompiler.ast.TypeAnalysis.inferTypeForExpression(TypeAnalysis.java:803)
        //     at com.strobel.decompiler.ast.TypeAnalysis.inferTypeForExpression(TypeAnalysis.java:770)
        //     at com.strobel.decompiler.ast.TypeAnalysis.inferTypeForExpression(TypeAnalysis.java:766)
        //     at com.strobel.decompiler.ast.TypeAnalysis.inferCall(TypeAnalysis.java:2445)
        //     at com.strobel.decompiler.ast.TypeAnalysis.doInferTypeForExpression(TypeAnalysis.java:1029)
        //     at com.strobel.decompiler.ast.TypeAnalysis.inferTypeForExpression(TypeAnalysis.java:803)
        //     at com.strobel.decompiler.ast.TypeAnalysis.inferTypeForExpression(TypeAnalysis.java:770)
        //     at com.strobel.decompiler.ast.TypeAnalysis.inferTypeForExpression(TypeAnalysis.java:766)
        //     at com.strobel.decompiler.ast.TypeAnalysis.inferCall(TypeAnalysis.java:2445)
        //     at com.strobel.decompiler.ast.TypeAnalysis.doInferTypeForExpression(TypeAnalysis.java:1029)
        //     at com.strobel.decompiler.ast.TypeAnalysis.inferTypeForExpression(TypeAnalysis.java:803)
        //     at com.strobel.decompiler.ast.TypeAnalysis.inferTypeForExpression(TypeAnalysis.java:770)
        //     at com.strobel.decompiler.ast.TypeAnalysis.inferTypeForExpression(TypeAnalysis.java:766)
        //     at com.strobel.decompiler.ast.TypeAnalysis.inferCall(TypeAnalysis.java:2445)
        //     at com.strobel.decompiler.ast.TypeAnalysis.doInferTypeForExpression(TypeAnalysis.java:1029)
        //     at com.strobel.decompiler.ast.TypeAnalysis.inferTypeForExpression(TypeAnalysis.java:803)
        //     at com.strobel.decompiler.ast.TypeAnalysis.inferTypeForExpression(TypeAnalysis.java:770)
        //     at com.strobel.decompiler.ast.TypeAnalysis.inferTypeForExpression(TypeAnalysis.java:766)
        //     at com.strobel.decompiler.ast.TypeAnalysis.inferCall(TypeAnalysis.java:2445)
        //     at com.strobel.decompiler.ast.TypeAnalysis.doInferTypeForExpression(TypeAnalysis.java:1029)
        //     at com.strobel.decompiler.ast.TypeAnalysis.inferTypeForExpression(TypeAnalysis.java:803)
        //     at com.strobel.decompiler.ast.TypeAnalysis.inferTypeForExpression(TypeAnalysis.java:770)
        //     at com.strobel.decompiler.ast.TypeAnalysis.inferTypeForExpression(TypeAnalysis.java:766)
        //     at com.strobel.decompiler.ast.TypeAnalysis.inferCall(TypeAnalysis.java:2445)
        //     at com.strobel.decompiler.ast.TypeAnalysis.doInferTypeForExpression(TypeAnalysis.java:1029)
        //     at com.strobel.decompiler.ast.TypeAnalysis.inferTypeForExpression(TypeAnalysis.java:803)
        //     at com.strobel.decompiler.ast.TypeAnalysis.inferTypeForExpression(TypeAnalysis.java:770)
        //     at com.strobel.decompiler.ast.TypeAnalysis.inferTypeForExpression(TypeAnalysis.java:766)
        //     at com.strobel.decompiler.ast.TypeAnalysis.inferCall(TypeAnalysis.java:2445)
        //     at com.strobel.decompiler.ast.TypeAnalysis.doInferTypeForExpression(TypeAnalysis.java:1029)
        //     at com.strobel.decompiler.ast.TypeAnalysis.inferTypeForExpression(TypeAnalysis.java:803)
        //     at com.strobel.decompiler.ast.TypeAnalysis.inferTypeForExpression(TypeAnalysis.java:770)
        //     at com.strobel.decompiler.ast.TypeAnalysis.inferTypeForExpression(TypeAnalysis.java:766)
        //     at com.strobel.decompiler.ast.TypeAnalysis.inferCall(TypeAnalysis.java:2445)
        //     at com.strobel.decompiler.ast.TypeAnalysis.doInferTypeForExpression(TypeAnalysis.java:1029)
        //     at com.strobel.decompiler.ast.TypeAnalysis.inferTypeForExpression(TypeAnalysis.java:803)
        //     at com.strobel.decompiler.ast.TypeAnalysis.inferTypeForExpression(TypeAnalysis.java:770)
        //     at com.strobel.decompiler.ast.TypeAnalysis.inferTypeForExpression(TypeAnalysis.java:766)
        //     at com.strobel.decompiler.ast.TypeAnalysis.inferCall(TypeAnalysis.java:2445)
        //     at com.strobel.decompiler.ast.TypeAnalysis.doInferTypeForExpression(TypeAnalysis.java:1029)
        //     at com.strobel.decompiler.ast.TypeAnalysis.inferTypeForExpression(TypeAnalysis.java:803)
        //     at com.strobel.decompiler.ast.TypeAnalysis.inferTypeForExpression(TypeAnalysis.java:770)
        //     at com.strobel.decompiler.ast.TypeAnalysis.inferTypeForExpression(TypeAnalysis.java:766)
        //     at com.strobel.decompiler.ast.TypeAnalysis.inferCall(TypeAnalysis.java:2445)
        //     at com.strobel.decompiler.ast.TypeAnalysis.doInferTypeForExpression(TypeAnalysis.java:1029)
        //     at com.strobel.decompiler.ast.TypeAnalysis.inferTypeForExpression(TypeAnalysis.java:803)
        //     at com.strobel.decompiler.ast.TypeAnalysis.inferTypeForExpression(TypeAnalysis.java:770)
        //     at com.strobel.decompiler.ast.TypeAnalysis.inferTypeForExpression(TypeAnalysis.java:766)
        //     at com.strobel.decompiler.ast.TypeAnalysis.inferCall(TypeAnalysis.java:2445)
        //     at com.strobel.decompiler.ast.TypeAnalysis.doInferTypeForExpression(TypeAnalysis.java:1029)
        //     at com.strobel.decompiler.ast.TypeAnalysis.inferTypeForExpression(TypeAnalysis.java:803)
        //     at com.strobel.decompiler.ast.TypeAnalysis.inferTypeForExpression(TypeAnalysis.java:770)
        //     at com.strobel.decompiler.ast.TypeAnalysis.inferTypeForExpression(TypeAnalysis.java:766)
        //     at com.strobel.decompiler.ast.TypeAnalysis.inferCall(TypeAnalysis.java:2445)
        //     at com.strobel.decompiler.ast.TypeAnalysis.doInferTypeForExpression(TypeAnalysis.java:1029)
        //     at com.strobel.decompiler.ast.TypeAnalysis.inferTypeForExpression(TypeAnalysis.java:803)
        //     at com.strobel.decompiler.ast.TypeAnalysis.inferTypeForExpression(TypeAnalysis.java:770)
        //     at com.strobel.decompiler.ast.TypeAnalysis.inferTypeForExpression(TypeAnalysis.java:766)
        //     at com.strobel.decompiler.ast.TypeAnalysis.inferCall(TypeAnalysis.java:2445)
        //     at com.strobel.decompiler.ast.TypeAnalysis.doInferTypeForExpression(TypeAnalysis.java:1029)
        //     at com.strobel.decompiler.ast.TypeAnalysis.inferTypeForExpression(TypeAnalysis.java:803)
        //     at com.strobel.decompiler.ast.TypeAnalysis.inferTypeForExpression(TypeAnalysis.java:770)
        //     at com.strobel.decompiler.ast.TypeAnalysis.inferTypeForExpression(TypeAnalysis.java:766)
        //     at com.strobel.decompiler.ast.TypeAnalysis.inferCall(TypeAnalysis.java:2445)
        //     at com.strobel.decompiler.ast.TypeAnalysis.doInferTypeForExpression(TypeAnalysis.java:1029)
        //     at com.strobel.decompiler.ast.TypeAnalysis.inferTypeForExpression(TypeAnalysis.java:803)
        //     at com.strobel.decompiler.ast.TypeAnalysis.inferTypeForExpression(TypeAnalysis.java:770)
        //     at com.strobel.decompiler.ast.TypeAnalysis.inferTypeForExpression(TypeAnalysis.java:766)
        //     at com.strobel.decompiler.ast.TypeAnalysis.inferCall(TypeAnalysis.java:2445)
        //     at com.strobel.decompiler.ast.TypeAnalysis.doInferTypeForExpression(TypeAnalysis.java:1029)
        //     at com.strobel.decompiler.ast.TypeAnalysis.inferTypeForExpression(TypeAnalysis.java:803)
        //     at com.strobel.decompiler.ast.TypeAnalysis.inferTypeForExpression(TypeAnalysis.java:770)
        //     at com.strobel.decompiler.ast.TypeAnalysis.inferTypeForExpression(TypeAnalysis.java:766)
        //     at com.strobel.decompiler.ast.TypeAnalysis.inferCall(TypeAnalysis.java:2445)
        //     at com.strobel.decompiler.ast.TypeAnalysis.doInferTypeForExpression(TypeAnalysis.java:1029)
        //     at com.strobel.decompiler.ast.TypeAnalysis.inferTypeForExpression(TypeAnalysis.java:803)
        //     at com.strobel.decompiler.ast.TypeAnalysis.inferTypeForExpression(TypeAnalysis.java:770)
        //     at com.strobel.decompiler.ast.TypeAnalysis.inferTypeForExpression(TypeAnalysis.java:766)
        //     at com.strobel.decompiler.ast.TypeAnalysis.inferCall(TypeAnalysis.java:2445)
        //     at com.strobel.decompiler.ast.TypeAnalysis.doInferTypeForExpression(TypeAnalysis.java:1029)
        //     at com.strobel.decompiler.ast.TypeAnalysis.inferTypeForExpression(TypeAnalysis.java:803)
        //     at com.strobel.decompiler.ast.TypeAnalysis.inferTypeForExpression(TypeAnalysis.java:770)
        //     at com.strobel.decompiler.ast.TypeAnalysis.inferTypeForExpression(TypeAnalysis.java:766)
        //     at com.strobel.decompiler.ast.TypeAnalysis.inferCall(TypeAnalysis.java:2445)
        //     at com.strobel.decompiler.ast.TypeAnalysis.doInferTypeForExpression(TypeAnalysis.java:1029)
        //     at com.strobel.decompiler.ast.TypeAnalysis.inferTypeForExpression(TypeAnalysis.java:803)
        //     at com.strobel.decompiler.ast.TypeAnalysis.inferTypeForExpression(TypeAnalysis.java:770)
        //     at com.strobel.decompiler.ast.TypeAnalysis.inferTypeForExpression(TypeAnalysis.java:766)
        //     at com.strobel.decompiler.ast.TypeAnalysis.inferCall(TypeAnalysis.java:2445)
        //     at com.strobel.decompiler.ast.TypeAnalysis.doInferTypeForExpression(TypeAnalysis.java:1029)
        //     at com.strobel.decompiler.ast.TypeAnalysis.inferTypeForExpression(TypeAnalysis.java:803)
        //     at com.strobel.decompiler.ast.TypeAnalysis.inferTypeForExpression(TypeAnalysis.java:770)
        //     at com.strobel.decompiler.ast.TypeAnalysis.inferTypeForExpression(TypeAnalysis.java:766)
        //     at com.strobel.decompiler.ast.TypeAnalysis.inferCall(TypeAnalysis.java:2445)
        //     at com.strobel.decompiler.ast.TypeAnalysis.doInferTypeForExpression(TypeAnalysis.java:1029)
        //     at com.strobel.decompiler.ast.TypeAnalysis.inferTypeForExpression(TypeAnalysis.java:803)
        //     at com.strobel.decompiler.ast.TypeAnalysis.inferTypeForExpression(TypeAnalysis.java:770)
        //     at com.strobel.decompiler.ast.TypeAnalysis.inferTypeForExpression(TypeAnalysis.java:766)
        //     at com.strobel.decompiler.ast.TypeAnalysis.inferCall(TypeAnalysis.java:2445)
        //     at com.strobel.decompiler.ast.TypeAnalysis.doInferTypeForExpression(TypeAnalysis.java:1029)
        //     at com.strobel.decompiler.ast.TypeAnalysis.inferTypeForExpression(TypeAnalysis.java:803)
        //     at com.strobel.decompiler.ast.TypeAnalysis.inferTypeForExpression(TypeAnalysis.java:770)
        //     at com.strobel.decompiler.ast.TypeAnalysis.inferTypeForExpression(TypeAnalysis.java:766)
        //     at com.strobel.decompiler.ast.TypeAnalysis.inferCall(TypeAnalysis.java:2445)
        //     at com.strobel.decompiler.ast.TypeAnalysis.doInferTypeForExpression(TypeAnalysis.java:1029)
        //     at com.strobel.decompiler.ast.TypeAnalysis.inferTypeForExpression(TypeAnalysis.java:803)
        //     at com.strobel.decompiler.ast.TypeAnalysis.inferTypeForExpression(TypeAnalysis.java:770)
        //     at com.strobel.decompiler.ast.TypeAnalysis.inferTypeForExpression(TypeAnalysis.java:766)
        //     at com.strobel.decompiler.ast.TypeAnalysis.inferCall(TypeAnalysis.java:2445)
        //     at com.strobel.decompiler.ast.TypeAnalysis.doInferTypeForExpression(TypeAnalysis.java:1029)
        //     at com.strobel.decompiler.ast.TypeAnalysis.inferTypeForExpression(TypeAnalysis.java:803)
        //     at com.strobel.decompiler.ast.TypeAnalysis.inferTypeForExpression(TypeAnalysis.java:770)
        //     at com.strobel.decompiler.ast.TypeAnalysis.inferTypeForExpression(TypeAnalysis.java:766)
        //     at com.strobel.decompiler.ast.TypeAnalysis.inferCall(TypeAnalysis.java:2445)
        //     at com.strobel.decompiler.ast.TypeAnalysis.doInferTypeForExpression(TypeAnalysis.java:1029)
        //     at com.strobel.decompiler.ast.TypeAnalysis.inferTypeForExpression(TypeAnalysis.java:803)
        //     at com.strobel.decompiler.ast.TypeAnalysis.inferTypeForExpression(TypeAnalysis.java:770)
        //     at com.strobel.decompiler.ast.TypeAnalysis.inferTypeForExpression(TypeAnalysis.java:766)
        //     at com.strobel.decompiler.ast.TypeAnalysis.inferCall(TypeAnalysis.java:2445)
        //     at com.strobel.decompiler.ast.TypeAnalysis.doInferTypeForExpression(TypeAnalysis.java:1029)
        //     at com.strobel.decompiler.ast.TypeAnalysis.inferTypeForExpression(TypeAnalysis.java:803)
        //     at com.strobel.decompiler.ast.TypeAnalysis.inferTypeForExpression(TypeAnalysis.java:770)
        //     at com.strobel.decompiler.ast.TypeAnalysis.inferTypeForExpression(TypeAnalysis.java:766)
        //     at com.strobel.decompiler.ast.TypeAnalysis.inferCall(TypeAnalysis.java:2445)
        //     at com.strobel.decompiler.ast.TypeAnalysis.doInferTypeForExpression(TypeAnalysis.java:1029)
        //     at com.strobel.decompiler.ast.TypeAnalysis.inferTypeForExpression(TypeAnalysis.java:803)
        //     at com.strobel.decompiler.ast.TypeAnalysis.inferTypeForExpression(TypeAnalysis.java:770)
        //     at com.strobel.decompiler.ast.TypeAnalysis.inferTypeForExpression(TypeAnalysis.java:766)
        //     at com.strobel.decompiler.ast.TypeAnalysis.inferCall(TypeAnalysis.java:2445)
        //     at com.strobel.decompiler.ast.TypeAnalysis.doInferTypeForExpression(TypeAnalysis.java:1029)
        //     at com.strobel.decompiler.ast.TypeAnalysis.inferTypeForExpression(TypeAnalysis.java:803)
        //     at com.strobel.decompiler.ast.TypeAnalysis.inferTypeForExpression(TypeAnalysis.java:770)
        //     at com.strobel.decompiler.ast.TypeAnalysis.inferTypeForExpression(TypeAnalysis.java:766)
        //     at com.strobel.decompiler.ast.TypeAnalysis.inferCall(TypeAnalysis.java:2445)
        //     at com.strobel.decompiler.ast.TypeAnalysis.doInferTypeForExpression(TypeAnalysis.java:1029)
        //     at com.strobel.decompiler.ast.TypeAnalysis.inferTypeForExpression(TypeAnalysis.java:803)
        //     at com.strobel.decompiler.ast.TypeAnalysis.inferTypeForExpression(TypeAnalysis.java:770)
        //     at com.strobel.decompiler.ast.TypeAnalysis.inferTypeForExpression(TypeAnalysis.java:766)
        //     at com.strobel.decompiler.ast.TypeAnalysis.inferCall(TypeAnalysis.java:2445)
        //     at com.strobel.decompiler.ast.TypeAnalysis.doInferTypeForExpression(TypeAnalysis.java:1029)
        //     at com.strobel.decompiler.ast.TypeAnalysis.inferTypeForExpression(TypeAnalysis.java:803)
        //     at com.strobel.decompiler.ast.TypeAnalysis.inferTypeForExpression(TypeAnalysis.java:770)
        //     at com.strobel.decompiler.ast.TypeAnalysis.inferTypeForExpression(TypeAnalysis.java:766)
        //     at com.strobel.decompiler.ast.TypeAnalysis.inferCall(TypeAnalysis.java:2445)
        //     at com.strobel.decompiler.ast.TypeAnalysis.doInferTypeForExpression(TypeAnalysis.java:1029)
        //     at com.strobel.decompiler.ast.TypeAnalysis.inferTypeForExpression(TypeAnalysis.java:803)
        //     at com.strobel.decompiler.ast.TypeAnalysis.inferTypeForExpression(TypeAnalysis.java:770)
        //     at com.strobel.decompiler.ast.TypeAnalysis.inferTypeForExpression(TypeAnalysis.java:766)
        //     at com.strobel.decompiler.ast.TypeAnalysis.inferCall(TypeAnalysis.java:2445)
        //     at com.strobel.decompiler.ast.TypeAnalysis.doInferTypeForExpression(TypeAnalysis.java:1029)
        //     at com.strobel.decompiler.ast.TypeAnalysis.inferTypeForExpression(TypeAnalysis.java:803)
        //     at com.strobel.decompiler.ast.TypeAnalysis.inferTypeForExpression(TypeAnalysis.java:770)
        //     at com.strobel.decompiler.ast.TypeAnalysis.inferTypeForExpression(TypeAnalysis.java:766)
        //     at com.strobel.decompiler.ast.TypeAnalysis.inferCall(TypeAnalysis.java:2445)
        //     at com.strobel.decompiler.ast.TypeAnalysis.doInferTypeForExpression(TypeAnalysis.java:1029)
        //     at com.strobel.decompiler.ast.TypeAnalysis.inferTypeForExpression(TypeAnalysis.java:803)
        //     at com.strobel.decompiler.ast.TypeAnalysis.inferTypeForExpression(TypeAnalysis.java:770)
        //     at com.strobel.decompiler.ast.TypeAnalysis.inferTypeForExpression(TypeAnalysis.java:766)
        //     at com.strobel.decompiler.ast.TypeAnalysis.inferCall(TypeAnalysis.java:2445)
        //     at com.strobel.decompiler.ast.TypeAnalysis.doInferTypeForExpression(TypeAnalysis.java:1029)
        //     at com.strobel.decompiler.ast.TypeAnalysis.inferTypeForExpression(TypeAnalysis.java:803)
        //     at com.strobel.decompiler.ast.TypeAnalysis.inferTypeForExpression(TypeAnalysis.java:770)
        //     at com.strobel.decompiler.ast.TypeAnalysis.inferTypeForExpression(TypeAnalysis.java:766)
        //     at com.strobel.decompiler.ast.TypeAnalysis.inferCall(TypeAnalysis.java:2445)
        //     at com.strobel.decompiler.ast.TypeAnalysis.doInferTypeForExpression(TypeAnalysis.java:1029)
        //     at com.strobel.decompiler.ast.TypeAnalysis.inferTypeForExpression(TypeAnalysis.java:803)
        //     at com.strobel.decompiler.ast.TypeAnalysis.inferTypeForExpression(TypeAnalysis.java:770)
        //     at com.strobel.decompiler.ast.TypeAnalysis.inferTypeForExpression(TypeAnalysis.java:766)
        //     at com.strobel.decompiler.ast.TypeAnalysis.inferCall(TypeAnalysis.java:2445)
        //     at com.strobel.decompiler.ast.TypeAnalysis.doInferTypeForExpression(TypeAnalysis.java:1029)
        //     at com.strobel.decompiler.ast.TypeAnalysis.inferTypeForExpression(TypeAnalysis.java:803)
        //     at com.strobel.decompiler.ast.TypeAnalysis.inferTypeForExpression(TypeAnalysis.java:770)
        //     at com.strobel.decompiler.ast.TypeAnalysis.inferTypeForExpression(TypeAnalysis.java:766)
        //     at com.strobel.decompiler.ast.TypeAnalysis.inferCall(TypeAnalysis.java:2445)
        //     at com.strobel.decompiler.ast.TypeAnalysis.doInferTypeForExpression(TypeAnalysis.java:1029)
        //     at com.strobel.decompiler.ast.TypeAnalysis.inferTypeForExpression(TypeAnalysis.java:803)
        //     at com.strobel.decompiler.ast.TypeAnalysis.inferTypeForExpression(TypeAnalysis.java:770)
        //     at com.strobel.decompiler.ast.TypeAnalysis.doInferTypeForExpression(TypeAnalysis.java:881)
        //     at com.strobel.decompiler.ast.TypeAnalysis.inferTypeForExpression(TypeAnalysis.java:803)
        //     at com.strobel.decompiler.ast.TypeAnalysis.runInference(TypeAnalysis.java:672)
        //     at com.strobel.decompiler.ast.TypeAnalysis.inferTypesForVariables(TypeAnalysis.java:586)
        //     at com.strobel.decompiler.ast.TypeAnalysis.runInference(TypeAnalysis.java:397)
        //     at com.strobel.decompiler.ast.TypeAnalysis.run(TypeAnalysis.java:96)
        //     at com.strobel.decompiler.ast.AstOptimizer.optimize(AstOptimizer.java:109)
        //     at com.strobel.decompiler.ast.AstOptimizer.optimize(AstOptimizer.java:42)
        //     at com.strobel.decompiler.languages.java.ast.AstMethodBodyBuilder.createMethodBody(AstMethodBodyBuilder.java:214)
        //     at com.strobel.decompiler.languages.java.ast.AstMethodBodyBuilder.createMethodBody(AstMethodBodyBuilder.java:99)
        //     at com.strobel.decompiler.languages.java.ast.AstBuilder.createMethodBody(AstBuilder.java:757)
        //     at com.strobel.decompiler.languages.java.ast.AstBuilder.createMethod(AstBuilder.java:655)
        //     at com.strobel.decompiler.languages.java.ast.AstBuilder.addTypeMembers(AstBuilder.java:532)
        //     at com.strobel.decompiler.languages.java.ast.AstBuilder.createTypeCore(AstBuilder.java:499)
        //     at com.strobel.decompiler.languages.java.ast.AstBuilder.createTypeNoCache(AstBuilder.java:141)
        //     at com.strobel.decompiler.languages.java.ast.AstBuilder.createType(AstBuilder.java:130)
        //     at com.strobel.decompiler.languages.java.ast.AstBuilder.addType(AstBuilder.java:105)
        //     at com.strobel.decompiler.languages.java.JavaLanguage.buildAst(JavaLanguage.java:71)
        //     at com.strobel.decompiler.languages.java.JavaLanguage.decompileType(JavaLanguage.java:59)
        //     at com.strobel.decompiler.Decompiler.decompile(Decompiler.java:70)
        //     at com.edu.dibyarup.DecompilerUtil.decompileFiles(DecompilerUtil.java:28)
        //     at com.edu.dibyarup.FileDB.decompileAllFiles(FileDB.java:48)
        //     at com.edu.dibyarup.FileDB.decompileAllFiles(FileDB.java:42)
        //     at com.edu.dibyarup.FileDB.decompileAllFiles(FileDB.java:42)
        //     at com.edu.dibyarup.FileDB.decompileAllFiles(FileDB.java:42)
        //     at com.edu.dibyarup.FileDB.decompileAllFiles(FileDB.java:42)
        //     at com.edu.dibyarup.FileDB.main(FileDB.java:14)
        // 
        throw new IllegalStateException("An error occurred while decompiling this method.");
    }
    
    public String EssayTypeQuestion(final Vector<String> response, final Vector<String> question, final int no1) {
        final StringBuffer strHTML = new StringBuffer();
        final String no2 = String.valueOf(no1);
        final String strQuesNo = question.elementAt(0);
        final String strQues = question.elementAt(1);
        final String strScore = response.elementAt(1);
        final String strbraces = ")  ";
        final table table3 = new table().setCellPadding(0).setCellSpacing(4).setWidth("100%");
        final table table2 = new table().setBorder(0).setCellPadding(0).setCellSpacing(4).setWidth(607);
        final tr tr13 = new tr();
        final td td24 = new td().setWidth(560);
        final tr tr2 = new tr();
        final td td2 = new td().setWidth(47).setAlign("right");
        final td td3 = new td().setWidth(560);
        final tr tr3 = new tr();
        final td td4 = new td().setWidth(400);
        final tr tr4 = new tr();
        final td td5 = new td().setWidth(560);
        final textarea textarea1 = new textarea().setName("q" + strQuesNo).setCols(50).setRows(10);
        table3.addElement((Element)tr13.addElement(td24.addElement(no2).addElement(strbraces).addElement(strQues).setClass("QuestionOption")));
        final input inputButton1 = new input();
        table3.addElement((Element)tr4.addElement((Element)td5.addElement((Element)table2)));
        final String javaScript5 = "\n    //<![CDATA[\n    function preview_onclick() {\n    document.getElementById('frm').method=\"post\";\n    document.getElementById('frm').action=\"learnityasmtserver.assessmentportal.embeddedasmt.EassyTypeAnswerPreview?noticedetails=\"+encodeURIComponent(document.getElementById('frm').q" + strQuesNo + ".value);" + "\n    window.open(\"\",\"New123\",\"width=600,height=400,status=yes,scrollbars=yes,resizable=yes,toolbar=no,menubar=no\");" + "\n    document.getElementById('frm').target=\"New123\";" + "\n\tdocument.getElementById('frm').submit();" + "\n    }" + "\n     //]]>";
        table3.addElement((Element)new script().setLanguage("javascript").addElement(javaScript5));
        td5.addElement((Element)tr3.addElement((Element)td4.addElement(inputButton1.setName("add").setTabindex("2").setType("button").setValue("Preview").setClass("sbttn"))));
        table2.addElement((Element)tr2.addElement((Element)td2).addElement(td3.addElement((Element)textarea1).setClass("AnswerOption")));
        inputButton1.setOnClick("preview_onclick();");
        return table3.toString();
    }
    
    public String Slider(final Vector response, final Vector question, final int no1) {
        final String no2 = String.valueOf(no1);
        final StringBuffer strHTML = new StringBuffer();
        final String strQuesNo = (String) question.elementAt(0);
        final String strQues = (String) question.elementAt(1);
        final Vector multiAns = (Vector)question.elementAt(2);
        GenerateXHTML.log.debug("strQuesNo:=====Slider===========" + strQuesNo);
        GenerateXHTML.log.debug("strQues:=====Slider===========" + strQues);
        GenerateXHTML.log.debug("multiAns:=====Slider===========" + multiAns);
        final Vector vFeedback = (Vector) response.elementAt(2);
        String strCorrectFeedback = "";
        String strIncorrectFeedback = "";
        final String strbraces = ")  ";
        if (vFeedback != null) {
            for (int i = 0; i < vFeedback.size(); ++i) {
                final Vector vFeedbackItem = (Vector) vFeedback.elementAt(i);
                if (vFeedbackItem != null) {
                    final String strFeedback = (String) vFeedbackItem.elementAt(0);
                    final String strFor = (String) vFeedbackItem.elementAt(1);
                    final String strView = (String) vFeedbackItem.elementAt(2);
                    if (strFor.equals("Correct") && strView.equals("Candidate")) {
                        strCorrectFeedback = strFeedback;
                    }
                    if (strFor.equals("Incorrect") && strView.equals("Candidate")) {
                        strIncorrectFeedback = strFeedback;
                    }
                }
            }
        }
        String javaScriptStr2 = "";
        javaScriptStr2 = "";
        final String javaScriptStr3 = "\n // Store a value from 0 to 100 related to the slider's position\n sldValue=0\n // Slider's head left and top\n sldTop=0\n sldLeft=0\n // Drag action is on going is set to true\n doDrag=true\n // Mouse cursor position relatively to the slider's head\n sldMouseLeft=0\n sldMouseTop=0\n // Slider's container left and top boundaries\n minLeft=0\n maxLeft=0\n // Get and set positions\n function getAbsLeft(o) {\n oLeft = o.offsetLeft\n while(o.offsetParent!=null) {\n oParent = o.offsetParent\n oLeft += oParent.offsetLeft\n o = oParent\n \t}\n return oLeft\n }\n function getAbsTop(o) {\n\toTop = o.offsetTop\n while(o.offsetParent!=null) {\n oParent = o.offsetParent\n oTop += oParent.offsetTop\n o = oParent\n }\n return oTop\n }\n function setLeft(o,oLeft) {\n \to.style.left = oLeft + \"px\" \t\n }\n function setTop(o,oTop) {\n o.style.top = oTop + \"px\" \n }\n function setPosition(o,oLeft,oTop) {\n setLeft(o,oLeft)\n setTop(o,oTop)\n }\n // Slider's head mouse down handler\n function sldMouseDown(e)\n {\n // Get event object for IE\n if (!e) {e = window.event}\n // Drag action begins\n doDrag=true\n o1=document.getElementById(\"sldHead\")\n o2=document.getElementById(\"sldContainer\")\n // Get slider's head position\n sldLeft=o1.offsetLeft\n sldTop=o1.offsetTop\n // Get mouse cursor position relatively to the slider's head\n sldMouseLeft=e.clientX-sldLeft\n sldMouseTop=e.clientY-sldTop\n // Get slider's container boundaries\n minLeft=getAbsLeft(o2)\n maxLeft=o2.offsetWidth-o1.offsetWidth\n }\n // Generic mouse up handler\n function sldMouseUp(e)\n {\n // Drag action stops\n doDrag=false\n }\n // Generic mouse move handler\n function sldMouseMove(e)\n {\n // Get event object for IE\n if (!e) {e = window.event}\n // If drag action is on going...\n if (doDrag)\n {\n o=document.getElementById(\"sldHead\")\n // Get slider's head new position\n newPos = e.clientX-sldMouseLeft\n // Check slider's container boundaries\n if(newPos&#60;&#61;minLeft){newPos=0}\n if(newPos>=maxLeft) {newPos=maxLeft}\n //Set slider's head new position\n setPosition(o,newPos,sldTop)\n // Get slider's value (0 to 100)\n sldValue = Math.round((newPos *" + multiAns.size() + " )/maxLeft)" + "\n switch(sldValue){ ";
        for (int j = 0; j < multiAns.size(); ++j) {
            final Vector label = (Vector) multiAns.elementAt(j);
            final String strAns = (String) label.elementAt(1);
            javaScriptStr2 = "\n case " + j + ": sldValue=" + Integer.parseInt(strAns) + "\n         break";
            javaScriptStr2 += javaScriptStr2;
        }
        final String javaScriptStr4 = "\n\t\t}\n document.getElementById(\"watcher\").innerHTML = sldValue \n test=sldValue;\n // Stop event propagation\n return false\n }\n }\n// Set generic handlers\n document.onmousemove = sldMouseMove\n document.onmouseup= sldMouseUp\n";
        final String javaScript4 = "\n " + javaScriptStr3 + javaScriptStr2 + javaScriptStr4;
        final table table3 = new table().setCellPadding(0).setCellSpacing(4).setWidth("100%");
        final tr tr13 = new tr();
        final td td24 = new td().setWidth(560);
        table3.addElement((Element)tr13.addElement(td24.addElement(no2).addElement(strbraces).addElement(strQues).setClass("QuestionOption")));
        table3.addElement((Element)new tr().addElement((Element)new td().setWidth(560).addElement((Element)new blink().addElement("<font face=\"impact\" color=\"#000000\" size=\"1\">(Please drag the Slider bar to give the right answer)</font>"))));
        table3.addElement((Element)new script().setLanguage("javascript").addElement(javaScript4));
        final div div1 = new div();
        div1.setOnMouseDown("sldMouseDown(event)");
        div1.setStyle("position:relative;top:50px;left:0px;width:10px;height:10px;cursor:pointer;cursor:hand");
        final div div2 = new div();
        div2.setStyle("position:relative;top:10px;left:30px;width:150px;height:10px;background-color:#00CC33");
        final div div3 = new div();
        div3.setStyle("position:relative;top:10px;left:200px;width:100px;height:100px;color:#FF3300;font-family:arial");
        table3.addElement((Element)new tr().addElement((Element)new td().setWidth(560).addElement(div2.addElement(div1.addElement(new img().setSrc("../img/head.gif").setStyle("height:10px;width:10px;border:0")).setID("sldHead")).setID("sldContainer")).addElement(div3.addElement("<small><strong><font face=\"verdana\" color=\"#ff0000\" size=\"3\"></font></strong></small>").setID("watcher"))).addElement((Element)new td()));
        return table3.toString();
    }
    
    public String MultipleChoiceHTML(final Vector response, final Vector question, final int no1) {
        final String no2 = String.valueOf(no1);
        final StringBuffer strHTML = new StringBuffer();
        final String strQuesNo = (String) question.elementAt(0);
        final String strQues = (String) question.elementAt(1);
        final Vector multiAns = (Vector)question.elementAt(2);
        final Vector vFeedback = (Vector) response.elementAt(2);
        System.out.println("strQuesNo............................ = " + strQuesNo);
        String strCorrectFeedback = "";
        String strIncorrectFeedback = "";
        final String strbraces = ")  ";
        if (vFeedback != null) {
            for (int i = 0; i < vFeedback.size(); ++i) {
                final Vector vFeedbackItem = (Vector) vFeedback.elementAt(i);
                if (vFeedbackItem != null) {
                    final String strFeedback = (String) vFeedbackItem.elementAt(0);
                    final String strFor = (String) vFeedbackItem.elementAt(1);
                    final String strView = (String) vFeedbackItem.elementAt(2);
                    if (strFor.equals("Correct") && strView.equals("Candidate")) {
                        strCorrectFeedback = strFeedback;
                    }
                    if (strFor.equals("Incorrect") && strView.equals("Candidate")) {
                        strIncorrectFeedback = strFeedback;
                    }
                }
            }
        }
        System.out.println("111111111111111111111111111111111111111111111" + strQues);
        final table table3 = new table().setCellPadding(0).setCellSpacing(4).setWidth("100%");
        table3.addElement((Element)new tr().addElement(new td().addElement(no2).addElement(strbraces).addElement(strQues).setClass("QuestionOption")));
        final tr ttrr1 = new tr();
        for (int j = 0; j < multiAns.size(); ++j) {
            final Vector label = (Vector) multiAns.elementAt(j);
            final Character cLabel = (Character) label.elementAt(0);
            final String strAns = (String) label.elementAt(1);
            final int q_no1 = j + 1;
            final String q_no2 = String.valueOf(q_no1);
            ttrr1.addElement((Element)new tr().addElement(new td().setWidth(550).setAlign("left").addElement("<input name=\"" + strQuesNo + "\" type=\"radio\" value=\"" + cLabel.toString() + "\"/>").addElement(q_no2).addElement(strbraces).addElement(strAns).setClass("AnswerOption")));
        }
        table3.addElement((Element)new tr().addElement((Element)new td().setWidth(560).addElement((Element)new table().setBorder(0).setCellPadding(0).setCellSpacing(4).setWidth(607).addElement((Element)ttrr1))));
        return table3.toString();
    }
    
    public String MultipleResponseHTML(final Vector response, final Vector question, final int no1) {
        final String no2 = String.valueOf(no1);
        final StringBuffer strHTML = new StringBuffer();
        final String strQuesNo = (String) question.elementAt(0);
        final String strQues = (String) question.elementAt(1);
        final Vector multiAns = (Vector)question.elementAt(2);
        final Vector vCorrectAns = (Vector)question.elementAt(3);
        final Vector vFeedback = (Vector) response.elementAt(2);
        String strCorrectFeedback = "";
        String strIncorrectFeedback = "";
        final String strbraces = ")  ";
        if (vFeedback != null) {
            for (int i = 0; i < vFeedback.size(); ++i) {
                final Vector vFeedbackItem = (Vector) vFeedback.elementAt(i);
                if (vFeedbackItem != null) {
                    final String strFeedback = (String) vFeedbackItem.elementAt(0);
                    final String strFor = (String) vFeedbackItem.elementAt(1);
                    final String strView = (String) vFeedbackItem.elementAt(2);
                    if (strFor.equals("Correct") && strView.equals("Candidate")) {
                        strCorrectFeedback = strFeedback;
                    }
                    if (strFor.equals("Incorrect") && strView.equals("Candidate")) {
                        strIncorrectFeedback = strFeedback;
                    }
                }
            }
        }
        final table table3 = new table().setCellPadding(0).setCellSpacing(4).setWidth("100%");
        final table table2 = new table().setBorder(0).setCellPadding(0).setCellSpacing(4).setWidth(607);
        table3.addElement((Element)new tr().addElement(new td().addElement(no2).addElement(strbraces).addElement(strQues).setClass("QuestionOption")));
        table3.addElement((Element)new tr().addElement((Element)new td().setWidth(560).addElement((Element)table2)));
        for (int j = 0; j < multiAns.size(); ++j) {
            final int q_no1 = j + 1;
            final String q_no2 = String.valueOf(q_no1);
            final Vector label = (Vector) multiAns.elementAt(j);
            final Character cLabel = (Character) label.elementAt(0);
            final String strAns = (String) label.elementAt(1);
            table2.addElement((Element)new tr().addElement(new td().setWidth(550).setAlign("left").addElement("<input name=\"" + strQuesNo + "\" type=\"checkbox\" value=\"" + cLabel.toString() + "\"/>").addElement(q_no2).addElement(strbraces).addElement(strAns).setClass("AnswerOption")));
        }
        for (int k = 0; k < vCorrectAns.size(); ++k) {
            String strLabel = "";
            final String strCorrectAns = (String) vCorrectAns.elementAt(k);
            for (int l = 0; l < multiAns.size(); ++l) {
                final Vector label2 = (Vector) multiAns.elementAt(l);
                final Character cLabel2 = (Character) label2.elementAt(0);
                final String strAns2 = (String) label2.elementAt(1);
                if (strCorrectAns.equals(strAns2)) {
                    strLabel = cLabel2.toString();
                }
            }
        }
        return table3.toString();
    }
    
    public String FillBlanks(final Vector response, final Vector question, final int no1) {
        final String no2 = String.valueOf(no1);
        final StringBuffer strHTML = new StringBuffer();
        final String strQuesNo = (String) question.elementAt(0);
        final String strQues = (String) question.elementAt(1);
        final Vector multiAns = (Vector)question.elementAt(2);
        final Vector vFeedback = (Vector) response.elementAt(2);
        String strCorrectFeedback = "";
        String strIncorrectFeedback = "";
        final String strbraces = ")  ";
        if (vFeedback != null) {
            for (int i = 0; i < vFeedback.size(); ++i) {
                final Vector vFeedbackItem = (Vector) vFeedback.elementAt(i);
                if (vFeedbackItem != null) {
                    final String strFeedback = (String) vFeedbackItem.elementAt(0);
                    final String strFor = (String) vFeedbackItem.elementAt(1);
                    final String strView = (String) vFeedbackItem.elementAt(2);
                    if (strFor.equals("Correct") && strView.equals("Candidate")) {
                        strCorrectFeedback = strFeedback;
                    }
                    if (strFor.equals("Incorrect") && strView.equals("Candidate")) {
                        strIncorrectFeedback = strFeedback;
                    }
                }
            }
        }
        final table table3 = new table().setCellPadding(0).setCellSpacing(4).setWidth("100%");
        table3.addElement((Element)new tr().addElement(new td().setWidth(560).addElement(no2).addElement(strbraces).addElement(strQues).setClass("QuestionOption")));
        table3.addElement((Element)new tr().addElement((Element)new td().setWidth(560).addElement((Element)new table().setBorder(0).setCellPadding(0).setCellSpacing(4).setWidth(607).addElement((Element)new tr().addElement((Element)new td().setWidth(47).setAlign("right")).addElement(new td().setWidth(560).addElement("<input name=\"" + strQuesNo + "\"/>").setClass("AnswerOption"))))));
        return table3.toString();
    }
    
    public String MultipleChoiceImage(final Vector response, final Vector question, final int no1) {
        final String no2 = String.valueOf(no1);
        final StringBuffer strHTML = new StringBuffer();
        final String strQuesNo = (String) question.elementAt(0);
        final String strQues = (String) question.elementAt(1);
        final Vector multiAns = (Vector)question.elementAt(2);
        final Vector vFeedback = (Vector) response.elementAt(2);
        String strCorrectFeedback = "";
        String strIncorrectFeedback = "";
        final String strbraces = ")  ";
        if (vFeedback != null) {
            for (int i = 0; i < vFeedback.size(); ++i) {
                final Vector vFeedbackItem = (Vector) vFeedback.elementAt(i);
                if (vFeedbackItem != null) {
                    final String strFeedback = (String) vFeedbackItem.elementAt(0);
                    final String strFor = (String) vFeedbackItem.elementAt(1);
                    final String strView = (String) vFeedbackItem.elementAt(2);
                    if (strFor.equals("Correct") && strView.equals("Candidate")) {
                        strCorrectFeedback = strFeedback;
                    }
                    if (strFor.equals("Incorrect") && strView.equals("Candidate")) {
                        strIncorrectFeedback = strFeedback;
                    }
                }
            }
        }
        final table table3 = new table().setCellPadding(0).setCellSpacing(4).setWidth("100%");
        final table table2 = new table().setBorder(0).setCellPadding(0).setCellSpacing(4).setWidth(607);
        table3.addElement((Element)new tr().addElement(new td().addElement(no2).addElement(strbraces).addElement(strQues).setClass("QuestionOption")));
        table3.addElement((Element)new tr().addElement((Element)new td().setWidth(560).addElement((Element)table2)));
        for (int j = 0; j < multiAns.size(); ++j) {
            final Vector label = (Vector) multiAns.elementAt(j);
            final Character cLabel = (Character) label.elementAt(0);
            final String strAns = (String) label.elementAt(2);
            String strServerDocPath = Host.getServerDocumentPathEngine();
            strServerDocPath = strServerDocPath + "" + this.course_id;
            table2.addElement((Element)new tr().addElement((Element)new td().setWidth(47).setAlign("right").addElement("<input name=\"" + strQuesNo + "\" type=\"radio\" value=\"" + cLabel.toString() + "\"/>")).addElement(new td().setWidth(20).addElement(cLabel.toString()).addElement(strbraces).setClass("AnswerOption")).addElement((Element)new td().addElement((Element)new div().addElement((Element)new img().setAlign("left").setSrc("../images/" + strAns)))));
        }
        return table3.toString();
    }
    
    public String MatchingQuestionHTML(final Vector response, final Vector question, final int no1) {
        final String no2 = String.valueOf(no1);
        final StringBuffer strHTML = new StringBuffer();
        final String strQuesNo = (String) question.elementAt(0);
        final String strQues = (String) question.elementAt(1);
        final Vector vOption = (Vector)question.elementAt(2);
        final Vector leftoption = (Vector) vOption.elementAt(0);
        final Vector rightoption = (Vector) vOption.elementAt(1);
        final Vector vFeedback = (Vector) response.elementAt(2);
        String strCorrectFeedback = "";
        String strIncorrectFeedback = "";
        final String strbraces = ")  ";
        if (vFeedback != null) {
            for (int i = 0; i < vFeedback.size(); ++i) {
                final Vector vFeedbackItem = (Vector) vFeedback.elementAt(i);
                if (vFeedbackItem != null) {
                    final String strFeedback = (String) vFeedbackItem.elementAt(0);
                    final String strFor = (String) vFeedbackItem.elementAt(1);
                    final String strView = (String) vFeedbackItem.elementAt(2);
                    if (strFor.equals("Correct") && strView.equals("Candidate")) {
                        strCorrectFeedback = strFeedback;
                    }
                    if (strFor.equals("Incorrect") && strView.equals("Candidate")) {
                        strIncorrectFeedback = strFeedback;
                    }
                }
            }
        }
        final table table3 = new table().setCellPadding(0).setCellSpacing(4).setWidth("100%");
        table3.addElement((Element)new tr().addElement(new td().addElement(no2).addElement(strbraces).addElement(strQues).setClass("QuestionOption")));
        final tr ttrr1 = new tr();
        final tr ttrr2 = new tr();
        final table tblematch = new table();
        final table tblematch2 = new table();
        final tr ttrr3 = new tr();
        final table ttdd11 = new table();
        final table ttdd2 = new table();
        ttrr1.addElement((Element)tblematch2);
        tblematch2.addElement((Element)ttrr3);
        ttrr1.addElement((Element)new td().addElement((Element)ttdd11)).addElement((Element)new td().addElement((Element)ttdd2));
        ttrr2.addElement((Element)tblematch);
        ttdd11.addElement(new tr().addElement("<u>Left Choice</u>").setClass("headingMatchingtype"));
        ttdd2.addElement(new tr().addElement("<u>Right Choice</u>").setClass("headingMatchingtype"));
        final String[] alp = { "A", "B", "C", "D", "E", "F", "G", "H", "I", "J" };
        final String[] alp2 = { "L1", "L2", "L3", "L4", "L5", "L6", "L7", "L8", "L9", "L10" };
        final String[] alp3 = { "R1", "R2", "R3", "R4", "R5", "R6", "R7", "R8", "R9", "R10" };
        String noalp = "";
        tblematch.addElement(new tr().addElement("Match Left and Right").setClass("headingMatchingtype"));
        for (int j = 0; j < leftoption.size(); ++j) {
            final String[] leftOP1 = (String[]) leftoption.elementAt(j);
            final option[] option1 = new option[leftoption.size() + 1];
            option1[0] = new option("0").addElement("Choose One");
            for (int j2 = 0; j2 < leftoption.size(); ++j2) {
                final String[] leftOP2 = (String[]) leftoption.elementAt(j2);
                option1[j2 + 1] = new option(leftOP2[1]).addElement(alp2[j2]);
            }
            ttdd11.addElement(new tr().addElement(alp2[j]).addElement(" : ").addElement(leftOP1[1]).setClass("AnswerOptionl"));
            final String[] ritOP1 = (String[]) rightoption.elementAt(j);
            final option[] option2 = new option[rightoption.size() + 1];
            option2[0] = new option("0").addElement("Choose One");
            for (int j3 = 0; j3 < rightoption.size(); ++j3) {
                final String[] ritOP2 = (String[]) rightoption.elementAt(j3);
                option2[j3 + 1] = new option(ritOP2[1]).addElement(alp3[j3]);
            }
            ttdd2.addElement(new tr().addElement(alp3[j]).addElement(" : ").addElement(ritOP1[1]).setClass("AnswerOptionr"));
            noalp = alp[j];
            final String type1 = "l" + strQuesNo + noalp;
            final String type2 = "r" + strQuesNo + noalp;
            tblematch.addElement((Element)new tr().addElement(new td().addElement(alp[j]).addElement(strbraces).addElement((Element)new select().setName(type1).setTabindex(1).addElement(option1)).setClass("AnswerOptionleft")).addElement((Element)new td()).addElement((Element)new td()).addElement((Element)new td()).addElement(new td().addElement((Element)new select().setName(type2).setTabindex(1).addElement(option2)).setClass("AnswerOptionright")));
        }
        table3.addElement((Element)new tr().addElement((Element)new td().setWidth(560).addElement((Element)new table().setBorder(0).setCellPadding(0).setCellSpacing(4).setWidth(607).addElement((Element)ttrr1)))).addElement((Element)new tr().addElement((Element)new td().setWidth(560).addElement((Element)new table().setBorder(0).setCellPadding(0).setCellSpacing(4).setWidth(607).addElement((Element)ttrr2))));
        return table3.toString();
    }
    
    static {
        log = new SimpleLogger((Class)GenerateXHTML.class, true);
    }
}
